Workbook
Name m: 'M stock'!$A$5:$BQ$271
Name p: 'p2'!$A$5:$BQ$271
Name PQ: PQ!$A$5:$BQ$271

Sheet USA Long History
A2: Period | B2: P | C2: Observe | D2: Economy | E2: Diagnosis | F2: Δ P % | G2: Q | H2: Δ Q | I2: Δ Q % | J2: PQ | K2: Δ PQ | L2: Δ PQ % | M2: Δ PQ % - Δ Q % | N2: test | O2: match? | P2: (Δ PQ % - Δ Q %) -Δ P % = Δ P x Δ Q (interaction) | Q2: ΔPQ | R2: Δ%PQ | S2: M | T2: ΔM % | U2: MV | V2: ΔMV % | W2: M(d.) | X2: ΔM(d.) % | Y2: V | Z2: Δ V % | AA2: MV(d.) | AB2: ΔMV(d.) | AC2: Δ%MV(d.) | AD2: PQ-MV(d.) (FAC) | AE2: MV(d.) + FAC | AF2: Δ MV(d.)+FAC % | AG2: Δ MV(d.)+FAC % - Δ Q % | AH2: Δ MV(d.)+FAC % - Δ M % | AI2: Δ MV(d.)+FAC % - Δ M % | AJ2: Δ MV(d.)+FAC % - Δ V % | AK2: test | AL2: match? | AM2: M_FAC | AN2: V_FAC
A3: 1781 | G3: =J3/B3 -> #DIV/0! | H3: =G3-G2 -> #DIV/0! | I3: =H3-H2 -> #DIV/0! | K3: =J3-J2 -> #VALUE! | L3: =(K3-K2)/K2 -> #VALUE! | M3: =L3-I3 -> #VALUE! | U3: =S3*Y3 -> #DIV/0! | W3: =S3/B3 -> #DIV/0! | Y3: =J3/S3 -> #DIV/0! | AA3: =W3*Y3 -> #DIV/0! | AD3: =J3-AA3 -> #DIV/0! | AE3: =AA3+AD3 -> #DIV/0! | AG3: =AF3-I3 -> #DIV/0! | AH3: =AF3-T4 -> #DIV/0! | AI3: =AF3-X3 -> 0 | AJ3: =AF3-Z3 -> 0
A4: 1782 | C4: =IF(B4>B3,"inflation",IF(B4<B3,"deflation","stable")) -> stable | D4: =IFERROR(IF(I4>0,"expansive","contractive"),"") | E4: =IF(AND(C4="inflation",D4="expansive"),"inflationary expansion",IF(AND(C4="inflation",D4="contractive"),"stagflation",IF(AND(C4="deflation",D4="expansive"),"deflationary growth",IF(AND(C4="deflation",D4="contractive"),"recession",0)))) -> 0 | F4: =(B4-B3)/B3 -> #DIV/0! | G4: =J4/B4 -> #DIV/0! | H4: =G4-G3 -> #DIV/0! | I4: =H4/G3 -> #DIV/0! | K4: =J4-J3 -> 0 | L4: =K4/J3 -> #DIV/0! | M4: =L4-I4 -> #DIV/0! | N4: =IF(L4>I4, "inflation",IF(L4<I4, "deflation","stable")) -> #DIV/0! | O4: =IFERROR(IF(N4=C4,1,0),"") | P4: =M4-F4 -> #DIV/0! | Q4: =J4-J3 -> 0 | R4: =Q4/J3 -> #DIV/0! | T4: =(S4-S3)/S3 -> #DIV/0! | U4: =S4*Y4 -> #DIV/0! | V4: =(U4-U3)/U3 -> #DIV/0! | W4: =S4/B4 -> #DIV/0! | X4: =(W4-W3)/W3 -> #DIV/0! | Y4: =J4/S4 -> #DIV/0! | Z4: =(Y4-Y3)/Y3 -> #DIV/0! | AA4: =W4*Y4 -> #DIV/0! | AB4: =AA4-AA3 -> #DIV/0! | AC4: =AB4/AA3 -> #DIV/0! | AD4: =J4-AA4 -> #DIV/0! | AE4: =AA4+AD4 -> #DIV/0! | AF4: =(AE4-AE3)/AE3 -> #DIV/0! | AG4: =AF4-I4 -> #DIV/0! | AH4: =AF4-T5 -> #DIV/0! | AI4: =AF4-X4 -> #DIV/0! | AJ4: =AF4-Z4 -> #DIV/0! | AK4: =IF(AG4>0, "inflation",IF(AG4<0,"deflation","stable")) -> #DIV/0! | AL4: =IFERROR(IF(AK4=C4,1,0),"") | AM4: =AD4/AN4 -> #DIV/0! | AN4: =Y4 -> #DIV/0!
A5: 1783 | C5: =IF(B5>B4,"inflation",IF(B5<B4,"deflation","stable")) -> stable | D5: =IF(I5>0,"expansive","contractive") -> #DIV/0! | E5: =IF(AND(C5="inflation",D5="expansive"),"inflationary expansion",IF(AND(C5="inflation",D5="contractive"),"stagflation",IF(AND(C5="deflation",D5="expansive"),"deflationary growth",IF(AND(C5="deflation",D5="contractive"),"recession",0)))) -> #DIV/0! | F5: =(B5-B4)/B4 -> #DIV/0! | G5: =J5/B5 -> #DIV/0! | H5: =G5-G4 -> #DIV/0! | I5: =H5/G4 -> #DIV/0! | K5: =J5-J4 -> 0 | L5: =K5/J4 -> #DIV/0! | M5: =L5-I5 -> #DIV/0! | N5: =IF(L5>I5, "inflation",IF(L5<I5, "deflation","stable")) -> #DIV/0! | O5: =IFERROR(IF(N5=C5,1,0),"") | P5: =M5-F5 -> #DIV/0! | Q5: =J5-J4 -> 0 | R5: =Q5/J4 -> #DIV/0! | T5: =(S5-S4)/S4 -> #DIV/0! | U5: =S5*Y5 -> #DIV/0! | V5: =(U5-U4)/U4 -> #DIV/0! | W5: =S5/B5 -> #DIV/0! | X5: =(W5-W4)/W4 -> #DIV/0! | Y5: =J5/S5 -> #DIV/0! | Z5: =(Y5-Y4)/Y4 -> #DIV/0! | AA5: =W5*Y5 -> #DIV/0! | AB5: =AA5-AA4 -> #DIV/0! | AC5: =AB5/AA4 -> #DIV/0! | AD5: =J5-AA5 -> #DIV/0! | AE5: =AA5+AD5 -> #DIV/0! | AF5: =(AE5-AE4)/AE4 -> #DIV/0! | AG5: =AF5-I5 -> #DIV/0! | AH5: =AF5-T6 -> #DIV/0! | AI5: =AF5-X5 -> #DIV/0! | AJ5: =AF5-Z5 -> #DIV/0! | AK5: =IF(AG5>0, "inflation",IF(AG5<0,"deflation","stable")) -> #DIV/0! | AL5: =IFERROR(IF(AK5=C5,1,0),"") | AM5: =AD5/AN5 -> #DIV/0! | AN5: =Y5 -> #DIV/0!
A6: 1784 | C6: =IF(B6>B5,"inflation",IF(B6<B5,"deflation","stable")) -> stable | D6: =IF(I6>0,"expansive","contractive") -> #DIV/0! | E6: =IF(AND(C6="inflation",D6="expansive"),"inflationary expansion",IF(AND(C6="inflation",D6="contractive"),"stagflation",IF(AND(C6="deflation",D6="expansive"),"deflationary growth",IF(AND(C6="deflation",D6="contractive"),"recession",0)))) -> #DIV/0! | F6: =(B6-B5)/B5 -> #DIV/0! | G6: =J6/B6 -> #DIV/0! | H6: =G6-G5 -> #DIV/0! | I6: =H6/G5 -> #DIV/0! | K6: =J6-J5 -> 0 | L6: =K6/J5 -> #DIV/0! | M6: =L6-I6 -> #DIV/0! | N6: =IF(L6>I6, "inflation",IF(L6<I6, "deflation","stable")) -> #DIV/0! | O6: =IFERROR(IF(N6=C6,1,0),"") | P6: =M6-F6 -> #DIV/0! | Q6: =J6-J5 -> 0 | R6: =Q6/J5 -> #DIV/0! | T6: =(S6-S5)/S5 -> #DIV/0! | U6: =S6*Y6 -> #DIV/0! | V6: =(U6-U5)/U5 -> #DIV/0! | W6: =S6/B6 -> #DIV/0! | X6: =(W6-W5)/W5 -> #DIV/0! | Y6: =J6/S6 -> #DIV/0! | Z6: =(Y6-Y5)/Y5 -> #DIV/0! | AA6: =W6*Y6 -> #DIV/0! | AB6: =AA6-AA5 -> #DIV/0! | AC6: =AB6/AA5 -> #DIV/0! | AD6: =J6-AA6 -> #DIV/0! | AE6: =AA6+AD6 -> #DIV/0! | AF6: =(AE6-AE5)/AE5 -> #DIV/0! | AG6: =AF6-I6 -> #DIV/0! | AH6: =AF6-T7 -> #DIV/0! | AI6: =AF6-X6 -> #DIV/0! | AJ6: =AF6-Z6 -> #DIV/0! | AK6: =IF(AG6>0, "inflation",IF(AG6<0,"deflation","stable")) -> #DIV/0! | AL6: =IFERROR(IF(AK6=C6,1,0),"") | AM6: =AD6/AN6 -> #DIV/0! | AN6: =Y6 -> #DIV/0!
A7: 1785 | C7: =IF(B7>B6,"inflation",IF(B7<B6,"deflation","stable")) -> stable | D7: =IF(I7>0,"expansive","contractive") -> #DIV/0! | E7: =IF(AND(C7="inflation",D7="expansive"),"inflationary expansion",IF(AND(C7="inflation",D7="contractive"),"stagflation",IF(AND(C7="deflation",D7="expansive"),"deflationary growth",IF(AND(C7="deflation",D7="contractive"),"recession",0)))) -> #DIV/0! | F7: =(B7-B6)/B6 -> #DIV/0! | G7: =J7/B7 -> #DIV/0! | H7: =G7-G6 -> #DIV/0! | I7: =H7/G6 -> #DIV/0! | K7: =J7-J6 -> 0 | L7: =K7/J6 -> #DIV/0! | M7: =L7-I7 -> #DIV/0! | N7: =IF(L7>I7, "inflation",IF(L7<I7, "deflation","stable")) -> #DIV/0! | O7: =IFERROR(IF(N7=C7,1,0),"") | P7: =M7-F7 -> #DIV/0! | Q7: =J7-J6 -> 0 | R7: =Q7/J6 -> #DIV/0! | T7: =(S7-S6)/S6 -> #DIV/0! | U7: =S7*Y7 -> #DIV/0! | V7: =(U7-U6)/U6 -> #DIV/0! | W7: =S7/B7 -> #DIV/0! | X7: =(W7-W6)/W6 -> #DIV/0! | Y7: =J7/S7 -> #DIV/0! | Z7: =(Y7-Y6)/Y6 -> #DIV/0! | AA7: =W7*Y7 -> #DIV/0! | AB7: =AA7-AA6 -> #DIV/0! | AC7: =AB7/AA6 -> #DIV/0! | AD7: =J7-AA7 -> #DIV/0! | AE7: =AA7+AD7 -> #DIV/0! | AF7: =(AE7-AE6)/AE6 -> #DIV/0! | AG7: =AF7-I7 -> #DIV/0! | AH7: =AF7-T8 -> #DIV/0! | AI7: =AF7-X7 -> #DIV/0! | AJ7: =AF7-Z7 -> #DIV/0! | AK7: =IF(AG7>0, "inflation",IF(AG7<0,"deflation","stable")) -> #DIV/0! | AL7: =IFERROR(IF(AK7=C7,1,0),"") | AM7: =AD7/AN7 -> #DIV/0! | AN7: =Y7 -> #DIV/0!
A8: 1786 | C8: =IF(B8>B7,"inflation",IF(B8<B7,"deflation","stable")) -> stable | D8: =IF(I8>0,"expansive","contractive") -> #DIV/0! | E8: =IF(AND(C8="inflation",D8="expansive"),"inflationary expansion",IF(AND(C8="inflation",D8="contractive"),"stagflation",IF(AND(C8="deflation",D8="expansive"),"deflationary growth",IF(AND(C8="deflation",D8="contractive"),"recession",0)))) -> #DIV/0! | F8: =(B8-B7)/B7 -> #DIV/0! | G8: =J8/B8 -> #DIV/0! | H8: =G8-G7 -> #DIV/0! | I8: =H8/G7 -> #DIV/0! | K8: =J8-J7 -> 0 | L8: =K8/J7 -> #DIV/0! | M8: =L8-I8 -> #DIV/0! | N8: =IF(L8>I8, "inflation",IF(L8<I8, "deflation","stable")) -> #DIV/0! | O8: =IFERROR(IF(N8=C8,1,0),"") | P8: =M8-F8 -> #DIV/0! | Q8: =J8-J7 -> 0 | R8: =Q8/J7 -> #DIV/0! | T8: =(S8-S7)/S7 -> #DIV/0! | U8: =S8*Y8 -> #DIV/0! | V8: =(U8-U7)/U7 -> #DIV/0! | W8: =S8/B8 -> #DIV/0! | X8: =(W8-W7)/W7 -> #DIV/0! | Y8: =J8/S8 -> #DIV/0! | Z8: =(Y8-Y7)/Y7 -> #DIV/0! | AA8: =W8*Y8 -> #DIV/0! | AB8: =AA8-AA7 -> #DIV/0! | AC8: =AB8/AA7 -> #DIV/0! | AD8: =J8-AA8 -> #DIV/0! | AE8: =AA8+AD8 -> #DIV/0! | AF8: =(AE8-AE7)/AE7 -> #DIV/0! | AG8: =AF8-I8 -> #DIV/0! | AH8: =AF8-T9 -> #DIV/0! | AI8: =AF8-X8 -> #DIV/0! | AJ8: =AF8-Z8 -> #DIV/0! | AK8: =IF(AG8>0, "inflation",IF(AG8<0,"deflation","stable")) -> #DIV/0! | AL8: =IFERROR(IF(AK8=C8,1,0),"") | AM8: =AD8/AN8 -> #DIV/0! | AN8: =Y8 -> #DIV/0!
A9: 1787 | C9: =IF(B9>B8,"inflation",IF(B9<B8,"deflation","stable")) -> stable | D9: =IF(I9>0,"expansive","contractive") -> #DIV/0! | E9: =IF(AND(C9="inflation",D9="expansive"),"inflationary expansion",IF(AND(C9="inflation",D9="contractive"),"stagflation",IF(AND(C9="deflation",D9="expansive"),"deflationary growth",IF(AND(C9="deflation",D9="contractive"),"recession",0)))) -> #DIV/0! | F9: =(B9-B8)/B8 -> #DIV/0! | G9: =J9/B9 -> #DIV/0! | H9: =G9-G8 -> #DIV/0! | I9: =H9/G8 -> #DIV/0! | K9: =J9-J8 -> 0 | L9: =K9/J8 -> #DIV/0! | M9: =L9-I9 -> #DIV/0! | N9: =IF(L9>I9, "inflation",IF(L9<I9, "deflation","stable")) -> #DIV/0! | O9: =IFERROR(IF(N9=C9,1,0),"") | P9: =M9-F9 -> #DIV/0! | Q9: =J9-J8 -> 0 | R9: =Q9/J8 -> #DIV/0! | T9: =(S9-S8)/S8 -> #DIV/0! | U9: =S9*Y9 -> #DIV/0! | V9: =(U9-U8)/U8 -> #DIV/0! | W9: =S9/B9 -> #DIV/0! | X9: =(W9-W8)/W8 -> #DIV/0! | Y9: =J9/S9 -> #DIV/0! | Z9: =(Y9-Y8)/Y8 -> #DIV/0! | AA9: =W9*Y9 -> #DIV/0! | AB9: =AA9-AA8 -> #DIV/0! | AC9: =AB9/AA8 -> #DIV/0! | AD9: =J9-AA9 -> #DIV/0! | AE9: =AA9+AD9 -> #DIV/0! | AF9: =(AE9-AE8)/AE8 -> #DIV/0! | AG9: =AF9-I9 -> #DIV/0! | AH9: =AF9-T10 -> #DIV/0! | AI9: =AF9-X9 -> #DIV/0! | AJ9: =AF9-Z9 -> #DIV/0! | AK9: =IF(AG9>0, "inflation",IF(AG9<0,"deflation","stable")) -> #DIV/0! | AL9: =IFERROR(IF(AK9=C9,1,0),"") | AM9: =AD9/AN9 -> #DIV/0! | AN9: =Y9 -> #DIV/0!
A10: 1788 | C10: =IF(B10>B9,"inflation",IF(B10<B9,"deflation","stable")) -> stable | D10: =IF(I10>0,"expansive","contractive") -> #DIV/0! | E10: =IF(AND(C10="inflation",D10="expansive"),"inflationary expansion",IF(AND(C10="inflation",D10="contractive"),"stagflation",IF(AND(C10="deflation",D10="expansive"),"deflationary growth",IF(AND(C10="deflation",D10="contractive"),"recession",0)))) -> #DIV/0! | F10: =(B10-B9)/B9 -> #DIV/0! | G10: =J10/B10 -> #DIV/0! | H10: =G10-G9 -> #DIV/0! | I10: =H10/G9 -> #DIV/0! | K10: =J10-J9 -> 0 | L10: =K10/J9 -> #DIV/0! | M10: =L10-I10 -> #DIV/0! | N10: =IF(L10>I10, "inflation",IF(L10<I10, "deflation","stable")) -> #DIV/0! | O10: =IFERROR(IF(N10=C10,1,0),"") | P10: =M10-F10 -> #DIV/0! | Q10: =J10-J9 -> 0 | R10: =Q10/J9 -> #DIV/0! | T10: =(S10-S9)/S9 -> #DIV/0! | U10: =S10*Y10 -> #DIV/0! | V10: =(U10-U9)/U9 -> #DIV/0! | W10: =S10/B10 -> #DIV/0! | X10: =(W10-W9)/W9 -> #DIV/0! | Y10: =J10/S10 -> #DIV/0! | Z10: =(Y10-Y9)/Y9 -> #DIV/0! | AA10: =W10*Y10 -> #DIV/0! | AB10: =AA10-AA9 -> #DIV/0! | AC10: =AB10/AA9 -> #DIV/0! | AD10: =J10-AA10 -> #DIV/0! | AE10: =AA10+AD10 -> #DIV/0! | AF10: =(AE10-AE9)/AE9 -> #DIV/0! | AG10: =AF10-I10 -> #DIV/0! | AH10: =AF10-T11 -> #DIV/0! | AI10: =AF10-X10 -> #DIV/0! | AJ10: =AF10-Z10 -> #DIV/0! | AK10: =IF(AG10>0, "inflation",IF(AG10<0,"deflation","stable")) -> #DIV/0! | AL10: =IFERROR(IF(AK10=C10,1,0),"") | AM10: =AD10/AN10 -> #DIV/0! | AN10: =Y10 -> #DIV/0!
A11: 1789 | C11: =IF(B11>B10,"inflation",IF(B11<B10,"deflation","stable")) -> stable | D11: =IF(I11>0,"expansive","contractive") -> #DIV/0! | E11: =IF(AND(C11="inflation",D11="expansive"),"inflationary expansion",IF(AND(C11="inflation",D11="contractive"),"stagflation",IF(AND(C11="deflation",D11="expansive"),"deflationary growth",IF(AND(C11="deflation",D11="contractive"),"recession",0)))) -> #DIV/0! | F11: =(B11-B10)/B10 -> #DIV/0! | G11: =J11/B11 -> #DIV/0! | H11: =G11-G10 -> #DIV/0! | I11: =H11/G10 -> #DIV/0! | K11: =J11-J10 -> 0 | L11: =K11/J10 -> #DIV/0! | M11: =L11-I11 -> #DIV/0! | N11: =IF(L11>I11, "inflation",IF(L11<I11, "deflation","stable")) -> #DIV/0! | O11: =IFERROR(IF(N11=C11,1,0),"") | P11: =M11-F11 -> #DIV/0! | Q11: =J11-J10 -> 0 | R11: =Q11/J10 -> #DIV/0! | T11: =(S11-S10)/S10 -> #DIV/0! | U11: =S11*Y11 -> #DIV/0! | V11: =(U11-U10)/U10 -> #DIV/0! | W11: =S11/B11 -> #DIV/0! | X11: =(W11-W10)/W10 -> #DIV/0! | Y11: =J11/S11 -> #DIV/0! | Z11: =(Y11-Y10)/Y10 -> #DIV/0! | AA11: =W11*Y11 -> #DIV/0! | AB11: =AA11-AA10 -> #DIV/0! | AC11: =AB11/AA10 -> #DIV/0! | AD11: =J11-AA11 -> #DIV/0! | AE11: =AA11+AD11 -> #DIV/0! | AF11: =(AE11-AE10)/AE10 -> #DIV/0! | AG11: =AF11-I11 -> #DIV/0! | AH11: =AF11-T12 -> #DIV/0! | AI11: =AF11-X11 -> #DIV/0! | AJ11: =AF11-Z11 -> #DIV/0! | AK11: =IF(AG11>0, "inflation",IF(AG11<0,"deflation","stable")) -> #DIV/0! | AL11: =IFERROR(IF(AK11=C11,1,0),"") | AM11: =AD11/AN11 -> #DIV/0! | AN11: =Y11 -> #DIV/0!
A12: 1790 | B12: 1 | C12: =IF(B12>B11,"inflation",IF(B12<B11,"deflation","stable")) -> inflation | D12: =IF(I12>0,"expansive","contractive") -> #DIV/0! | E12: =IF(AND(C12="inflation",D12="expansive"),"inflationary expansion",IF(AND(C12="inflation",D12="contractive"),"stagflation",IF(AND(C12="deflation",D12="expansive"),"deflationary growth",IF(AND(C12="deflation",D12="contractive"),"recession",0)))) -> #DIV/0! | F12: =(B12-B11)/B11 -> #DIV/0! | G12: =J12/B12 -> 0.19289785 | H12: =G12-G11 -> #DIV/0! | I12: =H12/G11 -> #DIV/0! | J12: 0.19289785 | K12: =J12-J11 -> 0.19289785 | L12: =K12/J11 -> #DIV/0! | M12: =L12-I12 -> #DIV/0! | N12: =IF(L12>I12, "inflation",IF(L12<I12, "deflation","stable")) -> #DIV/0! | O12: =IFERROR(IF(N12=C12,1,0),"") | P12: =M12-F12 -> #DIV/0! | Q12: =J12-J11 -> 0.19289785 | R12: =Q12/J11 -> #DIV/0! | T12: =(S12-S11)/S11 -> #DIV/0! | U12: =S12*Y12 -> #DIV/0! | V12: =(U12-U11)/U11 -> #DIV/0! | W12: =S12/B12 -> 0 | X12: =(W12-W11)/W11 -> #DIV/0! | Y12: =J12/S12 -> #DIV/0! | Z12: =(Y12-Y11)/Y11 -> #DIV/0! | AA12: =W12*Y12 -> #DIV/0! | AB12: =AA12-AA11 -> #DIV/0! | AC12: =AB12/AA11 -> #DIV/0! | AD12: =J12-AA12 -> #DIV/0! | AE12: =AA12+AD12 -> #DIV/0! | AF12: =(AE12-AE11)/AE11 -> #DIV/0! | AG12: =AF12-I12 -> #DIV/0! | AH12: =AF12-T13 -> #DIV/0! | AI12: =AF12-X12 -> #DIV/0! | AJ12: =AF12-Z12 -> #DIV/0! | AK12: =IF(AG12>0, "inflation",IF(AG12<0,"deflation","stable")) -> #DIV/0! | AL12: =IFERROR(IF(AK12=C12,1,0),"") | AM12: =AD12/AN12 -> #DIV/0! | AN12: =Y12 -> #DIV/0!
A13: 1791 | B13: 1.0272727 | C13: =IF(B13>B12,"inflation",IF(B13<B12,"deflation","stable")) -> inflation | D13: =IF(I13>0,"expansive","contractive") -> expansive | E13: =IF(AND(C13="inflation",D13="expansive"),"inflationary expansion",IF(AND(C13="inflation",D13="contractive"),"stagflation",IF(AND(C13="deflation",D13="expansive"),"deflationary growth",IF(AND(C13="deflation",D13="contractive"),"recession",0)))) -> inflationary expansion | F13: =(B13-B12)/B12 -> 0.027272727 | G13: =J13/B13 -> 0.20448798 | H13: =G13-G12 -> 0.011590128 | I13: =H13/G12 -> 0.060084275 | J13: 0.21006493 | K13: =J13-J12 -> 0.017167073 | L13: =K13/J12 -> 0.088995664 | M13: =L13-I13 -> 0.028911389 | N13: =IF(L13>I13, "inflation",IF(L13<I13, "deflation","stable")) -> inflation | O13: =IFERROR(IF(N13=C13,1,0),"") -> 1 | P13: =M13-F13 -> 0.001638662 | Q13: =J13-J12 -> 0.017167073 | R13: =Q13/J12 -> 0.088995664 | T13: =(S13-S12)/S12 -> #DIV/0! | U13: =S13*Y13 -> #DIV/0! | V13: =(U13-U12)/U12 -> #DIV/0! | W13: =S13/B13 -> 0 | X13: =(W13-W12)/W12 -> #DIV/0! | Y13: =J13/S13 -> #DIV/0! | Z13: =(Y13-Y12)/Y12 -> #DIV/0! | AA13: =W13*Y13 -> #DIV/0! | AB13: =AA13-AA12 -> #DIV/0! | AC13: =AB13/AA12 -> #DIV/0! | AD13: =J13-AA13 -> #DIV/0! | AE13: =AA13+AD13 -> #DIV/0! | AF13: =(AE13-AE12)/AE12 -> #DIV/0! | AG13: =AF13-I13 -> #DIV/0! | AH13: =AF13-T14 -> #DIV/0! | AI13: =AF13-X13 -> #DIV/0! | AJ13: =AF13-Z13 -> #DIV/0! | AK13: =IF(AG13>0, "inflation",IF(AG13<0,"deflation","stable")) -> #DIV/0! | AL13: =IFERROR(IF(AK13=C13,1,0),"") | AM13: =AD13/AN13 -> #DIV/0! | AN13: =Y13 -> #DIV/0!
A14: 1792 | B14: 1.0454545 | C14: =IF(B14>B13,"inflation",IF(B14<B13,"deflation","stable")) -> inflation | D14: =IF(I14>0,"expansive","contractive") -> expansive | E14: =IF(AND(C14="inflation",D14="expansive"),"inflationary expansion",IF(AND(C14="inflation",D14="contractive"),"stagflation",IF(AND(C14="deflation",D14="expansive"),"deflationary growth",IF(AND(C14="deflation",D14="contractive"),"recession",0)))) -> inflationary expansion | F14: =(B14-B13)/B13 -> 0.017699115 | G14: =J14/B14 -> 0.21955966 | H14: =G14-G13 -> 0.015071681 | I14: =H14/G13 -> 0.073704482 | J14: 0.22953965 | K14: =J14-J13 -> 0.01947472 | L14: =K14/J13 -> 0.092708101 | M14: =L14-I14 -> 0.019003619 | N14: =IF(L14>I14, "inflation",IF(L14<I14, "deflation","stable")) -> inflation | O14: =IFERROR(IF(N14=C14,1,0),"") -> 1 | P14: =M14-F14 -> 0.0013045041 | Q14: =J14-J13 -> 0.01947472 | R14: =Q14/J13 -> 0.092708101 | T14: =(S14-S13)/S13 -> #DIV/0! | U14: =S14*Y14 -> #DIV/0! | V14: =(U14-U13)/U13 -> #DIV/0! | W14: =S14/B14 -> 0 | X14: =(W14-W13)/W13 -> #DIV/0! | Y14: =J14/S14 -> #DIV/0! | Z14: =(Y14-Y13)/Y13 -> #DIV/0! | AA14: =W14*Y14 -> #DIV/0! | AB14: =AA14-AA13 -> #DIV/0! | AC14: =AB14/AA13 -> #DIV/0! | AD14: =J14-AA14 -> #DIV/0! | AE14: =AA14+AD14 -> #DIV/0! | AF14: =(AE14-AE13)/AE13 -> #DIV/0! | AG14: =AF14-I14 -> #DIV/0! | AH14: =AF14-T15 -> #DIV/0! | AI14: =AF14-X14 -> #DIV/0! | AJ14: =AF14-Z14 -> #DIV/0! | AK14: =IF(AG14>0, "inflation",IF(AG14<0,"deflation","stable")) -> #DIV/0! | AL14: =IFERROR(IF(AK14=C14,1,0),"") | AM14: =AD14/AN14 -> #DIV/0! | AN14: =Y14 -> #DIV/0!
A15: 1793 | B15: 1.0818182 | C15: =IF(B15>B14,"inflation",IF(B15<B14,"deflation","stable")) -> inflation | D15: =IF(I15>0,"expansive","contractive") -> expansive | E15: =IF(AND(C15="inflation",D15="expansive"),"inflationary expansion",IF(AND(C15="inflation",D15="contractive"),"stagflation",IF(AND(C15="deflation",D15="expansive"),"deflationary growth",IF(AND(C15="deflation",D15="contractive"),"recession",0)))) -> inflationary expansion | F15: =(B15-B14)/B14 -> 0.034782609 | G15: =J15/B15 -> 0.23700405 | H15: =G15-G14 -> 0.017444385 | I15: =H15/G14 -> 0.079451686 | J15: 0.25639529 | K15: =J15-J14 -> 0.026855641 | L15: =K15/J14 -> 0.11699783 | M15: =L15-I15 -> 0.037546146 | N15: =IF(L15>I15, "inflation",IF(L15<I15, "deflation","stable")) -> inflation | O15: =IFERROR(IF(N15=C15,1,0),"") -> 1 | P15: =M15-F15 -> 0.0027635369 | Q15: =J15-J14 -> 0.026855641 | R15: =Q15/J14 -> 0.11699783 | T15: =(S15-S14)/S14 -> #DIV/0! | U15: =S15*Y15 -> #DIV/0! | V15: =(U15-U14)/U14 -> #DIV/0! | W15: =S15/B15 -> 0 | X15: =(W15-W14)/W14 -> #DIV/0! | Y15: =J15/S15 -> #DIV/0! | Z15: =(Y15-Y14)/Y14 -> #DIV/0! | AA15: =W15*Y15 -> #DIV/0! | AB15: =AA15-AA14 -> #DIV/0! | AC15: =AB15/AA14 -> #DIV/0! | AD15: =J15-AA15 -> #DIV/0! | AE15: =AA15+AD15 -> #DIV/0! | AF15: =(AE15-AE14)/AE14 -> #DIV/0! | AG15: =AF15-I15 -> #DIV/0! | AH15: =AF15-T16 -> #DIV/0! | AI15: =AF15-X15 -> #DIV/0! | AJ15: =AF15-Z15 -> #DIV/0! | AK15: =IF(AG15>0, "inflation",IF(AG15<0,"deflation","stable")) -> #DIV/0! | AL15: =IFERROR(IF(AK15=C15,1,0),"") | AM15: =AD15/AN15 -> #DIV/0! | AN15: =Y15 -> #DIV/0!
A16: 1794 | B16: 1.2 | C16: =IF(B16>B15,"inflation",IF(B16<B15,"deflation","stable")) -> inflation | D16: =IF(I16>0,"expansive","contractive") -> expansive | E16: =IF(AND(C16="inflation",D16="expansive"),"inflationary expansion",IF(AND(C16="inflation",D16="contractive"),"stagflation",IF(AND(C16="deflation",D16="expansive"),"deflationary growth",IF(AND(C16="deflation",D16="contractive"),"recession",0)))) -> inflationary expansion | F16: =(B16-B15)/B15 -> 0.1092437 | G16: =J16/B16 -> 0.26773939 | H16: =G16-G15 -> 0.030735341 | I16: =H16/G15 -> 0.12968277 | J16: 0.32128727 | K16: =J16-J15 -> 0.064891979 | L16: =K16/J15 -> 0.25309349 | M16: =L16-I16 -> 0.12341072 | N16: =IF(L16>I16, "inflation",IF(L16<I16, "deflation","stable")) -> inflation | O16: =IFERROR(IF(N16=C16,1,0),"") -> 1 | P16: =M16-F16 -> 0.014167025 | Q16: =J16-J15 -> 0.064891979 | R16: =Q16/J15 -> 0.25309349 | T16: =(S16-S15)/S15 -> #DIV/0! | U16: =S16*Y16 -> #DIV/0! | V16: =(U16-U15)/U15 -> #DIV/0! | W16: =S16/B16 -> 0 | X16: =(W16-W15)/W15 -> #DIV/0! | Y16: =J16/S16 -> #DIV/0! | Z16: =(Y16-Y15)/Y15 -> #DIV/0! | AA16: =W16*Y16 -> #DIV/0! | AB16: =AA16-AA15 -> #DIV/0! | AC16: =AB16/AA15 -> #DIV/0! | AD16: =J16-AA16 -> #DIV/0! | AE16: =AA16+AD16 -> #DIV/0! | AF16: =(AE16-AE15)/AE15 -> #DIV/0! | AG16: =AF16-I16 -> #DIV/0! | AH16: =AF16-T17 -> #DIV/0! | AI16: =AF16-X16 -> #DIV/0! | AJ16: =AF16-Z16 -> #DIV/0! | AK16: =IF(AG16>0, "inflation",IF(AG16<0,"deflation","stable")) -> #DIV/0! | AL16: =IFERROR(IF(AK16=C16,1,0),"") | AM16: =AD16/AN16 -> #DIV/0! | AN16: =Y16 -> #DIV/0!
A17: 1795 | B17: 1.3727273 | C17: =IF(B17>B16,"inflation",IF(B17<B16,"deflation","stable")) -> inflation | D17: =IF(I17>0,"expansive","contractive") -> expansive | E17: =IF(AND(C17="inflation",D17="expansive"),"inflationary expansion",IF(AND(C17="inflation",D17="contractive"),"stagflation",IF(AND(C17="deflation",D17="expansive"),"deflationary growth",IF(AND(C17="deflation",D17="contractive"),"recession",0)))) -> inflationary expansion | F17: =(B17-B16)/B16 -> 0.14393939 | G17: =J17/B17 -> 0.28425703 | H17: =G17-G16 -> 0.016517646 | I17: =H17/G16 -> 0.061692998 | J17: 0.39020738 | K17: =J17-J16 -> 0.068920117 | L17: =K17/J16 -> 0.21451245 | M17: =L17-I17 -> 0.15281945 | N17: =IF(L17>I17, "inflation",IF(L17<I17, "deflation","stable")) -> inflation | O17: =IFERROR(IF(N17=C17,1,0),"") -> 1 | P17: =M17-F17 -> 0.0088800528 | Q17: =J17-J16 -> 0.068920117 | R17: =Q17/J16 -> 0.21451245 | T17: =(S17-S16)/S16 -> #DIV/0! | U17: =S17*Y17 -> #DIV/0! | V17: =(U17-U16)/U16 -> #DIV/0! | W17: =S17/B17 -> 0 | X17: =(W17-W16)/W16 -> #DIV/0! | Y17: =J17/S17 -> #DIV/0! | Z17: =(Y17-Y16)/Y16 -> #DIV/0! | AA17: =W17*Y17 -> #DIV/0! | AB17: =AA17-AA16 -> #DIV/0! | AC17: =AB17/AA16 -> #DIV/0! | AD17: =J17-AA17 -> #DIV/0! | AE17: =AA17+AD17 -> #DIV/0! | AF17: =(AE17-AE16)/AE16 -> #DIV/0! | AG17: =AF17-I17 -> #DIV/0! | AH17: =AF17-T18 -> #DIV/0! | AI17: =AF17-X17 -> #DIV/0! | AJ17: =AF17-Z17 -> #DIV/0! | AK17: =IF(AG17>0, "inflation",IF(AG17<0,"deflation","stable")) -> #DIV/0! | AL17: =IFERROR(IF(AK17=C17,1,0),"") | AM17: =AD17/AN17 -> #DIV/0! | AN17: =Y17 -> #DIV/0!
A18: 1796 | B18: 1.4454545 | C18: =IF(B18>B17,"inflation",IF(B18<B17,"deflation","stable")) -> inflation | D18: =IF(I18>0,"expansive","contractive") -> expansive | E18: =IF(AND(C18="inflation",D18="expansive"),"inflationary expansion",IF(AND(C18="inflation",D18="contractive"),"stagflation",IF(AND(C18="deflation",D18="expansive"),"deflationary growth",IF(AND(C18="deflation",D18="contractive"),"recession",0)))) -> inflationary expansion | F18: =(B18-B17)/B17 -> 0.052980132 | G18: =J18/B18 -> 0.29283567 | H18: =G18-G17 -> 0.0085786341 | I18: =H18/G17 -> 0.030179144 | J18: 0.42328065 | K18: =J18-J17 -> 0.033073265 | L18: =K18/J17 -> 0.084758172 | M18: =L18-I18 -> 0.054579028 | N18: =IF(L18>I18, "inflation",IF(L18<I18, "deflation","stable")) -> inflation | O18: =IFERROR(IF(N18=C18,1,0),"") -> 1 | P18: =M18-F18 -> 0.0015988951 | Q18: =J18-J17 -> 0.033073265 | R18: =Q18/J17 -> 0.084758172 | T18: =(S18-S17)/S17 -> #DIV/0! | U18: =S18*Y18 -> #DIV/0! | V18: =(U18-U17)/U17 -> #DIV/0! | W18: =S18/B18 -> 0 | X18: =(W18-W17)/W17 -> #DIV/0! | Y18: =J18/S18 -> #DIV/0! | Z18: =(Y18-Y17)/Y17 -> #DIV/0! | AA18: =W18*Y18 -> #DIV/0! | AB18: =AA18-AA17 -> #DIV/0! | AC18: =AB18/AA17 -> #DIV/0! | AD18: =J18-AA18 -> #DIV/0! | AE18: =AA18+AD18 -> #DIV/0! | AF18: =(AE18-AE17)/AE17 -> #DIV/0! | AG18: =AF18-I18 -> #DIV/0! | AH18: =AF18-T19 -> #DIV/0! | AI18: =AF18-X18 -> #DIV/0! | AJ18: =AF18-Z18 -> #DIV/0! | AK18: =IF(AG18>0, "inflation",IF(AG18<0,"deflation","stable")) -> #DIV/0! | AL18: =IFERROR(IF(AK18=C18,1,0),"") | AM18: =AD18/AN18 -> #DIV/0! | AN18: =Y18 -> #DIV/0!
A19: 1797 | B19: 1.3909091 | C19: =IF(B19>B18,"inflation",IF(B19<B18,"deflation","stable")) -> deflation | D19: =IF(I19>0,"expansive","contractive") -> expansive | E19: =IF(AND(C19="inflation",D19="expansive"),"inflationary expansion",IF(AND(C19="inflation",D19="contractive"),"stagflation",IF(AND(C19="deflation",D19="expansive"),"deflationary growth",IF(AND(C19="deflation",D19="contractive"),"recession",0)))) -> deflationary growth | F19: =(B19-B18)/B18 -> -0.037735849 | G19: =J19/B19 -> 0.29824088 | H19: =G19-G18 -> 0.0054052131 | I19: =H19/G18 -> 0.018458179 | J19: 0.41482595 | K19: =J19-J18 -> -0.0084546946 | L19: =K19/J18 -> -0.019974205 | M19: =L19-I19 -> -0.038432384 | N19: =IF(L19>I19, "inflation",IF(L19<I19, "deflation","stable")) -> deflation | O19: =IFERROR(IF(N19=C19,1,0),"") -> 1 | P19: =M19-F19 -> -0.00069653504 | Q19: =J19-J18 -> -0.0084546946 | R19: =Q19/J18 -> -0.019974205 | T19: =(S19-S18)/S18 -> #DIV/0! | U19: =S19*Y19 -> #DIV/0! | V19: =(U19-U18)/U18 -> #DIV/0! | W19: =S19/B19 -> 0 | X19: =(W19-W18)/W18 -> #DIV/0! | Y19: =J19/S19 -> #DIV/0! | Z19: =(Y19-Y18)/Y18 -> #DIV/0! | AA19: =W19*Y19 -> #DIV/0! | AB19: =AA19-AA18 -> #DIV/0! | AC19: =AB19/AA18 -> #DIV/0! | AD19: =J19-AA19 -> #DIV/0! | AE19: =AA19+AD19 -> #DIV/0! | AF19: =(AE19-AE18)/AE18 -> #DIV/0! | AG19: =AF19-I19 -> #DIV/0! | AH19: =AF19-T20 -> #DIV/0! | AI19: =AF19-X19 -> #DIV/0! | AJ19: =AF19-Z19 -> #DIV/0! | AK19: =IF(AG19>0, "inflation",IF(AG19<0,"deflation","stable")) -> #DIV/0! | AL19: =IFERROR(IF(AK19=C19,1,0),"") | AM19: =AD19/AN19 -> #DIV/0! | AN19: =Y19 -> #DIV/0!
A20: 1798 | B20: 1.3454545 | C20: =IF(B20>B19,"inflation",IF(B20<B19,"deflation","stable")) -> deflation | D20: =IF(I20>0,"expansive","contractive") -> expansive | E20: =IF(AND(C20="inflation",D20="expansive"),"inflationary expansion",IF(AND(C20="inflation",D20="contractive"),"stagflation",IF(AND(C20="deflation",D20="expansive"),"deflationary growth",IF(AND(C20="deflation",D20="contractive"),"recession",0)))) -> deflationary growth | F20: =(B20-B19)/B19 -> -0.032679739 | G20: =J20/B20 -> 0.31054937 | H20: =G20-G19 -> 0.012308485 | I20: =H20/G19 -> 0.041270282 | J20: 0.41783006 | K20: =J20-J19 -> 0.003004104 | L20: =K20/J19 -> 0.0072418419 | M20: =L20-I20 -> -0.034028441 | N20: =IF(L20>I20, "inflation",IF(L20<I20, "deflation","stable")) -> deflation | O20: =IFERROR(IF(N20=C20,1,0),"") -> 1 | P20: =M20-F20 -> -0.001348702 | Q20: =J20-J19 -> 0.003004104 | R20: =Q20/J19 -> 0.0072418419 | T20: =(S20-S19)/S19 -> #DIV/0! | U20: =S20*Y20 -> #DIV/0! | V20: =(U20-U19)/U19 -> #DIV/0! | W20: =S20/B20 -> 0 | X20: =(W20-W19)/W19 -> #DIV/0! | Y20: =J20/S20 -> #DIV/0! | Z20: =(Y20-Y19)/Y19 -> #DIV/0! | AA20: =W20*Y20 -> #DIV/0! | AB20: =AA20-AA19 -> #DIV/0! | AC20: =AB20/AA19 -> #DIV/0! | AD20: =J20-AA20 -> #DIV/0! | AE20: =AA20+AD20 -> #DIV/0! | AF20: =(AE20-AE19)/AE19 -> #DIV/0! | AG20: =AF20-I20 -> #DIV/0! | AH20: =AF20-T21 -> #DIV/0! | AI20: =AF20-X20 -> #DIV/0! | AJ20: =AF20-Z20 -> #DIV/0! | AK20: =IF(AG20>0, "inflation",IF(AG20<0,"deflation","stable")) -> #DIV/0! | AL20: =IFERROR(IF(AK20=C20,1,0),"") | AM20: =AD20/AN20 -> #DIV/0! | AN20: =Y20 -> #DIV/0!
A21: 1799 | B21: 1.3454545 | C21: =IF(B21>B20,"inflation",IF(B21<B20,"deflation","stable")) -> stable | D21: =IF(I21>0,"expansive","contractive") -> expansive | E21: =IF(AND(C21="inflation",D21="expansive"),"inflationary expansion",IF(AND(C21="inflation",D21="contractive"),"stagflation",IF(AND(C21="deflation",D21="expansive"),"deflationary growth",IF(AND(C21="deflation",D21="contractive"),"recession",0)))) -> 0 | F21: =(B21-B20)/B20 -> 0 | G21: =J21/B21 -> 0.33193739 | H21: =G21-G20 -> 0.021388026 | I21: =H21/G20 -> 0.068871581 | J21: 0.44660667 | K21: =J21-J20 -> 0.028776617 | L21: =K21/J20 -> 0.068871581 | M21: =L21-I21 -> 0 | N21: =IF(L21>I21, "inflation",IF(L21<I21, "deflation","stable")) -> inflation | O21: =IFERROR(IF(N21=C21,1,0),"") -> 0 | P21: =M21-F21 -> 0 | Q21: =J21-J20 -> 0.028776617 | R21: =Q21/J20 -> 0.068871581 | T21: =(S21-S20)/S20 -> #DIV/0! | U21: =S21*Y21 -> #DIV/0! | V21: =(U21-U20)/U20 -> #DIV/0! | W21: =S21/B21 -> 0 | X21: =(W21-W20)/W20 -> #DIV/0! | Y21: =J21/S21 -> #DIV/0! | Z21: =(Y21-Y20)/Y20 -> #DIV/0! | AA21: =W21*Y21 -> #DIV/0! | AB21: =AA21-AA20 -> #DIV/0! | AC21: =AB21/AA20 -> #DIV/0! | AD21: =J21-AA21 -> #DIV/0! | AE21: =AA21+AD21 -> #DIV/0! | AF21: =(AE21-AE20)/AE20 -> #DIV/0! | AG21: =AF21-I21 -> #DIV/0! | AH21: =AF21-T22 -> #DIV/0! | AI21: =AF21-X21 -> #DIV/0! | AJ21: =AF21-Z21 -> #DIV/0! | AK21: =IF(AG21>0, "inflation",IF(AG21<0,"deflation","stable")) -> #DIV/0! | AL21: =IFERROR(IF(AK21=C21,1,0),"") | AM21: =AD21/AN21 -> #DIV/0! | AN21: =Y21 -> #DIV/0!
A22: 1800 | B22: 1.3837977 | C22: =IF(B22>B21,"inflation",IF(B22<B21,"deflation","stable")) -> inflation | D22: =IF(I22>0,"expansive","contractive") -> expansive | E22: =IF(AND(C22="inflation",D22="expansive"),"inflationary expansion",IF(AND(C22="inflation",D22="contractive"),"stagflation",IF(AND(C22="deflation",D22="expansive"),"deflationary growth",IF(AND(C22="deflation",D22="contractive"),"recession",0)))) -> inflationary expansion | F22: =(B22-B21)/B21 -> 0.028498256 | G22: =J22/B22 -> 0.35084877 | H22: =G22-G21 -> 0.018911375 | I22: =H22/G21 -> 0.056972716 | J22: 0.4855037 | K22: =J22-J21 -> 0.038897027 | L22: =K22/J21 -> 0.087094595 | M22: =L22-I22 -> 0.030121879 | N22: =IF(L22>I22, "inflation",IF(L22<I22, "deflation","stable")) -> inflation | O22: =IFERROR(IF(N22=C22,1,0),"") -> 1 | P22: =M22-F22 -> 0.0016236231 | Q22: =J22-J21 -> 0.038897027 | R22: =Q22/J21 -> 0.087094595 | S22: 0.028 | T22: =(S22-S21)/S21 -> #DIV/0! | U22: =S22*Y22 -> 0.4855037 | V22: =(U22-U21)/U21 -> #DIV/0! | W22: =S22/B22 -> 0.020234172 | X22: =(W22-W21)/W21 -> #DIV/0! | Y22: =J22/S22 -> 17.339418 | Z22: =(Y22-Y21)/Y21 -> #DIV/0! | AA22: =W22*Y22 -> 0.35084877 | AB22: =AA22-AA21 -> #DIV/0! | AC22: =AB22/AA21 -> #DIV/0! | AD22: =J22-AA22 -> 0.13465493 | AE22: =AA22+AD22 -> 0.4855037 | AF22: =(AE22-AE21)/AE21 -> #DIV/0! | AG22: =AF22-I22 -> #DIV/0! | AH22: =AF22-T23 -> #DIV/0! | AI22: =AF22-X22 -> #DIV/0! | AJ22: =AF22-Z22 -> #DIV/0! | AK22: =IF(AG22>0, "inflation",IF(AG22<0,"deflation","stable")) -> #DIV/0! | AL22: =IFERROR(IF(AK22=C22,1,0),"") | AM22: =AD22/AN22 -> 0.0077658278 | AN22: =Y22 -> 17.339418
A23: 1801 | B23: 1.4133431 | C23: =IF(B23>B22,"inflation",IF(B23<B22,"deflation","stable")) -> inflation | D23: =IF(I23>0,"expansive","contractive") -> expansive | E23: =IF(AND(C23="inflation",D23="expansive"),"inflationary expansion",IF(AND(C23="inflation",D23="contractive"),"stagflation",IF(AND(C23="deflation",D23="expansive"),"deflationary growth",IF(AND(C23="deflation",D23="contractive"),"recession",0)))) -> inflationary expansion | F23: =(B23-B22)/B22 -> 0.021350993 | G23: =J23/B23 -> 0.36794688 | H23: =G23-G22 -> 0.017098107 | I23: =H23/G22 -> 0.048733554 | J23: 0.52003518 | K23: =J23-J22 -> 0.034531479 | L23: =K23/J22 -> 0.071125057 | M23: =L23-I23 -> 0.022391503 | N23: =IF(L23>I23, "inflation",IF(L23<I23, "deflation","stable")) -> inflation | O23: =IFERROR(IF(N23=C23,1,0),"") -> 1 | P23: =M23-F23 -> 0.0010405098 | Q23: =J23-J22 -> 0.034531479 | R23: =Q23/J22 -> 0.071125057 | S23: 0 | T23: =(S23-S22)/S22 -> -1 | U23: =S23*Y23 -> #DIV/0! | V23: =(U23-U22)/U22 -> #DIV/0! | W23: =S23/B23 -> 0 | X23: =(W23-W22)/W22 -> -1 | Y23: =J23/S23 -> #DIV/0! | Z23: =(Y23-Y22)/Y22 -> #DIV/0! | AA23: =W23*Y23 -> #DIV/0! | AB23: =AA23-AA22 -> #DIV/0! | AC23: =AB23/AA22 -> #DIV/0! | AD23: =J23-AA23 -> #DIV/0! | AE23: =AA23+AD23 -> #DIV/0! | AF23: =(AE23-AE22)/AE22 -> #DIV/0! | AG23: =AF23-I23 -> #DIV/0! | AH23: =AF23-T24 -> #DIV/0! | AI23: =AF23-X23 -> #DIV/0! | AJ23: =AF23-Z23 -> #DIV/0! | AK23: =IF(AG23>0, "inflation",IF(AG23<0,"deflation","stable")) -> #DIV/0! | AL23: =IFERROR(IF(AK23=C23,1,0),"") | AM23: =AD23/AN23 -> #DIV/0! | AN23: =Y23 -> #DIV/0!
A24: 1802 | B24: 1.2010997 | C24: =IF(B24>B23,"inflation",IF(B24<B23,"deflation","stable")) -> deflation | D24: =IF(I24>0,"expansive","contractive") -> expansive | E24: =IF(AND(C24="inflation",D24="expansive"),"inflationary expansion",IF(AND(C24="inflation",D24="contractive"),"stagflation",IF(AND(C24="deflation",D24="expansive"),"deflationary growth",IF(AND(C24="deflation",D24="contractive"),"recession",0)))) -> deflationary growth | F24: =(B24-B23)/B23 -> -0.15017118 | G24: =J24/B24 -> 0.37951843 | H24: =G24-G23 -> 0.011571554 | I24: =H24/G23 -> 0.031448979 | J24: 0.45583947 | K24: =J24-J23 -> -0.064195707 | L24: =K24/J23 -> -0.12344493 | M24: =L24-I24 -> -0.15489391 | N24: =IF(L24>I24, "inflation",IF(L24<I24, "deflation","stable")) -> deflation | O24: =IFERROR(IF(N24=C24,1,0),"") -> 1 | P24: =M24-F24 -> -0.0047227303 | Q24: =J24-J23 -> -0.064195707 | R24: =Q24/J23 -> -0.12344493 | S24: 0 | T24: =(S24-S23)/S23 -> #DIV/0! | U24: =S24*Y24 -> #DIV/0! | V24: =(U24-U23)/U23 -> #DIV/0! | W24: =S24/B24 -> 0 | X24: =(W24-W23)/W23 -> #DIV/0! | Y24: =J24/S24 -> #DIV/0! | Z24: =(Y24-Y23)/Y23 -> #DIV/0! | AA24: =W24*Y24 -> #DIV/0! | AB24: =AA24-AA23 -> #DIV/0! | AC24: =AB24/AA23 -> #DIV/0! | AD24: =J24-AA24 -> #DIV/0! | AE24: =AA24+AD24 -> #DIV/0! | AF24: =(AE24-AE23)/AE23 -> #DIV/0! | AG24: =AF24-I24 -> #DIV/0! | AH24: =AF24-T25 -> #DIV/0! | AI24: =AF24-X24 -> #DIV/0! | AJ24: =AF24-Z24 -> #DIV/0! | AK24: =IF(AG24>0, "inflation",IF(AG24<0,"deflation","stable")) -> #DIV/0! | AL24: =IFERROR(IF(AK24=C24,1,0),"") | AM24: =AD24/AN24 -> #DIV/0! | AN24: =Y24 -> #DIV/0!
A25: 1803 | B25: 1.2762463 | C25: =IF(B25>B24,"inflation",IF(B25<B24,"deflation","stable")) -> inflation | D25: =IF(I25>0,"expansive","contractive") -> expansive | E25: =IF(AND(C25="inflation",D25="expansive"),"inflationary expansion",IF(AND(C25="inflation",D25="contractive"),"stagflation",IF(AND(C25="deflation",D25="expansive"),"deflationary growth",IF(AND(C25="deflation",D25="contractive"),"recession",0)))) -> inflationary expansion | F25: =(B25-B24)/B24 -> 0.062564854 | G25: =J25/B25 -> 0.38595236 | H25: =G25-G24 -> 0.0064339303 | I25: =H25/G24 -> 0.01695288 | J25: 0.49257028 | K25: =J25-J24 -> 0.03673081 | L25: =K25/J24 -> 0.080578388 | M25: =L25-I25 -> 0.063625508 | N25: =IF(L25>I25, "inflation",IF(L25<I25, "deflation","stable")) -> inflation | O25: =IFERROR(IF(N25=C25,1,0),"") -> 1 | P25: =M25-F25 -> 0.0010606544 | Q25: =J25-J24 -> 0.03673081 | R25: =Q25/J24 -> 0.080578388 | S25: 0 | T25: =(S25-S24)/S24 -> #DIV/0! | U25: =S25*Y25 -> #DIV/0! | V25: =(U25-U24)/U24 -> #DIV/0! | W25: =S25/B25 -> 0 | X25: =(W25-W24)/W24 -> #DIV/0! | Y25: =J25/S25 -> #DIV/0! | Z25: =(Y25-Y24)/Y24 -> #DIV/0! | AA25: =W25*Y25 -> #DIV/0! | AB25: =AA25-AA24 -> #DIV/0! | AC25: =AB25/AA24 -> #DIV/0! | AD25: =J25-AA25 -> #DIV/0! | AE25: =AA25+AD25 -> #DIV/0! | AF25: =(AE25-AE24)/AE24 -> #DIV/0! | AG25: =AF25-I25 -> #DIV/0! | AH25: =AF25-T26 -> #DIV/0! | AI25: =AF25-X25 -> #DIV/0! | AJ25: =AF25-Z25 -> #DIV/0! | AK25: =IF(AG25>0, "inflation",IF(AG25<0,"deflation","stable")) -> #DIV/0! | AL25: =IFERROR(IF(AK25=C25,1,0),"") | AM25: =AD25/AN25 -> #DIV/0! | AN25: =Y25 -> #DIV/0!
A26: 1804 | B26: 1.3429619 | C26: =IF(B26>B25,"inflation",IF(B26<B25,"deflation","stable")) -> inflation | D26: =IF(I26>0,"expansive","contractive") -> expansive | E26: =IF(AND(C26="inflation",D26="expansive"),"inflationary expansion",IF(AND(C26="inflation",D26="contractive"),"stagflation",IF(AND(C26="deflation",D26="expansive"),"deflationary growth",IF(AND(C26="deflation",D26="contractive"),"recession",0)))) -> inflationary expansion | F26: =(B26-B25)/B25 -> 0.052274816 | G26: =J26/B26 -> 0.40093907 | H26: =G26-G25 -> 0.014986707 | I26: =H26/G25 -> 0.038830458 | J26: 0.53844588 | K26: =J26-J25 -> 0.045875597 | L26: =K26/J25 -> 0.093135129 | M26: =L26-I26 -> 0.054304671 | N26: =IF(L26>I26, "inflation",IF(L26<I26, "deflation","stable")) -> inflation | O26: =IFERROR(IF(N26=C26,1,0),"") -> 1 | P26: =M26-F26 -> 0.0020298551 | Q26: =J26-J25 -> 0.045875597 | R26: =Q26/J25 -> 0.093135129 | S26: 0 | T26: =(S26-S25)/S25 -> #DIV/0! | U26: =S26*Y26 -> #DIV/0! | V26: =(U26-U25)/U25 -> #DIV/0! | W26: =S26/B26 -> 0 | X26: =(W26-W25)/W25 -> #DIV/0! | Y26: =J26/S26 -> #DIV/0! | Z26: =(Y26-Y25)/Y25 -> #DIV/0! | AA26: =W26*Y26 -> #DIV/0! | AB26: =AA26-AA25 -> #DIV/0! | AC26: =AB26/AA25 -> #DIV/0! | AD26: =J26-AA26 -> #DIV/0! | AE26: =AA26+AD26 -> #DIV/0! | AF26: =(AE26-AE25)/AE25 -> #DIV/0! | AG26: =AF26-I26 -> #DIV/0! | AH26: =AF26-T27 -> #DIV/0! | AI26: =AF26-X26 -> #DIV/0! | AJ26: =AF26-Z26 -> #DIV/0! | AK26: =IF(AG26>0, "inflation",IF(AG26<0,"deflation","stable")) -> #DIV/0! | AL26: =IFERROR(IF(AK26=C26,1,0),"") | AM26: =AD26/AN26 -> #DIV/0! | AN26: =Y26 -> #DIV/0!
A27: 1805 | B27: 1.3438416 | C27: =IF(B27>B26,"inflation",IF(B27<B26,"deflation","stable")) -> inflation | D27: =IF(I27>0,"expansive","contractive") -> expansive | E27: =IF(AND(C27="inflation",D27="expansive"),"inflationary expansion",IF(AND(C27="inflation",D27="contractive"),"stagflation",IF(AND(C27="deflation",D27="expansive"),"deflationary growth",IF(AND(C27="deflation",D27="contractive"),"recession",0)))) -> inflationary expansion | F27: =(B27-B26)/B26 -> 0.00065509335 | G27: =J27/B27 -> 0.42218369 | H27: =G27-G26 -> 0.021244621 | I27: =H27/G26 -> 0.052987156 | J27: 0.56734802 | K27: =J27-J26 -> 0.028902139 | L27: =K27/J26 -> 0.053676961 | M27: =L27-I27 -> 0.00068980488 | N27: =IF(L27>I27, "inflation",IF(L27<I27, "deflation","stable")) -> inflation | O27: =IFERROR(IF(N27=C27,1,0),"") -> 1 | P27: =M27-F27 -> 3.4711534e-05 | Q27: =J27-J26 -> 0.028902139 | R27: =Q27/J26 -> 0.053676961 | S27: 0 | T27: =(S27-S26)/S26 -> #DIV/0! | U27: =S27*Y27 -> #DIV/0! | V27: =(U27-U26)/U26 -> #DIV/0! | W27: =S27/B27 -> 0 | X27: =(W27-W26)/W26 -> #DIV/0! | Y27: =J27/S27 -> #DIV/0! | Z27: =(Y27-Y26)/Y26 -> #DIV/0! | AA27: =W27*Y27 -> #DIV/0! | AB27: =AA27-AA26 -> #DIV/0! | AC27: =AB27/AA26 -> #DIV/0! | AD27: =J27-AA27 -> #DIV/0! | AE27: =AA27+AD27 -> #DIV/0! | AF27: =(AE27-AE26)/AE26 -> #DIV/0! | AG27: =AF27-I27 -> #DIV/0! | AH27: =AF27-T28 -> #DIV/0! | AI27: =AF27-X27 -> #DIV/0! | AJ27: =AF27-Z27 -> #DIV/0! | AK27: =IF(AG27>0, "inflation",IF(AG27<0,"deflation","stable")) -> #DIV/0! | AL27: =IFERROR(IF(AK27=C27,1,0),"") | AM27: =AD27/AN27 -> #DIV/0! | AN27: =Y27 -> #DIV/0!
A28: 1806 | B28: 1.4118035 | C28: =IF(B28>B27,"inflation",IF(B28<B27,"deflation","stable")) -> inflation | D28: =IF(I28>0,"expansive","contractive") -> expansive | E28: =IF(AND(C28="inflation",D28="expansive"),"inflationary expansion",IF(AND(C28="inflation",D28="contractive"),"stagflation",IF(AND(C28="deflation",D28="expansive"),"deflationary growth",IF(AND(C28="deflation",D28="contractive"),"recession",0)))) -> inflationary expansion | F28: =(B28-B27)/B27 -> 0.050572831 | G28: =J28/B28 -> 0.4421442 | H28: =G28-G27 -> 0.019960508 | I28: =H28/G27 -> 0.047279202 | J28: 0.62422073 | K28: =J28-J27 -> 0.056872711 | L28: =K28/J27 -> 0.10024308 | M28: =L28-I28 -> 0.052963875 | N28: =IF(L28>I28, "inflation",IF(L28<I28, "deflation","stable")) -> inflation | O28: =IFERROR(IF(N28=C28,1,0),"") -> 1 | P28: =M28-F28 -> 0.0023910431 | Q28: =J28-J27 -> 0.056872711 | R28: =Q28/J27 -> 0.10024308 | S28: 0 | T28: =(S28-S27)/S27 -> #DIV/0! | U28: =S28*Y28 -> #DIV/0! | V28: =(U28-U27)/U27 -> #DIV/0! | W28: =S28/B28 -> 0 | X28: =(W28-W27)/W27 -> #DIV/0! | Y28: =J28/S28 -> #DIV/0! | Z28: =(Y28-Y27)/Y27 -> #DIV/0! | AA28: =W28*Y28 -> #DIV/0! | AB28: =AA28-AA27 -> #DIV/0! | AC28: =AB28/AA27 -> #DIV/0! | AD28: =J28-AA28 -> #DIV/0! | AE28: =AA28+AD28 -> #DIV/0! | AF28: =(AE28-AE27)/AE27 -> #DIV/0! | AG28: =AF28-I28 -> #DIV/0! | AH28: =AF28-T29 -> #DIV/0! | AI28: =AF28-X28 -> #DIV/0! | AJ28: =AF28-Z28 -> #DIV/0! | AK28: =IF(AG28>0, "inflation",IF(AG28<0,"deflation","stable")) -> #DIV/0! | AL28: =IFERROR(IF(AK28=C28,1,0),"") | AM28: =AD28/AN28 -> #DIV/0! | AN28: =Y28 -> #DIV/0!
A29: 1807 | B29: 1.3451613 | C29: =IF(B29>B28,"inflation",IF(B29<B28,"deflation","stable")) -> deflation | D29: =IF(I29>0,"expansive","contractive") -> expansive | E29: =IF(AND(C29="inflation",D29="expansive"),"inflationary expansion",IF(AND(C29="inflation",D29="contractive"),"stagflation",IF(AND(C29="deflation",D29="expansive"),"deflationary growth",IF(AND(C29="deflation",D29="contractive"),"recession",0)))) -> deflationary growth | F29: =(B29-B28)/B28 -> -0.047203614 | G29: =J29/B29 -> 0.44255534 | H29: =G29-G28 -> 0.00041114192 | I29: =H29/G28 -> 0.00092988199 | J29: 0.59530831 | K29: =J29-J28 -> -0.028912422 | L29: =K29/J28 -> -0.046317626 | M29: =L29-I29 -> -0.047247508 | N29: =IF(L29>I29, "inflation",IF(L29<I29, "deflation","stable")) -> deflation | O29: =IFERROR(IF(N29=C29,1,0),"") -> 1 | P29: =M29-F29 -> -4.3893791e-05 | Q29: =J29-J28 -> -0.028912422 | R29: =Q29/J28 -> -0.046317626 | S29: 0 | T29: =(S29-S28)/S28 -> #DIV/0! | U29: =S29*Y29 -> #DIV/0! | V29: =(U29-U28)/U28 -> #DIV/0! | W29: =S29/B29 -> 0 | X29: =(W29-W28)/W28 -> #DIV/0! | Y29: =J29/S29 -> #DIV/0! | Z29: =(Y29-Y28)/Y28 -> #DIV/0! | AA29: =W29*Y29 -> #DIV/0! | AB29: =AA29-AA28 -> #DIV/0! | AC29: =AB29/AA28 -> #DIV/0! | AD29: =J29-AA29 -> #DIV/0! | AE29: =AA29+AD29 -> #DIV/0! | AF29: =(AE29-AE28)/AE28 -> #DIV/0! | AG29: =AF29-I29 -> #DIV/0! | AH29: =AF29-T30 -> #DIV/0! | AI29: =AF29-X29 -> #DIV/0! | AJ29: =AF29-Z29 -> #DIV/0! | AK29: =IF(AG29>0, "inflation",IF(AG29<0,"deflation","stable")) -> #DIV/0! | AL29: =IFERROR(IF(AK29=C29,1,0),"") | AM29: =AD29/AN29 -> #DIV/0! | AN29: =Y29 -> #DIV/0!
A30: 1808 | B30: 1.4723607 | C30: =IF(B30>B29,"inflation",IF(B30<B29,"deflation","stable")) -> inflation | D30: =IF(I30>0,"expansive","contractive") -> expansive | E30: =IF(AND(C30="inflation",D30="expansive"),"inflationary expansion",IF(AND(C30="inflation",D30="contractive"),"stagflation",IF(AND(C30="deflation",D30="expansive"),"deflationary growth",IF(AND(C30="deflation",D30="contractive"),"recession",0)))) -> inflationary expansion | F30: =(B30-B29)/B29 -> 0.094560715 | G30: =J30/B30 -> 0.44354292 | H30: =G30-G29 -> 0.00098758551 | I30: =H30/G29 -> 0.0022315526 | J30: 0.65305517 | K30: =J30-J29 -> 0.057746861 | L30: =K30/J29 -> 0.097003285 | M30: =L30-I30 -> 0.094771732 | N30: =IF(L30>I30, "inflation",IF(L30<I30, "deflation","stable")) -> inflation | O30: =IFERROR(IF(N30=C30,1,0),"") -> 1 | P30: =M30-F30 -> 0.00021101721 | Q30: =J30-J29 -> 0.057746861 | R30: =Q30/J29 -> 0.097003285 | S30: 0 | T30: =(S30-S29)/S29 -> #DIV/0! | U30: =S30*Y30 -> #DIV/0! | V30: =(U30-U29)/U29 -> #DIV/0! | W30: =S30/B30 -> 0 | X30: =(W30-W29)/W29 -> #DIV/0! | Y30: =J30/S30 -> #DIV/0! | Z30: =(Y30-Y29)/Y29 -> #DIV/0! | AA30: =W30*Y30 -> #DIV/0! | AB30: =AA30-AA29 -> #DIV/0! | AC30: =AB30/AA29 -> #DIV/0! | AD30: =J30-AA30 -> #DIV/0! | AE30: =AA30+AD30 -> #DIV/0! | AF30: =(AE30-AE29)/AE29 -> #DIV/0! | AG30: =AF30-I30 -> #DIV/0! | AH30: =AF30-T31 -> #DIV/0! | AI30: =AF30-X30 -> #DIV/0! | AJ30: =AF30-Z30 -> #DIV/0! | AK30: =IF(AG30>0, "inflation",IF(AG30<0,"deflation","stable")) -> #DIV/0! | AL30: =IFERROR(IF(AK30=C30,1,0),"") | AM30: =AD30/AN30 -> #DIV/0! | AN30: =Y30 -> #DIV/0!
A31: 1809 | B31: 1.4539589 | C31: =IF(B31>B30,"inflation",IF(B31<B30,"deflation","stable")) -> deflation | D31: =IF(I31>0,"expansive","contractive") -> expansive | E31: =IF(AND(C31="inflation",D31="expansive"),"inflationary expansion",IF(AND(C31="inflation",D31="contractive"),"stagflation",IF(AND(C31="deflation",D31="expansive"),"deflationary growth",IF(AND(C31="deflation",D31="contractive"),"recession",0)))) -> deflationary growth | F31: =(B31-B30)/B30 -> -0.012498133 | G31: =J31/B31 -> 0.4774725 | H31: =G31-G30 -> 0.033929578 | I31: =H31/G30 -> 0.076496718 | J31: 0.69422541 | K31: =J31-J30 -> 0.041170243 | L31: =K31/J30 -> 0.063042519 | M31: =L31-I31 -> -0.013454199 | N31: =IF(L31>I31, "inflation",IF(L31<I31, "deflation","stable")) -> deflation | O31: =IFERROR(IF(N31=C31,1,0),"") -> 1 | P31: =M31-F31 -> -0.00095606613 | Q31: =J31-J30 -> 0.041170243 | R31: =Q31/J30 -> 0.063042519 | S31: 0 | T31: =(S31-S30)/S30 -> #DIV/0! | U31: =S31*Y31 -> #DIV/0! | V31: =(U31-U30)/U30 -> #DIV/0! | W31: =S31/B31 -> 0 | X31: =(W31-W30)/W30 -> #DIV/0! | Y31: =J31/S31 -> #DIV/0! | Z31: =(Y31-Y30)/Y30 -> #DIV/0! | AA31: =W31*Y31 -> #DIV/0! | AB31: =AA31-AA30 -> #DIV/0! | AC31: =AB31/AA30 -> #DIV/0! | AD31: =J31-AA31 -> #DIV/0! | AE31: =AA31+AD31 -> #DIV/0! | AF31: =(AE31-AE30)/AE30 -> #DIV/0! | AG31: =AF31-I31 -> #DIV/0! | AH31: =AF31-T32 -> #DIV/0! | AI31: =AF31-X31 -> #DIV/0! | AJ31: =AF31-Z31 -> #DIV/0! | AK31: =IF(AG31>0, "inflation",IF(AG31<0,"deflation","stable")) -> #DIV/0! | AL31: =IFERROR(IF(AK31=C31,1,0),"") | AM31: =AD31/AN31 -> #DIV/0! | AN31: =Y31 -> #DIV/0!
A32: 1810 | B32: 1.4166703 | C32: =IF(B32>B31,"inflation",IF(B32<B31,"deflation","stable")) -> deflation | D32: =IF(I32>0,"expansive","contractive") -> expansive | E32: =IF(AND(C32="inflation",D32="expansive"),"inflationary expansion",IF(AND(C32="inflation",D32="contractive"),"stagflation",IF(AND(C32="deflation",D32="expansive"),"deflationary growth",IF(AND(C32="deflation",D32="contractive"),"recession",0)))) -> deflationary growth | F32: =(B32-B31)/B31 -> -0.025646278 | G32: =J32/B32 -> 0.50392749 | H32: =G32-G31 -> 0.026454989 | I32: =H32/G31 -> 0.055406309 | J32: 0.71389911 | K32: =J32-J31 -> 0.019673699 | L32: =K32/J31 -> 0.028339065 | M32: =L32-I32 -> -0.027067244 | N32: =IF(L32>I32, "inflation",IF(L32<I32, "deflation","stable")) -> deflation | O32: =IFERROR(IF(N32=C32,1,0),"") -> 1 | P32: =M32-F32 -> -0.0014209656 | Q32: =J32-J31 -> 0.019673699 | R32: =Q32/J31 -> 0.028339065 | S32: 0.058 | T32: =(S32-S31)/S31 -> #DIV/0! | U32: =S32*Y32 -> 0.71389911 | V32: =(U32-U31)/U31 -> #DIV/0! | W32: =S32/B32 -> 0.040941071 | X32: =(W32-W31)/W31 -> #DIV/0! | Y32: =J32/S32 -> 12.308605 | Z32: =(Y32-Y31)/Y31 -> #DIV/0! | AA32: =W32*Y32 -> 0.50392749 | AB32: =AA32-AA31 -> #DIV/0! | AC32: =AB32/AA31 -> #DIV/0! | AD32: =J32-AA32 -> 0.20997162 | AE32: =AA32+AD32 -> 0.71389911 | AF32: =(AE32-AE31)/AE31 -> #DIV/0! | AG32: =AF32-I32 -> #DIV/0! | AH32: =AF32-T33 -> #DIV/0! | AI32: =AF32-X32 -> #DIV/0! | AJ32: =AF32-Z32 -> #DIV/0! | AK32: =IF(AG32>0, "inflation",IF(AG32<0,"deflation","stable")) -> #DIV/0! | AL32: =IFERROR(IF(AK32=C32,1,0),"") | AM32: =AD32/AN32 -> 0.017058929 | AN32: =Y32 -> 12.308605
A33: 1811 | B33: 1.4725831 | C33: =IF(B33>B32,"inflation",IF(B33<B32,"deflation","stable")) -> inflation | D33: =IF(I33>0,"expansive","contractive") -> expansive | E33: =IF(AND(C33="inflation",D33="expansive"),"inflationary expansion",IF(AND(C33="inflation",D33="contractive"),"stagflation",IF(AND(C33="deflation",D33="expansive"),"deflationary growth",IF(AND(C33="deflation",D33="contractive"),"recession",0)))) -> inflationary expansion | F33: =(B33-B32)/B32 -> 0.039467777 | G33: =J33/B33 -> 0.52683857 | H33: =G33-G32 -> 0.022911085 | I33: =H33/G32 -> 0.045465044 | J33: 0.7758136 | K33: =J33-J32 -> 0.061914489 | L33: =K33/J32 -> 0.086727225 | M33: =L33-I33 -> 0.041262182 | N33: =IF(L33>I33, "inflation",IF(L33<I33, "deflation","stable")) -> inflation | O33: =IFERROR(IF(N33=C33,1,0),"") -> 1 | P33: =M33-F33 -> 0.0017944042 | Q33: =J33-J32 -> 0.061914489 | R33: =Q33/J32 -> 0.086727225 | S33: 0 | T33: =(S33-S32)/S32 -> -1 | U33: =S33*Y33 -> #DIV/0! | V33: =(U33-U32)/U32 -> #DIV/0! | W33: =S33/B33 -> 0 | X33: =(W33-W32)/W32 -> -1 | Y33: =J33/S33 -> #DIV/0! | Z33: =(Y33-Y32)/Y32 -> #DIV/0! | AA33: =W33*Y33 -> #DIV/0! | AB33: =AA33-AA32 -> #DIV/0! | AC33: =AB33/AA32 -> #DIV/0! | AD33: =J33-AA33 -> #DIV/0! | AE33: =AA33+AD33 -> #DIV/0! | AF33: =(AE33-AE32)/AE32 -> #DIV/0! | AG33: =AF33-I33 -> #DIV/0! | AH33: =AF33-T34 -> #DIV/0! | AI33: =AF33-X33 -> #DIV/0! | AJ33: =AF33-Z33 -> #DIV/0! | AK33: =IF(AG33>0, "inflation",IF(AG33<0,"deflation","stable")) -> #DIV/0! | AL33: =IFERROR(IF(AK33=C33,1,0),"") | AM33: =AD33/AN33 -> #DIV/0! | AN33: =Y33 -> #DIV/0!
... A244: 2022 | B244: 30.432385 | C244: =IF(B244>B243,"inflation",IF(B244<B243,"deflation","stable")) -> inflation | D244: =IF(I244>0,"expansive","contractive") -> expansive | E244: =IF(AND(C244="inflation",D244="expansive"),"inflationary expansion",IF(AND(C244="inflation",D244="contractive"),"stagflation",IF(AND(C244="deflation",D244="expansive"),"deflationary growth",IF(AND(C244="deflation",D244="contractive"),"recession",0)))) -> inflationary expansion | F244: =(B244-B243)/B243 -> 0.070549809 | G244: =J244/B244 -> 845.94447 | H244: =G244-G243 -> 15.954142 | I244: =H244/G243 -> 0.019222082 | J244: 25744.108 | K244: =J244-J243 -> 2150.077 | L244: =K244/J243 -> 0.091128006 | M244: =L244-I244 -> 0.071905924 | N244: =IF(L244>I244, "inflation",IF(L244<I244, "deflation","stable")) -> inflation | O244: =IFERROR(IF(N244=C244,1,0),"") -> 1 | P244: =M244-F244 -> 0.0013561142 | Q244: =J244-J243 -> 2150.077 | R244: =Q244/J243 -> 0.091128006 | S244: 21031.424 | T244: =(S244-S243)/S243 -> 0.12720601 | U244: =S244*Y244 -> 25744.108 | V244: =(U244-U243)/U243 -> 0.091128006 | W244: =S244/B244 -> 691.08693 | X244: =(W244-W243)/W243 -> 0.052922527 | Y244: =J244/S244 -> 1.2240782 | Z244: =(Y244-Y243)/Y243 -> -0.032006576 | AA244: =W244*Y244 -> 845.94447 | AB244: =AA244-AA243 -> 15.954142 | AC244: =AB244/AA243 -> 0.019222082 | AD244: =J244-AA244 -> 24898.164 | AE244: =AA244+AD244 -> 25744.108 | AF244: =(AE244-AE243)/AE243 -> 0.091128006 | AG244: =AF244-I244 -> 0.071905924 | AH244: =AF244-T245 -> 0.091128006 | AI244: =AF244-X244 -> 0.038205479 | AJ244: =AF244-Z244 -> 0.12313458 | AK244: =IF(AG244>0, "inflation",IF(AG244<0,"deflation","stable")) -> inflation | AL244: =IFERROR(IF(AK244=C244,1,0),"") -> 1 | AM244: =AD244/AN244 -> 20340.337 | AN244: =Y244 -> 1.2240782
N246: Matches | O246: =SUM(O3:O244) -> 231 | AK246: Matches | AL246: =SUM(AL3:AL244) -> 192
N247: Count | O247: =COUNT(O3:O244) -> 232 | AK247: Count | AL247: =COUNT(AL3:AL244) -> 192
N248: Economic Themal Dynamic Accuracy (Left Side PQ) | O248: =O246/O247 -> 0.99568966 | AK248: Economic Themal Dynamic Accuracy (Right Side MV+FAC) | AL248: =AL246/AL247 -> 1
A252: Source:
A254: Nominal GDP (PQ) and Price (P):
A255: 1790-2022:
A256: GDP deflator was scaled to 1970
A257: https://www.measuringworth.com/datasets/usgdp/newGDP.xlsx
A258: Construction of Annual GDP, 1790–1928” was composed by the team behind MeasuringWorth,
A259: a research initiative focused economists and historians, including:
A260: Louis Johnston and Samuel H. Williamson, who are credited with the compilation and publication of the GDP series.
A262: The document also references extensive work by scholars such as Gallman, Weiss, Kendrick, McCusker, and others,
A263: indicating collaboration or reliance on historical economic research from institutions like the
A264: National Bureau of Economic Research (NBER) and various universities
A267: Money Supply Calculation:
... A280: Federal Reserve Bank of St. Louis

Sheet United States
B1: =VLOOKUP(C1,PQ!A6:B271,2,FALSE) -> USA | C1: United States | H1: =IFERROR(B3+B4,"wrong") -> 2.0113897
A2: Period | B2: P | C2: Observe | D2: Economy | E2: Diagnosis | F2: Δ P % | G2: Q | H2: Δ Q | I2: Δ Q % | J2: PQ | K2: Δ PQ | L2: Δ PQ % | M2: Δ PQ % - Δ Q % | N2: test | O2: match? | P2: (Δ PQ % - Δ Q %) -Δ P % = Δ P x Δ Q (interaction) | Q2: ΔPQ | R2: Δ%PQ | S2: M | T2: ΔM % | U2: MV | V2: ΔMV % | W2: M(d.) | X2: ΔM(d.) % | Y2: V | Z2: Δ V % | AA2: MV(d.) | AB2: ΔMV(d.) | AC2: Δ%MV(d.) | AD2: PQ-MV(d.) (FAC) | AE2: MV(d.) + FAC | AF2: Δ MV(d.)+FAC % | AG2: Δ MV(d.)+FAC % - Δ Q % | AH2: Δ MV(d.)+FAC % - Δ M % | AI2: Δ MV(d.)+FAC % - Δ M % | AJ2: Δ MV(d.)+FAC % - Δ V % | AK2: test | AL2: match? | AM2: M_FAC | AN2: V_FAC
A3: 1960 | B3: =INDEX(p, MATCH($B$1, 'p2'!$B$5:$B$271, 0), MATCH(A3, 'p2'!$A$5:$BQ$5, 0)) -> 1 | G3: =J3/B3 -> 5.4239048e+11 | H3: =G3-G2 -> #VALUE! | I3: =H3-H2 -> #VALUE! | J3: =INDEX(PQ, MATCH($B$1, PQ!$B$5:$B$271, 0), MATCH(A3, PQ!$A$5:$BQ$5, 0)) -> 5.4239048e+11 | K3: =J3-J2 -> #VALUE! | L3: =(K3-K2)/K2 -> #VALUE! | M3: =L3-I3 -> #VALUE! | S3: =INDEX(m, MATCH($B$1, 'M stock'!$B$5:$B$271, 0), MATCH(A3, 'M stock'!$A$5:$BQ$5, 0)) -> 3.26239e+11 | U3: =S3*Y3 -> 5.4239048e+11 | W3: =S3/B3 -> 3.26239e+11 | Y3: =J3/S3 -> 1.6625556 | AA3: =W3*Y3 -> 5.4239048e+11 | AD3: =J3-AA3 -> 0 | AE3: =AA3+AD3 -> 5.4239048e+11 | AG3: =AF3-I3 -> #VALUE! | AH3: =AF3-T4 -> -0.081946058 | AI3: =AF3-X3 -> 0 | AJ3: =AF3-Z3 -> 0
A4: 1961 | B4: =INDEX(p, MATCH($B$1, 'p2'!$B$5:$B$271, 0), MATCH(A4, 'p2'!$A$5:$BQ$5, 0)) -> 1.0113897 | C4: =IF(B4>B3,"inflation",IF(B4<B3,"deflation","stable")) -> inflation | D4: =IF(I4>0,"expansive","contractive") -> expansive | E4: =IF(AND(C4="inflation",D4="expansive"),"inflationary expansion",IF(AND(C4="inflation",D4="contractive"),"stagflation",IF(AND(C4="deflation",D4="expansive"),"deflationary growth",IF(AND(C4="deflation",D4="contractive"),"recession",0)))) -> inflationary expansion | F4: =(B4-B3)/B3 -> 0.011389667 | G4: =J4/B4 -> 5.5630465e+11 | H4: =G4-G3 -> 1.3914179e+10 | I4: =H4/G3 -> 0.025653435 | J4: =INDEX(PQ, MATCH($B$1, PQ!$B$5:$B$271, 0), MATCH(A4, PQ!$A$5:$BQ$5, 0)) -> 5.6264078e+11 | K4: =J4-J3 -> 2.0250303e+10 | L4: =K4/J3 -> 0.037335286 | M4: =L4-I4 -> 0.011681851 | N4: =IF(L4>I4, "inflation",IF(L4<I4, "deflation","stable")) -> inflation | O4: =IFERROR(IF(N4=C4,1,0),"") -> 1 | P4: =M4-F4 -> 0.00029218407 | Q4: =J4-J3 -> 2.0250303e+10 | R4: =Q4/J3 -> 0.037335286 | S4: =INDEX(m, MATCH($B$1, 'M stock'!$B$5:$B$271, 0), MATCH(A4, 'M stock'!$A$5:$BQ$5, 0)) -> 3.52973e+11 | T4: =(S4-S3)/S3 -> 0.081946058 | U4: =S4*Y4 -> 5.6264078e+11 | V4: =(U4-U3)/U3 -> 0.037335286 | W4: =S4/B4 -> 3.4899803e+11 | X4: =(W4-W3)/W3 -> 0.069761827 | Y4: =J4/S4 -> 1.5940051 | Z4: =(Y4-Y3)/Y3 -> -0.041231975 | AA4: =W4*Y4 -> 5.5630465e+11 | AB4: =AA4-AA3 -> 1.3914179e+10 | AC4: =AB4/AA3 -> 0.025653435 | AD4: =J4-AA4 -> 6.3361245e+09 | AE4: =AA4+AD4 -> 5.6264078e+11 | AF4: =(AE4-AE3)/AE3 -> 0.037335286 | AG4: =AF4-I4 -> 0.011681851 | AH4: =AF4-T5 -> -0.052002992 | AI4: =AF4-X4 -> -0.032426542 | AJ4: =AF4-Z4 -> 0.07856726 | AK4: =IF(AG4>0, "inflation",IF(AG4<0,"deflation","stable")) -> inflation | AL4: =IFERROR(IF(AK4=C4,1,0),"") -> 1 | AM4: =AD4/AN4 -> 3.9749712e+09 | AN4: =Y4 -> 1.5940051
A5: 1962 | B5: =INDEX(p, MATCH($B$1, 'p2'!$B$5:$B$271, 0), MATCH(A5, 'p2'!$A$5:$BQ$5, 0)) -> 1.024264 | C5: =IF(B5>B4,"inflation",IF(B5<B4,"deflation","stable")) -> inflation | D5: =IF(I5>0,"expansive","contractive") -> expansive | E5: =IF(AND(C5="inflation",D5="expansive"),"inflationary expansion",IF(AND(C5="inflation",D5="contractive"),"stagflation",IF(AND(C5="deflation",D5="expansive"),"deflationary growth",IF(AND(C5="deflation",D5="contractive"),"recession",0)))) -> inflationary expansion | F5: =(B5-B4)/B4 -> 0.012729302 | G5: =J5/B5 -> 5.9040411e+11 | H5: =G5-G4 -> 3.4099454e+10 | I5: =H5/G4 -> 0.061296366 | J5: =INDEX(PQ, MATCH($B$1, PQ!$B$5:$B$271, 0), MATCH(A5, PQ!$A$5:$BQ$5, 0)) -> 6.0472964e+11 | K5: =J5-J4 -> 4.2088866e+10 | L5: =K5/J4 -> 0.074805928 | M5: =L5-I5 -> 0.013509562 | N5: =IF(L5>I5, "inflation",IF(L5<I5, "deflation","stable")) -> inflation | O5: =IFERROR(IF(N5=C5,1,0),"") -> 1 | P5: =M5-F5 -> 0.00078025995 | Q5: =J5-J4 -> 4.2088866e+10 | R5: =Q5/J4 -> 0.074805928 | S5: =INDEX(m, MATCH($B$1, 'M stock'!$B$5:$B$271, 0), MATCH(A5, 'M stock'!$A$5:$BQ$5, 0)) -> 3.84507e+11 | T5: =(S5-S4)/S4 -> 0.089338278 | U5: =S5*Y5 -> 6.0472964e+11 | V5: =(U5-U4)/U4 -> 0.074805928 | W5: =S5/B5 -> 3.7539835e+11 | X5: =(W5-W4)/W4 -> 0.075646055 | Y5: =J5/S5 -> 1.5727403 | Z5: =(Y5-Y4)/Y4 -> -0.01334053 | AA5: =W5*Y5 -> 5.9040411e+11 | AB5: =AA5-AA4 -> 3.4099454e+10 | AC5: =AB5/AA4 -> 0.061296366 | AD5: =J5-AA5 -> 1.4325536e+10 | AE5: =AA5+AD5 -> 6.0472964e+11 | AF5: =(AE5-AE4)/AE4 -> 0.074805928 | AG5: =AF5-I5 -> 0.013509562 | AH5: =AF5-T6 -> -0.018365328 | AI5: =AF5-X5 -> -0.00084012659 | AJ5: =AF5-Z5 -> 0.088146458 | AK5: =IF(AG5>0, "inflation",IF(AG5<0,"deflation","stable")) -> inflation | AL5: =IFERROR(IF(AK5=C5,1,0),"") -> 1 | AM5: =AD5/AN5 -> 9.1086472e+09 | AN5: =Y5 -> 1.5727403
A6: 1963 | B6: =INDEX(p, MATCH($B$1, 'p2'!$B$5:$B$271, 0), MATCH(A6, 'p2'!$A$5:$BQ$5, 0)) -> 1.0361144 | C6: =IF(B6>B5,"inflation",IF(B6<B5,"deflation","stable")) -> inflation | D6: =IF(I6>0,"expansive","contractive") -> expansive | E6: =IF(AND(C6="inflation",D6="expansive"),"inflationary expansion",IF(AND(C6="inflation",D6="contractive"),"stagflation",IF(AND(C6="deflation",D6="expansive"),"deflationary growth",IF(AND(C6="deflation",D6="contractive"),"recession",0)))) -> inflationary expansion | F6: =(B6-B5)/B5 -> 0.011569762 | G6: =J6/B6 -> 6.161297e+11 | H6: =G6-G5 -> 2.5725596e+10 | I6: =H6/G5 -> 0.04357286 | J6: =INDEX(PQ, MATCH($B$1, PQ!$B$5:$B$271, 0), MATCH(A6, PQ!$A$5:$BQ$5, 0)) -> 6.3838088e+11 | K6: =J6-J5 -> 3.3651239e+10 | L6: =K6/J5 -> 0.05564675 | M6: =L6-I6 -> 0.01207389 | N6: =IF(L6>I6, "inflation",IF(L6<I6, "deflation","stable")) -> inflation | O6: =IFERROR(IF(N6=C6,1,0),"") -> 1 | P6: =M6-F6 -> 0.00050412763 | Q6: =J6-J5 -> 3.3651239e+10 | R6: =Q6/J5 -> 0.05564675 | S6: =INDEX(m, MATCH($B$1, 'M stock'!$B$5:$B$271, 0), MATCH(A6, 'M stock'!$A$5:$BQ$5, 0)) -> 4.20332e+11 | T6: =(S6-S5)/S5 -> 0.093171256 | U6: =S6*Y6 -> 6.3838088e+11 | V6: =(U6-U5)/U5 -> 0.05564675 | W6: =S6/B6 -> 4.0568106e+11 | X6: =(W6-W5)/W5 -> 0.080668182 | Y6: =J6/S6 -> 1.5187539 | Z6: =(Y6-Y5)/Y5 -> -0.034326283 | AA6: =W6*Y6 -> 6.161297e+11 | AB6: =AA6-AA5 -> 2.5725596e+10 | AC6: =AB6/AA5 -> 0.04357286 | AD6: =J6-AA6 -> 2.225118e+10 | AE6: =AA6+AD6 -> 6.3838088e+11 | AF6: =(AE6-AE5)/AE5 -> 0.05564675 | AG6: =AF6-I6 -> 0.01207389 | AH6: =AF6-T7 -> -0.034669952 | AI6: =AF6-X6 -> -0.025021432 | AJ6: =AF6-Z6 -> 0.089973033 | AK6: =IF(AG6>0, "inflation",IF(AG6<0,"deflation","stable")) -> inflation | AL6: =IFERROR(IF(AK6=C6,1,0),"") -> 1 | AM6: =AD6/AN6 -> 1.4650945e+10 | AN6: =Y6 -> 1.5187539
A7: 1964 | B7: =INDEX(p, MATCH($B$1, 'p2'!$B$5:$B$271, 0), MATCH(A7, 'p2'!$A$5:$BQ$5, 0)) -> 1.0521701 | C7: =IF(B7>B6,"inflation",IF(B7<B6,"deflation","stable")) -> inflation | D7: =IF(I7>0,"expansive","contractive") -> expansive | E7: =IF(AND(C7="inflation",D7="expansive"),"inflationary expansion",IF(AND(C7="inflation",D7="contractive"),"stagflation",IF(AND(C7="deflation",D7="expansive"),"deflationary growth",IF(AND(C7="deflation",D7="contractive"),"recession",0)))) -> inflationary expansion | F7: =(B7-B6)/B6 -> 0.015496017 | G7: =J7/B7 -> 6.516357e+11 | H7: =G7-G6 -> 3.5505995e+10 | I7: =H7/G6 -> 0.057627469 | J7: =INDEX(PQ, MATCH($B$1, PQ!$B$5:$B$271, 0), MATCH(A7, PQ!$A$5:$BQ$5, 0)) -> 6.8563159e+11 | K7: =J7-J6 -> 4.7250708e+10 | L7: =K7/J6 -> 0.074016483 | M7: =L7-I7 -> 0.016389014 | N7: =IF(L7>I7, "inflation",IF(L7<I7, "deflation","stable")) -> inflation | O7: =IFERROR(IF(N7=C7,1,0),"") -> 1 | P7: =M7-F7 -> 0.00089299626 | Q7: =J7-J6 -> 4.7250708e+10 | R7: =Q7/J6 -> 0.074016483 | S7: =INDEX(m, MATCH($B$1, 'M stock'!$B$5:$B$271, 0), MATCH(A7, 'M stock'!$A$5:$BQ$5, 0)) -> 4.58295e+11 | T7: =(S7-S6)/S6 -> 0.090316702 | U7: =S7*Y7 -> 6.8563159e+11 | V7: =(U7-U6)/U6 -> 0.074016483 | W7: =S7/B7 -> 4.3557121e+11 | X7: =(W7-W6)/W6 -> 0.073678954 | Y7: =J7/S7 -> 1.4960486 | Z7: =(Y7-Y6)/Y6 -> -0.014949986 | AA7: =W7*Y7 -> 6.516357e+11 | AB7: =AA7-AA6 -> 3.5505995e+10 | AC7: =AB7/AA6 -> 0.057627469 | AD7: =J7-AA7 -> 3.3995892e+10 | AE7: =AA7+AD7 -> 6.8563159e+11 | AF7: =(AE7-AE6)/AE6 -> 0.074016483 | AG7: =AF7-I7 -> 0.016389014 | AH7: =AF7-T8 -> -0.012198728 | AI7: =AF7-X7 -> 0.00033752834 | AJ7: =AF7-Z7 -> 0.088966469 | AK7: =IF(AG7>0, "inflation",IF(AG7<0,"deflation","stable")) -> inflation | AL7: =IFERROR(IF(AK7=C7,1,0),"") -> 1 | AM7: =AD7/AN7 -> 2.2723789e+10 | AN7: =Y7 -> 1.4960486
A8: 1965 | B8: =INDEX(p, MATCH($B$1, 'p2'!$B$5:$B$271, 0), MATCH(A8, 'p2'!$A$5:$BQ$5, 0)) -> 1.071359 | C8: =IF(B8>B7,"inflation",IF(B8<B7,"deflation","stable")) -> inflation | D8: =IF(I8>0,"expansive","contractive") -> expansive | E8: =IF(AND(C8="inflation",D8="expansive"),"inflationary expansion",IF(AND(C8="inflation",D8="contractive"),"stagflation",IF(AND(C8="deflation",D8="expansive"),"deflationary growth",IF(AND(C8="deflation",D8="contractive"),"recession",0)))) -> inflationary expansion | F8: =(B8-B7)/B7 -> 0.01823743 | G8: =J8/B8 -> 6.9398195e+11 | H8: =G8-G7 -> 4.2346247e+10 | I8: =H8/G7 -> 0.064984542 | J8: =INDEX(PQ, MATCH($B$1, PQ!$B$5:$B$271, 0), MATCH(A8, PQ!$A$5:$BQ$5, 0)) -> 7.4350378e+11 | K8: =J8-J7 -> 5.787219e+10 | L8: =K8/J7 -> 0.084407123 | M8: =L8-I8 -> 0.019422581 | N8: =IF(L8>I8, "inflation",IF(L8<I8, "deflation","stable")) -> inflation | O8: =IFERROR(IF(N8=C8,1,0),"") -> 1 | P8: =M8-F8 -> 0.001185151 | Q8: =J8-J7 -> 5.787219e+10 | R8: =Q8/J7 -> 0.084407123 | S8: =INDEX(m, MATCH($B$1, 'M stock'!$B$5:$B$271, 0), MATCH(A8, 'M stock'!$A$5:$BQ$5, 0)) -> 4.97807e+11 | T8: =(S8-S7)/S7 -> 0.086215211 | U8: =S8*Y8 -> 7.4350378e+11 | V8: =(U8-U7)/U7 -> 0.084407123 | W8: =S8/B8 -> 4.6465005e+11 | X8: =(W8-W7)/W7 -> 0.066760245 | Y8: =J8/S8 -> 1.4935583 | Z8: =(Y8-Y7)/Y7 -> -0.0016645758 | AA8: =W8*Y8 -> 6.9398195e+11 | AB8: =AA8-AA7 -> 4.2346247e+10 | AC8: =AB8/AA7 -> 0.064984542 | AD8: =J8-AA8 -> 4.9521835e+10 | AE8: =AA8+AD8 -> 7.4350378e+11 | AF8: =(AE8-AE7)/AE7 -> 0.084407123 | AG8: =AF8-I8 -> 0.019422581 | AH8: =AF8-T9 -> 0.037208108 | AI8: =AF8-X8 -> 0.017646878 | AJ8: =AF8-Z8 -> 0.086071699 | AK8: =IF(AG8>0, "inflation",IF(AG8<0,"deflation","stable")) -> inflation | AL8: =IFERROR(IF(AK8=C8,1,0),"") -> 1 | AM8: =AD8/AN8 -> 3.3156948e+10 | AN8: =Y8 -> 1.4935583
A9: 1966 | B9: =INDEX(p, MATCH($B$1, 'p2'!$B$5:$B$271, 0), MATCH(A9, 'p2'!$A$5:$BQ$5, 0)) -> 1.100479 | C9: =IF(B9>B8,"inflation",IF(B9<B8,"deflation","stable")) -> inflation | D9: =IF(I9>0,"expansive","contractive") -> expansive | E9: =IF(AND(C9="inflation",D9="expansive"),"inflationary expansion",IF(AND(C9="inflation",D9="contractive"),"stagflation",IF(AND(C9="deflation",D9="expansive"),"deflationary growth",IF(AND(C9="deflation",D9="contractive"),"recession",0)))) -> inflationary expansion | F9: =(B9-B8)/B8 -> 0.027180506 | G9: =J9/B9 -> 7.3975243e+11 | H9: =G9-G8 -> 4.577048e+10 | I9: =H9/G8 -> 0.065953416 | J9: =INDEX(PQ, MATCH($B$1, PQ!$B$5:$B$271, 0), MATCH(A9, PQ!$A$5:$BQ$5, 0)) -> 8.1408204e+11 | K9: =J9-J8 -> 7.0578263e+10 | L9: =K9/J8 -> 0.094926569 | M9: =L9-I9 -> 0.028973153 | N9: =IF(L9>I9, "inflation",IF(L9<I9, "deflation","stable")) -> inflation | O9: =IFERROR(IF(N9=C9,1,0),"") -> 1 | P9: =M9-F9 -> 0.0017926472 | Q9: =J9-J8 -> 7.0578263e+10 | R9: =Q9/J8 -> 0.094926569 | S9: =INDEX(m, MATCH($B$1, 'M stock'!$B$5:$B$271, 0), MATCH(A9, 'M stock'!$A$5:$BQ$5, 0)) -> 5.21303e+11 | T9: =(S9-S8)/S8 -> 0.047199015 | U9: =S9*Y9 -> 8.1408204e+11 | V9: =(U9-U8)/U8 -> 0.094926569 | W9: =S9/B9 -> 4.7370552e+11 | X9: =(W9-W8)/W8 -> 0.019488794 | Y9: =J9/S9 -> 1.5616293 | Z9: =(Y9-Y8)/Y8 -> 0.045576393 | AA9: =W9*Y9 -> 7.3975243e+11 | AB9: =AA9-AA8 -> 4.577048e+10 | AC9: =AB9/AA8 -> 0.065953416 | AD9: =J9-AA9 -> 7.4329618e+10 | AE9: =AA9+AD9 -> 8.1408204e+11 | AF9: =(AE9-AE8)/AE8 -> 0.094926569 | AG9: =AF9-I9 -> 0.028973153 | AH9: =AF9-T10 -> -0.0078485927 | AI9: =AF9-X9 -> 0.075437775 | AJ9: =AF9-Z9 -> 0.049350176 | AK9: =IF(AG9>0, "inflation",IF(AG9<0,"deflation","stable")) -> inflation | AL9: =IFERROR(IF(AK9=C9,1,0),"") -> 1 | AM9: =AD9/AN9 -> 4.7597479e+10 | AN9: =Y9 -> 1.5616293
A10: 1967 | B10: =INDEX(p, MATCH($B$1, 'p2'!$B$5:$B$271, 0), MATCH(A10, 'p2'!$A$5:$BQ$5, 0)) -> 1.1324872 | C10: =IF(B10>B9,"inflation",IF(B10<B9,"deflation","stable")) -> inflation | D10: =IF(I10>0,"expansive","contractive") -> expansive | E10: =IF(AND(C10="inflation",D10="expansive"),"inflationary expansion",IF(AND(C10="inflation",D10="contractive"),"stagflation",IF(AND(C10="deflation",D10="expansive"),"deflationary growth",IF(AND(C10="deflation",D10="contractive"),"recession",0)))) -> inflationary expansion | F10: =(B10-B9)/B9 -> 0.029085697 | G10: =J10/B10 -> 7.6004137e+11 | H10: =G10-G9 -> 2.0288941e+10 | I10: =H10/G9 -> 0.027426664 | J10: =INDEX(PQ, MATCH($B$1, PQ!$B$5:$B$271, 0), MATCH(A10, PQ!$A$5:$BQ$5, 0)) -> 8.6073715e+11 | K10: =J10-J9 -> 4.665511e+10 | L10: =K10/J9 -> 0.057310084 | M10: =L10-I10 -> 0.02988342 | N10: =IF(L10>I10, "inflation",IF(L10<I10, "deflation","stable")) -> inflation | O10: =IFERROR(IF(N10=C10,1,0),"") -> 1 | P10: =M10-F10 -> 0.00079772362 | Q10: =J10-J9 -> 4.665511e+10 | R10: =Q10/J9 -> 0.057310084 | S10: =INDEX(m, MATCH($B$1, 'M stock'!$B$5:$B$271, 0), MATCH(A10, 'M stock'!$A$5:$BQ$5, 0)) -> 5.7488e+11 | T10: =(S10-S9)/S9 -> 0.10277516 | U10: =S10*Y10 -> 8.6073715e+11 | V10: =(U10-U9)/U9 -> 0.057310084 | W10: =S10/B10 -> 5.0762603e+11 | X10: =(W10-W9)/W9 -> 0.071606733 | Y10: =J10/S10 -> 1.4972466 | Z10: =(Y10-Y9)/Y9 -> -0.041227876 | AA10: =W10*Y10 -> 7.6004137e+11 | AB10: =AA10-AA9 -> 2.0288941e+10 | AC10: =AB10/AA9 -> 0.027426664 | AD10: =J10-AA10 -> 1.0069579e+11 | AE10: =AA10+AD10 -> 8.6073715e+11 | AF10: =(AE10-AE9)/AE9 -> 0.057310084 | AG10: =AF10-I10 -> 0.02988342 | AH10: =AF10-T11 -> -0.030480411 | AI10: =AF10-X10 -> -0.014296649 | AJ10: =AF10-Z10 -> 0.09853796 | AK10: =IF(AG10>0, "inflation",IF(AG10<0,"deflation","stable")) -> inflation | AL10: =IFERROR(IF(AK10=C10,1,0),"") -> 1 | AM10: =AD10/AN10 -> 6.7253974e+10 | AN10: =Y10 -> 1.4972466
A11: 1968 | B11: =INDEX(p, MATCH($B$1, 'p2'!$B$5:$B$271, 0), MATCH(A11, 'p2'!$A$5:$BQ$5, 0)) -> 1.1808961 | C11: =IF(B11>B10,"inflation",IF(B11<B10,"deflation","stable")) -> inflation | D11: =IF(I11>0,"expansive","contractive") -> expansive | E11: =IF(AND(C11="inflation",D11="expansive"),"inflationary expansion",IF(AND(C11="inflation",D11="contractive"),"stagflation",IF(AND(C11="deflation",D11="expansive"),"deflationary growth",IF(AND(C11="deflation",D11="contractive"),"recession",0)))) -> inflationary expansion | F11: =(B11-B10)/B10 -> 0.042745634 | G11: =J11/B11 -> 7.9739367e+11 | H11: =G11-G10 -> 3.7352304e+10 | I11: =H11/G10 -> 0.049145094 | J11: =INDEX(PQ, MATCH($B$1, PQ!$B$5:$B$271, 0), MATCH(A11, PQ!$A$5:$BQ$5, 0)) -> 9.416391e+11 | K11: =J11-J10 -> 8.0901947e+10 | L11: =K11/J10 -> 0.093991466 | M11: =L11-I11 -> 0.044846372 | N11: =IF(L11>I11, "inflation",IF(L11<I11, "deflation","stable")) -> inflation | O11: =IFERROR(IF(N11=C11,1,0),"") -> 1 | P11: =M11-F11 -> 0.0021007382 | Q11: =J11-J10 -> 8.0901947e+10 | R11: =Q11/J10 -> 0.093991466 | S11: =INDEX(m, MATCH($B$1, 'M stock'!$B$5:$B$271, 0), MATCH(A11, 'M stock'!$A$5:$BQ$5, 0)) -> 6.25349e+11 | T11: =(S11-S10)/S10 -> 0.087790495 | U11: =S11*Y11 -> 9.416391e+11 | V11: =(U11-U10)/U10 -> 0.093991466 | W11: =S11/B11 -> 5.2955462e+11 | X11: =(W11-W10)/W10 -> 0.043198322 | Y11: =J11/S11 -> 1.5057817 | Z11: =(Y11-Y10)/Y10 -> 0.005700519 | AA11: =W11*Y11 -> 7.9739367e+11 | AB11: =AA11-AA10 -> 3.7352304e+10 | AC11: =AB11/AA10 -> 0.049145094 | AD11: =J11-AA11 -> 1.4424543e+11 | AE11: =AA11+AD11 -> 9.416391e+11 | AF11: =(AE11-AE10)/AE10 -> 0.093991466 | AG11: =AF11-I11 -> 0.044846372 | AH11: =AF11-T12 -> 0.084408017 | AI11: =AF11-X11 -> 0.050793144 | AJ11: =AF11-Z11 -> 0.088290947 | AK11: =IF(AG11>0, "inflation",IF(AG11<0,"deflation","stable")) -> inflation | AL11: =IFERROR(IF(AK11=C11,1,0),"") -> 1 | AM11: =AD11/AN11 -> 9.5794382e+10 | AN11: =Y11 -> 1.5057817
A12: 1969 | B12: =INDEX(p, MATCH($B$1, 'p2'!$B$5:$B$271, 0), MATCH(A12, 'p2'!$A$5:$BQ$5, 0)) -> 1.2385758 | C12: =IF(B12>B11,"inflation",IF(B12<B11,"deflation","stable")) -> inflation | D12: =IF(I12>0,"expansive","contractive") -> expansive | E12: =IF(AND(C12="inflation",D12="expansive"),"inflationary expansion",IF(AND(C12="inflation",D12="contractive"),"stagflation",IF(AND(C12="deflation",D12="expansive"),"deflationary growth",IF(AND(C12="deflation",D12="contractive"),"recession",0)))) -> inflationary expansion | F12: =(B12-B11)/B11 -> 0.048844011 | G12: =J12/B12 -> 8.2229211e+11 | H12: =G12-G11 -> 2.4898437e+10 | I12: =H12/G11 -> 0.031224774 | J12: =INDEX(PQ, MATCH($B$1, PQ!$B$5:$B$271, 0), MATCH(A12, PQ!$A$5:$BQ$5, 0)) -> 1.0184711e+12 | K12: =J12-J11 -> 7.6832033e+10 | L12: =K12/J11 -> 0.081593928 | M12: =L12-I12 -> 0.050369154 | N12: =IF(L12>I12, "inflation",IF(L12<I12, "deflation","stable")) -> inflation | O12: =IFERROR(IF(N12=C12,1,0),"") -> 1 | P12: =M12-F12 -> 0.0015251432 | Q12: =J12-J11 -> 7.6832033e+10 | R12: =Q12/J11 -> 0.081593928 | S12: =INDEX(m, MATCH($B$1, 'M stock'!$B$5:$B$271, 0), MATCH(A12, 'M stock'!$A$5:$BQ$5, 0)) -> 6.31342e+11 | T12: =(S12-S11)/S11 -> 0.0095834486 | U12: =S12*Y12 -> 1.0184711e+12 | V12: =(U12-U11)/U11 -> 0.081593928 | W12: =S12/B12 -> 5.0973221e+11 | X12: =(W12-W11)/W11 -> -0.037432223 | Y12: =J12/S12 -> 1.6131845 | Z12: =(Y12-Y11)/Y11 -> 0.071326921 | AA12: =W12*Y12 -> 8.2229211e+11 | AB12: =AA12-AA11 -> 2.4898437e+10 | AC12: =AB12/AA11 -> 0.031224774 | AD12: =J12-AA12 -> 1.9617903e+11 | AE12: =AA12+AD12 -> 1.0184711e+12 | AF12: =(AE12-AE11)/AE11 -> 0.081593928 | AG12: =AF12-I12 -> 0.050369154 | AH12: =AF12-T13 -> -0.030256701 | AI12: =AF12-X12 -> 0.11902615 | AJ12: =AF12-Z12 -> 0.010267006 | AK12: =IF(AG12>0, "inflation",IF(AG12<0,"deflation","stable")) -> inflation | AL12: =IFERROR(IF(AK12=C12,1,0),"") -> 1 | AM12: =AD12/AN12 -> 1.2160979e+11 | AN12: =Y12 -> 1.6131845
A13: 1970 | B13: =INDEX(p, MATCH($B$1, 'p2'!$B$5:$B$271, 0), MATCH(A13, 'p2'!$A$5:$BQ$5, 0)) -> 1.3028523 | C13: =IF(B13>B12,"inflation",IF(B13<B12,"deflation","stable")) -> inflation | D13: =IF(I13>0,"expansive","contractive") -> expansive | E13: =IF(AND(C13="inflation",D13="expansive"),"inflationary expansion",IF(AND(C13="inflation",D13="contractive"),"stagflation",IF(AND(C13="deflation",D13="expansive"),"deflationary growth",IF(AND(C13="deflation",D13="contractive"),"recession",0)))) -> inflationary expansion | F13: =(B13-B12)/B12 -> 0.051895425 | G13: =J13/B13 -> 8.2381022e+11 | H13: =G13-G12 -> 1.5181104e+09 | I13: =H13/G12 -> 0.0018461936 | J13: =INDEX(PQ, MATCH($B$1, PQ!$B$5:$B$271, 0), MATCH(A13, PQ!$A$5:$BQ$5, 0)) -> 1073303000000 | K13: =J13-J12 -> 5.4831866e+10 | L13: =K13/J12 -> 0.053837428 | M13: =L13-I13 -> 0.051991234 | N13: =IF(L13>I13, "inflation",IF(L13<I13, "deflation","stable")) -> inflation | O13: =IFERROR(IF(N13=C13,1,0),"") -> 1 | P13: =M13-F13 -> 9.5809003e-05 | Q13: =J13-J12 -> 5.4831866e+10 | R13: =Q13/J12 -> 0.053837428 | S13: =INDEX(m, MATCH($B$1, 'M stock'!$B$5:$B$271, 0), MATCH(A13, 'M stock'!$A$5:$BQ$5, 0)) -> 7.01958e+11 | T13: =(S13-S12)/S12 -> 0.11185063 | U13: =S13*Y13 -> 1073303000000 | V13: =(U13-U12)/U12 -> 0.053837428 | W13: =S13/B13 -> 5.3878557e+11 | X13: =(W13-W12)/W12 -> 0.056997305 | Y13: =J13/S13 -> 1.5290131 | Z13: =(Y13-Y12)/Y12 -> -0.052177154 | AA13: =W13*Y13 -> 8.2381022e+11 | AB13: =AA13-AA12 -> 1.5181104e+09 | AC13: =AB13/AA12 -> 0.0018461936 | AD13: =J13-AA13 -> 2.4949278e+11 | AE13: =AA13+AD13 -> 1073303000000 | AF13: =(AE13-AE12)/AE12 -> 0.053837428 | AG13: =AF13-I13 -> 0.051991234 | AH13: =AF13-T14 -> -0.085715081 | AI13: =AF13-X13 -> -0.0031598766 | AJ13: =AF13-Z13 -> 0.10601458 | AK13: =IF(AG13>0, "inflation",IF(AG13<0,"deflation","stable")) -> inflation | AL13: =IFERROR(IF(AK13=C13,1,0),"") -> 1 | AM13: =AD13/AN13 -> 1.6317243e+11 | AN13: =Y13 -> 1.5290131
A14: 1971 | B14: =INDEX(p, MATCH($B$1, 'p2'!$B$5:$B$271, 0), MATCH(A14, 'p2'!$A$5:$BQ$5, 0)) -> 1.3689044 | C14: =IF(B14>B13,"inflation",IF(B14<B13,"deflation","stable")) -> inflation | D14: =IF(I14>0,"expansive","contractive") -> expansive | E14: =IF(AND(C14="inflation",D14="expansive"),"inflationary expansion",IF(AND(C14="inflation",D14="contractive"),"stagflation",IF(AND(C14="deflation",D14="expansive"),"deflationary growth",IF(AND(C14="deflation",D14="contractive"),"recession",0)))) -> inflationary expansion | F14: =(B14-B13)/B13 -> 0.050698075 | G14: =J14/B14 -> 8.50936e+11 | H14: =G14-G13 -> 2.7125784e+10 | I14: =H14/G13 -> 0.032927225 | J14: =INDEX(PQ, MATCH($B$1, PQ!$B$5:$B$271, 0), MATCH(A14, PQ!$A$5:$BQ$5, 0)) -> 1164850000000 | K14: =J14-J13 -> 91547000000 | L14: =K14/J13 -> 0.085294647 | M14: =L14-I14 -> 0.052367422 | N14: =IF(L14>I14, "inflation",IF(L14<I14, "deflation","stable")) -> inflation | O14: =IFERROR(IF(N14=C14,1,0),"") -> 1 | P14: =M14-F14 -> 0.0016693469 | Q14: =J14-J13 -> 91547000000 | R14: =Q14/J13 -> 0.085294647 | S14: =INDEX(m, MATCH($B$1, 'M stock'!$B$5:$B$271, 0), MATCH(A14, 'M stock'!$A$5:$BQ$5, 0)) -> 7.99918e+11 | T14: =(S14-S13)/S13 -> 0.13955251 | U14: =S14*Y14 -> 1164850000000 | V14: =(U14-U13)/U13 -> 0.085294647 | W14: =S14/B14 -> 5.8434908e+11 | X14: =(W14-W13)/W13 -> 0.084567047 | Y14: =J14/S14 -> 1.4562118 | Z14: =(Y14-Y13)/Y13 -> -0.047613306 | AA14: =W14*Y14 -> 8.50936e+11 | AB14: =AA14-AA13 -> 2.7125784e+10 | AC14: =AB14/AA13 -> 0.032927225 | AD14: =J14-AA14 -> 3.13914e+11 | AE14: =AA14+AD14 -> 1164850000000 | AF14: =(AE14-AE13)/AE13 -> 0.085294647 | AG14: =AF14-I14 -> 0.052367422 | AH14: =AF14-T15 -> -0.050609284 | AI14: =AF14-X14 -> 0.00072759932 | AJ14: =AF14-Z14 -> 0.13290795 | AK14: =IF(AG14>0, "inflation",IF(AG14<0,"deflation","stable")) -> inflation | AL14: =IFERROR(IF(AK14=C14,1,0),"") -> 1 | AM14: =AD14/AN14 -> 2.1556892e+11 | AN14: =Y14 -> 1.4562118
A15: 1972 | B15: =INDEX(p, MATCH($B$1, 'p2'!$B$5:$B$271, 0), MATCH(A15, 'p2'!$A$5:$BQ$5, 0)) -> 1.4281249 | C15: =IF(B15>B14,"inflation",IF(B15<B14,"deflation","stable")) -> inflation | D15: =IF(I15>0,"expansive","contractive") -> expansive | E15: =IF(AND(C15="inflation",D15="expansive"),"inflationary expansion",IF(AND(C15="inflation",D15="contractive"),"stagflation",IF(AND(C15="deflation",D15="expansive"),"deflationary growth",IF(AND(C15="deflation",D15="contractive"),"recession",0)))) -> inflationary expansion | F15: =(B15-B14)/B14 -> 0.043261266 | G15: =J15/B15 -> 8.9565696e+11 | H15: =G15-G14 -> 4.4720958e+10 | I15: =H15/G14 -> 0.05255502 | J15: =INDEX(PQ, MATCH($B$1, PQ!$B$5:$B$271, 0), MATCH(A15, PQ!$A$5:$BQ$5, 0)) -> 1279110000000 | K15: =J15-J14 -> 114260000000 | L15: =K15/J14 -> 0.098089883 | M15: =L15-I15 -> 0.045534863 | N15: =IF(L15>I15, "inflation",IF(L15<I15, "deflation","stable")) -> inflation | O15: =IFERROR(IF(N15=C15,1,0),"") -> 1 | P15: =M15-F15 -> 0.0022735967 | Q15: =J15-J14 -> 114260000000 | R15: =Q15/J14 -> 0.098089883 | S15: =INDEX(m, MATCH($B$1, 'M stock'!$B$5:$B$271, 0), MATCH(A15, 'M stock'!$A$5:$BQ$5, 0)) -> 9.0863e+11 | T15: =(S15-S14)/S14 -> 0.13590393 | U15: =S15*Y15 -> 1279110000000 | V15: =(U15-U14)/U14 -> 0.098089883 | W15: =S15/B15 -> 6.3623987e+11 | X15: =(W15-W14)/W14 -> 0.088801019 | Y15: =J15/S15 -> 1.4077347 | Z15: =(Y15-Y14)/Y14 -> -0.033289829 | AA15: =W15*Y15 -> 8.9565696e+11 | AB15: =AA15-AA14 -> 4.4720958e+10 | AC15: =AB15/AA14 -> 0.05255502 | AD15: =J15-AA15 -> 3.8345304e+11 | AE15: =AA15+AD15 -> 1279110000000 | AF15: =(AE15-AE14)/AE14 -> 0.098089883 | AG15: =AF15-I15 -> 0.045534863 | AH15: =AF15-T16 -> -0.0036699094 | AI15: =AF15-X15 -> 0.0092888637 | AJ15: =AF15-Z15 -> 0.13137971 | AK15: =IF(AG15>0, "inflation",IF(AG15<0,"deflation","stable")) -> inflation | AL15: =IFERROR(IF(AK15=C15,1,0),"") -> 1 | AM15: =AD15/AN15 -> 2.7239013e+11 | AN15: =Y15 -> 1.4077347
... A67: 2024 | B67: =INDEX(p, MATCH($B$1, 'p2'!$B$5:$B$271, 0), MATCH(A67, 'p2'!$A$5:$BQ$5, 0)) -> 8.081617 | C67: =IF(B67>B66,"inflation",IF(B67<B66,"deflation","stable")) -> inflation | D67: =IF(I67>0,"expansive","contractive") -> expansive | E67: =IF(AND(C67="inflation",D67="expansive"),"inflationary expansion",IF(AND(C67="inflation",D67="contractive"),"stagflation",IF(AND(C67="deflation",D67="expansive"),"deflationary growth",IF(AND(C67="deflation",D67="contractive"),"recession",0)))) -> inflationary expansion | F67: =(B67-B66)/B66 -> 0.024180982 | G67: =J67/B67 -> 3.6112686e+12 | H67: =G67-G66 -> 9.8231214e+10 | I67: =H67/G66 -> 0.027961904 | J67: =INDEX(PQ, MATCH($B$1, PQ!$B$5:$B$271, 0), MATCH(A67, PQ!$A$5:$BQ$5, 0)) -> 29184890000000 | K67: =J67-J66 -> 1464181000000 | L67: =K67/J66 -> 0.052819031 | M67: =L67-I67 -> 0.024857128 | N67: =IF(L67>I67, "inflation",IF(L67<I67, "deflation","stable")) -> inflation | O67: =IFERROR(IF(N67=C67,1,0),"") -> 1 | P67: =M67-F67 -> 0.00067614628 | Q67: =J67-J66 -> 1464181000000 | R67: =Q67/J66 -> 0.052819031 | S67: =INDEX(m, MATCH($B$1, 'M stock'!$B$5:$B$271, 0), MATCH(A67, 'M stock'!$A$5:$BQ$5, 0)) -> 0 | T67: =(S67-S66)/S66 -> -1 | U67: =S67*Y67 -> #DIV/0! | V67: =(U67-U66)/U66 -> #DIV/0! | W67: =S67/B67 -> 0 | X67: =(W67-W66)/W66 -> -1 | Y67: =J67/S67 -> #DIV/0! | Z67: =(Y67-Y66)/Y66 -> #DIV/0! | AA67: =W67*Y67 -> #DIV/0! | AB67: =AA67-AA66 -> #DIV/0! | AC67: =AB67/AA66 -> #DIV/0! | AD67: =J67-AA67 -> #DIV/0! | AE67: =AA67+AD67 -> #DIV/0! | AF67: =(AE67-AE66)/AE66 -> #DIV/0! | AG67: =AF67-I67 -> #DIV/0! | AH67: =AF67-T68 -> #DIV/0! | AI67: =AF67-X67 -> #DIV/0! | AJ67: =AF67-Z67 -> #DIV/0! | AK67: =IF(AG67>0, "inflation",IF(AG67<0,"deflation","stable")) -> #DIV/0! | AL67: =IFERROR(IF(AK67=C67,1,0),"") | AM67: =AD67/AN67 -> #DIV/0! | AN67: =Y67 -> #DIV/0!
N69: Economic Themal Dynamic Accuracy (Left Side PQ) | O69: =SUM(O4:O57)/COUNT(O4:O57) -> 1 | AK69: Economic Themal Dynamic Accuracy (Right Side MV+FAC) | AL69: =SUM(AL4:AL57)/COUNT(AL4:AL57) -> 1
N71: Matches | O71: =SUM(O3:O67) -> 64 | AK71: Matches | AL71: =SUM(AL3:AL67) -> 63
N72: Count | O72: =COUNT(O3:O67) -> 64 | AK72: Count | AL72: =COUNT(AL3:AL67) -> 63
A74: Source:
A75: World Bank
A76: https://data.worldbank.org/
A78: Broad Money (% of GDP)
A79: API_FM.LBL.BMNY.GD.ZS_DS2_en_csv_v2_123670
A80: Used to analyze monetary aggregates relative to GDP
A82: GDP Deflator (scaled to start meaningful P at 1)_
A83: API_NY.GDP.DEFL.ZS_DS2_en_csv_v2_124034
A84: Used to convert nominal GDP to real terms and track change in P over time
A86: GDP (current US$)
A87: API_NY.GDP.MKTP.CD_DS2_en_csv_v2_130122
A88: Core GDP series for nominal valuation
... A108: affirming the robustness of our own data sources and calculations.

Sheet China
B1: =VLOOKUP(C1,PQ!A6:B271,2,FALSE) -> CHN | C1: China | H1: =IFERROR(B3+B4,"wrong") -> 2.1524631
A2: Period | B2: P | C2: Observe | D2: Economy | E2: Diagnosis | F2: Δ P % | G2: Q | H2: Δ Q | I2: Δ Q % | J2: PQ | K2: Δ PQ | L2: Δ PQ % | M2: Δ PQ % - Δ Q % | N2: test | O2: match? | P2: (Δ PQ % - Δ Q %) -Δ P % = Δ P x Δ Q (interaction) | Q2: ΔPQ | R2: Δ%PQ | S2: M | T2: ΔM % | U2: MV | V2: ΔMV % | W2: M(d.) | X2: ΔM(d.) % | Y2: V | Z2: Δ V % | AA2: MV(d.) | AB2: ΔMV(d.) | AC2: Δ%MV(d.) | AD2: PQ-MV(d.) (FAC) | AE2: MV(d.) + FAC | AF2: Δ MV(d.)+FAC % | AG2: Δ MV(d.)+FAC % - Δ Q % | AH2: Δ MV(d.)+FAC % - Δ M % | AI2: Δ MV(d.)+FAC % - Δ M % | AJ2: Δ MV(d.)+FAC % - Δ V % | AK2: test | AL2: match? | AM2: M_FAC | AN2: V_FAC
A3: 1960 | B3: =INDEX(p, MATCH($B$1, 'p2'!$B$5:$B$271, 0), MATCH(A3, 'p2'!$A$5:$BQ$5, 0)) -> 1 | G3: =J3/B3 -> 5.9846235e+10 | H3: =G3-G2 -> #VALUE! | I3: =H3-H2 -> #VALUE! | J3: =INDEX(PQ, MATCH($B$1, PQ!$B$5:$B$271, 0), MATCH(A3, PQ!$A$5:$BQ$5, 0)) -> 5.9846235e+10 | K3: =J3-J2 -> #VALUE! | L3: =(K3-K2)/K2 -> #VALUE! | M3: =L3-I3 -> #VALUE! | S3: =INDEX(m, MATCH($B$1, 'M stock'!$B$5:$B$271, 0), MATCH(A3, 'M stock'!$A$5:$BQ$5, 0)) -> 0 | U3: =S3*Y3 -> #DIV/0! | W3: =S3/B3 -> 0 | Y3: =J3/S3 -> #DIV/0! | AA3: =W3*Y3 -> #DIV/0! | AD3: =J3-AA3 -> #DIV/0! | AE3: =AA3+AD3 -> #DIV/0! | AG3: =AF3-I3 -> #VALUE! | AH3: =AF3-T4 -> #DIV/0! | AI3: =AF3-X3 -> 0 | AJ3: =AF3-Z3 -> 0
A4: 1961 | B4: =INDEX(p, MATCH($B$1, 'p2'!$B$5:$B$271, 0), MATCH(A4, 'p2'!$A$5:$BQ$5, 0)) -> 1.1524631 | C4: =IF(B4>B3,"inflation",IF(B4<B3,"deflation","stable")) -> inflation | D4: =IF(I4>0,"expansive","contractive") -> contractive | E4: =IF(AND(C4="inflation",D4="expansive"),"inflationary expansion",IF(AND(C4="inflation",D4="contractive"),"stagflation",IF(AND(C4="deflation",D4="expansive"),"deflationary growth",IF(AND(C4="deflation",D4="contractive"),"recession",0)))) -> stagflation | F4: =(B4-B3)/B3 -> 0.15246306 | G4: =J4/B4 -> 4.3526167e+10 | H4: =G4-G3 -> -1.6320068e+10 | I4: =H4/G3 -> -0.2727 | J4: =INDEX(PQ, MATCH($B$1, PQ!$B$5:$B$271, 0), MATCH(A4, PQ!$A$5:$BQ$5, 0)) -> 5.0162299e+10 | K4: =J4-J3 -> -9.6839357e+09 | L4: =K4/J3 -> -0.16181362 | M4: =L4-I4 -> 0.11088638 | N4: =IF(L4>I4, "inflation",IF(L4<I4, "deflation","stable")) -> inflation | O4: =IFERROR(IF(N4=C4,1,0),"") -> 1 | P4: =M4-F4 -> -0.041576677 | Q4: =J4-J3 -> -9.6839357e+09 | R4: =Q4/J3 -> -0.16181362 | S4: =INDEX(m, MATCH($B$1, 'M stock'!$B$5:$B$271, 0), MATCH(A4, 'M stock'!$A$5:$BQ$5, 0)) -> 0 | T4: =(S4-S3)/S3 -> #DIV/0! | U4: =S4*Y4 -> #DIV/0! | V4: =(U4-U3)/U3 -> #DIV/0! | W4: =S4/B4 -> 0 | X4: =(W4-W3)/W3 -> #DIV/0! | Y4: =J4/S4 -> #DIV/0! | Z4: =(Y4-Y3)/Y3 -> #DIV/0! | AA4: =W4*Y4 -> #DIV/0! | AB4: =AA4-AA3 -> #DIV/0! | AC4: =AB4/AA3 -> #DIV/0! | AD4: =J4-AA4 -> #DIV/0! | AE4: =AA4+AD4 -> #DIV/0! | AF4: =(AE4-AE3)/AE3 -> #DIV/0! | AG4: =AF4-I4 -> #DIV/0! | AH4: =AF4-T5 -> #DIV/0! | AI4: =AF4-X4 -> #DIV/0! | AJ4: =AF4-Z4 -> #DIV/0! | AK4: =IF(AG4>0, "inflation",IF(AG4<0,"deflation","stable")) -> #DIV/0! | AL4: =IFERROR(IF(AK4=C4,1,0),"") | AM4: =AD4/AN4 -> #DIV/0! | AN4: =Y4 -> #DIV/0!
A5: 1962 | B5: =INDEX(p, MATCH($B$1, 'p2'!$B$5:$B$271, 0), MATCH(A5, 'p2'!$A$5:$BQ$5, 0)) -> 1.1511855 | C5: =IF(B5>B4,"inflation",IF(B5<B4,"deflation","stable")) -> deflation | D5: =IF(I5>0,"expansive","contractive") -> contractive | E5: =IF(AND(C5="inflation",D5="expansive"),"inflationary expansion",IF(AND(C5="inflation",D5="contractive"),"stagflation",IF(AND(C5="deflation",D5="expansive"),"deflationary growth",IF(AND(C5="deflation",D5="contractive"),"recession",0)))) -> recession | F5: =(B5-B4)/B4 -> -0.0011085663 | G5: =J5/B5 -> 4.1097407e+10 | H5: =G5-G4 -> -2.4287601e+09 | I5: =H5/G4 -> -0.0558 | J5: =INDEX(PQ, MATCH($B$1, PQ!$B$5:$B$271, 0), MATCH(A5, PQ!$A$5:$BQ$5, 0)) -> 4.7310738e+10 | K5: =J5-J4 -> -2.8515616e+09 | L5: =K5/J4 -> -0.056846708 | M5: =L5-I5 -> -0.0010467083 | N5: =IF(L5>I5, "inflation",IF(L5<I5, "deflation","stable")) -> deflation | O5: =IFERROR(IF(N5=C5,1,0),"") -> 1 | P5: =M5-F5 -> 6.1858001e-05 | Q5: =J5-J4 -> -2.8515616e+09 | R5: =Q5/J4 -> -0.056846708 | S5: =INDEX(m, MATCH($B$1, 'M stock'!$B$5:$B$271, 0), MATCH(A5, 'M stock'!$A$5:$BQ$5, 0)) -> 0 | T5: =(S5-S4)/S4 -> #DIV/0! | U5: =S5*Y5 -> #DIV/0! | V5: =(U5-U4)/U4 -> #DIV/0! | W5: =S5/B5 -> 0 | X5: =(W5-W4)/W4 -> #DIV/0! | Y5: =J5/S5 -> #DIV/0! | Z5: =(Y5-Y4)/Y4 -> #DIV/0! | AA5: =W5*Y5 -> #DIV/0! | AB5: =AA5-AA4 -> #DIV/0! | AC5: =AB5/AA4 -> #DIV/0! | AD5: =J5-AA5 -> #DIV/0! | AE5: =AA5+AD5 -> #DIV/0! | AF5: =(AE5-AE4)/AE4 -> #DIV/0! | AG5: =AF5-I5 -> #DIV/0! | AH5: =AF5-T6 -> #DIV/0! | AI5: =AF5-X5 -> #DIV/0! | AJ5: =AF5-Z5 -> #DIV/0! | AK5: =IF(AG5>0, "inflation",IF(AG5<0,"deflation","stable")) -> #DIV/0! | AL5: =IFERROR(IF(AK5=C5,1,0),"") | AM5: =AD5/AN5 -> #DIV/0! | AN5: =Y5 -> #DIV/0!
A6: 1963 | B6: =INDEX(p, MATCH($B$1, 'p2'!$B$5:$B$271, 0), MATCH(A6, 'p2'!$A$5:$BQ$5, 0)) -> 1.1209295 | C6: =IF(B6>B5,"inflation",IF(B6<B5,"deflation","stable")) -> deflation | D6: =IF(I6>0,"expansive","contractive") -> expansive | E6: =IF(AND(C6="inflation",D6="expansive"),"inflationary expansion",IF(AND(C6="inflation",D6="contractive"),"stagflation",IF(AND(C6="deflation",D6="expansive"),"deflationary growth",IF(AND(C6="deflation",D6="contractive"),"recession",0)))) -> deflationary growth | F6: =(B6-B5)/B5 -> -0.026282434 | G6: =J6/B6 -> 4.533044e+10 | H6: =G6-G5 -> 4.2330329e+09 | I6: =H6/G5 -> 0.103 | J6: =INDEX(PQ, MATCH($B$1, PQ!$B$5:$B$271, 0), MATCH(A6, PQ!$A$5:$BQ$5, 0)) -> 5.0812228e+10 | K6: =J6-J5 -> 3.5014902e+09 | L6: =K6/J5 -> 0.074010475 | M6: =L6-I6 -> -0.028989525 | N6: =IF(L6>I6, "inflation",IF(L6<I6, "deflation","stable")) -> deflation | O6: =IFERROR(IF(N6=C6,1,0),"") -> 1 | P6: =M6-F6 -> -0.0027070907 | Q6: =J6-J5 -> 3.5014902e+09 | R6: =Q6/J5 -> 0.074010475 | S6: =INDEX(m, MATCH($B$1, 'M stock'!$B$5:$B$271, 0), MATCH(A6, 'M stock'!$A$5:$BQ$5, 0)) -> 0 | T6: =(S6-S5)/S5 -> #DIV/0! | U6: =S6*Y6 -> #DIV/0! | V6: =(U6-U5)/U5 -> #DIV/0! | W6: =S6/B6 -> 0 | X6: =(W6-W5)/W5 -> #DIV/0! | Y6: =J6/S6 -> #DIV/0! | Z6: =(Y6-Y5)/Y5 -> #DIV/0! | AA6: =W6*Y6 -> #DIV/0! | AB6: =AA6-AA5 -> #DIV/0! | AC6: =AB6/AA5 -> #DIV/0! | AD6: =J6-AA6 -> #DIV/0! | AE6: =AA6+AD6 -> #DIV/0! | AF6: =(AE6-AE5)/AE5 -> #DIV/0! | AG6: =AF6-I6 -> #DIV/0! | AH6: =AF6-T7 -> #DIV/0! | AI6: =AF6-X6 -> #DIV/0! | AJ6: =AF6-Z6 -> #DIV/0! | AK6: =IF(AG6>0, "inflation",IF(AG6<0,"deflation","stable")) -> #DIV/0! | AL6: =IFERROR(IF(AK6=C6,1,0),"") | AM6: =AD6/AN6 -> #DIV/0! | AN6: =Y6 -> #DIV/0!
A7: 1964 | B7: =INDEX(p, MATCH($B$1, 'p2'!$B$5:$B$271, 0), MATCH(A7, 'p2'!$A$5:$BQ$5, 0)) -> 1.116673 | C7: =IF(B7>B6,"inflation",IF(B7<B6,"deflation","stable")) -> deflation | D7: =IF(I7>0,"expansive","contractive") -> expansive | E7: =IF(AND(C7="inflation",D7="expansive"),"inflationary expansion",IF(AND(C7="inflation",D7="contractive"),"stagflation",IF(AND(C7="deflation",D7="expansive"),"deflationary growth",IF(AND(C7="deflation",D7="contractive"),"recession",0)))) -> deflationary growth | F7: =(B7-B6)/B6 -> -0.0037973133 | G7: =J7/B7 -> 5.3571513e+10 | H7: =G7-G6 -> 8.2410739e+09 | I7: =H7/G6 -> 0.1818 | J7: =INDEX(PQ, MATCH($B$1, PQ!$B$5:$B$271, 0), MATCH(A7, PQ!$A$5:$BQ$5, 0)) -> 5.9821863e+10 | K7: =J7-J6 -> 9.0096348e+09 | L7: =K7/J6 -> 0.17731234 | M7: =L7-I7 -> -0.0044876648 | N7: =IF(L7>I7, "inflation",IF(L7<I7, "deflation","stable")) -> deflation | O7: =IFERROR(IF(N7=C7,1,0),"") -> 1 | P7: =M7-F7 -> -0.00069035155 | Q7: =J7-J6 -> 9.0096348e+09 | R7: =Q7/J6 -> 0.17731234 | S7: =INDEX(m, MATCH($B$1, 'M stock'!$B$5:$B$271, 0), MATCH(A7, 'M stock'!$A$5:$BQ$5, 0)) -> 0 | T7: =(S7-S6)/S6 -> #DIV/0! | U7: =S7*Y7 -> #DIV/0! | V7: =(U7-U6)/U6 -> #DIV/0! | W7: =S7/B7 -> 0 | X7: =(W7-W6)/W6 -> #DIV/0! | Y7: =J7/S7 -> #DIV/0! | Z7: =(Y7-Y6)/Y6 -> #DIV/0! | AA7: =W7*Y7 -> #DIV/0! | AB7: =AA7-AA6 -> #DIV/0! | AC7: =AB7/AA6 -> #DIV/0! | AD7: =J7-AA7 -> #DIV/0! | AE7: =AA7+AD7 -> #DIV/0! | AF7: =(AE7-AE6)/AE6 -> #DIV/0! | AG7: =AF7-I7 -> #DIV/0! | AH7: =AF7-T8 -> #DIV/0! | AI7: =AF7-X7 -> #DIV/0! | AJ7: =AF7-Z7 -> #DIV/0! | AK7: =IF(AG7>0, "inflation",IF(AG7<0,"deflation","stable")) -> #DIV/0! | AL7: =IFERROR(IF(AK7=C7,1,0),"") | AM7: =AD7/AN7 -> #DIV/0! | AN7: =Y7 -> #DIV/0!
A8: 1965 | B8: =INDEX(p, MATCH($B$1, 'p2'!$B$5:$B$271, 0), MATCH(A8, 'p2'!$A$5:$BQ$5, 0)) -> 1.1263188 | C8: =IF(B8>B7,"inflation",IF(B8<B7,"deflation","stable")) -> inflation | D8: =IF(I8>0,"expansive","contractive") -> expansive | E8: =IF(AND(C8="inflation",D8="expansive"),"inflationary expansion",IF(AND(C8="inflation",D8="contractive"),"stagflation",IF(AND(C8="deflation",D8="expansive"),"deflationary growth",IF(AND(C8="deflation",D8="contractive"),"recession",0)))) -> inflationary expansion | F8: =(B8-B7)/B7 -> 0.0086379576 | G8: =J8/B8 -> 6.2651885e+10 | H8: =G8-G7 -> 9.0803715e+09 | I8: =H8/G7 -> 0.1695 | J8: =INDEX(PQ, MATCH($B$1, PQ!$B$5:$B$271, 0), MATCH(A8, PQ!$A$5:$BQ$5, 0)) -> 7.0565994e+10 | K8: =J8-J7 -> 1.0744132e+10 | L8: =K8/J7 -> 0.17960209 | M8: =L8-I8 -> 0.010102091 | N8: =IF(L8>I8, "inflation",IF(L8<I8, "deflation","stable")) -> inflation | O8: =IFERROR(IF(N8=C8,1,0),"") -> 1 | P8: =M8-F8 -> 0.0014641338 | Q8: =J8-J7 -> 1.0744132e+10 | R8: =Q8/J7 -> 0.17960209 | S8: =INDEX(m, MATCH($B$1, 'M stock'!$B$5:$B$271, 0), MATCH(A8, 'M stock'!$A$5:$BQ$5, 0)) -> 0 | T8: =(S8-S7)/S7 -> #DIV/0! | U8: =S8*Y8 -> #DIV/0! | V8: =(U8-U7)/U7 -> #DIV/0! | W8: =S8/B8 -> 0 | X8: =(W8-W7)/W7 -> #DIV/0! | Y8: =J8/S8 -> #DIV/0! | Z8: =(Y8-Y7)/Y7 -> #DIV/0! | AA8: =W8*Y8 -> #DIV/0! | AB8: =AA8-AA7 -> #DIV/0! | AC8: =AB8/AA7 -> #DIV/0! | AD8: =J8-AA8 -> #DIV/0! | AE8: =AA8+AD8 -> #DIV/0! | AF8: =(AE8-AE7)/AE7 -> #DIV/0! | AG8: =AF8-I8 -> #DIV/0! | AH8: =AF8-T9 -> #DIV/0! | AI8: =AF8-X8 -> #DIV/0! | AJ8: =AF8-Z8 -> #DIV/0! | AK8: =IF(AG8>0, "inflation",IF(AG8<0,"deflation","stable")) -> #DIV/0! | AL8: =IFERROR(IF(AK8=C8,1,0),"") | AM8: =AD8/AN8 -> #DIV/0! | AN8: =Y8 -> #DIV/0!
A9: 1966 | B9: =INDEX(p, MATCH($B$1, 'p2'!$B$5:$B$271, 0), MATCH(A9, 'p2'!$A$5:$BQ$5, 0)) -> 1.1086162 | C9: =IF(B9>B8,"inflation",IF(B9<B8,"deflation","stable")) -> deflation | D9: =IF(I9>0,"expansive","contractive") -> expansive | E9: =IF(AND(C9="inflation",D9="expansive"),"inflationary expansion",IF(AND(C9="inflation",D9="contractive"),"stagflation",IF(AND(C9="deflation",D9="expansive"),"deflationary growth",IF(AND(C9="deflation",D9="contractive"),"recession",0)))) -> deflationary growth | F9: =(B9-B8)/B8 -> -0.015717207 | G9: =J9/B9 -> 6.9324311e+10 | H9: =G9-G8 -> 6.6724257e+09 | I9: =H9/G8 -> 0.1065 | J9: =INDEX(PQ, MATCH($B$1, PQ!$B$5:$B$271, 0), MATCH(A9, PQ!$A$5:$BQ$5, 0)) -> 7.6854053e+10 | K9: =J9-J8 -> 6.2880589e+09 | L9: =K9/J8 -> 0.089108911 | M9: =L9-I9 -> -0.017391089 | N9: =IF(L9>I9, "inflation",IF(L9<I9, "deflation","stable")) -> deflation | O9: =IFERROR(IF(N9=C9,1,0),"") -> 1 | P9: =M9-F9 -> -0.0016738825 | Q9: =J9-J8 -> 6.2880589e+09 | R9: =Q9/J8 -> 0.089108911 | S9: =INDEX(m, MATCH($B$1, 'M stock'!$B$5:$B$271, 0), MATCH(A9, 'M stock'!$A$5:$BQ$5, 0)) -> 0 | T9: =(S9-S8)/S8 -> #DIV/0! | U9: =S9*Y9 -> #DIV/0! | V9: =(U9-U8)/U8 -> #DIV/0! | W9: =S9/B9 -> 0 | X9: =(W9-W8)/W8 -> #DIV/0! | Y9: =J9/S9 -> #DIV/0! | Z9: =(Y9-Y8)/Y8 -> #DIV/0! | AA9: =W9*Y9 -> #DIV/0! | AB9: =AA9-AA8 -> #DIV/0! | AC9: =AB9/AA8 -> #DIV/0! | AD9: =J9-AA9 -> #DIV/0! | AE9: =AA9+AD9 -> #DIV/0! | AF9: =(AE9-AE8)/AE8 -> #DIV/0! | AG9: =AF9-I9 -> #DIV/0! | AH9: =AF9-T10 -> #DIV/0! | AI9: =AF9-X9 -> #DIV/0! | AJ9: =AF9-Z9 -> #DIV/0! | AK9: =IF(AG9>0, "inflation",IF(AG9<0,"deflation","stable")) -> #DIV/0! | AL9: =IFERROR(IF(AK9=C9,1,0),"") | AM9: =AD9/AN9 -> #DIV/0! | AN9: =Y9 -> #DIV/0!
A10: 1967 | B10: =INDEX(p, MATCH($B$1, 'p2'!$B$5:$B$271, 0), MATCH(A10, 'p2'!$A$5:$BQ$5, 0)) -> 1.1176752 | C10: =IF(B10>B9,"inflation",IF(B10<B9,"deflation","stable")) -> inflation | D10: =IF(I10>0,"expansive","contractive") -> contractive | E10: =IF(AND(C10="inflation",D10="expansive"),"inflationary expansion",IF(AND(C10="inflation",D10="contractive"),"stagflation",IF(AND(C10="deflation",D10="expansive"),"deflationary growth",IF(AND(C10="deflation",D10="contractive"),"recession",0)))) -> stagflation | F10: =(B10-B9)/B9 -> 0.0081714953 | G10: =J10/B10 -> 6.5324298e+10 | H10: =G10-G9 -> -4.0000127e+09 | I10: =H10/G9 -> -0.0577 | J10: =INDEX(PQ, MATCH($B$1, PQ!$B$5:$B$271, 0), MATCH(A10, PQ!$A$5:$BQ$5, 0)) -> 7.3011351e+10 | K10: =J10-J9 -> -3.8427027e+09 | L10: =K10/J9 -> -0.05 | M10: =L10-I10 -> 0.0077 | N10: =IF(L10>I10, "inflation",IF(L10<I10, "deflation","stable")) -> inflation | O10: =IFERROR(IF(N10=C10,1,0),"") -> 1 | P10: =M10-F10 -> -0.00047149528 | Q10: =J10-J9 -> -3.8427027e+09 | R10: =Q10/J9 -> -0.05 | S10: =INDEX(m, MATCH($B$1, 'M stock'!$B$5:$B$271, 0), MATCH(A10, 'M stock'!$A$5:$BQ$5, 0)) -> 0 | T10: =(S10-S9)/S9 -> #DIV/0! | U10: =S10*Y10 -> #DIV/0! | V10: =(U10-U9)/U9 -> #DIV/0! | W10: =S10/B10 -> 0 | X10: =(W10-W9)/W9 -> #DIV/0! | Y10: =J10/S10 -> #DIV/0! | Z10: =(Y10-Y9)/Y9 -> #DIV/0! | AA10: =W10*Y10 -> #DIV/0! | AB10: =AA10-AA9 -> #DIV/0! | AC10: =AB10/AA9 -> #DIV/0! | AD10: =J10-AA10 -> #DIV/0! | AE10: =AA10+AD10 -> #DIV/0! | AF10: =(AE10-AE9)/AE9 -> #DIV/0! | AG10: =AF10-I10 -> #DIV/0! | AH10: =AF10-T11 -> #DIV/0! | AI10: =AF10-X10 -> #DIV/0! | AJ10: =AF10-Z10 -> #DIV/0! | AK10: =IF(AG10>0, "inflation",IF(AG10<0,"deflation","stable")) -> #DIV/0! | AL10: =IFERROR(IF(AK10=C10,1,0),"") | AM10: =AD10/AN10 -> #DIV/0! | AN10: =Y10 -> #DIV/0!
A11: 1968 | B11: =INDEX(p, MATCH($B$1, 'p2'!$B$5:$B$271, 0), MATCH(A11, 'p2'!$A$5:$BQ$5, 0)) -> 1.1330384 | C11: =IF(B11>B10,"inflation",IF(B11<B10,"deflation","stable")) -> inflation | D11: =IF(I11>0,"expansive","contractive") -> contractive | E11: =IF(AND(C11="inflation",D11="expansive"),"inflationary expansion",IF(AND(C11="inflation",D11="contractive"),"stagflation",IF(AND(C11="deflation",D11="expansive"),"deflationary growth",IF(AND(C11="deflation",D11="contractive"),"recession",0)))) -> stagflation | F11: =(B11-B10)/B10 -> 0.013745611 | G11: =J11/B11 -> 6.2646002e+10 | H11: =G11-G10 -> -2.6782962e+09 | I11: =H11/G10 -> -0.041 | J11: =INDEX(PQ, MATCH($B$1, PQ!$B$5:$B$271, 0), MATCH(A11, PQ!$A$5:$BQ$5, 0)) -> 7.0980324e+10 | K11: =J11-J10 -> -2.0310268e+09 | L11: =K11/J10 -> -0.027817959 | M11: =L11-I11 -> 0.013182041 | N11: =IF(L11>I11, "inflation",IF(L11<I11, "deflation","stable")) -> inflation | O11: =IFERROR(IF(N11=C11,1,0),"") -> 1 | P11: =M11-F11 -> -0.00056357003 | Q11: =J11-J10 -> -2.0310268e+09 | R11: =Q11/J10 -> -0.027817959 | S11: =INDEX(m, MATCH($B$1, 'M stock'!$B$5:$B$271, 0), MATCH(A11, 'M stock'!$A$5:$BQ$5, 0)) -> 0 | T11: =(S11-S10)/S10 -> #DIV/0! | U11: =S11*Y11 -> #DIV/0! | V11: =(U11-U10)/U10 -> #DIV/0! | W11: =S11/B11 -> 0 | X11: =(W11-W10)/W10 -> #DIV/0! | Y11: =J11/S11 -> #DIV/0! | Z11: =(Y11-Y10)/Y10 -> #DIV/0! | AA11: =W11*Y11 -> #DIV/0! | AB11: =AA11-AA10 -> #DIV/0! | AC11: =AB11/AA10 -> #DIV/0! | AD11: =J11-AA11 -> #DIV/0! | AE11: =AA11+AD11 -> #DIV/0! | AF11: =(AE11-AE10)/AE10 -> #DIV/0! | AG11: =AF11-I11 -> #DIV/0! | AH11: =AF11-T12 -> #DIV/0! | AI11: =AF11-X11 -> #DIV/0! | AJ11: =AF11-Z11 -> #DIV/0! | AK11: =IF(AG11>0, "inflation",IF(AG11<0,"deflation","stable")) -> #DIV/0! | AL11: =IFERROR(IF(AK11=C11,1,0),"") | AM11: =AD11/AN11 -> #DIV/0! | AN11: =Y11 -> #DIV/0!
A12: 1969 | B12: =INDEX(p, MATCH($B$1, 'p2'!$B$5:$B$271, 0), MATCH(A12, 'p2'!$A$5:$BQ$5, 0)) -> 1.0899496 | C12: =IF(B12>B11,"inflation",IF(B12<B11,"deflation","stable")) -> deflation | D12: =IF(I12>0,"expansive","contractive") -> expansive | E12: =IF(AND(C12="inflation",D12="expansive"),"inflationary expansion",IF(AND(C12="inflation",D12="contractive"),"stagflation",IF(AND(C12="deflation",D12="expansive"),"deflationary growth",IF(AND(C12="deflation",D12="contractive"),"recession",0)))) -> deflationary growth | F12: =(B12-B11)/B11 -> -0.038029361 | G12: =J12/B12 -> 7.3258234e+10 | H12: =G12-G11 -> 1.0612233e+10 | I12: =H12/G11 -> 0.1694 | J12: =INDEX(PQ, MATCH($B$1, PQ!$B$5:$B$271, 0), MATCH(A12, PQ!$A$5:$BQ$5, 0)) -> 7.9847787e+10 | K12: =J12-J11 -> 8.8674629e+09 | L12: =K12/J11 -> 0.12492847 | M12: =L12-I12 -> -0.044471535 | N12: =IF(L12>I12, "inflation",IF(L12<I12, "deflation","stable")) -> deflation | O12: =IFERROR(IF(N12=C12,1,0),"") -> 1 | P12: =M12-F12 -> -0.0064421738 | Q12: =J12-J11 -> 8.8674629e+09 | R12: =Q12/J11 -> 0.12492847 | S12: =INDEX(m, MATCH($B$1, 'M stock'!$B$5:$B$271, 0), MATCH(A12, 'M stock'!$A$5:$BQ$5, 0)) -> 0 | T12: =(S12-S11)/S11 -> #DIV/0! | U12: =S12*Y12 -> #DIV/0! | V12: =(U12-U11)/U11 -> #DIV/0! | W12: =S12/B12 -> 0 | X12: =(W12-W11)/W11 -> #DIV/0! | Y12: =J12/S12 -> #DIV/0! | Z12: =(Y12-Y11)/Y11 -> #DIV/0! | AA12: =W12*Y12 -> #DIV/0! | AB12: =AA12-AA11 -> #DIV/0! | AC12: =AB12/AA11 -> #DIV/0! | AD12: =J12-AA12 -> #DIV/0! | AE12: =AA12+AD12 -> #DIV/0! | AF12: =(AE12-AE11)/AE11 -> #DIV/0! | AG12: =AF12-I12 -> #DIV/0! | AH12: =AF12-T13 -> #DIV/0! | AI12: =AF12-X12 -> #DIV/0! | AJ12: =AF12-Z12 -> #DIV/0! | AK12: =IF(AG12>0, "inflation",IF(AG12<0,"deflation","stable")) -> #DIV/0! | AL12: =IFERROR(IF(AK12=C12,1,0),"") | AM12: =AD12/AN12 -> #DIV/0! | AN12: =Y12 -> #DIV/0!
A13: 1970 | B13: =INDEX(p, MATCH($B$1, 'p2'!$B$5:$B$271, 0), MATCH(A13, 'p2'!$A$5:$BQ$5, 0)) -> 1.0612819 | C13: =IF(B13>B12,"inflation",IF(B13<B12,"deflation","stable")) -> deflation | D13: =IF(I13>0,"expansive","contractive") -> expansive | E13: =IF(AND(C13="inflation",D13="expansive"),"inflationary expansion",IF(AND(C13="inflation",D13="contractive"),"stagflation",IF(AND(C13="deflation",D13="expansive"),"deflationary growth",IF(AND(C13="deflation",D13="contractive"),"recession",0)))) -> deflationary growth | F13: =(B13-B12)/B12 -> -0.026301916 | G13: =J13/B13 -> 8.7397074e+10 | H13: =G13-G12 -> 1.4138839e+10 | I13: =H13/G12 -> 0.193 | J13: =INDEX(PQ, MATCH($B$1, PQ!$B$5:$B$271, 0), MATCH(A13, PQ!$A$5:$BQ$5, 0)) -> 9.2752931e+10 | K13: =J13-J12 -> 1.2905144e+10 | L13: =K13/J12 -> 0.16162181 | M13: =L13-I13 -> -0.031378186 | N13: =IF(L13>I13, "inflation",IF(L13<I13, "deflation","stable")) -> deflation | O13: =IFERROR(IF(N13=C13,1,0),"") -> 1 | P13: =M13-F13 -> -0.0050762698 | Q13: =J13-J12 -> 1.2905144e+10 | R13: =Q13/J12 -> 0.16162181 | S13: =INDEX(m, MATCH($B$1, 'M stock'!$B$5:$B$271, 0), MATCH(A13, 'M stock'!$A$5:$BQ$5, 0)) -> 0 | T13: =(S13-S12)/S12 -> #DIV/0! | U13: =S13*Y13 -> #DIV/0! | V13: =(U13-U12)/U12 -> #DIV/0! | W13: =S13/B13 -> 0 | X13: =(W13-W12)/W12 -> #DIV/0! | Y13: =J13/S13 -> #DIV/0! | Z13: =(Y13-Y12)/Y12 -> #DIV/0! | AA13: =W13*Y13 -> #DIV/0! | AB13: =AA13-AA12 -> #DIV/0! | AC13: =AB13/AA12 -> #DIV/0! | AD13: =J13-AA13 -> #DIV/0! | AE13: =AA13+AD13 -> #DIV/0! | AF13: =(AE13-AE12)/AE12 -> #DIV/0! | AG13: =AF13-I13 -> #DIV/0! | AH13: =AF13-T14 -> #DIV/0! | AI13: =AF13-X13 -> #DIV/0! | AJ13: =AF13-Z13 -> #DIV/0! | AK13: =IF(AG13>0, "inflation",IF(AG13<0,"deflation","stable")) -> #DIV/0! | AL13: =IFERROR(IF(AK13=C13,1,0),"") | AM13: =AD13/AN13 -> #DIV/0! | AN13: =Y13 -> #DIV/0!
A14: 1971 | B14: =INDEX(p, MATCH($B$1, 'p2'!$B$5:$B$271, 0), MATCH(A14, 'p2'!$A$5:$BQ$5, 0)) -> 1.0683113 | C14: =IF(B14>B13,"inflation",IF(B14<B13,"deflation","stable")) -> inflation | D14: =IF(I14>0,"expansive","contractive") -> expansive | E14: =IF(AND(C14="inflation",D14="expansive"),"inflationary expansion",IF(AND(C14="inflation",D14="contractive"),"stagflation",IF(AND(C14="deflation",D14="expansive"),"deflationary growth",IF(AND(C14="deflation",D14="contractive"),"recession",0)))) -> inflationary expansion | F14: =(B14-B13)/B13 -> 0.0066235404 | G14: =J14/B14 -> 9.3567307e+10 | H14: =G14-G13 -> 6.1702334e+09 | I14: =H14/G13 -> 0.0706 | J14: =INDEX(PQ, MATCH($B$1, PQ!$B$5:$B$271, 0), MATCH(A14, PQ!$A$5:$BQ$5, 0)) -> 9.9959014e+10 | K14: =J14-J13 -> 7.206083e+09 | L14: =K14/J13 -> 0.077691162 | M14: =L14-I14 -> 0.0070911623 | N14: =IF(L14>I14, "inflation",IF(L14<I14, "deflation","stable")) -> inflation | O14: =IFERROR(IF(N14=C14,1,0),"") -> 1 | P14: =M14-F14 -> 0.00046762195 | Q14: =J14-J13 -> 7.206083e+09 | R14: =Q14/J13 -> 0.077691162 | S14: =INDEX(m, MATCH($B$1, 'M stock'!$B$5:$B$271, 0), MATCH(A14, 'M stock'!$A$5:$BQ$5, 0)) -> 0 | T14: =(S14-S13)/S13 -> #DIV/0! | U14: =S14*Y14 -> #DIV/0! | V14: =(U14-U13)/U13 -> #DIV/0! | W14: =S14/B14 -> 0 | X14: =(W14-W13)/W13 -> #DIV/0! | Y14: =J14/S14 -> #DIV/0! | Z14: =(Y14-Y13)/Y13 -> #DIV/0! | AA14: =W14*Y14 -> #DIV/0! | AB14: =AA14-AA13 -> #DIV/0! | AC14: =AB14/AA13 -> #DIV/0! | AD14: =J14-AA14 -> #DIV/0! | AE14: =AA14+AD14 -> #DIV/0! | AF14: =(AE14-AE13)/AE13 -> #DIV/0! | AG14: =AF14-I14 -> #DIV/0! | AH14: =AF14-T15 -> #DIV/0! | AI14: =AF14-X14 -> #DIV/0! | AJ14: =AF14-Z14 -> #DIV/0! | AK14: =IF(AG14>0, "inflation",IF(AG14<0,"deflation","stable")) -> #DIV/0! | AL14: =IFERROR(IF(AK14=C14,1,0),"") | AM14: =AD14/AN14 -> #DIV/0! | AN14: =Y14 -> #DIV/0!
A15: 1972 | B15: =INDEX(p, MATCH($B$1, 'p2'!$B$5:$B$271, 0), MATCH(A15, 'p2'!$A$5:$BQ$5, 0)) -> 1.0691241 | C15: =IF(B15>B14,"inflation",IF(B15<B14,"deflation","stable")) -> inflation | D15: =IF(I15>0,"expansive","contractive") -> expansive | E15: =IF(AND(C15="inflation",D15="expansive"),"inflationary expansion",IF(AND(C15="inflation",D15="contractive"),"stagflation",IF(AND(C15="deflation",D15="expansive"),"deflationary growth",IF(AND(C15="deflation",D15="contractive"),"recession",0)))) -> inflationary expansion | F15: =(B15-B14)/B14 -> 0.00076080526 | G15: =J15/B15 -> 1.0650955e+11 | H15: =G15-G14 -> 1.2942246e+10 | I15: =H15/G14 -> 0.13832018 | J15: =INDEX(PQ, MATCH($B$1, PQ!$B$5:$B$271, 0), MATCH(A15, PQ!$A$5:$BQ$5, 0)) -> 1.1387193e+11 | K15: =J15-J14 -> 1.3912917e+10 | L15: =K15/J14 -> 0.13918622 | M15: =L15-I15 -> 0.00086603997 | N15: =IF(L15>I15, "inflation",IF(L15<I15, "deflation","stable")) -> inflation | O15: =IFERROR(IF(N15=C15,1,0),"") -> 1 | P15: =M15-F15 -> 0.00010523472 | Q15: =J15-J14 -> 1.3912917e+10 | R15: =Q15/J14 -> 0.13918622 | S15: =INDEX(m, MATCH($B$1, 'M stock'!$B$5:$B$271, 0), MATCH(A15, 'M stock'!$A$5:$BQ$5, 0)) -> 0 | T15: =(S15-S14)/S14 -> #DIV/0! | U15: =S15*Y15 -> #DIV/0! | V15: =(U15-U14)/U14 -> #DIV/0! | W15: =S15/B15 -> 0 | X15: =(W15-W14)/W14 -> #DIV/0! | Y15: =J15/S15 -> #DIV/0! | Z15: =(Y15-Y14)/Y14 -> #DIV/0! | AA15: =W15*Y15 -> #DIV/0! | AB15: =AA15-AA14 -> #DIV/0! | AC15: =AB15/AA14 -> #DIV/0! | AD15: =J15-AA15 -> #DIV/0! | AE15: =AA15+AD15 -> #DIV/0! | AF15: =(AE15-AE14)/AE14 -> #DIV/0! | AG15: =AF15-I15 -> #DIV/0! | AH15: =AF15-T16 -> #DIV/0! | AI15: =AF15-X15 -> #DIV/0! | AJ15: =AF15-Z15 -> #DIV/0! | AK15: =IF(AG15>0, "inflation",IF(AG15<0,"deflation","stable")) -> #DIV/0! | AL15: =IFERROR(IF(AK15=C15,1,0),"") | AM15: =AD15/AN15 -> #DIV/0! | AN15: =Y15 -> #DIV/0!
... A67: 2024 | B67: =INDEX(p, MATCH($B$1, 'p2'!$B$5:$B$271, 0), MATCH(A67, 'p2'!$A$5:$BQ$5, 0)) -> 7.9752314 | C67: =IF(B67>B66,"inflation",IF(B67<B66,"deflation","stable")) -> deflation | D67: =IF(I67>0,"expansive","contractive") -> expansive | E67: =IF(AND(C67="inflation",D67="expansive"),"inflationary expansion",IF(AND(C67="inflation",D67="contractive"),"stagflation",IF(AND(C67="deflation",D67="expansive"),"deflationary growth",IF(AND(C67="deflation",D67="contractive"),"recession",0)))) -> deflationary growth | F67: =(B67-B66)/B66 -> -0.0070720001 | G67: =J67/B67 -> 2.3502519e+12 | H67: =G67-G66 -> 7.5565767e+10 | I67: =H67/G66 -> 0.033220304 | J67: =INDEX(PQ, MATCH($B$1, PQ!$B$5:$B$271, 0), MATCH(A67, PQ!$A$5:$BQ$5, 0)) -> 1.8743803e+13 | K67: =J67-J66 -> 473446516294 | L67: =K67/J66 -> 0.02591337 | M67: =L67-I67 -> -0.0073069341 | N67: =IF(L67>I67, "inflation",IF(L67<I67, "deflation","stable")) -> deflation | O67: =IFERROR(IF(N67=C67,1,0),"") -> 1 | P67: =M67-F67 -> -0.000234934 | Q67: =J67-J66 -> 473446516294 | R67: =Q67/J66 -> 0.02591337 | S67: =INDEX(m, MATCH($B$1, 'M stock'!$B$5:$B$271, 0), MATCH(A67, 'M stock'!$A$5:$BQ$5, 0)) -> 4.2641654e+13 | T67: =(S67-S66)/S66 -> 0.051264719 | U67: =S67*Y67 -> 1.8743803e+13 | V67: =(U67-U66)/U66 -> 0.02591337 | W67: =S67/B67 -> 5.3467607e+12 | X67: =(W67-W66)/W66 -> 0.058752215 | Y67: =J67/S67 -> 0.43956557 | Z67: =(Y67-Y66)/Y66 -> -0.024115095 | AA67: =W67*Y67 -> 2.3502519e+12 | AB67: =AA67-AA66 -> 7.5565767e+10 | AC67: =AB67/AA66 -> 0.033220304 | AD67: =J67-AA67 -> 1.6393551e+13 | AE67: =AA67+AD67 -> 1.8743803e+13 | AF67: =(AE67-AE66)/AE66 -> 0.02591337 | AG67: =AF67-I67 -> -0.0073069341 | AH67: =AF67-T68 -> 0.02591337 | AI67: =AF67-X67 -> -0.032838845 | AJ67: =AF67-Z67 -> 0.050028465 | AK67: =IF(AG67>0, "inflation",IF(AG67<0,"deflation","stable")) -> deflation | AL67: =IFERROR(IF(AK67=C67,1,0),"") -> 1 | AM67: =AD67/AN67 -> 3.7294893e+13 | AN67: =Y67 -> 0.43956557
N69: Economic Themal Dynamic Accuracy (Left Side PQ) | O69: =SUM(O4:O57)/COUNT(O4:O57) -> 1 | AK69: Economic Themal Dynamic Accuracy (Right Side MV+FAC) | AL69: =SUM(AL4:AL57)/COUNT(AL4:AL57) -> 1
N71: Matches | O71: =SUM(O3:O67) -> 64 | AK71: Matches | AL71: =SUM(AL3:AL67) -> 47
N72: Count | O72: =COUNT(O3:O67) -> 64 | AK72: Count | AL72: =COUNT(AL3:AL67) -> 47
A74: Source:
A75: World Bank
A76: https://data.worldbank.org/
A78: Broad Money (% of GDP)
A79: API_FM.LBL.BMNY.GD.ZS_DS2_en_csv_v2_123670
A80: Used to analyze monetary aggregates relative to GDP
A82: GDP Deflator (scaled to start meaningful P at 1)_
A83: API_NY.GDP.DEFL.ZS_DS2_en_csv_v2_124034
A84: Used to convert nominal GDP to real terms and track change in P over time
A86: GDP (current US$)
A87: API_NY.GDP.MKTP.CD_DS2_en_csv_v2_130122
A88: Core GDP series for nominal valuation
... A108: affirming the robustness of our own data sources and calculations.

Sheet Germany
B1: =VLOOKUP(C1,PQ!A6:B271,2,FALSE) -> DEU | C1: Germany | H1: =IFERROR(B3+B4,"wrong") -> 2.0506399
A2: Period | B2: P | C2: Observe | D2: Economy | E2: Diagnosis | F2: Δ P % | G2: Q | H2: Δ Q | I2: Δ Q % | J2: PQ | K2: Δ PQ | L2: Δ PQ % | M2: Δ PQ % - Δ Q % | N2: test | O2: match? | P2: (Δ PQ % - Δ Q %) -Δ P % = Δ P x Δ Q (interaction) | Q2: ΔPQ | R2: Δ%PQ | S2: M | T2: ΔM % | U2: MV | V2: ΔMV % | W2: M(d.) | X2: ΔM(d.) % | Y2: V | Z2: Δ V % | AA2: MV(d.) | AB2: ΔMV(d.) | AC2: Δ%MV(d.) | AD2: PQ-MV(d.) (FAC) | AE2: MV(d.) + FAC | AF2: Δ MV(d.)+FAC % | AG2: Δ MV(d.)+FAC % - Δ Q % | AH2: Δ MV(d.)+FAC % - Δ M % | AI2: Δ MV(d.)+FAC % - Δ M % | AJ2: Δ MV(d.)+FAC % - Δ V % | AK2: test | AL2: match? | AM2: M_FAC | AN2: V_FAC
A3: 1960 | B3: =INDEX(p, MATCH($B$1, 'p2'!$B$5:$B$271, 0), MATCH(A3, 'p2'!$A$5:$BQ$5, 0)) -> 1 | G3: =J3/B3 -> 8.4619846e+10 | H3: =G3-G2 -> #VALUE! | I3: =H3-H2 -> #VALUE! | J3: =INDEX(PQ, MATCH($B$1, PQ!$B$5:$B$271, 0), MATCH(A3, PQ!$A$5:$BQ$5, 0)) -> 8.4619846e+10 | K3: =J3-J2 -> #VALUE! | L3: =(K3-K2)/K2 -> #VALUE! | M3: =L3-I3 -> #VALUE! | S3: =INDEX(m, MATCH($B$1, 'M stock'!$B$5:$B$271, 0), MATCH(A3, 'M stock'!$A$5:$BQ$5, 0)) -> 0 | U3: =S3*Y3 -> #DIV/0! | W3: =S3/B3 -> 0 | Y3: =J3/S3 -> #DIV/0! | AA3: =W3*Y3 -> #DIV/0! | AD3: =J3-AA3 -> #DIV/0! | AE3: =AA3+AD3 -> #DIV/0! | AG3: =AF3-I3 -> #VALUE! | AH3: =AF3-T4 -> #DIV/0! | AI3: =AF3-X3 -> 0 | AJ3: =AF3-Z3 -> 0
A4: 1961 | B4: =INDEX(p, MATCH($B$1, 'p2'!$B$5:$B$271, 0), MATCH(A4, 'p2'!$A$5:$BQ$5, 0)) -> 1.0506399 | C4: =IF(B4>B3,"inflation",IF(B4<B3,"deflation","stable")) -> inflation | D4: =IF(I4>0,"expansive","contractive") -> expansive | E4: =IF(AND(C4="inflation",D4="expansive"),"inflationary expansion",IF(AND(C4="inflation",D4="contractive"),"stagflation",IF(AND(C4="deflation",D4="expansive"),"deflationary growth",IF(AND(C4="deflation",D4="contractive"),"recession",0)))) -> inflationary expansion | F4: =(B4-B3)/B3 -> 0.050639948 | G4: =J4/B4 -> 9.1904181e+10 | H4: =G4-G3 -> 7.2843352e+09 | I4: =H4/G3 -> 0.086083059 | J4: =INDEX(PQ, MATCH($B$1, PQ!$B$5:$B$271, 0), MATCH(A4, PQ!$A$5:$BQ$5, 0)) -> 9.6558204e+10 | K4: =J4-J3 -> 1.1938358e+10 | L4: =K4/J3 -> 0.14108225 | M4: =L4-I4 -> 0.05499919 | N4: =IF(L4>I4, "inflation",IF(L4<I4, "deflation","stable")) -> inflation | O4: =IFERROR(IF(N4=C4,1,0),"") -> 1 | P4: =M4-F4 -> 0.0043592417 | Q4: =J4-J3 -> 1.1938358e+10 | R4: =Q4/J3 -> 0.14108225 | S4: =INDEX(m, MATCH($B$1, 'M stock'!$B$5:$B$271, 0), MATCH(A4, 'M stock'!$A$5:$BQ$5, 0)) -> 0 | T4: =(S4-S3)/S3 -> #DIV/0! | U4: =S4*Y4 -> #DIV/0! | V4: =(U4-U3)/U3 -> #DIV/0! | W4: =S4/B4 -> 0 | X4: =(W4-W3)/W3 -> #DIV/0! | Y4: =J4/S4 -> #DIV/0! | Z4: =(Y4-Y3)/Y3 -> #DIV/0! | AA4: =W4*Y4 -> #DIV/0! | AB4: =AA4-AA3 -> #DIV/0! | AC4: =AB4/AA3 -> #DIV/0! | AD4: =J4-AA4 -> #DIV/0! | AE4: =AA4+AD4 -> #DIV/0! | AF4: =(AE4-AE3)/AE3 -> #DIV/0! | AG4: =AF4-I4 -> #DIV/0! | AH4: =AF4-T5 -> #DIV/0! | AI4: =AF4-X4 -> #DIV/0! | AJ4: =AF4-Z4 -> #DIV/0! | AK4: =IF(AG4>0, "inflation",IF(AG4<0,"deflation","stable")) -> #DIV/0! | AL4: =IFERROR(IF(AK4=C4,1,0),"") | AM4: =AD4/AN4 -> #DIV/0! | AN4: =Y4 -> #DIV/0!
A5: 1962 | B5: =INDEX(p, MATCH($B$1, 'p2'!$B$5:$B$271, 0), MATCH(A5, 'p2'!$A$5:$BQ$5, 0)) -> 1.0922166 | C5: =IF(B5>B4,"inflation",IF(B5<B4,"deflation","stable")) -> inflation | D5: =IF(I5>0,"expansive","contractive") -> expansive | E5: =IF(AND(C5="inflation",D5="expansive"),"inflationary expansion",IF(AND(C5="inflation",D5="contractive"),"stagflation",IF(AND(C5="deflation",D5="expansive"),"deflationary growth",IF(AND(C5="deflation",D5="contractive"),"recession",0)))) -> inflationary expansion | F5: =(B5-B4)/B4 -> 0.039572665 | G5: =J5/B5 -> 9.6954613e+10 | H5: =G5-G4 -> 5.0504322e+09 | I5: =H5/G4 -> 0.054953237 | J5: =INDEX(PQ, MATCH($B$1, PQ!$B$5:$B$271, 0), MATCH(A5, PQ!$A$5:$BQ$5, 0)) -> 1.0589544e+11 | K5: =J5-J4 -> 9.3372312e+09 | L5: =K5/J4 -> 0.096700547 | M5: =L5-I5 -> 0.041747311 | N5: =IF(L5>I5, "inflation",IF(L5<I5, "deflation","stable")) -> inflation | O5: =IFERROR(IF(N5=C5,1,0),"") -> 1 | P5: =M5-F5 -> 0.002174646 | Q5: =J5-J4 -> 9.3372312e+09 | R5: =Q5/J4 -> 0.096700547 | S5: =INDEX(m, MATCH($B$1, 'M stock'!$B$5:$B$271, 0), MATCH(A5, 'M stock'!$A$5:$BQ$5, 0)) -> 0 | T5: =(S5-S4)/S4 -> #DIV/0! | U5: =S5*Y5 -> #DIV/0! | V5: =(U5-U4)/U4 -> #DIV/0! | W5: =S5/B5 -> 0 | X5: =(W5-W4)/W4 -> #DIV/0! | Y5: =J5/S5 -> #DIV/0! | Z5: =(Y5-Y4)/Y4 -> #DIV/0! | AA5: =W5*Y5 -> #DIV/0! | AB5: =AA5-AA4 -> #DIV/0! | AC5: =AB5/AA4 -> #DIV/0! | AD5: =J5-AA5 -> #DIV/0! | AE5: =AA5+AD5 -> #DIV/0! | AF5: =(AE5-AE4)/AE4 -> #DIV/0! | AG5: =AF5-I5 -> #DIV/0! | AH5: =AF5-T6 -> #DIV/0! | AI5: =AF5-X5 -> #DIV/0! | AJ5: =AF5-Z5 -> #DIV/0! | AK5: =IF(AG5>0, "inflation",IF(AG5<0,"deflation","stable")) -> #DIV/0! | AL5: =IFERROR(IF(AK5=C5,1,0),"") | AM5: =AD5/AN5 -> #DIV/0! | AN5: =Y5 -> #DIV/0!
A6: 1963 | B6: =INDEX(p, MATCH($B$1, 'p2'!$B$5:$B$271, 0), MATCH(A6, 'p2'!$A$5:$BQ$5, 0)) -> 1.1267576 | C6: =IF(B6>B5,"inflation",IF(B6<B5,"deflation","stable")) -> inflation | D6: =IF(I6>0,"expansive","contractive") -> expansive | E6: =IF(AND(C6="inflation",D6="expansive"),"inflationary expansion",IF(AND(C6="inflation",D6="contractive"),"stagflation",IF(AND(C6="deflation",D6="expansive"),"deflationary growth",IF(AND(C6="deflation",D6="contractive"),"recession",0)))) -> inflationary expansion | F6: =(B6-B5)/B5 -> 0.031624704 | G6: =J6/B6 -> 9.9606609e+10 | H6: =G6-G5 -> 2.6519961e+09 | I6: =H6/G5 -> 0.027352964 | J6: =INDEX(PQ, MATCH($B$1, PQ!$B$5:$B$271, 0), MATCH(A6, PQ!$A$5:$BQ$5, 0)) -> 1.122325e+11 | K6: =J6-J5 -> 6.3370685e+09 | L6: =K6/J5 -> 0.059842698 | M6: =L6-I6 -> 0.032489734 | N6: =IF(L6>I6, "inflation",IF(L6<I6, "deflation","stable")) -> inflation | O6: =IFERROR(IF(N6=C6,1,0),"") -> 1 | P6: =M6-F6 -> 0.0008650294 | Q6: =J6-J5 -> 6.3370685e+09 | R6: =Q6/J5 -> 0.059842698 | S6: =INDEX(m, MATCH($B$1, 'M stock'!$B$5:$B$271, 0), MATCH(A6, 'M stock'!$A$5:$BQ$5, 0)) -> 0 | T6: =(S6-S5)/S5 -> #DIV/0! | U6: =S6*Y6 -> #DIV/0! | V6: =(U6-U5)/U5 -> #DIV/0! | W6: =S6/B6 -> 0 | X6: =(W6-W5)/W5 -> #DIV/0! | Y6: =J6/S6 -> #DIV/0! | Z6: =(Y6-Y5)/Y5 -> #DIV/0! | AA6: =W6*Y6 -> #DIV/0! | AB6: =AA6-AA5 -> #DIV/0! | AC6: =AB6/AA5 -> #DIV/0! | AD6: =J6-AA6 -> #DIV/0! | AE6: =AA6+AD6 -> #DIV/0! | AF6: =(AE6-AE5)/AE5 -> #DIV/0! | AG6: =AF6-I6 -> #DIV/0! | AH6: =AF6-T7 -> #DIV/0! | AI6: =AF6-X6 -> #DIV/0! | AJ6: =AF6-Z6 -> #DIV/0! | AK6: =IF(AG6>0, "inflation",IF(AG6<0,"deflation","stable")) -> #DIV/0! | AL6: =IFERROR(IF(AK6=C6,1,0),"") | AM6: =AD6/AN6 -> #DIV/0! | AN6: =Y6 -> #DIV/0!
A7: 1964 | B7: =INDEX(p, MATCH($B$1, 'p2'!$B$5:$B$271, 0), MATCH(A7, 'p2'!$A$5:$BQ$5, 0)) -> 1.161085 | C7: =IF(B7>B6,"inflation",IF(B7<B6,"deflation","stable")) -> inflation | D7: =IF(I7>0,"expansive","contractive") -> expansive | E7: =IF(AND(C7="inflation",D7="expansive"),"inflationary expansion",IF(AND(C7="inflation",D7="contractive"),"stagflation",IF(AND(C7="deflation",D7="expansive"),"deflationary growth",IF(AND(C7="deflation",D7="contractive"),"recession",0)))) -> inflationary expansion | F7: =(B7-B6)/B6 -> 0.030465669 | G7: =J7/B7 -> 1.0621996e+11 | H7: =G7-G6 -> 6.6133509e+09 | I7: =H7/G6 -> 0.066394699 | J7: =INDEX(PQ, MATCH($B$1, PQ!$B$5:$B$271, 0), MATCH(A7, PQ!$A$5:$BQ$5, 0)) -> 1.233304e+11 | K7: =J7-J6 -> 1.1097901e+10 | L7: =K7/J6 -> 0.098883127 | M7: =L7-I7 -> 0.032488428 | N7: =IF(L7>I7, "inflation",IF(L7<I7, "deflation","stable")) -> inflation | O7: =IFERROR(IF(N7=C7,1,0),"") -> 1 | P7: =M7-F7 -> 0.0020227589 | Q7: =J7-J6 -> 1.1097901e+10 | R7: =Q7/J6 -> 0.098883127 | S7: =INDEX(m, MATCH($B$1, 'M stock'!$B$5:$B$271, 0), MATCH(A7, 'M stock'!$A$5:$BQ$5, 0)) -> 0 | T7: =(S7-S6)/S6 -> #DIV/0! | U7: =S7*Y7 -> #DIV/0! | V7: =(U7-U6)/U6 -> #DIV/0! | W7: =S7/B7 -> 0 | X7: =(W7-W6)/W6 -> #DIV/0! | Y7: =J7/S7 -> #DIV/0! | Z7: =(Y7-Y6)/Y6 -> #DIV/0! | AA7: =W7*Y7 -> #DIV/0! | AB7: =AA7-AA6 -> #DIV/0! | AC7: =AB7/AA6 -> #DIV/0! | AD7: =J7-AA7 -> #DIV/0! | AE7: =AA7+AD7 -> #DIV/0! | AF7: =(AE7-AE6)/AE6 -> #DIV/0! | AG7: =AF7-I7 -> #DIV/0! | AH7: =AF7-T8 -> #DIV/0! | AI7: =AF7-X7 -> #DIV/0! | AJ7: =AF7-Z7 -> #DIV/0! | AK7: =IF(AG7>0, "inflation",IF(AG7<0,"deflation","stable")) -> #DIV/0! | AL7: =IFERROR(IF(AK7=C7,1,0),"") | AM7: =AD7/AN7 -> #DIV/0! | AN7: =Y7 -> #DIV/0!
A8: 1965 | B8: =INDEX(p, MATCH($B$1, 'p2'!$B$5:$B$271, 0), MATCH(A8, 'p2'!$A$5:$BQ$5, 0)) -> 1.2056026 | C8: =IF(B8>B7,"inflation",IF(B8<B7,"deflation","stable")) -> inflation | D8: =IF(I8>0,"expansive","contractive") -> expansive | E8: =IF(AND(C8="inflation",D8="expansive"),"inflationary expansion",IF(AND(C8="inflation",D8="contractive"),"stagflation",IF(AND(C8="deflation",D8="expansive"),"deflationary growth",IF(AND(C8="deflation",D8="contractive"),"recession",0)))) -> inflationary expansion | F8: =(B8-B7)/B7 -> 0.038341367 | G8: =J8/B8 -> 1.1179031e+11 | H8: =G8-G7 -> 5.570349e+09 | I8: =H8/G7 -> 0.052441641 | J8: =INDEX(PQ, MATCH($B$1, PQ!$B$5:$B$271, 0), MATCH(A8, PQ!$A$5:$BQ$5, 0)) -> 1.3477469e+11 | K8: =J8-J7 -> 1.1444284e+10 | L8: =K8/J7 -> 0.092793692 | M8: =L8-I8 -> 0.040352051 | N8: =IF(L8>I8, "inflation",IF(L8<I8, "deflation","stable")) -> inflation | O8: =IFERROR(IF(N8=C8,1,0),"") -> 1 | P8: =M8-F8 -> 0.0020106842 | Q8: =J8-J7 -> 1.1444284e+10 | R8: =Q8/J7 -> 0.092793692 | S8: =INDEX(m, MATCH($B$1, 'M stock'!$B$5:$B$271, 0), MATCH(A8, 'M stock'!$A$5:$BQ$5, 0)) -> 0 | T8: =(S8-S7)/S7 -> #DIV/0! | U8: =S8*Y8 -> #DIV/0! | V8: =(U8-U7)/U7 -> #DIV/0! | W8: =S8/B8 -> 0 | X8: =(W8-W7)/W7 -> #DIV/0! | Y8: =J8/S8 -> #DIV/0! | Z8: =(Y8-Y7)/Y7 -> #DIV/0! | AA8: =W8*Y8 -> #DIV/0! | AB8: =AA8-AA7 -> #DIV/0! | AC8: =AB8/AA7 -> #DIV/0! | AD8: =J8-AA8 -> #DIV/0! | AE8: =AA8+AD8 -> #DIV/0! | AF8: =(AE8-AE7)/AE7 -> #DIV/0! | AG8: =AF8-I8 -> #DIV/0! | AH8: =AF8-T9 -> #DIV/0! | AI8: =AF8-X8 -> #DIV/0! | AJ8: =AF8-Z8 -> #DIV/0! | AK8: =IF(AG8>0, "inflation",IF(AG8<0,"deflation","stable")) -> #DIV/0! | AL8: =IFERROR(IF(AK8=C8,1,0),"") | AM8: =AD8/AN8 -> #DIV/0! | AN8: =Y8 -> #DIV/0!
A9: 1966 | B9: =INDEX(p, MATCH($B$1, 'p2'!$B$5:$B$271, 0), MATCH(A9, 'p2'!$A$5:$BQ$5, 0)) -> 1.2468391 | C9: =IF(B9>B8,"inflation",IF(B9<B8,"deflation","stable")) -> inflation | D9: =IF(I9>0,"expansive","contractive") -> expansive | E9: =IF(AND(C9="inflation",D9="expansive"),"inflationary expansion",IF(AND(C9="inflation",D9="contractive"),"stagflation",IF(AND(C9="deflation",D9="expansive"),"deflationary growth",IF(AND(C9="deflation",D9="contractive"),"recession",0)))) -> inflationary expansion | F9: =(B9-B8)/B8 -> 0.034204062 | G9: =J9/B9 -> 1.1493406e+11 | H9: =G9-G8 -> 3.1437461e+09 | I9: =H9/G8 -> 0.028121813 | J9: =INDEX(PQ, MATCH($B$1, PQ!$B$5:$B$271, 0), MATCH(A9, PQ!$A$5:$BQ$5, 0)) -> 1.4330428e+11 | K9: =J9-J8 -> 8.5295875e+09 | L9: =K9/J8 -> 0.063287755 | M9: =L9-I9 -> 0.035165943 | N9: =IF(L9>I9, "inflation",IF(L9<I9, "deflation","stable")) -> inflation | O9: =IFERROR(IF(N9=C9,1,0),"") -> 1 | P9: =M9-F9 -> 0.00096188024 | Q9: =J9-J8 -> 8.5295875e+09 | R9: =Q9/J8 -> 0.063287755 | S9: =INDEX(m, MATCH($B$1, 'M stock'!$B$5:$B$271, 0), MATCH(A9, 'M stock'!$A$5:$BQ$5, 0)) -> 0 | T9: =(S9-S8)/S8 -> #DIV/0! | U9: =S9*Y9 -> #DIV/0! | V9: =(U9-U8)/U8 -> #DIV/0! | W9: =S9/B9 -> 0 | X9: =(W9-W8)/W8 -> #DIV/0! | Y9: =J9/S9 -> #DIV/0! | Z9: =(Y9-Y8)/Y8 -> #DIV/0! | AA9: =W9*Y9 -> #DIV/0! | AB9: =AA9-AA8 -> #DIV/0! | AC9: =AB9/AA8 -> #DIV/0! | AD9: =J9-AA9 -> #DIV/0! | AE9: =AA9+AD9 -> #DIV/0! | AF9: =(AE9-AE8)/AE8 -> #DIV/0! | AG9: =AF9-I9 -> #DIV/0! | AH9: =AF9-T10 -> #DIV/0! | AI9: =AF9-X9 -> #DIV/0! | AJ9: =AF9-Z9 -> #DIV/0! | AK9: =IF(AG9>0, "inflation",IF(AG9<0,"deflation","stable")) -> #DIV/0! | AL9: =IFERROR(IF(AK9=C9,1,0),"") | AM9: =AD9/AN9 -> #DIV/0! | AN9: =Y9 -> #DIV/0!
A10: 1967 | B10: =INDEX(p, MATCH($B$1, 'p2'!$B$5:$B$271, 0), MATCH(A10, 'p2'!$A$5:$BQ$5, 0)) -> 1.2666521 | C10: =IF(B10>B9,"inflation",IF(B10<B9,"deflation","stable")) -> inflation | D10: =IF(I10>0,"expansive","contractive") -> contractive | E10: =IF(AND(C10="inflation",D10="expansive"),"inflationary expansion",IF(AND(C10="inflation",D10="contractive"),"stagflation",IF(AND(C10="deflation",D10="expansive"),"deflationary growth",IF(AND(C10="deflation",D10="contractive"),"recession",0)))) -> stagflation | F10: =(B10-B9)/B9 -> 0.015890554 | G10: =J10/B10 -> 1.1455448e+11 | H10: =G10-G9 -> -3.7957717e+08 | I10: =H10/G9 -> -0.0033025649 | J10: =INDEX(PQ, MATCH($B$1, PQ!$B$5:$B$271, 0), MATCH(A10, PQ!$A$5:$BQ$5, 0)) -> 1.4510067e+11 | K10: =J10-J9 -> 1.7963921e+09 | L10: =K10/J9 -> 0.012535509 | M10: =L10-I10 -> 0.015838074 | N10: =IF(L10>I10, "inflation",IF(L10<I10, "deflation","stable")) -> inflation | O10: =IFERROR(IF(N10=C10,1,0),"") -> 1 | P10: =M10-F10 -> -5.2479584e-05 | Q10: =J10-J9 -> 1.7963921e+09 | R10: =Q10/J9 -> 0.012535509 | S10: =INDEX(m, MATCH($B$1, 'M stock'!$B$5:$B$271, 0), MATCH(A10, 'M stock'!$A$5:$BQ$5, 0)) -> 0 | T10: =(S10-S9)/S9 -> #DIV/0! | U10: =S10*Y10 -> #DIV/0! | V10: =(U10-U9)/U9 -> #DIV/0! | W10: =S10/B10 -> 0 | X10: =(W10-W9)/W9 -> #DIV/0! | Y10: =J10/S10 -> #DIV/0! | Z10: =(Y10-Y9)/Y9 -> #DIV/0! | AA10: =W10*Y10 -> #DIV/0! | AB10: =AA10-AA9 -> #DIV/0! | AC10: =AB10/AA9 -> #DIV/0! | AD10: =J10-AA10 -> #DIV/0! | AE10: =AA10+AD10 -> #DIV/0! | AF10: =(AE10-AE9)/AE9 -> #DIV/0! | AG10: =AF10-I10 -> #DIV/0! | AH10: =AF10-T11 -> #DIV/0! | AI10: =AF10-X10 -> #DIV/0! | AJ10: =AF10-Z10 -> #DIV/0! | AK10: =IF(AG10>0, "inflation",IF(AG10<0,"deflation","stable")) -> #DIV/0! | AL10: =IFERROR(IF(AK10=C10,1,0),"") | AM10: =AD10/AN10 -> #DIV/0! | AN10: =Y10 -> #DIV/0!
A11: 1968 | B11: =INDEX(p, MATCH($B$1, 'p2'!$B$5:$B$271, 0), MATCH(A11, 'p2'!$A$5:$BQ$5, 0)) -> 1.2930977 | C11: =IF(B11>B10,"inflation",IF(B11<B10,"deflation","stable")) -> inflation | D11: =IF(I11>0,"expansive","contractive") -> expansive | E11: =IF(AND(C11="inflation",D11="expansive"),"inflationary expansion",IF(AND(C11="inflation",D11="contractive"),"stagflation",IF(AND(C11="deflation",D11="expansive"),"deflationary growth",IF(AND(C11="deflation",D11="contractive"),"recession",0)))) -> inflationary expansion | F11: =(B11-B10)/B10 -> 0.020878359 | G11: =J11/B11 -> 1.2104831e+11 | H11: =G11-G10 -> 6.4938334e+09 | I11: =H11/G10 -> 0.056687731 | J11: =INDEX(PQ, MATCH($B$1, PQ!$B$5:$B$271, 0), MATCH(A11, PQ!$A$5:$BQ$5, 0)) -> 1.5652729e+11 | K11: =J11-J10 -> 1.1426625e+10 | L11: =K11/J10 -> 0.078749637 | M11: =L11-I11 -> 0.022061906 | N11: =IF(L11>I11, "inflation",IF(L11<I11, "deflation","stable")) -> inflation | O11: =IFERROR(IF(N11=C11,1,0),"") -> 1 | P11: =M11-F11 -> 0.0011835468 | Q11: =J11-J10 -> 1.1426625e+10 | R11: =Q11/J10 -> 0.078749637 | S11: =INDEX(m, MATCH($B$1, 'M stock'!$B$5:$B$271, 0), MATCH(A11, 'M stock'!$A$5:$BQ$5, 0)) -> 0 | T11: =(S11-S10)/S10 -> #DIV/0! | U11: =S11*Y11 -> #DIV/0! | V11: =(U11-U10)/U10 -> #DIV/0! | W11: =S11/B11 -> 0 | X11: =(W11-W10)/W10 -> #DIV/0! | Y11: =J11/S11 -> #DIV/0! | Z11: =(Y11-Y10)/Y10 -> #DIV/0! | AA11: =W11*Y11 -> #DIV/0! | AB11: =AA11-AA10 -> #DIV/0! | AC11: =AB11/AA10 -> #DIV/0! | AD11: =J11-AA11 -> #DIV/0! | AE11: =AA11+AD11 -> #DIV/0! | AF11: =(AE11-AE10)/AE10 -> #DIV/0! | AG11: =AF11-I11 -> #DIV/0! | AH11: =AF11-T12 -> #DIV/0! | AI11: =AF11-X11 -> #DIV/0! | AJ11: =AF11-Z11 -> #DIV/0! | AK11: =IF(AG11>0, "inflation",IF(AG11<0,"deflation","stable")) -> #DIV/0! | AL11: =IFERROR(IF(AK11=C11,1,0),"") | AM11: =AD11/AN11 -> #DIV/0! | AN11: =Y11 -> #DIV/0!
A12: 1969 | B12: =INDEX(p, MATCH($B$1, 'p2'!$B$5:$B$271, 0), MATCH(A12, 'p2'!$A$5:$BQ$5, 0)) -> 1.347524 | C12: =IF(B12>B11,"inflation",IF(B12<B11,"deflation","stable")) -> inflation | D12: =IF(I12>0,"expansive","contractive") -> expansive | E12: =IF(AND(C12="inflation",D12="expansive"),"inflationary expansion",IF(AND(C12="inflation",D12="contractive"),"stagflation",IF(AND(C12="deflation",D12="expansive"),"deflationary growth",IF(AND(C12="deflation",D12="contractive"),"recession",0)))) -> inflationary expansion | F12: =(B12-B11)/B11 -> 0.042089879 | G12: =J12/B12 -> 1.3189634e+11 | H12: =G12-G11 -> 1.0848028e+10 | I12: =H12/G11 -> 0.089617345 | J12: =INDEX(PQ, MATCH($B$1, PQ!$B$5:$B$271, 0), MATCH(A12, PQ!$A$5:$BQ$5, 0)) -> 1.7773349e+11 | K12: =J12-J11 -> 2.1206194e+10 | L12: =K12/J11 -> 0.13547921 | M12: =L12-I12 -> 0.045861863 | N12: =IF(L12>I12, "inflation",IF(L12<I12, "deflation","stable")) -> inflation | O12: =IFERROR(IF(N12=C12,1,0),"") -> 1 | P12: =M12-F12 -> 0.0037719833 | Q12: =J12-J11 -> 2.1206194e+10 | R12: =Q12/J11 -> 0.13547921 | S12: =INDEX(m, MATCH($B$1, 'M stock'!$B$5:$B$271, 0), MATCH(A12, 'M stock'!$A$5:$BQ$5, 0)) -> 0 | T12: =(S12-S11)/S11 -> #DIV/0! | U12: =S12*Y12 -> #DIV/0! | V12: =(U12-U11)/U11 -> #DIV/0! | W12: =S12/B12 -> 0 | X12: =(W12-W11)/W11 -> #DIV/0! | Y12: =J12/S12 -> #DIV/0! | Z12: =(Y12-Y11)/Y11 -> #DIV/0! | AA12: =W12*Y12 -> #DIV/0! | AB12: =AA12-AA11 -> #DIV/0! | AC12: =AB12/AA11 -> #DIV/0! | AD12: =J12-AA12 -> #DIV/0! | AE12: =AA12+AD12 -> #DIV/0! | AF12: =(AE12-AE11)/AE11 -> #DIV/0! | AG12: =AF12-I12 -> #DIV/0! | AH12: =AF12-T13 -> #DIV/0! | AI12: =AF12-X12 -> #DIV/0! | AJ12: =AF12-Z12 -> #DIV/0! | AK12: =IF(AG12>0, "inflation",IF(AG12<0,"deflation","stable")) -> #DIV/0! | AL12: =IFERROR(IF(AK12=C12,1,0),"") | AM12: =AD12/AN12 -> #DIV/0! | AN12: =Y12 -> #DIV/0!
A13: 1970 | B13: =INDEX(p, MATCH($B$1, 'p2'!$B$5:$B$271, 0), MATCH(A13, 'p2'!$A$5:$BQ$5, 0)) -> 1.4503729 | C13: =IF(B13>B12,"inflation",IF(B13<B12,"deflation","stable")) -> inflation | D13: =IF(I13>0,"expansive","contractive") -> expansive | E13: =IF(AND(C13="inflation",D13="expansive"),"inflationary expansion",IF(AND(C13="inflation",D13="contractive"),"stagflation",IF(AND(C13="deflation",D13="expansive"),"deflationary growth",IF(AND(C13="deflation",D13="contractive"),"recession",0)))) -> inflationary expansion | F13: =(B13-B12)/B12 -> 0.076324344 | G13: =J13/B13 -> 1.4936106e+11 | H13: =G13-G12 -> 1.7464717e+10 | I13: =H13/G12 -> 0.13241244 | J13: =INDEX(PQ, MATCH($B$1, PQ!$B$5:$B$271, 0), MATCH(A13, PQ!$A$5:$BQ$5, 0)) -> 2.1662923e+11 | K13: =J13-J12 -> 3.8895744e+10 | L13: =K13/J12 -> 0.21884308 | M13: =L13-I13 -> 0.086430637 | N13: =IF(L13>I13, "inflation",IF(L13<I13, "deflation","stable")) -> inflation | O13: =IFERROR(IF(N13=C13,1,0),"") -> 1 | P13: =M13-F13 -> 0.010106293 | Q13: =J13-J12 -> 3.8895744e+10 | R13: =Q13/J12 -> 0.21884308 | S13: =INDEX(m, MATCH($B$1, 'M stock'!$B$5:$B$271, 0), MATCH(A13, 'M stock'!$A$5:$BQ$5, 0)) -> 0 | T13: =(S13-S12)/S12 -> #DIV/0! | U13: =S13*Y13 -> #DIV/0! | V13: =(U13-U12)/U12 -> #DIV/0! | W13: =S13/B13 -> 0 | X13: =(W13-W12)/W12 -> #DIV/0! | Y13: =J13/S13 -> #DIV/0! | Z13: =(Y13-Y12)/Y12 -> #DIV/0! | AA13: =W13*Y13 -> #DIV/0! | AB13: =AA13-AA12 -> #DIV/0! | AC13: =AB13/AA12 -> #DIV/0! | AD13: =J13-AA13 -> #DIV/0! | AE13: =AA13+AD13 -> #DIV/0! | AF13: =(AE13-AE12)/AE12 -> #DIV/0! | AG13: =AF13-I13 -> #DIV/0! | AH13: =AF13-T14 -> #DIV/0! | AI13: =AF13-X13 -> #DIV/0! | AJ13: =AF13-Z13 -> #DIV/0! | AK13: =IF(AG13>0, "inflation",IF(AG13<0,"deflation","stable")) -> #DIV/0! | AL13: =IFERROR(IF(AK13=C13,1,0),"") | AM13: =AD13/AN13 -> #DIV/0! | AN13: =Y13 -> #DIV/0!
A14: 1971 | B14: =INDEX(p, MATCH($B$1, 'p2'!$B$5:$B$271, 0), MATCH(A14, 'p2'!$A$5:$BQ$5, 0)) -> 1.5609107 | C14: =IF(B14>B13,"inflation",IF(B14<B13,"deflation","stable")) -> inflation | D14: =IF(I14>0,"expansive","contractive") -> expansive | E14: =IF(AND(C14="inflation",D14="expansive"),"inflationary expansion",IF(AND(C14="inflation",D14="contractive"),"stagflation",IF(AND(C14="deflation",D14="expansive"),"deflationary growth",IF(AND(C14="deflation",D14="contractive"),"recession",0)))) -> inflationary expansion | F14: =(B14-B13)/B13 -> 0.076213364 | G14: =J14/B14 -> 1.607401e+11 | H14: =G14-G13 -> 1.1379043e+10 | I14: =H14/G13 -> 0.076184805 | J14: =INDEX(PQ, MATCH($B$1, PQ!$B$5:$B$271, 0), MATCH(A14, PQ!$A$5:$BQ$5, 0)) -> 2.5090094e+11 | K14: =J14-J13 -> 3.4271712e+10 | L14: =K14/J13 -> 0.15820447 | M14: =L14-I14 -> 0.082019664 | N14: =IF(L14>I14, "inflation",IF(L14<I14, "deflation","stable")) -> inflation | O14: =IFERROR(IF(N14=C14,1,0),"") -> 1 | P14: =M14-F14 -> 0.0058063003 | Q14: =J14-J13 -> 3.4271712e+10 | R14: =Q14/J13 -> 0.15820447 | S14: =INDEX(m, MATCH($B$1, 'M stock'!$B$5:$B$271, 0), MATCH(A14, 'M stock'!$A$5:$BQ$5, 0)) -> 0 | T14: =(S14-S13)/S13 -> #DIV/0! | U14: =S14*Y14 -> #DIV/0! | V14: =(U14-U13)/U13 -> #DIV/0! | W14: =S14/B14 -> 0 | X14: =(W14-W13)/W13 -> #DIV/0! | Y14: =J14/S14 -> #DIV/0! | Z14: =(Y14-Y13)/Y13 -> #DIV/0! | AA14: =W14*Y14 -> #DIV/0! | AB14: =AA14-AA13 -> #DIV/0! | AC14: =AB14/AA13 -> #DIV/0! | AD14: =J14-AA14 -> #DIV/0! | AE14: =AA14+AD14 -> #DIV/0! | AF14: =(AE14-AE13)/AE13 -> #DIV/0! | AG14: =AF14-I14 -> #DIV/0! | AH14: =AF14-T15 -> #DIV/0! | AI14: =AF14-X14 -> #DIV/0! | AJ14: =AF14-Z14 -> #DIV/0! | AK14: =IF(AG14>0, "inflation",IF(AG14<0,"deflation","stable")) -> #DIV/0! | AL14: =IFERROR(IF(AK14=C14,1,0),"") | AM14: =AD14/AN14 -> #DIV/0! | AN14: =Y14 -> #DIV/0!
A15: 1972 | B15: =INDEX(p, MATCH($B$1, 'p2'!$B$5:$B$271, 0), MATCH(A15, 'p2'!$A$5:$BQ$5, 0)) -> 1.631649 | C15: =IF(B15>B14,"inflation",IF(B15<B14,"deflation","stable")) -> inflation | D15: =IF(I15>0,"expansive","contractive") -> expansive | E15: =IF(AND(C15="inflation",D15="expansive"),"inflationary expansion",IF(AND(C15="inflation",D15="contractive"),"stagflation",IF(AND(C15="deflation",D15="expansive"),"deflationary growth",IF(AND(C15="deflation",D15="contractive"),"recession",0)))) -> inflationary expansion | F15: =(B15-B14)/B14 -> 0.045318571 | G15: =J15/B15 -> 1.8441463e+11 | H15: =G15-G14 -> 2.3674535e+10 | I15: =H15/G14 -> 0.14728456 | J15: =INDEX(PQ, MATCH($B$1, PQ!$B$5:$B$271, 0), MATCH(A15, PQ!$A$5:$BQ$5, 0)) -> 3.0089994e+11 | K15: =J15-J14 -> 4.9999002e+10 | L15: =K15/J14 -> 0.19927786 | M15: =L15-I15 -> 0.051993297 | N15: =IF(L15>I15, "inflation",IF(L15<I15, "deflation","stable")) -> inflation | O15: =IFERROR(IF(N15=C15,1,0),"") -> 1 | P15: =M15-F15 -> 0.0066747258 | Q15: =J15-J14 -> 4.9999002e+10 | R15: =Q15/J14 -> 0.19927786 | S15: =INDEX(m, MATCH($B$1, 'M stock'!$B$5:$B$271, 0), MATCH(A15, 'M stock'!$A$5:$BQ$5, 0)) -> 0 | T15: =(S15-S14)/S14 -> #DIV/0! | U15: =S15*Y15 -> #DIV/0! | V15: =(U15-U14)/U14 -> #DIV/0! | W15: =S15/B15 -> 0 | X15: =(W15-W14)/W14 -> #DIV/0! | Y15: =J15/S15 -> #DIV/0! | Z15: =(Y15-Y14)/Y14 -> #DIV/0! | AA15: =W15*Y15 -> #DIV/0! | AB15: =AA15-AA14 -> #DIV/0! | AC15: =AB15/AA14 -> #DIV/0! | AD15: =J15-AA15 -> #DIV/0! | AE15: =AA15+AD15 -> #DIV/0! | AF15: =(AE15-AE14)/AE14 -> #DIV/0! | AG15: =AF15-I15 -> #DIV/0! | AH15: =AF15-T16 -> #DIV/0! | AI15: =AF15-X15 -> #DIV/0! | AJ15: =AF15-Z15 -> #DIV/0! | AK15: =IF(AG15>0, "inflation",IF(AG15<0,"deflation","stable")) -> #DIV/0! | AL15: =IFERROR(IF(AK15=C15,1,0),"") | AM15: =AD15/AN15 -> #DIV/0! | AN15: =Y15 -> #DIV/0!
... A67: 2024 | B67: =INDEX(p, MATCH($B$1, 'p2'!$B$5:$B$271, 0), MATCH(A67, 'p2'!$A$5:$BQ$5, 0)) -> 5.9012411 | C67: =IF(B67>B66,"inflation",IF(B67<B66,"deflation","stable")) -> inflation | D67: =IF(I67>0,"expansive","contractive") -> contractive | E67: =IF(AND(C67="inflation",D67="expansive"),"inflationary expansion",IF(AND(C67="inflation",D67="contractive"),"stagflation",IF(AND(C67="deflation",D67="expansive"),"deflationary growth",IF(AND(C67="deflation",D67="contractive"),"recession",0)))) -> stagflation | F67: =(B67-B66)/B66 -> 0.031060137 | G67: =J67/B67 -> 7.8965242e+11 | H67: =G67-G66 -> -1.0749515e+09 | I67: =H67/G66 -> -0.0013594465 | J67: =INDEX(PQ, MATCH($B$1, PQ!$B$5:$B$271, 0), MATCH(A67, PQ!$A$5:$BQ$5, 0)) -> 4.6599293e+12 | K67: =J67-J66 -> 1.3422543e+11 | L67: =K67/J66 -> 0.029658466 | M67: =L67-I67 -> 0.031017912 | N67: =IF(L67>I67, "inflation",IF(L67<I67, "deflation","stable")) -> inflation | O67: =IFERROR(IF(N67=C67,1,0),"") -> 1 | P67: =M67-F67 -> -4.2224593e-05 | Q67: =J67-J66 -> 1.3422543e+11 | R67: =Q67/J66 -> 0.029658466 | S67: =INDEX(m, MATCH($B$1, 'M stock'!$B$5:$B$271, 0), MATCH(A67, 'M stock'!$A$5:$BQ$5, 0)) -> 0 | T67: =(S67-S66)/S66 -> #DIV/0! | U67: =S67*Y67 -> #DIV/0! | V67: =(U67-U66)/U66 -> #DIV/0! | W67: =S67/B67 -> 0 | X67: =(W67-W66)/W66 -> #DIV/0! | Y67: =J67/S67 -> #DIV/0! | Z67: =(Y67-Y66)/Y66 -> #DIV/0! | AA67: =W67*Y67 -> #DIV/0! | AB67: =AA67-AA66 -> #DIV/0! | AC67: =AB67/AA66 -> #DIV/0! | AD67: =J67-AA67 -> #DIV/0! | AE67: =AA67+AD67 -> #DIV/0! | AF67: =(AE67-AE66)/AE66 -> #DIV/0! | AG67: =AF67-I67 -> #DIV/0! | AH67: =AF67-T68 -> #DIV/0! | AI67: =AF67-X67 -> #DIV/0! | AJ67: =AF67-Z67 -> #DIV/0! | AK67: =IF(AG67>0, "inflation",IF(AG67<0,"deflation","stable")) -> #DIV/0! | AL67: =IFERROR(IF(AK67=C67,1,0),"") | AM67: =AD67/AN67 -> #DIV/0! | AN67: =Y67 -> #DIV/0!
N69: Economic Themal Dynamic Accuracy (Left Side PQ) | O69: =SUM(O4:O57)/COUNT(O4:O57) -> 1 | AK69: Economic Themal Dynamic Accuracy (Right Side MV+FAC) | AL69: =SUM(AL4:AL57)/COUNT(AL4:AL57) -> #DIV/0!
N71: Matches | O71: =SUM(O3:O67) -> 64 | AK71: Matches | AL71: =SUM(AL3:AL67) -> 0
N72: Count | O72: =COUNT(O3:O67) -> 64 | AK72: Count | AL72: =COUNT(AL3:AL67) -> 0
A74: Source:
A75: World Bank
A76: https://data.worldbank.org/
A78: Broad Money (% of GDP)
A79: API_FM.LBL.BMNY.GD.ZS_DS2_en_csv_v2_123670
A80: Used to analyze monetary aggregates relative to GDP
A82: GDP Deflator (scaled to start meaningful P at 1)_
A83: API_NY.GDP.DEFL.ZS_DS2_en_csv_v2_124034
A84: Used to convert nominal GDP to real terms and track change in P over time
A86: GDP (current US$)
A87: API_NY.GDP.MKTP.CD_DS2_en_csv_v2_130122
A88: Core GDP series for nominal valuation
... A108: affirming the robustness of our own data sources and calculations.

Sheet France
B1: =VLOOKUP(C1,PQ!A6:B271,2,FALSE) -> FRA | C1: France | H1: =IFERROR(B3+B4,"wrong") -> 2.0321833
A2: Period | B2: P | C2: Observe | D2: Economy | E2: Diagnosis | F2: Δ P % | G2: Q | H2: Δ Q | I2: Δ Q % | J2: PQ | K2: Δ PQ | L2: Δ PQ % | M2: Δ PQ % - Δ Q % | N2: test | O2: match? | P2: (Δ PQ % - Δ Q %) -Δ P % = Δ P x Δ Q (interaction) | Q2: ΔPQ | R2: Δ%PQ | S2: M | T2: ΔM % | U2: MV | V2: ΔMV % | W2: M(d.) | X2: ΔM(d.) % | Y2: V | Z2: Δ V % | AA2: MV(d.) | AB2: ΔMV(d.) | AC2: Δ%MV(d.) | AD2: PQ-MV(d.) (FAC) | AE2: MV(d.) + FAC | AF2: Δ MV(d.)+FAC % | AG2: Δ MV(d.)+FAC % - Δ Q % | AH2: Δ MV(d.)+FAC % - Δ M % | AI2: Δ MV(d.)+FAC % - Δ M % | AJ2: Δ MV(d.)+FAC % - Δ V % | AK2: test | AL2: match? | AM2: M_FAC | AN2: V_FAC
A3: 1960 | B3: =INDEX(p, MATCH($B$1, 'p2'!$B$5:$B$271, 0), MATCH(A3, 'p2'!$A$5:$BQ$5, 0)) -> 1 | G3: =J3/B3 -> 6.1756879e+10 | H3: =G3-G2 -> #VALUE! | I3: =H3-H2 -> #VALUE! | J3: =INDEX(PQ, MATCH($B$1, PQ!$B$5:$B$271, 0), MATCH(A3, PQ!$A$5:$BQ$5, 0)) -> 6.1756879e+10 | K3: =J3-J2 -> #VALUE! | L3: =(K3-K2)/K2 -> #VALUE! | M3: =L3-I3 -> #VALUE! | S3: =INDEX(m, MATCH($B$1, 'M stock'!$B$5:$B$271, 0), MATCH(A3, 'M stock'!$A$5:$BQ$5, 0)) -> 0 | U3: =S3*Y3 -> #DIV/0! | W3: =S3/B3 -> 0 | Y3: =J3/S3 -> #DIV/0! | AA3: =W3*Y3 -> #DIV/0! | AD3: =J3-AA3 -> #DIV/0! | AE3: =AA3+AD3 -> #DIV/0! | AG3: =AF3-I3 -> #VALUE! | AH3: =AF3-T4 -> #DIV/0! | AI3: =AF3-X3 -> 0 | AJ3: =AF3-Z3 -> 0
A4: 1961 | B4: =INDEX(p, MATCH($B$1, 'p2'!$B$5:$B$271, 0), MATCH(A4, 'p2'!$A$5:$BQ$5, 0)) -> 1.0321833 | C4: =IF(B4>B3,"inflation",IF(B4<B3,"deflation","stable")) -> inflation | D4: =IF(I4>0,"expansive","contractive") -> expansive | E4: =IF(AND(C4="inflation",D4="expansive"),"inflationary expansion",IF(AND(C4="inflation",D4="contractive"),"stagflation",IF(AND(C4="deflation",D4="expansive"),"deflationary growth",IF(AND(C4="deflation",D4="contractive"),"recession",0)))) -> inflationary expansion | F4: =(B4-B3)/B3 -> 0.032183333 | G4: =J4/B4 -> 6.4723576e+10 | H4: =G4-G3 -> 2.9666966e+09 | I4: =H4/G3 -> 0.048038318 | J4: =INDEX(PQ, MATCH($B$1, PQ!$B$5:$B$271, 0), MATCH(A4, PQ!$A$5:$BQ$5, 0)) -> 6.6806596e+10 | K4: =J4-J3 -> 5.049717e+09 | L4: =K4/J3 -> 0.081767684 | M4: =L4-I4 -> 0.033729366 | N4: =IF(L4>I4, "inflation",IF(L4<I4, "deflation","stable")) -> inflation | O4: =IFERROR(IF(N4=C4,1,0),"") -> 1 | P4: =M4-F4 -> 0.0015460332 | Q4: =J4-J3 -> 5.049717e+09 | R4: =Q4/J3 -> 0.081767684 | S4: =INDEX(m, MATCH($B$1, 'M stock'!$B$5:$B$271, 0), MATCH(A4, 'M stock'!$A$5:$BQ$5, 0)) -> 0 | T4: =(S4-S3)/S3 -> #DIV/0! | U4: =S4*Y4 -> #DIV/0! | V4: =(U4-U3)/U3 -> #DIV/0! | W4: =S4/B4 -> 0 | X4: =(W4-W3)/W3 -> #DIV/0! | Y4: =J4/S4 -> #DIV/0! | Z4: =(Y4-Y3)/Y3 -> #DIV/0! | AA4: =W4*Y4 -> #DIV/0! | AB4: =AA4-AA3 -> #DIV/0! | AC4: =AB4/AA3 -> #DIV/0! | AD4: =J4-AA4 -> #DIV/0! | AE4: =AA4+AD4 -> #DIV/0! | AF4: =(AE4-AE3)/AE3 -> #DIV/0! | AG4: =AF4-I4 -> #DIV/0! | AH4: =AF4-T5 -> #DIV/0! | AI4: =AF4-X4 -> #DIV/0! | AJ4: =AF4-Z4 -> #DIV/0! | AK4: =IF(AG4>0, "inflation",IF(AG4<0,"deflation","stable")) -> #DIV/0! | AL4: =IFERROR(IF(AK4=C4,1,0),"") | AM4: =AD4/AN4 -> #DIV/0! | AN4: =Y4 -> #DIV/0!
A5: 1962 | B5: =INDEX(p, MATCH($B$1, 'p2'!$B$5:$B$271, 0), MATCH(A5, 'p2'!$A$5:$BQ$5, 0)) -> 1.082656 | C5: =IF(B5>B4,"inflation",IF(B5<B4,"deflation","stable")) -> inflation | D5: =IF(I5>0,"expansive","contractive") -> expansive | E5: =IF(AND(C5="inflation",D5="expansive"),"inflationary expansion",IF(AND(C5="inflation",D5="contractive"),"stagflation",IF(AND(C5="deflation",D5="expansive"),"deflationary growth",IF(AND(C5="deflation",D5="contractive"),"recession",0)))) -> inflationary expansion | F5: =(B5-B4)/B4 -> 0.048898893 | G5: =J5/B5 -> 6.9171185e+10 | H5: =G5-G4 -> 4.4476093e+09 | I5: =H5/G4 -> 0.06871699 | J5: =INDEX(PQ, MATCH($B$1, PQ!$B$5:$B$271, 0), MATCH(A5, PQ!$A$5:$BQ$5, 0)) -> 7.4888595e+10 | K5: =J5-J4 -> 8.0819993e+09 | L5: =K5/J4 -> 0.12097607 | M5: =L5-I5 -> 0.052259078 | N5: =IF(L5>I5, "inflation",IF(L5<I5, "deflation","stable")) -> inflation | O5: =IFERROR(IF(N5=C5,1,0),"") -> 1 | P5: =M5-F5 -> 0.0033601848 | Q5: =J5-J4 -> 8.0819993e+09 | R5: =Q5/J4 -> 0.12097607 | S5: =INDEX(m, MATCH($B$1, 'M stock'!$B$5:$B$271, 0), MATCH(A5, 'M stock'!$A$5:$BQ$5, 0)) -> 0 | T5: =(S5-S4)/S4 -> #DIV/0! | U5: =S5*Y5 -> #DIV/0! | V5: =(U5-U4)/U4 -> #DIV/0! | W5: =S5/B5 -> 0 | X5: =(W5-W4)/W4 -> #DIV/0! | Y5: =J5/S5 -> #DIV/0! | Z5: =(Y5-Y4)/Y4 -> #DIV/0! | AA5: =W5*Y5 -> #DIV/0! | AB5: =AA5-AA4 -> #DIV/0! | AC5: =AB5/AA4 -> #DIV/0! | AD5: =J5-AA5 -> #DIV/0! | AE5: =AA5+AD5 -> #DIV/0! | AF5: =(AE5-AE4)/AE4 -> #DIV/0! | AG5: =AF5-I5 -> #DIV/0! | AH5: =AF5-T6 -> #DIV/0! | AI5: =AF5-X5 -> #DIV/0! | AJ5: =AF5-Z5 -> #DIV/0! | AK5: =IF(AG5>0, "inflation",IF(AG5<0,"deflation","stable")) -> #DIV/0! | AL5: =IFERROR(IF(AK5=C5,1,0),"") | AM5: =AD5/AN5 -> #DIV/0! | AN5: =Y5 -> #DIV/0!
A6: 1963 | B6: =INDEX(p, MATCH($B$1, 'p2'!$B$5:$B$271, 0), MATCH(A6, 'p2'!$A$5:$BQ$5, 0)) -> 1.1429144 | C6: =IF(B6>B5,"inflation",IF(B6<B5,"deflation","stable")) -> inflation | D6: =IF(I6>0,"expansive","contractive") -> expansive | E6: =IF(AND(C6="inflation",D6="expansive"),"inflationary expansion",IF(AND(C6="inflation",D6="contractive"),"stagflation",IF(AND(C6="deflation",D6="expansive"),"deflationary growth",IF(AND(C6="deflation",D6="contractive"),"recession",0)))) -> inflationary expansion | F6: =(B6-B5)/B5 -> 0.055657983 | G6: =J6/B6 -> 7.3458854e+10 | H6: =G6-G5 -> 4.287669e+09 | I6: =H6/G5 -> 0.061986346 | J6: =INDEX(PQ, MATCH($B$1, PQ!$B$5:$B$271, 0), MATCH(A6, PQ!$A$5:$BQ$5, 0)) -> 8.3957182e+10 | K6: =J6-J5 -> 9.0685868e+09 | L6: =K6/J5 -> 0.12109436 | M6: =L6-I6 -> 0.059108018 | N6: =IF(L6>I6, "inflation",IF(L6<I6, "deflation","stable")) -> inflation | O6: =IFERROR(IF(N6=C6,1,0),"") -> 1 | P6: =M6-F6 -> 0.003450035 | Q6: =J6-J5 -> 9.0685868e+09 | R6: =Q6/J5 -> 0.12109436 | S6: =INDEX(m, MATCH($B$1, 'M stock'!$B$5:$B$271, 0), MATCH(A6, 'M stock'!$A$5:$BQ$5, 0)) -> 0 | T6: =(S6-S5)/S5 -> #DIV/0! | U6: =S6*Y6 -> #DIV/0! | V6: =(U6-U5)/U5 -> #DIV/0! | W6: =S6/B6 -> 0 | X6: =(W6-W5)/W5 -> #DIV/0! | Y6: =J6/S6 -> #DIV/0! | Z6: =(Y6-Y5)/Y5 -> #DIV/0! | AA6: =W6*Y6 -> #DIV/0! | AB6: =AA6-AA5 -> #DIV/0! | AC6: =AB6/AA5 -> #DIV/0! | AD6: =J6-AA6 -> #DIV/0! | AE6: =AA6+AD6 -> #DIV/0! | AF6: =(AE6-AE5)/AE5 -> #DIV/0! | AG6: =AF6-I6 -> #DIV/0! | AH6: =AF6-T7 -> #DIV/0! | AI6: =AF6-X6 -> #DIV/0! | AJ6: =AF6-Z6 -> #DIV/0! | AK6: =IF(AG6>0, "inflation",IF(AG6<0,"deflation","stable")) -> #DIV/0! | AL6: =IFERROR(IF(AK6=C6,1,0),"") | AM6: =AD6/AN6 -> #DIV/0! | AN6: =Y6 -> #DIV/0!
A7: 1964 | B7: =INDEX(p, MATCH($B$1, 'p2'!$B$5:$B$271, 0), MATCH(A7, 'p2'!$A$5:$BQ$5, 0)) -> 1.1905878 | C7: =IF(B7>B6,"inflation",IF(B7<B6,"deflation","stable")) -> inflation | D7: =IF(I7>0,"expansive","contractive") -> expansive | E7: =IF(AND(C7="inflation",D7="expansive"),"inflationary expansion",IF(AND(C7="inflation",D7="contractive"),"stagflation",IF(AND(C7="deflation",D7="expansive"),"deflationary growth",IF(AND(C7="deflation",D7="contractive"),"recession",0)))) -> inflationary expansion | F7: =(B7-B6)/B6 -> 0.041712104 | G7: =J7/B7 -> 7.8179221e+10 | H7: =G7-G6 -> 4.7203671e+09 | I7: =H7/G6 -> 0.064258654 | J7: =INDEX(PQ, MATCH($B$1, PQ!$B$5:$B$271, 0), MATCH(A7, PQ!$A$5:$BQ$5, 0)) -> 9.3079224e+10 | K7: =J7-J6 -> 9.122042e+09 | L7: =K7/J6 -> 0.10865112 | M7: =L7-I7 -> 0.044392467 | N7: =IF(L7>I7, "inflation",IF(L7<I7, "deflation","stable")) -> inflation | O7: =IFERROR(IF(N7=C7,1,0),"") -> 1 | P7: =M7-F7 -> 0.0026803636 | Q7: =J7-J6 -> 9.122042e+09 | R7: =Q7/J6 -> 0.10865112 | S7: =INDEX(m, MATCH($B$1, 'M stock'!$B$5:$B$271, 0), MATCH(A7, 'M stock'!$A$5:$BQ$5, 0)) -> 0 | T7: =(S7-S6)/S6 -> #DIV/0! | U7: =S7*Y7 -> #DIV/0! | V7: =(U7-U6)/U6 -> #DIV/0! | W7: =S7/B7 -> 0 | X7: =(W7-W6)/W6 -> #DIV/0! | Y7: =J7/S7 -> #DIV/0! | Z7: =(Y7-Y6)/Y6 -> #DIV/0! | AA7: =W7*Y7 -> #DIV/0! | AB7: =AA7-AA6 -> #DIV/0! | AC7: =AB7/AA6 -> #DIV/0! | AD7: =J7-AA7 -> #DIV/0! | AE7: =AA7+AD7 -> #DIV/0! | AF7: =(AE7-AE6)/AE6 -> #DIV/0! | AG7: =AF7-I7 -> #DIV/0! | AH7: =AF7-T8 -> #DIV/0! | AI7: =AF7-X7 -> #DIV/0! | AJ7: =AF7-Z7 -> #DIV/0! | AK7: =IF(AG7>0, "inflation",IF(AG7<0,"deflation","stable")) -> #DIV/0! | AL7: =IFERROR(IF(AK7=C7,1,0),"") | AM7: =AD7/AN7 -> #DIV/0! | AN7: =Y7 -> #DIV/0!
A8: 1965 | B8: =INDEX(p, MATCH($B$1, 'p2'!$B$5:$B$271, 0), MATCH(A8, 'p2'!$A$5:$BQ$5, 0)) -> 1.2268123 | C8: =IF(B8>B7,"inflation",IF(B8<B7,"deflation","stable")) -> inflation | D8: =IF(I8>0,"expansive","contractive") -> expansive | E8: =IF(AND(C8="inflation",D8="expansive"),"inflationary expansion",IF(AND(C8="inflation",D8="contractive"),"stagflation",IF(AND(C8="deflation",D8="expansive"),"deflationary growth",IF(AND(C8="deflation",D8="contractive"),"recession",0)))) -> inflationary expansion | F8: =(B8-B7)/B7 -> 0.030425721 | G8: =J8/B8 -> 8.1938014e+10 | H8: =G8-G7 -> 3.758793e+09 | I8: =H8/G7 -> 0.048079182 | J8: =INDEX(PQ, MATCH($B$1, PQ!$B$5:$B$271, 0), MATCH(A8, PQ!$A$5:$BQ$5, 0)) -> 1.0052256e+11 | K8: =J8-J7 -> 7.4433358e+09 | L8: =K8/J7 -> 0.079967747 | M8: =L8-I8 -> 0.031888565 | N8: =IF(L8>I8, "inflation",IF(L8<I8, "deflation","stable")) -> inflation | O8: =IFERROR(IF(N8=C8,1,0),"") -> 1 | P8: =M8-F8 -> 0.0014628438 | Q8: =J8-J7 -> 7.4433358e+09 | R8: =Q8/J7 -> 0.079967747 | S8: =INDEX(m, MATCH($B$1, 'M stock'!$B$5:$B$271, 0), MATCH(A8, 'M stock'!$A$5:$BQ$5, 0)) -> 0 | T8: =(S8-S7)/S7 -> #DIV/0! | U8: =S8*Y8 -> #DIV/0! | V8: =(U8-U7)/U7 -> #DIV/0! | W8: =S8/B8 -> 0 | X8: =(W8-W7)/W7 -> #DIV/0! | Y8: =J8/S8 -> #DIV/0! | Z8: =(Y8-Y7)/Y7 -> #DIV/0! | AA8: =W8*Y8 -> #DIV/0! | AB8: =AA8-AA7 -> #DIV/0! | AC8: =AB8/AA7 -> #DIV/0! | AD8: =J8-AA8 -> #DIV/0! | AE8: =AA8+AD8 -> #DIV/0! | AF8: =(AE8-AE7)/AE7 -> #DIV/0! | AG8: =AF8-I8 -> #DIV/0! | AH8: =AF8-T9 -> #DIV/0! | AI8: =AF8-X8 -> #DIV/0! | AJ8: =AF8-Z8 -> #DIV/0! | AK8: =IF(AG8>0, "inflation",IF(AG8<0,"deflation","stable")) -> #DIV/0! | AL8: =IFERROR(IF(AK8=C8,1,0),"") | AM8: =AD8/AN8 -> #DIV/0! | AN8: =Y8 -> #DIV/0!
A9: 1966 | B9: =INDEX(p, MATCH($B$1, 'p2'!$B$5:$B$271, 0), MATCH(A9, 'p2'!$A$5:$BQ$5, 0)) -> 1.2635654 | C9: =IF(B9>B8,"inflation",IF(B9<B8,"deflation","stable")) -> inflation | D9: =IF(I9>0,"expansive","contractive") -> expansive | E9: =IF(AND(C9="inflation",D9="expansive"),"inflationary expansion",IF(AND(C9="inflation",D9="contractive"),"stagflation",IF(AND(C9="deflation",D9="expansive"),"deflationary growth",IF(AND(C9="deflation",D9="contractive"),"recession",0)))) -> inflationary expansion | F9: =(B9-B8)/B8 -> 0.029958285 | G9: =J9/B9 -> 8.6207134e+10 | H9: =G9-G8 -> 4.2691204e+09 | I9: =H9/G8 -> 0.052101829 | J9: =INDEX(PQ, MATCH($B$1, PQ!$B$5:$B$271, 0), MATCH(A9, PQ!$A$5:$BQ$5, 0)) -> 1.0892836e+11 | K9: =J9-J8 -> 8.4057966e+09 | L9: =K9/J8 -> 0.083620996 | M9: =L9-I9 -> 0.031519167 | N9: =IF(L9>I9, "inflation",IF(L9<I9, "deflation","stable")) -> inflation | O9: =IFERROR(IF(N9=C9,1,0),"") -> 1 | P9: =M9-F9 -> 0.0015608815 | Q9: =J9-J8 -> 8.4057966e+09 | R9: =Q9/J8 -> 0.083620996 | S9: =INDEX(m, MATCH($B$1, 'M stock'!$B$5:$B$271, 0), MATCH(A9, 'M stock'!$A$5:$BQ$5, 0)) -> 0 | T9: =(S9-S8)/S8 -> #DIV/0! | U9: =S9*Y9 -> #DIV/0! | V9: =(U9-U8)/U8 -> #DIV/0! | W9: =S9/B9 -> 0 | X9: =(W9-W8)/W8 -> #DIV/0! | Y9: =J9/S9 -> #DIV/0! | Z9: =(Y9-Y8)/Y8 -> #DIV/0! | AA9: =W9*Y9 -> #DIV/0! | AB9: =AA9-AA8 -> #DIV/0! | AC9: =AB9/AA8 -> #DIV/0! | AD9: =J9-AA9 -> #DIV/0! | AE9: =AA9+AD9 -> #DIV/0! | AF9: =(AE9-AE8)/AE8 -> #DIV/0! | AG9: =AF9-I9 -> #DIV/0! | AH9: =AF9-T10 -> #DIV/0! | AI9: =AF9-X9 -> #DIV/0! | AJ9: =AF9-Z9 -> #DIV/0! | AK9: =IF(AG9>0, "inflation",IF(AG9<0,"deflation","stable")) -> #DIV/0! | AL9: =IFERROR(IF(AK9=C9,1,0),"") | AM9: =AD9/AN9 -> #DIV/0! | AN9: =Y9 -> #DIV/0!
A10: 1967 | B10: =INDEX(p, MATCH($B$1, 'p2'!$B$5:$B$271, 0), MATCH(A10, 'p2'!$A$5:$BQ$5, 0)) -> 1.3021543 | C10: =IF(B10>B9,"inflation",IF(B10<B9,"deflation","stable")) -> inflation | D10: =IF(I10>0,"expansive","contractive") -> expansive | E10: =IF(AND(C10="inflation",D10="expansive"),"inflationary expansion",IF(AND(C10="inflation",D10="contractive"),"stagflation",IF(AND(C10="deflation",D10="expansive"),"deflationary growth",IF(AND(C10="deflation",D10="contractive"),"recession",0)))) -> inflationary expansion | F10: =(B10-B9)/B9 -> 0.030539649 | G10: =J10/B10 -> 9.0428144e+10 | H10: =G10-G9 -> 4.2210097e+09 | I10: =H10/G9 -> 0.048963577 | J10: =INDEX(PQ, MATCH($B$1, PQ!$B$5:$B$271, 0), MATCH(A10, PQ!$A$5:$BQ$5, 0)) -> 1.177514e+11 | K10: =J10-J9 -> 8.8230397e+09 | L10: =K10/J9 -> 0.080998557 | M10: =L10-I10 -> 0.03203498 | N10: =IF(L10>I10, "inflation",IF(L10<I10, "deflation","stable")) -> inflation | O10: =IFERROR(IF(N10=C10,1,0),"") -> 1 | P10: =M10-F10 -> 0.0014953305 | Q10: =J10-J9 -> 8.8230397e+09 | R10: =Q10/J9 -> 0.080998557 | S10: =INDEX(m, MATCH($B$1, 'M stock'!$B$5:$B$271, 0), MATCH(A10, 'M stock'!$A$5:$BQ$5, 0)) -> 0 | T10: =(S10-S9)/S9 -> #DIV/0! | U10: =S10*Y10 -> #DIV/0! | V10: =(U10-U9)/U9 -> #DIV/0! | W10: =S10/B10 -> 0 | X10: =(W10-W9)/W9 -> #DIV/0! | Y10: =J10/S10 -> #DIV/0! | Z10: =(Y10-Y9)/Y9 -> #DIV/0! | AA10: =W10*Y10 -> #DIV/0! | AB10: =AA10-AA9 -> #DIV/0! | AC10: =AB10/AA9 -> #DIV/0! | AD10: =J10-AA10 -> #DIV/0! | AE10: =AA10+AD10 -> #DIV/0! | AF10: =(AE10-AE9)/AE9 -> #DIV/0! | AG10: =AF10-I10 -> #DIV/0! | AH10: =AF10-T11 -> #DIV/0! | AI10: =AF10-X10 -> #DIV/0! | AJ10: =AF10-Z10 -> #DIV/0! | AK10: =IF(AG10>0, "inflation",IF(AG10<0,"deflation","stable")) -> #DIV/0! | AL10: =IFERROR(IF(AK10=C10,1,0),"") | AM10: =AD10/AN10 -> #DIV/0! | AN10: =Y10 -> #DIV/0!
A11: 1968 | B11: =INDEX(p, MATCH($B$1, 'p2'!$B$5:$B$271, 0), MATCH(A11, 'p2'!$A$5:$BQ$5, 0)) -> 1.3597031 | C11: =IF(B11>B10,"inflation",IF(B11<B10,"deflation","stable")) -> inflation | D11: =IF(I11>0,"expansive","contractive") -> expansive | E11: =IF(AND(C11="inflation",D11="expansive"),"inflationary expansion",IF(AND(C11="inflation",D11="contractive"),"stagflation",IF(AND(C11="deflation",D11="expansive"),"deflationary growth",IF(AND(C11="deflation",D11="contractive"),"recession",0)))) -> inflationary expansion | F11: =(B11-B10)/B10 -> 0.044195059 | G11: =J11/B11 -> 9.445261e+10 | H11: =G11-G10 -> 4.0244658e+09 | I11: =H11/G10 -> 0.044504571 | J11: =INDEX(PQ, MATCH($B$1, PQ!$B$5:$B$271, 0), MATCH(A11, PQ!$A$5:$BQ$5, 0)) -> 1.284275e+11 | K11: =J11-J10 -> 1.0676108e+10 | L11: =K11/J10 -> 0.090666513 | M11: =L11-I11 -> 0.046161941 | N11: =IF(L11>I11, "inflation",IF(L11<I11, "deflation","stable")) -> inflation | O11: =IFERROR(IF(N11=C11,1,0),"") -> 1 | P11: =M11-F11 -> 0.0019668822 | Q11: =J11-J10 -> 1.0676108e+10 | R11: =Q11/J10 -> 0.090666513 | S11: =INDEX(m, MATCH($B$1, 'M stock'!$B$5:$B$271, 0), MATCH(A11, 'M stock'!$A$5:$BQ$5, 0)) -> 0 | T11: =(S11-S10)/S10 -> #DIV/0! | U11: =S11*Y11 -> #DIV/0! | V11: =(U11-U10)/U10 -> #DIV/0! | W11: =S11/B11 -> 0 | X11: =(W11-W10)/W10 -> #DIV/0! | Y11: =J11/S11 -> #DIV/0! | Z11: =(Y11-Y10)/Y10 -> #DIV/0! | AA11: =W11*Y11 -> #DIV/0! | AB11: =AA11-AA10 -> #DIV/0! | AC11: =AB11/AA10 -> #DIV/0! | AD11: =J11-AA11 -> #DIV/0! | AE11: =AA11+AD11 -> #DIV/0! | AF11: =(AE11-AE10)/AE10 -> #DIV/0! | AG11: =AF11-I11 -> #DIV/0! | AH11: =AF11-T12 -> #DIV/0! | AI11: =AF11-X11 -> #DIV/0! | AJ11: =AF11-Z11 -> #DIV/0! | AK11: =IF(AG11>0, "inflation",IF(AG11<0,"deflation","stable")) -> #DIV/0! | AL11: =IFERROR(IF(AK11=C11,1,0),"") | AM11: =AD11/AN11 -> #DIV/0! | AN11: =Y11 -> #DIV/0!
A12: 1969 | B12: =INDEX(p, MATCH($B$1, 'p2'!$B$5:$B$271, 0), MATCH(A12, 'p2'!$A$5:$BQ$5, 0)) -> 1.4596284 | C12: =IF(B12>B11,"inflation",IF(B12<B11,"deflation","stable")) -> inflation | D12: =IF(I12>0,"expansive","contractive") -> expansive | E12: =IF(AND(C12="inflation",D12="expansive"),"inflationary expansion",IF(AND(C12="inflation",D12="contractive"),"stagflation",IF(AND(C12="deflation",D12="expansive"),"deflationary growth",IF(AND(C12="deflation",D12="contractive"),"recession",0)))) -> inflationary expansion | F12: =(B12-B11)/B11 -> 0.073490562 | G12: =J12/B12 -> 9.6162695e+10 | H12: =G12-G11 -> 1.7100849e+09 | I12: =H12/G11 -> 0.018105216 | J12: =INDEX(PQ, MATCH($B$1, PQ!$B$5:$B$271, 0), MATCH(A12, PQ!$A$5:$BQ$5, 0)) -> 1.403618e+11 | K12: =J12-J11 -> 1.1934298e+10 | L12: =K12/J11 -> 0.092926341 | M12: =L12-I12 -> 0.074821125 | N12: =IF(L12>I12, "inflation",IF(L12<I12, "deflation","stable")) -> inflation | O12: =IFERROR(IF(N12=C12,1,0),"") -> 1 | P12: =M12-F12 -> 0.0013305625 | Q12: =J12-J11 -> 1.1934298e+10 | R12: =Q12/J11 -> 0.092926341 | S12: =INDEX(m, MATCH($B$1, 'M stock'!$B$5:$B$271, 0), MATCH(A12, 'M stock'!$A$5:$BQ$5, 0)) -> 0 | T12: =(S12-S11)/S11 -> #DIV/0! | U12: =S12*Y12 -> #DIV/0! | V12: =(U12-U11)/U11 -> #DIV/0! | W12: =S12/B12 -> 0 | X12: =(W12-W11)/W11 -> #DIV/0! | Y12: =J12/S12 -> #DIV/0! | Z12: =(Y12-Y11)/Y11 -> #DIV/0! | AA12: =W12*Y12 -> #DIV/0! | AB12: =AA12-AA11 -> #DIV/0! | AC12: =AB12/AA11 -> #DIV/0! | AD12: =J12-AA12 -> #DIV/0! | AE12: =AA12+AD12 -> #DIV/0! | AF12: =(AE12-AE11)/AE11 -> #DIV/0! | AG12: =AF12-I12 -> #DIV/0! | AH12: =AF12-T13 -> #DIV/0! | AI12: =AF12-X12 -> #DIV/0! | AJ12: =AF12-Z12 -> #DIV/0! | AK12: =IF(AG12>0, "inflation",IF(AG12<0,"deflation","stable")) -> #DIV/0! | AL12: =IFERROR(IF(AK12=C12,1,0),"") | AM12: =AD12/AN12 -> #DIV/0! | AN12: =Y12 -> #DIV/0!
A13: 1970 | B13: =INDEX(p, MATCH($B$1, 'p2'!$B$5:$B$271, 0), MATCH(A13, 'p2'!$A$5:$BQ$5, 0)) -> 1.5383514 | C13: =IF(B13>B12,"inflation",IF(B13<B12,"deflation","stable")) -> inflation | D13: =IF(I13>0,"expansive","contractive") -> contractive | E13: =IF(AND(C13="inflation",D13="expansive"),"inflationary expansion",IF(AND(C13="inflation",D13="contractive"),"stagflation",IF(AND(C13="deflation",D13="expansive"),"deflationary growth",IF(AND(C13="deflation",D13="contractive"),"recession",0)))) -> stagflation | F13: =(B13-B12)/B12 -> 0.053933565 | G13: =J13/B13 -> 9.5509388e+10 | H13: =G13-G12 -> -6.5330736e+08 | I13: =H13/G12 -> -0.0067937713 | J13: =INDEX(PQ, MATCH($B$1, PQ!$B$5:$B$271, 0), MATCH(A13, PQ!$A$5:$BQ$5, 0)) -> 1.46927e+11 | K13: =J13-J12 -> 6.5651962e+09 | L13: =K13/J12 -> 0.046773382 | M13: =L13-I13 -> 0.053567153 | N13: =IF(L13>I13, "inflation",IF(L13<I13, "deflation","stable")) -> inflation | O13: =IFERROR(IF(N13=C13,1,0),"") -> 1 | P13: =M13-F13 -> -0.00036641231 | Q13: =J13-J12 -> 6.5651962e+09 | R13: =Q13/J12 -> 0.046773382 | S13: =INDEX(m, MATCH($B$1, 'M stock'!$B$5:$B$271, 0), MATCH(A13, 'M stock'!$A$5:$BQ$5, 0)) -> 0 | T13: =(S13-S12)/S12 -> #DIV/0! | U13: =S13*Y13 -> #DIV/0! | V13: =(U13-U12)/U12 -> #DIV/0! | W13: =S13/B13 -> 0 | X13: =(W13-W12)/W12 -> #DIV/0! | Y13: =J13/S13 -> #DIV/0! | Z13: =(Y13-Y12)/Y12 -> #DIV/0! | AA13: =W13*Y13 -> #DIV/0! | AB13: =AA13-AA12 -> #DIV/0! | AC13: =AB13/AA12 -> #DIV/0! | AD13: =J13-AA13 -> #DIV/0! | AE13: =AA13+AD13 -> #DIV/0! | AF13: =(AE13-AE12)/AE12 -> #DIV/0! | AG13: =AF13-I13 -> #DIV/0! | AH13: =AF13-T14 -> #DIV/0! | AI13: =AF13-X13 -> #DIV/0! | AJ13: =AF13-Z13 -> #DIV/0! | AK13: =IF(AG13>0, "inflation",IF(AG13<0,"deflation","stable")) -> #DIV/0! | AL13: =IFERROR(IF(AK13=C13,1,0),"") | AM13: =AD13/AN13 -> #DIV/0! | AN13: =Y13 -> #DIV/0!
A14: 1971 | B14: =INDEX(p, MATCH($B$1, 'p2'!$B$5:$B$271, 0), MATCH(A14, 'p2'!$A$5:$BQ$5, 0)) -> 1.6287269 | C14: =IF(B14>B13,"inflation",IF(B14<B13,"deflation","stable")) -> inflation | D14: =IF(I14>0,"expansive","contractive") -> expansive | E14: =IF(AND(C14="inflation",D14="expansive"),"inflationary expansion",IF(AND(C14="inflation",D14="contractive"),"stagflation",IF(AND(C14="deflation",D14="expansive"),"deflationary growth",IF(AND(C14="deflation",D14="contractive"),"recession",0)))) -> inflationary expansion | F14: =(B14-B13)/B13 -> 0.058748309 | G14: =J14/B14 -> 1.008388e+11 | H14: =G14-G13 -> 5.3294147e+09 | I14: =H14/G13 -> 0.055799905 | J14: =INDEX(PQ, MATCH($B$1, PQ!$B$5:$B$271, 0), MATCH(A14, PQ!$A$5:$BQ$5, 0)) -> 1.6423887e+11 | K14: =J14-J13 -> 1.7311874e+10 | L14: =K14/J13 -> 0.11782636 | M14: =L14-I14 -> 0.062026459 | N14: =IF(L14>I14, "inflation",IF(L14<I14, "deflation","stable")) -> inflation | O14: =IFERROR(IF(N14=C14,1,0),"") -> 1 | P14: =M14-F14 -> 0.00327815 | Q14: =J14-J13 -> 1.7311874e+10 | R14: =Q14/J13 -> 0.11782636 | S14: =INDEX(m, MATCH($B$1, 'M stock'!$B$5:$B$271, 0), MATCH(A14, 'M stock'!$A$5:$BQ$5, 0)) -> 0 | T14: =(S14-S13)/S13 -> #DIV/0! | U14: =S14*Y14 -> #DIV/0! | V14: =(U14-U13)/U13 -> #DIV/0! | W14: =S14/B14 -> 0 | X14: =(W14-W13)/W13 -> #DIV/0! | Y14: =J14/S14 -> #DIV/0! | Z14: =(Y14-Y13)/Y13 -> #DIV/0! | AA14: =W14*Y14 -> #DIV/0! | AB14: =AA14-AA13 -> #DIV/0! | AC14: =AB14/AA13 -> #DIV/0! | AD14: =J14-AA14 -> #DIV/0! | AE14: =AA14+AD14 -> #DIV/0! | AF14: =(AE14-AE13)/AE13 -> #DIV/0! | AG14: =AF14-I14 -> #DIV/0! | AH14: =AF14-T15 -> #DIV/0! | AI14: =AF14-X14 -> #DIV/0! | AJ14: =AF14-Z14 -> #DIV/0! | AK14: =IF(AG14>0, "inflation",IF(AG14<0,"deflation","stable")) -> #DIV/0! | AL14: =IFERROR(IF(AK14=C14,1,0),"") | AM14: =AD14/AN14 -> #DIV/0! | AN14: =Y14 -> #DIV/0!
A15: 1972 | B15: =INDEX(p, MATCH($B$1, 'p2'!$B$5:$B$271, 0), MATCH(A15, 'p2'!$A$5:$BQ$5, 0)) -> 1.7412533 | C15: =IF(B15>B14,"inflation",IF(B15<B14,"deflation","stable")) -> inflation | D15: =IF(I15>0,"expansive","contractive") -> expansive | E15: =IF(AND(C15="inflation",D15="expansive"),"inflationary expansion",IF(AND(C15="inflation",D15="contractive"),"stagflation",IF(AND(C15="deflation",D15="expansive"),"deflationary growth",IF(AND(C15="deflation",D15="contractive"),"recession",0)))) -> inflationary expansion | F15: =(B15-B14)/B14 -> 0.069088566 | G15: =J15/B15 -> 1.1579116e+11 | H15: =G15-G14 -> 1.4952362e+10 | I15: =H15/G14 -> 0.14827985 | J15: =INDEX(PQ, MATCH($B$1, PQ!$B$5:$B$271, 0), MATCH(A15, PQ!$A$5:$BQ$5, 0)) -> 2.0162175e+11 | K15: =J15-J14 -> 3.7382879e+10 | L15: =K15/J14 -> 0.22761285 | M15: =L15-I15 -> 0.079333008 | N15: =IF(L15>I15, "inflation",IF(L15<I15, "deflation","stable")) -> inflation | O15: =IFERROR(IF(N15=C15,1,0),"") -> 1 | P15: =M15-F15 -> 0.010244442 | Q15: =J15-J14 -> 3.7382879e+10 | R15: =Q15/J14 -> 0.22761285 | S15: =INDEX(m, MATCH($B$1, 'M stock'!$B$5:$B$271, 0), MATCH(A15, 'M stock'!$A$5:$BQ$5, 0)) -> 0 | T15: =(S15-S14)/S14 -> #DIV/0! | U15: =S15*Y15 -> #DIV/0! | V15: =(U15-U14)/U14 -> #DIV/0! | W15: =S15/B15 -> 0 | X15: =(W15-W14)/W14 -> #DIV/0! | Y15: =J15/S15 -> #DIV/0! | Z15: =(Y15-Y14)/Y14 -> #DIV/0! | AA15: =W15*Y15 -> #DIV/0! | AB15: =AA15-AA14 -> #DIV/0! | AC15: =AB15/AA14 -> #DIV/0! | AD15: =J15-AA15 -> #DIV/0! | AE15: =AA15+AD15 -> #DIV/0! | AF15: =(AE15-AE14)/AE14 -> #DIV/0! | AG15: =AF15-I15 -> #DIV/0! | AH15: =AF15-T16 -> #DIV/0! | AI15: =AF15-X15 -> #DIV/0! | AJ15: =AF15-Z15 -> #DIV/0! | AK15: =IF(AG15>0, "inflation",IF(AG15<0,"deflation","stable")) -> #DIV/0! | AL15: =IFERROR(IF(AK15=C15,1,0),"") | AM15: =AD15/AN15 -> #DIV/0! | AN15: =Y15 -> #DIV/0!
... A67: 2024 | B67: =INDEX(p, MATCH($B$1, 'p2'!$B$5:$B$271, 0), MATCH(A67, 'p2'!$A$5:$BQ$5, 0)) -> 11.835803 | C67: =IF(B67>B66,"inflation",IF(B67<B66,"deflation","stable")) -> inflation | D67: =IF(I67>0,"expansive","contractive") -> expansive | E67: =IF(AND(C67="inflation",D67="expansive"),"inflationary expansion",IF(AND(C67="inflation",D67="contractive"),"stagflation",IF(AND(C67="deflation",D67="expansive"),"deflationary growth",IF(AND(C67="deflation",D67="contractive"),"recession",0)))) -> inflationary expansion | F67: =(B67-B66)/B66 -> 0.02312958 | G67: =J67/B67 -> 2.6716219e+11 | H67: =G67-G66 -> 3.3508397e+09 | I67: =H67/G66 -> 0.012701651 | J67: =INDEX(PQ, MATCH($B$1, PQ!$B$5:$B$271, 0), MATCH(A67, PQ!$A$5:$BQ$5, 0)) -> 3.1620791e+12 | K67: =J67-J66 -> 1.1024746e+11 | L67: =K67/J66 -> 0.036125015 | M67: =L67-I67 -> 0.023423364 | N67: =IF(L67>I67, "inflation",IF(L67<I67, "deflation","stable")) -> inflation | O67: =IFERROR(IF(N67=C67,1,0),"") -> 1 | P67: =M67-F67 -> 0.00029378385 | Q67: =J67-J66 -> 1.1024746e+11 | R67: =Q67/J66 -> 0.036125015 | S67: =INDEX(m, MATCH($B$1, 'M stock'!$B$5:$B$271, 0), MATCH(A67, 'M stock'!$A$5:$BQ$5, 0)) -> 0 | T67: =(S67-S66)/S66 -> #DIV/0! | U67: =S67*Y67 -> #DIV/0! | V67: =(U67-U66)/U66 -> #DIV/0! | W67: =S67/B67 -> 0 | X67: =(W67-W66)/W66 -> #DIV/0! | Y67: =J67/S67 -> #DIV/0! | Z67: =(Y67-Y66)/Y66 -> #DIV/0! | AA67: =W67*Y67 -> #DIV/0! | AB67: =AA67-AA66 -> #DIV/0! | AC67: =AB67/AA66 -> #DIV/0! | AD67: =J67-AA67 -> #DIV/0! | AE67: =AA67+AD67 -> #DIV/0! | AF67: =(AE67-AE66)/AE66 -> #DIV/0! | AG67: =AF67-I67 -> #DIV/0! | AH67: =AF67-T68 -> #DIV/0! | AI67: =AF67-X67 -> #DIV/0! | AJ67: =AF67-Z67 -> #DIV/0! | AK67: =IF(AG67>0, "inflation",IF(AG67<0,"deflation","stable")) -> #DIV/0! | AL67: =IFERROR(IF(AK67=C67,1,0),"") | AM67: =AD67/AN67 -> #DIV/0! | AN67: =Y67 -> #DIV/0!
N69: Economic Themal Dynamic Accuracy (Left Side PQ) | O69: =SUM(O4:O57)/COUNT(O4:O57) -> 1 | AK69: Economic Themal Dynamic Accuracy (Right Side MV+FAC) | AL69: =SUM(AL4:AL57)/COUNT(AL4:AL57) -> #DIV/0!
N71: Matches | O71: =SUM(O3:O67) -> 64 | AK71: Matches | AL71: =SUM(AL3:AL67) -> 0
N72: Count | O72: =COUNT(O3:O67) -> 64 | AK72: Count | AL72: =COUNT(AL3:AL67) -> 0
A74: Source:
A75: World Bank
A76: https://data.worldbank.org/
A78: Broad Money (% of GDP)
A79: API_FM.LBL.BMNY.GD.ZS_DS2_en_csv_v2_123670
A80: Used to analyze monetary aggregates relative to GDP
A82: GDP Deflator (scaled to start meaningful P at 1)_
A83: API_NY.GDP.DEFL.ZS_DS2_en_csv_v2_124034
A84: Used to convert nominal GDP to real terms and track change in P over time
A86: GDP (current US$)
A87: API_NY.GDP.MKTP.CD_DS2_en_csv_v2_130122
A88: Core GDP series for nominal valuation
... A108: affirming the robustness of our own data sources and calculations.

Sheet Italy
B1: =VLOOKUP(C1,PQ!A6:B271,2,FALSE) -> ITA | C1: Italy | H1: =IFERROR(B3+B4,"wrong") -> 2.0278216
A2: Period | B2: P | C2: Observe | D2: Economy | E2: Diagnosis | F2: Δ P % | G2: Q | H2: Δ Q | I2: Δ Q % | J2: PQ | K2: Δ PQ | L2: Δ PQ % | M2: Δ PQ % - Δ Q % | N2: test | O2: match? | P2: (Δ PQ % - Δ Q %) -Δ P % = Δ P x Δ Q (interaction) | Q2: ΔPQ | R2: Δ%PQ | S2: M | T2: ΔM % | U2: MV | V2: ΔMV % | W2: M(d.) | X2: ΔM(d.) % | Y2: V | Z2: Δ V % | AA2: MV(d.) | AB2: ΔMV(d.) | AC2: Δ%MV(d.) | AD2: PQ-MV(d.) (FAC) | AE2: MV(d.) + FAC | AF2: Δ MV(d.)+FAC % | AG2: Δ MV(d.)+FAC % - Δ Q % | AH2: Δ MV(d.)+FAC % - Δ M % | AI2: Δ MV(d.)+FAC % - Δ M % | AJ2: Δ MV(d.)+FAC % - Δ V % | AK2: test | AL2: match? | AM2: M_FAC | AN2: V_FAC
A3: 1960 | B3: =INDEX(p, MATCH($B$1, 'p2'!$B$5:$B$271, 0), MATCH(A3, 'p2'!$A$5:$BQ$5, 0)) -> 1 | G3: =J3/B3 -> 4.2012423e+10 | H3: =G3-G2 -> #VALUE! | I3: =H3-H2 -> #VALUE! | J3: =INDEX(PQ, MATCH($B$1, PQ!$B$5:$B$271, 0), MATCH(A3, PQ!$A$5:$BQ$5, 0)) -> 4.2012423e+10 | K3: =J3-J2 -> #VALUE! | L3: =(K3-K2)/K2 -> #VALUE! | M3: =L3-I3 -> #VALUE! | S3: =INDEX(m, MATCH($B$1, 'M stock'!$B$5:$B$271, 0), MATCH(A3, 'M stock'!$A$5:$BQ$5, 0)) -> 0 | U3: =S3*Y3 -> #DIV/0! | W3: =S3/B3 -> 0 | Y3: =J3/S3 -> #DIV/0! | AA3: =W3*Y3 -> #DIV/0! | AD3: =J3-AA3 -> #DIV/0! | AE3: =AA3+AD3 -> #DIV/0! | AG3: =AF3-I3 -> #VALUE! | AH3: =AF3-T4 -> #DIV/0! | AI3: =AF3-X3 -> 0 | AJ3: =AF3-Z3 -> 0
A4: 1961 | B4: =INDEX(p, MATCH($B$1, 'p2'!$B$5:$B$271, 0), MATCH(A4, 'p2'!$A$5:$BQ$5, 0)) -> 1.0278216 | C4: =IF(B4>B3,"inflation",IF(B4<B3,"deflation","stable")) -> inflation | D4: =IF(I4>0,"expansive","contractive") -> expansive | E4: =IF(AND(C4="inflation",D4="expansive"),"inflationary expansion",IF(AND(C4="inflation",D4="contractive"),"stagflation",IF(AND(C4="deflation",D4="expansive"),"deflationary growth",IF(AND(C4="deflation",D4="contractive"),"recession",0)))) -> inflationary expansion | F4: =(B4-B3)/B3 -> 0.027821589 | G4: =J4/B4 -> 4.5386756e+10 | H4: =G4-G3 -> 3.3743331e+09 | I4: =H4/G3 -> 0.080317507 | J4: =INDEX(PQ, MATCH($B$1, PQ!$B$5:$B$271, 0), MATCH(A4, PQ!$A$5:$BQ$5, 0)) -> 4.6649487e+10 | K4: =J4-J3 -> 4.6370647e+09 | L4: =K4/J3 -> 0.11037366 | M4: =L4-I4 -> 0.030056149 | N4: =IF(L4>I4, "inflation",IF(L4<I4, "deflation","stable")) -> inflation | O4: =IFERROR(IF(N4=C4,1,0),"") -> 1 | P4: =M4-F4 -> 0.0022345607 | Q4: =J4-J3 -> 4.6370647e+09 | R4: =Q4/J3 -> 0.11037366 | S4: =INDEX(m, MATCH($B$1, 'M stock'!$B$5:$B$271, 0), MATCH(A4, 'M stock'!$A$5:$BQ$5, 0)) -> 0 | T4: =(S4-S3)/S3 -> #DIV/0! | U4: =S4*Y4 -> #DIV/0! | V4: =(U4-U3)/U3 -> #DIV/0! | W4: =S4/B4 -> 0 | X4: =(W4-W3)/W3 -> #DIV/0! | Y4: =J4/S4 -> #DIV/0! | Z4: =(Y4-Y3)/Y3 -> #DIV/0! | AA4: =W4*Y4 -> #DIV/0! | AB4: =AA4-AA3 -> #DIV/0! | AC4: =AB4/AA3 -> #DIV/0! | AD4: =J4-AA4 -> #DIV/0! | AE4: =AA4+AD4 -> #DIV/0! | AF4: =(AE4-AE3)/AE3 -> #DIV/0! | AG4: =AF4-I4 -> #DIV/0! | AH4: =AF4-T5 -> #DIV/0! | AI4: =AF4-X4 -> #DIV/0! | AJ4: =AF4-Z4 -> #DIV/0! | AK4: =IF(AG4>0, "inflation",IF(AG4<0,"deflation","stable")) -> #DIV/0! | AL4: =IFERROR(IF(AK4=C4,1,0),"") | AM4: =AD4/AN4 -> #DIV/0! | AN4: =Y4 -> #DIV/0!
A5: 1962 | B5: =INDEX(p, MATCH($B$1, 'p2'!$B$5:$B$271, 0), MATCH(A5, 'p2'!$A$5:$BQ$5, 0)) -> 1.0873708 | C5: =IF(B5>B4,"inflation",IF(B5<B4,"deflation","stable")) -> inflation | D5: =IF(I5>0,"expansive","contractive") -> expansive | E5: =IF(AND(C5="inflation",D5="expansive"),"inflationary expansion",IF(AND(C5="inflation",D5="contractive"),"stagflation",IF(AND(C5="deflation",D5="expansive"),"deflationary growth",IF(AND(C5="deflation",D5="contractive"),"recession",0)))) -> inflationary expansion | F5: =(B5-B4)/B4 -> 0.057937299 | G5: =J5/B5 -> 4.8202391e+10 | H5: =G5-G4 -> 2.8156357e+09 | I5: =H5/G4 -> 0.062036505 | J5: =INDEX(PQ, MATCH($B$1, PQ!$B$5:$B$271, 0), MATCH(A5, PQ!$A$5:$BQ$5, 0)) -> 5.2413873e+10 | K5: =J5-J4 -> 5.7643853e+09 | L5: =K5/J4 -> 0.12356803 | M5: =L5-I5 -> 0.061531527 | N5: =IF(L5>I5, "inflation",IF(L5<I5, "deflation","stable")) -> inflation | O5: =IFERROR(IF(N5=C5,1,0),"") -> 1 | P5: =M5-F5 -> 0.0035942275 | Q5: =J5-J4 -> 5.7643853e+09 | R5: =Q5/J4 -> 0.12356803 | S5: =INDEX(m, MATCH($B$1, 'M stock'!$B$5:$B$271, 0), MATCH(A5, 'M stock'!$A$5:$BQ$5, 0)) -> 0 | T5: =(S5-S4)/S4 -> #DIV/0! | U5: =S5*Y5 -> #DIV/0! | V5: =(U5-U4)/U4 -> #DIV/0! | W5: =S5/B5 -> 0 | X5: =(W5-W4)/W4 -> #DIV/0! | Y5: =J5/S5 -> #DIV/0! | Z5: =(Y5-Y4)/Y4 -> #DIV/0! | AA5: =W5*Y5 -> #DIV/0! | AB5: =AA5-AA4 -> #DIV/0! | AC5: =AB5/AA4 -> #DIV/0! | AD5: =J5-AA5 -> #DIV/0! | AE5: =AA5+AD5 -> #DIV/0! | AF5: =(AE5-AE4)/AE4 -> #DIV/0! | AG5: =AF5-I5 -> #DIV/0! | AH5: =AF5-T6 -> #DIV/0! | AI5: =AF5-X5 -> #DIV/0! | AJ5: =AF5-Z5 -> #DIV/0! | AK5: =IF(AG5>0, "inflation",IF(AG5<0,"deflation","stable")) -> #DIV/0! | AL5: =IFERROR(IF(AK5=C5,1,0),"") | AM5: =AD5/AN5 -> #DIV/0! | AN5: =Y5 -> #DIV/0!
A6: 1963 | B6: =INDEX(p, MATCH($B$1, 'p2'!$B$5:$B$271, 0), MATCH(A6, 'p2'!$A$5:$BQ$5, 0)) -> 1.1793391 | C6: =IF(B6>B5,"inflation",IF(B6<B5,"deflation","stable")) -> inflation | D6: =IF(I6>0,"expansive","contractive") -> expansive | E6: =IF(AND(C6="inflation",D6="expansive"),"inflationary expansion",IF(AND(C6="inflation",D6="contractive"),"stagflation",IF(AND(C6="deflation",D6="expansive"),"deflationary growth",IF(AND(C6="deflation",D6="contractive"),"recession",0)))) -> inflationary expansion | F6: =(B6-B5)/B5 -> 0.084578599 | G6: =J6/B6 -> 5.0906414e+10 | H6: =G6-G5 -> 2.704023e+09 | I6: =H6/G5 -> 0.05609728 | J6: =INDEX(PQ, MATCH($B$1, PQ!$B$5:$B$271, 0), MATCH(A6, PQ!$A$5:$BQ$5, 0)) -> 6.0035925e+10 | K6: =J6-J5 -> 7.622052e+09 | L6: =K6/J5 -> 0.14542051 | M6: =L6-I6 -> 0.089323228 | N6: =IF(L6>I6, "inflation",IF(L6<I6, "deflation","stable")) -> inflation | O6: =IFERROR(IF(N6=C6,1,0),"") -> 1 | P6: =M6-F6 -> 0.0047446293 | Q6: =J6-J5 -> 7.622052e+09 | R6: =Q6/J5 -> 0.14542051 | S6: =INDEX(m, MATCH($B$1, 'M stock'!$B$5:$B$271, 0), MATCH(A6, 'M stock'!$A$5:$BQ$5, 0)) -> 0 | T6: =(S6-S5)/S5 -> #DIV/0! | U6: =S6*Y6 -> #DIV/0! | V6: =(U6-U5)/U5 -> #DIV/0! | W6: =S6/B6 -> 0 | X6: =(W6-W5)/W5 -> #DIV/0! | Y6: =J6/S6 -> #DIV/0! | Z6: =(Y6-Y5)/Y5 -> #DIV/0! | AA6: =W6*Y6 -> #DIV/0! | AB6: =AA6-AA5 -> #DIV/0! | AC6: =AB6/AA5 -> #DIV/0! | AD6: =J6-AA6 -> #DIV/0! | AE6: =AA6+AD6 -> #DIV/0! | AF6: =(AE6-AE5)/AE5 -> #DIV/0! | AG6: =AF6-I6 -> #DIV/0! | AH6: =AF6-T7 -> #DIV/0! | AI6: =AF6-X6 -> #DIV/0! | AJ6: =AF6-Z6 -> #DIV/0! | AK6: =IF(AG6>0, "inflation",IF(AG6<0,"deflation","stable")) -> #DIV/0! | AL6: =IFERROR(IF(AK6=C6,1,0),"") | AM6: =AD6/AN6 -> #DIV/0! | AN6: =Y6 -> #DIV/0!
A7: 1964 | B7: =INDEX(p, MATCH($B$1, 'p2'!$B$5:$B$271, 0), MATCH(A7, 'p2'!$A$5:$BQ$5, 0)) -> 1.2558759 | C7: =IF(B7>B6,"inflation",IF(B7<B6,"deflation","stable")) -> inflation | D7: =IF(I7>0,"expansive","contractive") -> expansive | E7: =IF(AND(C7="inflation",D7="expansive"),"inflationary expansion",IF(AND(C7="inflation",D7="contractive"),"stagflation",IF(AND(C7="deflation",D7="expansive"),"deflationary growth",IF(AND(C7="deflation",D7="contractive"),"recession",0)))) -> inflationary expansion | F7: =(B7-B6)/B6 -> 0.064898079 | G7: =J7/B7 -> 5.2330624e+10 | H7: =G7-G6 -> 1.4242099e+09 | I7: =H7/G6 -> 0.027977023 | J7: =INDEX(PQ, MATCH($B$1, PQ!$B$5:$B$271, 0), MATCH(A7, PQ!$A$5:$BQ$5, 0)) -> 6.5720772e+10 | K7: =J7-J6 -> 5.6848472e+09 | L7: =K7/J6 -> 0.094690757 | M7: =L7-I7 -> 0.066713734 | N7: =IF(L7>I7, "inflation",IF(L7<I7, "deflation","stable")) -> inflation | O7: =IFERROR(IF(N7=C7,1,0),"") -> 1 | P7: =M7-F7 -> 0.001815655 | Q7: =J7-J6 -> 5.6848472e+09 | R7: =Q7/J6 -> 0.094690757 | S7: =INDEX(m, MATCH($B$1, 'M stock'!$B$5:$B$271, 0), MATCH(A7, 'M stock'!$A$5:$BQ$5, 0)) -> 0 | T7: =(S7-S6)/S6 -> #DIV/0! | U7: =S7*Y7 -> #DIV/0! | V7: =(U7-U6)/U6 -> #DIV/0! | W7: =S7/B7 -> 0 | X7: =(W7-W6)/W6 -> #DIV/0! | Y7: =J7/S7 -> #DIV/0! | Z7: =(Y7-Y6)/Y6 -> #DIV/0! | AA7: =W7*Y7 -> #DIV/0! | AB7: =AA7-AA6 -> #DIV/0! | AC7: =AB7/AA6 -> #DIV/0! | AD7: =J7-AA7 -> #DIV/0! | AE7: =AA7+AD7 -> #DIV/0! | AF7: =(AE7-AE6)/AE6 -> #DIV/0! | AG7: =AF7-I7 -> #DIV/0! | AH7: =AF7-T8 -> #DIV/0! | AI7: =AF7-X7 -> #DIV/0! | AJ7: =AF7-Z7 -> #DIV/0! | AK7: =IF(AG7>0, "inflation",IF(AG7<0,"deflation","stable")) -> #DIV/0! | AL7: =IFERROR(IF(AK7=C7,1,0),"") | AM7: =AD7/AN7 -> #DIV/0! | AN7: =Y7 -> #DIV/0!
A8: 1965 | B8: =INDEX(p, MATCH($B$1, 'p2'!$B$5:$B$271, 0), MATCH(A8, 'p2'!$A$5:$BQ$5, 0)) -> 1.3085856 | C8: =IF(B8>B7,"inflation",IF(B8<B7,"deflation","stable")) -> inflation | D8: =IF(I8>0,"expansive","contractive") -> expansive | E8: =IF(AND(C8="inflation",D8="expansive"),"inflationary expansion",IF(AND(C8="inflation",D8="contractive"),"stagflation",IF(AND(C8="deflation",D8="expansive"),"deflationary growth",IF(AND(C8="deflation",D8="contractive"),"recession",0)))) -> inflationary expansion | F8: =(B8-B7)/B7 -> 0.041970402 | G8: =J8/B8 -> 5.4040802e+10 | H8: =G8-G7 -> 1.7101772e+09 | I8: =H8/G7 -> 0.032680237 | J8: =INDEX(PQ, MATCH($B$1, PQ!$B$5:$B$271, 0), MATCH(A8, PQ!$A$5:$BQ$5, 0)) -> 7.0717012e+10 | K8: =J8-J7 -> 4.9962404e+09 | L8: =K8/J7 -> 0.076022242 | M8: =L8-I8 -> 0.043342005 | N8: =IF(L8>I8, "inflation",IF(L8<I8, "deflation","stable")) -> inflation | O8: =IFERROR(IF(N8=C8,1,0),"") -> 1 | P8: =M8-F8 -> 0.0013716027 | Q8: =J8-J7 -> 4.9962404e+09 | R8: =Q8/J7 -> 0.076022242 | S8: =INDEX(m, MATCH($B$1, 'M stock'!$B$5:$B$271, 0), MATCH(A8, 'M stock'!$A$5:$BQ$5, 0)) -> 0 | T8: =(S8-S7)/S7 -> #DIV/0! | U8: =S8*Y8 -> #DIV/0! | V8: =(U8-U7)/U7 -> #DIV/0! | W8: =S8/B8 -> 0 | X8: =(W8-W7)/W7 -> #DIV/0! | Y8: =J8/S8 -> #DIV/0! | Z8: =(Y8-Y7)/Y7 -> #DIV/0! | AA8: =W8*Y8 -> #DIV/0! | AB8: =AA8-AA7 -> #DIV/0! | AC8: =AB8/AA7 -> #DIV/0! | AD8: =J8-AA8 -> #DIV/0! | AE8: =AA8+AD8 -> #DIV/0! | AF8: =(AE8-AE7)/AE7 -> #DIV/0! | AG8: =AF8-I8 -> #DIV/0! | AH8: =AF8-T9 -> #DIV/0! | AI8: =AF8-X8 -> #DIV/0! | AJ8: =AF8-Z8 -> #DIV/0! | AK8: =IF(AG8>0, "inflation",IF(AG8<0,"deflation","stable")) -> #DIV/0! | AL8: =IFERROR(IF(AK8=C8,1,0),"") | AM8: =AD8/AN8 -> #DIV/0! | AN8: =Y8 -> #DIV/0!
A9: 1966 | B9: =INDEX(p, MATCH($B$1, 'p2'!$B$5:$B$271, 0), MATCH(A9, 'p2'!$A$5:$BQ$5, 0)) -> 1.3377984 | C9: =IF(B9>B8,"inflation",IF(B9<B8,"deflation","stable")) -> inflation | D9: =IF(I9>0,"expansive","contractive") -> expansive | E9: =IF(AND(C9="inflation",D9="expansive"),"inflationary expansion",IF(AND(C9="inflation",D9="contractive"),"stagflation",IF(AND(C9="deflation",D9="expansive"),"deflationary growth",IF(AND(C9="deflation",D9="contractive"),"recession",0)))) -> inflationary expansion | F9: =(B9-B8)/B8 -> 0.022323963 | G9: =J9/B9 -> 5.7275032e+10 | H9: =G9-G8 -> 3.2342308e+09 | I9: =H9/G8 -> 0.059847942 | J9: =INDEX(PQ, MATCH($B$1, PQ!$B$5:$B$271, 0), MATCH(A9, PQ!$A$5:$BQ$5, 0)) -> 7.6622445e+10 | K9: =J9-J8 -> 5.9054326e+09 | L9: =K9/J8 -> 0.083507948 | M9: =L9-I9 -> 0.023660006 | N9: =IF(L9>I9, "inflation",IF(L9<I9, "deflation","stable")) -> inflation | O9: =IFERROR(IF(N9=C9,1,0),"") -> 1 | P9: =M9-F9 -> 0.0013360432 | Q9: =J9-J8 -> 5.9054326e+09 | R9: =Q9/J8 -> 0.083507948 | S9: =INDEX(m, MATCH($B$1, 'M stock'!$B$5:$B$271, 0), MATCH(A9, 'M stock'!$A$5:$BQ$5, 0)) -> 0 | T9: =(S9-S8)/S8 -> #DIV/0! | U9: =S9*Y9 -> #DIV/0! | V9: =(U9-U8)/U8 -> #DIV/0! | W9: =S9/B9 -> 0 | X9: =(W9-W8)/W8 -> #DIV/0! | Y9: =J9/S9 -> #DIV/0! | Z9: =(Y9-Y8)/Y8 -> #DIV/0! | AA9: =W9*Y9 -> #DIV/0! | AB9: =AA9-AA8 -> #DIV/0! | AC9: =AB9/AA8 -> #DIV/0! | AD9: =J9-AA9 -> #DIV/0! | AE9: =AA9+AD9 -> #DIV/0! | AF9: =(AE9-AE8)/AE8 -> #DIV/0! | AG9: =AF9-I9 -> #DIV/0! | AH9: =AF9-T10 -> #DIV/0! | AI9: =AF9-X9 -> #DIV/0! | AJ9: =AF9-Z9 -> #DIV/0! | AK9: =IF(AG9>0, "inflation",IF(AG9<0,"deflation","stable")) -> #DIV/0! | AL9: =IFERROR(IF(AK9=C9,1,0),"") | AM9: =AD9/AN9 -> #DIV/0! | AN9: =Y9 -> #DIV/0!
A10: 1967 | B10: =INDEX(p, MATCH($B$1, 'p2'!$B$5:$B$271, 0), MATCH(A10, 'p2'!$A$5:$BQ$5, 0)) -> 1.3749257 | C10: =IF(B10>B9,"inflation",IF(B10<B9,"deflation","stable")) -> inflation | D10: =IF(I10>0,"expansive","contractive") -> expansive | E10: =IF(AND(C10="inflation",D10="expansive"),"inflationary expansion",IF(AND(C10="inflation",D10="contractive"),"stagflation",IF(AND(C10="deflation",D10="expansive"),"deflationary growth",IF(AND(C10="deflation",D10="contractive"),"recession",0)))) -> inflationary expansion | F10: =(B10-B9)/B9 -> 0.02775259 | G10: =J10/B10 -> 6.1386585e+10 | H10: =G10-G9 -> 4.1115526e+09 | I10: =H10/G9 -> 0.071786125 | J10: =INDEX(PQ, MATCH($B$1, PQ!$B$5:$B$271, 0), MATCH(A10, PQ!$A$5:$BQ$5, 0)) -> 8.4401996e+10 | K10: =J10-J9 -> 7.7795508e+09 | L10: =K10/J9 -> 0.10153097 | M10: =L10-I10 -> 0.029744841 | N10: =IF(L10>I10, "inflation",IF(L10<I10, "deflation","stable")) -> inflation | O10: =IFERROR(IF(N10=C10,1,0),"") -> 1 | P10: =M10-F10 -> 0.0019922509 | Q10: =J10-J9 -> 7.7795508e+09 | R10: =Q10/J9 -> 0.10153097 | S10: =INDEX(m, MATCH($B$1, 'M stock'!$B$5:$B$271, 0), MATCH(A10, 'M stock'!$A$5:$BQ$5, 0)) -> 0 | T10: =(S10-S9)/S9 -> #DIV/0! | U10: =S10*Y10 -> #DIV/0! | V10: =(U10-U9)/U9 -> #DIV/0! | W10: =S10/B10 -> 0 | X10: =(W10-W9)/W9 -> #DIV/0! | Y10: =J10/S10 -> #DIV/0! | Z10: =(Y10-Y9)/Y9 -> #DIV/0! | AA10: =W10*Y10 -> #DIV/0! | AB10: =AA10-AA9 -> #DIV/0! | AC10: =AB10/AA9 -> #DIV/0! | AD10: =J10-AA10 -> #DIV/0! | AE10: =AA10+AD10 -> #DIV/0! | AF10: =(AE10-AE9)/AE9 -> #DIV/0! | AG10: =AF10-I10 -> #DIV/0! | AH10: =AF10-T11 -> #DIV/0! | AI10: =AF10-X10 -> #DIV/0! | AJ10: =AF10-Z10 -> #DIV/0! | AK10: =IF(AG10>0, "inflation",IF(AG10<0,"deflation","stable")) -> #DIV/0! | AL10: =IFERROR(IF(AK10=C10,1,0),"") | AM10: =AD10/AN10 -> #DIV/0! | AN10: =Y10 -> #DIV/0!
A11: 1968 | B11: =INDEX(p, MATCH($B$1, 'p2'!$B$5:$B$271, 0), MATCH(A11, 'p2'!$A$5:$BQ$5, 0)) -> 1.3987732 | C11: =IF(B11>B10,"inflation",IF(B11<B10,"deflation","stable")) -> inflation | D11: =IF(I11>0,"expansive","contractive") -> expansive | E11: =IF(AND(C11="inflation",D11="expansive"),"inflationary expansion",IF(AND(C11="inflation",D11="contractive"),"stagflation",IF(AND(C11="deflation",D11="expansive"),"deflationary growth",IF(AND(C11="deflation",D11="contractive"),"recession",0)))) -> inflationary expansion | F11: =(B11-B10)/B10 -> 0.017344511 | G11: =J11/B11 -> 6.5404063e+10 | H11: =G11-G10 -> 4.0174786e+09 | I11: =H11/G10 -> 0.065445547 | J11: =INDEX(PQ, MATCH($B$1, PQ!$B$5:$B$271, 0), MATCH(A11, PQ!$A$5:$BQ$5, 0)) -> 9.1485448e+10 | K11: =J11-J10 -> 7.0834526e+09 | L11: =K11/J10 -> 0.083925179 | M11: =L11-I11 -> 0.018479632 | N11: =IF(L11>I11, "inflation",IF(L11<I11, "deflation","stable")) -> inflation | O11: =IFERROR(IF(N11=C11,1,0),"") -> 1 | P11: =M11-F11 -> 0.001135121 | Q11: =J11-J10 -> 7.0834526e+09 | R11: =Q11/J10 -> 0.083925179 | S11: =INDEX(m, MATCH($B$1, 'M stock'!$B$5:$B$271, 0), MATCH(A11, 'M stock'!$A$5:$BQ$5, 0)) -> 0 | T11: =(S11-S10)/S10 -> #DIV/0! | U11: =S11*Y11 -> #DIV/0! | V11: =(U11-U10)/U10 -> #DIV/0! | W11: =S11/B11 -> 0 | X11: =(W11-W10)/W10 -> #DIV/0! | Y11: =J11/S11 -> #DIV/0! | Z11: =(Y11-Y10)/Y10 -> #DIV/0! | AA11: =W11*Y11 -> #DIV/0! | AB11: =AA11-AA10 -> #DIV/0! | AC11: =AB11/AA10 -> #DIV/0! | AD11: =J11-AA11 -> #DIV/0! | AE11: =AA11+AD11 -> #DIV/0! | AF11: =(AE11-AE10)/AE10 -> #DIV/0! | AG11: =AF11-I11 -> #DIV/0! | AH11: =AF11-T12 -> #DIV/0! | AI11: =AF11-X11 -> #DIV/0! | AJ11: =AF11-Z11 -> #DIV/0! | AK11: =IF(AG11>0, "inflation",IF(AG11<0,"deflation","stable")) -> #DIV/0! | AL11: =IFERROR(IF(AK11=C11,1,0),"") | AM11: =AD11/AN11 -> #DIV/0! | AN11: =Y11 -> #DIV/0!
A12: 1969 | B12: =INDEX(p, MATCH($B$1, 'p2'!$B$5:$B$271, 0), MATCH(A12, 'p2'!$A$5:$BQ$5, 0)) -> 1.4554419 | C12: =IF(B12>B11,"inflation",IF(B12<B11,"deflation","stable")) -> inflation | D12: =IF(I12>0,"expansive","contractive") -> expansive | E12: =IF(AND(C12="inflation",D12="expansive"),"inflationary expansion",IF(AND(C12="inflation",D12="contractive"),"stagflation",IF(AND(C12="deflation",D12="expansive"),"deflationary growth",IF(AND(C12="deflation",D12="contractive"),"recession",0)))) -> inflationary expansion | F12: =(B12-B11)/B11 -> 0.040513167 | G12: =J12/B12 -> 6.9392443e+10 | H12: =G12-G11 -> 3.988379e+09 | I12: =H12/G11 -> 0.0609806 | J12: =INDEX(PQ, MATCH($B$1, PQ!$B$5:$B$271, 0), MATCH(A12, PQ!$A$5:$BQ$5, 0)) -> 1.0099667e+11 | K12: =J12-J11 -> 9.5112191e+09 | L12: =K12/J11 -> 0.10396428 | M12: =L12-I12 -> 0.042983684 | N12: =IF(L12>I12, "inflation",IF(L12<I12, "deflation","stable")) -> inflation | O12: =IFERROR(IF(N12=C12,1,0),"") -> 1 | P12: =M12-F12 -> 0.0024705172 | Q12: =J12-J11 -> 9.5112191e+09 | R12: =Q12/J11 -> 0.10396428 | S12: =INDEX(m, MATCH($B$1, 'M stock'!$B$5:$B$271, 0), MATCH(A12, 'M stock'!$A$5:$BQ$5, 0)) -> 0 | T12: =(S12-S11)/S11 -> #DIV/0! | U12: =S12*Y12 -> #DIV/0! | V12: =(U12-U11)/U11 -> #DIV/0! | W12: =S12/B12 -> 0 | X12: =(W12-W11)/W11 -> #DIV/0! | Y12: =J12/S12 -> #DIV/0! | Z12: =(Y12-Y11)/Y11 -> #DIV/0! | AA12: =W12*Y12 -> #DIV/0! | AB12: =AA12-AA11 -> #DIV/0! | AC12: =AB12/AA11 -> #DIV/0! | AD12: =J12-AA12 -> #DIV/0! | AE12: =AA12+AD12 -> #DIV/0! | AF12: =(AE12-AE11)/AE11 -> #DIV/0! | AG12: =AF12-I12 -> #DIV/0! | AH12: =AF12-T13 -> #DIV/0! | AI12: =AF12-X12 -> #DIV/0! | AJ12: =AF12-Z12 -> #DIV/0! | AK12: =IF(AG12>0, "inflation",IF(AG12<0,"deflation","stable")) -> #DIV/0! | AL12: =IFERROR(IF(AK12=C12,1,0),"") | AM12: =AD12/AN12 -> #DIV/0! | AN12: =Y12 -> #DIV/0!
A13: 1970 | B13: =INDEX(p, MATCH($B$1, 'p2'!$B$5:$B$271, 0), MATCH(A13, 'p2'!$A$5:$BQ$5, 0)) -> 1.5553585 | C13: =IF(B13>B12,"inflation",IF(B13<B12,"deflation","stable")) -> inflation | D13: =IF(I13>0,"expansive","contractive") -> expansive | E13: =IF(AND(C13="inflation",D13="expansive"),"inflationary expansion",IF(AND(C13="inflation",D13="contractive"),"stagflation",IF(AND(C13="deflation",D13="expansive"),"deflationary growth",IF(AND(C13="deflation",D13="contractive"),"recession",0)))) -> inflationary expansion | F13: =(B13-B12)/B12 -> 0.068650349 | G13: =J13/B13 -> 7.307426e+10 | H13: =G13-G12 -> 3.6818175e+09 | I13: =H13/G12 -> 0.053057903 | J13: =INDEX(PQ, MATCH($B$1, PQ!$B$5:$B$271, 0), MATCH(A13, PQ!$A$5:$BQ$5, 0)) -> 1.1365667e+11 | K13: =J13-J12 -> 1.2660003e+10 | L13: =K13/J12 -> 0.1253507 | M13: =L13-I13 -> 0.072292793 | N13: =IF(L13>I13, "inflation",IF(L13<I13, "deflation","stable")) -> inflation | O13: =IFERROR(IF(N13=C13,1,0),"") -> 1 | P13: =M13-F13 -> 0.0036424436 | Q13: =J13-J12 -> 1.2660003e+10 | R13: =Q13/J12 -> 0.1253507 | S13: =INDEX(m, MATCH($B$1, 'M stock'!$B$5:$B$271, 0), MATCH(A13, 'M stock'!$A$5:$BQ$5, 0)) -> 0 | T13: =(S13-S12)/S12 -> #DIV/0! | U13: =S13*Y13 -> #DIV/0! | V13: =(U13-U12)/U12 -> #DIV/0! | W13: =S13/B13 -> 0 | X13: =(W13-W12)/W12 -> #DIV/0! | Y13: =J13/S13 -> #DIV/0! | Z13: =(Y13-Y12)/Y12 -> #DIV/0! | AA13: =W13*Y13 -> #DIV/0! | AB13: =AA13-AA12 -> #DIV/0! | AC13: =AB13/AA12 -> #DIV/0! | AD13: =J13-AA13 -> #DIV/0! | AE13: =AA13+AD13 -> #DIV/0! | AF13: =(AE13-AE12)/AE12 -> #DIV/0! | AG13: =AF13-I13 -> #DIV/0! | AH13: =AF13-T14 -> #DIV/0! | AI13: =AF13-X13 -> #DIV/0! | AJ13: =AF13-Z13 -> #DIV/0! | AK13: =IF(AG13>0, "inflation",IF(AG13<0,"deflation","stable")) -> #DIV/0! | AL13: =IFERROR(IF(AK13=C13,1,0),"") | AM13: =AD13/AN13 -> #DIV/0! | AN13: =Y13 -> #DIV/0!
A14: 1971 | B14: =INDEX(p, MATCH($B$1, 'p2'!$B$5:$B$271, 0), MATCH(A14, 'p2'!$A$5:$BQ$5, 0)) -> 1.6670152 | C14: =IF(B14>B13,"inflation",IF(B14<B13,"deflation","stable")) -> inflation | D14: =IF(I14>0,"expansive","contractive") -> expansive | E14: =IF(AND(C14="inflation",D14="expansive"),"inflationary expansion",IF(AND(C14="inflation",D14="contractive"),"stagflation",IF(AND(C14="deflation",D14="expansive"),"deflationary growth",IF(AND(C14="deflation",D14="contractive"),"recession",0)))) -> inflationary expansion | F14: =(B14-B13)/B13 -> 0.071788396 | G14: =J14/B14 -> 7.4960153e+10 | H14: =G14-G13 -> 1.8858935e+09 | I14: =H14/G13 -> 0.025807904 | J14: =INDEX(PQ, MATCH($B$1, PQ!$B$5:$B$271, 0), MATCH(A14, PQ!$A$5:$BQ$5, 0)) -> 1.2495971e+11 | K14: =J14-J13 -> 1.1303043e+10 | L14: =K14/J13 -> 0.099449008 | M14: =L14-I14 -> 0.073641104 | N14: =IF(L14>I14, "inflation",IF(L14<I14, "deflation","stable")) -> inflation | O14: =IFERROR(IF(N14=C14,1,0),"") -> 1 | P14: =M14-F14 -> 0.001852708 | Q14: =J14-J13 -> 1.1303043e+10 | R14: =Q14/J13 -> 0.099449008 | S14: =INDEX(m, MATCH($B$1, 'M stock'!$B$5:$B$271, 0), MATCH(A14, 'M stock'!$A$5:$BQ$5, 0)) -> 0 | T14: =(S14-S13)/S13 -> #DIV/0! | U14: =S14*Y14 -> #DIV/0! | V14: =(U14-U13)/U13 -> #DIV/0! | W14: =S14/B14 -> 0 | X14: =(W14-W13)/W13 -> #DIV/0! | Y14: =J14/S14 -> #DIV/0! | Z14: =(Y14-Y13)/Y13 -> #DIV/0! | AA14: =W14*Y14 -> #DIV/0! | AB14: =AA14-AA13 -> #DIV/0! | AC14: =AB14/AA13 -> #DIV/0! | AD14: =J14-AA14 -> #DIV/0! | AE14: =AA14+AD14 -> #DIV/0! | AF14: =(AE14-AE13)/AE13 -> #DIV/0! | AG14: =AF14-I14 -> #DIV/0! | AH14: =AF14-T15 -> #DIV/0! | AI14: =AF14-X14 -> #DIV/0! | AJ14: =AF14-Z14 -> #DIV/0! | AK14: =IF(AG14>0, "inflation",IF(AG14<0,"deflation","stable")) -> #DIV/0! | AL14: =IFERROR(IF(AK14=C14,1,0),"") | AM14: =AD14/AN14 -> #DIV/0! | AN14: =Y14 -> #DIV/0!
A15: 1972 | B15: =INDEX(p, MATCH($B$1, 'p2'!$B$5:$B$271, 0), MATCH(A15, 'p2'!$A$5:$BQ$5, 0)) -> 1.7609177 | C15: =IF(B15>B14,"inflation",IF(B15<B14,"deflation","stable")) -> inflation | D15: =IF(I15>0,"expansive","contractive") -> expansive | E15: =IF(AND(C15="inflation",D15="expansive"),"inflationary expansion",IF(AND(C15="inflation",D15="contractive"),"stagflation",IF(AND(C15="deflation",D15="expansive"),"deflationary growth",IF(AND(C15="deflation",D15="contractive"),"recession",0)))) -> inflationary expansion | F15: =(B15-B14)/B14 -> 0.056329718 | G15: =J15/B15 -> 8.2681228e+10 | H15: =G15-G14 -> 7.7210741e+09 | I15: =H15/G14 -> 0.10300238 | J15: =INDEX(PQ, MATCH($B$1, PQ!$B$5:$B$271, 0), MATCH(A15, PQ!$A$5:$BQ$5, 0)) -> 1.4559483e+11 | K15: =J15-J14 -> 2.0635121e+10 | L15: =K15/J14 -> 0.16513419 | M15: =L15-I15 -> 0.062131813 | N15: =IF(L15>I15, "inflation",IF(L15<I15, "deflation","stable")) -> inflation | O15: =IFERROR(IF(N15=C15,1,0),"") -> 1 | P15: =M15-F15 -> 0.0058020949 | Q15: =J15-J14 -> 2.0635121e+10 | R15: =Q15/J14 -> 0.16513419 | S15: =INDEX(m, MATCH($B$1, 'M stock'!$B$5:$B$271, 0), MATCH(A15, 'M stock'!$A$5:$BQ$5, 0)) -> 0 | T15: =(S15-S14)/S14 -> #DIV/0! | U15: =S15*Y15 -> #DIV/0! | V15: =(U15-U14)/U14 -> #DIV/0! | W15: =S15/B15 -> 0 | X15: =(W15-W14)/W14 -> #DIV/0! | Y15: =J15/S15 -> #DIV/0! | Z15: =(Y15-Y14)/Y14 -> #DIV/0! | AA15: =W15*Y15 -> #DIV/0! | AB15: =AA15-AA14 -> #DIV/0! | AC15: =AB15/AA14 -> #DIV/0! | AD15: =J15-AA15 -> #DIV/0! | AE15: =AA15+AD15 -> #DIV/0! | AF15: =(AE15-AE14)/AE14 -> #DIV/0! | AG15: =AF15-I15 -> #DIV/0! | AH15: =AF15-T16 -> #DIV/0! | AI15: =AF15-X15 -> #DIV/0! | AJ15: =AF15-Z15 -> #DIV/0! | AK15: =IF(AG15>0, "inflation",IF(AG15<0,"deflation","stable")) -> #DIV/0! | AL15: =IFERROR(IF(AK15=C15,1,0),"") | AM15: =AD15/AN15 -> #DIV/0! | AN15: =Y15 -> #DIV/0!
... A67: 2024 | B67: =INDEX(p, MATCH($B$1, 'p2'!$B$5:$B$271, 0), MATCH(A67, 'p2'!$A$5:$BQ$5, 0)) -> 38.982725 | C67: =IF(B67>B66,"inflation",IF(B67<B66,"deflation","stable")) -> inflation | D67: =IF(I67>0,"expansive","contractive") -> expansive | E67: =IF(AND(C67="inflation",D67="expansive"),"inflationary expansion",IF(AND(C67="inflation",D67="contractive"),"stagflation",IF(AND(C67="deflation",D67="expansive"),"deflationary growth",IF(AND(C67="deflation",D67="contractive"),"recession",0)))) -> inflationary expansion | F67: =(B67-B66)/B66 -> 0.021110899 | G67: =J67/B67 -> 6.0867335e+10 | H67: =G67-G66 -> 5.0066078e+08 | I67: =H67/G66 -> 0.0082936618 | J67: =INDEX(PQ, MATCH($B$1, PQ!$B$5:$B$271, 0), MATCH(A67, PQ!$A$5:$BQ$5, 0)) -> 2.3727745e+12 | K67: =J67-J66 -> 6.8169408e+10 | L67: =K67/J66 -> 0.029579648 | M67: =L67-I67 -> 0.021285986 | N67: =IF(L67>I67, "inflation",IF(L67<I67, "deflation","stable")) -> inflation | O67: =IFERROR(IF(N67=C67,1,0),"") -> 1 | P67: =M67-F67 -> 0.00017508666 | Q67: =J67-J66 -> 6.8169408e+10 | R67: =Q67/J66 -> 0.029579648 | S67: =INDEX(m, MATCH($B$1, 'M stock'!$B$5:$B$271, 0), MATCH(A67, 'M stock'!$A$5:$BQ$5, 0)) -> 0 | T67: =(S67-S66)/S66 -> #DIV/0! | U67: =S67*Y67 -> #DIV/0! | V67: =(U67-U66)/U66 -> #DIV/0! | W67: =S67/B67 -> 0 | X67: =(W67-W66)/W66 -> #DIV/0! | Y67: =J67/S67 -> #DIV/0! | Z67: =(Y67-Y66)/Y66 -> #DIV/0! | AA67: =W67*Y67 -> #DIV/0! | AB67: =AA67-AA66 -> #DIV/0! | AC67: =AB67/AA66 -> #DIV/0! | AD67: =J67-AA67 -> #DIV/0! | AE67: =AA67+AD67 -> #DIV/0! | AF67: =(AE67-AE66)/AE66 -> #DIV/0! | AG67: =AF67-I67 -> #DIV/0! | AH67: =AF67-T68 -> #DIV/0! | AI67: =AF67-X67 -> #DIV/0! | AJ67: =AF67-Z67 -> #DIV/0! | AK67: =IF(AG67>0, "inflation",IF(AG67<0,"deflation","stable")) -> #DIV/0! | AL67: =IFERROR(IF(AK67=C67,1,0),"") | AM67: =AD67/AN67 -> #DIV/0! | AN67: =Y67 -> #DIV/0!
N69: Economic Themal Dynamic Accuracy (Left Side PQ) | O69: =SUM(O4:O57)/COUNT(O4:O57) -> 1 | AK69: Economic Themal Dynamic Accuracy (Right Side MV+FAC) | AL69: =SUM(AL4:AL57)/COUNT(AL4:AL57) -> #DIV/0!
N71: Matches | O71: =SUM(O3:O67) -> 64 | AK71: Matches | AL71: =SUM(AL3:AL67) -> 0
N72: Count | O72: =COUNT(O3:O67) -> 64 | AK72: Count | AL72: =COUNT(AL3:AL67) -> 0
A74: Source:
A75: World Bank
A76: https://data.worldbank.org/
A78: Broad Money (% of GDP)
A79: API_FM.LBL.BMNY.GD.ZS_DS2_en_csv_v2_123670
A80: Used to analyze monetary aggregates relative to GDP
A82: GDP Deflator (scaled to start meaningful P at 1)_
A83: API_NY.GDP.DEFL.ZS_DS2_en_csv_v2_124034
A84: Used to convert nominal GDP to real terms and track change in P over time
A86: GDP (current US$)
A87: API_NY.GDP.MKTP.CD_DS2_en_csv_v2_130122
A88: Core GDP series for nominal valuation
... A108: affirming the robustness of our own data sources and calculations.

Sheet Spain
B1: =VLOOKUP(C1,PQ!A6:B271,2,FALSE) -> ESP | C1: Spain | H1: =IFERROR(B3+B4,"wrong") -> 2.0246639
A2: Period | B2: P | C2: Observe | D2: Economy | E2: Diagnosis | F2: Δ P % | G2: Q | H2: Δ Q | I2: Δ Q % | J2: PQ | K2: Δ PQ | L2: Δ PQ % | M2: Δ PQ % - Δ Q % | N2: test | O2: match? | P2: (Δ PQ % - Δ Q %) -Δ P % = Δ P x Δ Q (interaction) | Q2: ΔPQ | R2: Δ%PQ | S2: M | T2: ΔM % | U2: MV | V2: ΔMV % | W2: M(d.) | X2: ΔM(d.) % | Y2: V | Z2: Δ V % | AA2: MV(d.) | AB2: ΔMV(d.) | AC2: Δ%MV(d.) | AD2: PQ-MV(d.) (FAC) | AE2: MV(d.) + FAC | AF2: Δ MV(d.)+FAC % | AG2: Δ MV(d.)+FAC % - Δ Q % | AH2: Δ MV(d.)+FAC % - Δ M % | AI2: Δ MV(d.)+FAC % - Δ M % | AJ2: Δ MV(d.)+FAC % - Δ V % | AK2: test | AL2: match? | AM2: M_FAC | AN2: V_FAC
A3: 1960 | B3: =INDEX(p, MATCH($B$1, 'p2'!$B$5:$B$271, 0), MATCH(A3, 'p2'!$A$5:$BQ$5, 0)) -> 1 | G3: =J3/B3 -> 1.2424514e+10 | H3: =G3-G2 -> #VALUE! | I3: =H3-H2 -> #VALUE! | J3: =INDEX(PQ, MATCH($B$1, PQ!$B$5:$B$271, 0), MATCH(A3, PQ!$A$5:$BQ$5, 0)) -> 1.2424514e+10 | K3: =J3-J2 -> #VALUE! | L3: =(K3-K2)/K2 -> #VALUE! | M3: =L3-I3 -> #VALUE! | S3: =INDEX(m, MATCH($B$1, 'M stock'!$B$5:$B$271, 0), MATCH(A3, 'M stock'!$A$5:$BQ$5, 0)) -> 0 | U3: =S3*Y3 -> #DIV/0! | W3: =S3/B3 -> 0 | Y3: =J3/S3 -> #DIV/0! | AA3: =W3*Y3 -> #DIV/0! | AD3: =J3-AA3 -> #DIV/0! | AE3: =AA3+AD3 -> #DIV/0! | AG3: =AF3-I3 -> #VALUE! | AH3: =AF3-T4 -> #DIV/0! | AI3: =AF3-X3 -> 0 | AJ3: =AF3-Z3 -> 0
A4: 1961 | B4: =INDEX(p, MATCH($B$1, 'p2'!$B$5:$B$271, 0), MATCH(A4, 'p2'!$A$5:$BQ$5, 0)) -> 1.0246639 | C4: =IF(B4>B3,"inflation",IF(B4<B3,"deflation","stable")) -> inflation | D4: =IF(I4>0,"expansive","contractive") -> expansive | E4: =IF(AND(C4="inflation",D4="expansive"),"inflationary expansion",IF(AND(C4="inflation",D4="contractive"),"stagflation",IF(AND(C4="deflation",D4="expansive"),"deflationary growth",IF(AND(C4="deflation",D4="contractive"),"recession",0)))) -> inflationary expansion | F4: =(B4-B3)/B3 -> 0.024663898 | G4: =J4/B4 -> 1.3895412e+10 | H4: =G4-G3 -> 1.4708977e+09 | I4: =H4/G3 -> 0.11838674 | J4: =INDEX(PQ, MATCH($B$1, PQ!$B$5:$B$271, 0), MATCH(A4, PQ!$A$5:$BQ$5, 0)) -> 1.4238127e+10 | K4: =J4-J3 -> 1.8136127e+09 | L4: =K4/J3 -> 0.14597052 | M4: =L4-I4 -> 0.027583776 | N4: =IF(L4>I4, "inflation",IF(L4<I4, "deflation","stable")) -> inflation | O4: =IFERROR(IF(N4=C4,1,0),"") -> 1 | P4: =M4-F4 -> 0.0029198785 | Q4: =J4-J3 -> 1.8136127e+09 | R4: =Q4/J3 -> 0.14597052 | S4: =INDEX(m, MATCH($B$1, 'M stock'!$B$5:$B$271, 0), MATCH(A4, 'M stock'!$A$5:$BQ$5, 0)) -> 0 | T4: =(S4-S3)/S3 -> #DIV/0! | U4: =S4*Y4 -> #DIV/0! | V4: =(U4-U3)/U3 -> #DIV/0! | W4: =S4/B4 -> 0 | X4: =(W4-W3)/W3 -> #DIV/0! | Y4: =J4/S4 -> #DIV/0! | Z4: =(Y4-Y3)/Y3 -> #DIV/0! | AA4: =W4*Y4 -> #DIV/0! | AB4: =AA4-AA3 -> #DIV/0! | AC4: =AB4/AA3 -> #DIV/0! | AD4: =J4-AA4 -> #DIV/0! | AE4: =AA4+AD4 -> #DIV/0! | AF4: =(AE4-AE3)/AE3 -> #DIV/0! | AG4: =AF4-I4 -> #DIV/0! | AH4: =AF4-T5 -> #DIV/0! | AI4: =AF4-X4 -> #DIV/0! | AJ4: =AF4-Z4 -> #DIV/0! | AK4: =IF(AG4>0, "inflation",IF(AG4<0,"deflation","stable")) -> #DIV/0! | AL4: =IFERROR(IF(AK4=C4,1,0),"") | AM4: =AD4/AN4 -> #DIV/0! | AN4: =Y4 -> #DIV/0!
A5: 1962 | B5: =INDEX(p, MATCH($B$1, 'p2'!$B$5:$B$271, 0), MATCH(A5, 'p2'!$A$5:$BQ$5, 0)) -> 1.0871258 | C5: =IF(B5>B4,"inflation",IF(B5<B4,"deflation","stable")) -> inflation | D5: =IF(I5>0,"expansive","contractive") -> expansive | E5: =IF(AND(C5="inflation",D5="expansive"),"inflationary expansion",IF(AND(C5="inflation",D5="contractive"),"stagflation",IF(AND(C5="deflation",D5="expansive"),"deflationary growth",IF(AND(C5="deflation",D5="contractive"),"recession",0)))) -> inflationary expansion | F5: =(B5-B4)/B4 -> 0.060958416 | G5: =J5/B5 -> 1.5278483e+10 | H5: =G5-G4 -> 1.3830712e+09 | I5: =H5/G4 -> 0.099534381 | J5: =INDEX(PQ, MATCH($B$1, PQ!$B$5:$B$271, 0), MATCH(A5, PQ!$A$5:$BQ$5, 0)) -> 1.6609633e+10 | K5: =J5-J4 -> 2.371506e+09 | L5: =K5/J4 -> 0.16656026 | M5: =L5-I5 -> 0.067025874 | N5: =IF(L5>I5, "inflation",IF(L5<I5, "deflation","stable")) -> inflation | O5: =IFERROR(IF(N5=C5,1,0),"") -> 1 | P5: =M5-F5 -> 0.0060674582 | Q5: =J5-J4 -> 2.371506e+09 | R5: =Q5/J4 -> 0.16656026 | S5: =INDEX(m, MATCH($B$1, 'M stock'!$B$5:$B$271, 0), MATCH(A5, 'M stock'!$A$5:$BQ$5, 0)) -> 0 | T5: =(S5-S4)/S4 -> #DIV/0! | U5: =S5*Y5 -> #DIV/0! | V5: =(U5-U4)/U4 -> #DIV/0! | W5: =S5/B5 -> 0 | X5: =(W5-W4)/W4 -> #DIV/0! | Y5: =J5/S5 -> #DIV/0! | Z5: =(Y5-Y4)/Y4 -> #DIV/0! | AA5: =W5*Y5 -> #DIV/0! | AB5: =AA5-AA4 -> #DIV/0! | AC5: =AB5/AA4 -> #DIV/0! | AD5: =J5-AA5 -> #DIV/0! | AE5: =AA5+AD5 -> #DIV/0! | AF5: =(AE5-AE4)/AE4 -> #DIV/0! | AG5: =AF5-I5 -> #DIV/0! | AH5: =AF5-T6 -> #DIV/0! | AI5: =AF5-X5 -> #DIV/0! | AJ5: =AF5-Z5 -> #DIV/0! | AK5: =IF(AG5>0, "inflation",IF(AG5<0,"deflation","stable")) -> #DIV/0! | AL5: =IFERROR(IF(AK5=C5,1,0),"") | AM5: =AD5/AN5 -> #DIV/0! | AN5: =Y5 -> #DIV/0!
A6: 1963 | B6: =INDEX(p, MATCH($B$1, 'p2'!$B$5:$B$271, 0), MATCH(A6, 'p2'!$A$5:$BQ$5, 0)) -> 1.1724149 | C6: =IF(B6>B5,"inflation",IF(B6<B5,"deflation","stable")) -> inflation | D6: =IF(I6>0,"expansive","contractive") -> expansive | E6: =IF(AND(C6="inflation",D6="expansive"),"inflationary expansion",IF(AND(C6="inflation",D6="contractive"),"stagflation",IF(AND(C6="deflation",D6="expansive"),"deflationary growth",IF(AND(C6="deflation",D6="contractive"),"recession",0)))) -> inflationary expansion | F6: =(B6-B5)/B5 -> 0.078453747 | G6: =J6/B6 -> 1.6744682e+10 | H6: =G6-G5 -> 1.4661994e+09 | I6: =H6/G5 -> 0.095964989 | J6: =INDEX(PQ, MATCH($B$1, PQ!$B$5:$B$271, 0), MATCH(A6, PQ!$A$5:$BQ$5, 0)) -> 1.9631715e+10 | K6: =J6-J5 -> 3.022082e+09 | L6: =K6/J5 -> 0.18194755 | M6: =L6-I6 -> 0.08598256 | N6: =IF(L6>I6, "inflation",IF(L6<I6, "deflation","stable")) -> inflation | O6: =IFERROR(IF(N6=C6,1,0),"") -> 1 | P6: =M6-F6 -> 0.0075288129 | Q6: =J6-J5 -> 3.022082e+09 | R6: =Q6/J5 -> 0.18194755 | S6: =INDEX(m, MATCH($B$1, 'M stock'!$B$5:$B$271, 0), MATCH(A6, 'M stock'!$A$5:$BQ$5, 0)) -> 0 | T6: =(S6-S5)/S5 -> #DIV/0! | U6: =S6*Y6 -> #DIV/0! | V6: =(U6-U5)/U5 -> #DIV/0! | W6: =S6/B6 -> 0 | X6: =(W6-W5)/W5 -> #DIV/0! | Y6: =J6/S6 -> #DIV/0! | Z6: =(Y6-Y5)/Y5 -> #DIV/0! | AA6: =W6*Y6 -> #DIV/0! | AB6: =AA6-AA5 -> #DIV/0! | AC6: =AB6/AA5 -> #DIV/0! | AD6: =J6-AA6 -> #DIV/0! | AE6: =AA6+AD6 -> #DIV/0! | AF6: =(AE6-AE5)/AE5 -> #DIV/0! | AG6: =AF6-I6 -> #DIV/0! | AH6: =AF6-T7 -> #DIV/0! | AI6: =AF6-X6 -> #DIV/0! | AJ6: =AF6-Z6 -> #DIV/0! | AK6: =IF(AG6>0, "inflation",IF(AG6<0,"deflation","stable")) -> #DIV/0! | AL6: =IFERROR(IF(AK6=C6,1,0),"") | AM6: =AD6/AN6 -> #DIV/0! | AN6: =Y6 -> #DIV/0!
A7: 1964 | B7: =INDEX(p, MATCH($B$1, 'p2'!$B$5:$B$271, 0), MATCH(A7, 'p2'!$A$5:$BQ$5, 0)) -> 1.2457415 | C7: =IF(B7>B6,"inflation",IF(B7<B6,"deflation","stable")) -> inflation | D7: =IF(I7>0,"expansive","contractive") -> expansive | E7: =IF(AND(C7="inflation",D7="expansive"),"inflationary expansion",IF(AND(C7="inflation",D7="contractive"),"stagflation",IF(AND(C7="deflation",D7="expansive"),"deflationary growth",IF(AND(C7="deflation",D7="contractive"),"recession",0)))) -> inflationary expansion | F7: =(B7-B6)/B6 -> 0.062543196 | G7: =J7/B7 -> 1.7633576e+10 | H7: =G7-G6 -> 8.8889318e+08 | I7: =H7/G6 -> 0.053085102 | J7: =INDEX(PQ, MATCH($B$1, PQ!$B$5:$B$271, 0), MATCH(A7, PQ!$A$5:$BQ$5, 0)) -> 2.1966876e+10 | K7: =J7-J6 -> 2.3351613e+09 | L7: =K7/J6 -> 0.11894841 | M7: =L7-I7 -> 0.065863308 | N7: =IF(L7>I7, "inflation",IF(L7<I7, "deflation","stable")) -> inflation | O7: =IFERROR(IF(N7=C7,1,0),"") -> 1 | P7: =M7-F7 -> 0.003320112 | Q7: =J7-J6 -> 2.3351613e+09 | R7: =Q7/J6 -> 0.11894841 | S7: =INDEX(m, MATCH($B$1, 'M stock'!$B$5:$B$271, 0), MATCH(A7, 'M stock'!$A$5:$BQ$5, 0)) -> 0 | T7: =(S7-S6)/S6 -> #DIV/0! | U7: =S7*Y7 -> #DIV/0! | V7: =(U7-U6)/U6 -> #DIV/0! | W7: =S7/B7 -> 0 | X7: =(W7-W6)/W6 -> #DIV/0! | Y7: =J7/S7 -> #DIV/0! | Z7: =(Y7-Y6)/Y6 -> #DIV/0! | AA7: =W7*Y7 -> #DIV/0! | AB7: =AA7-AA6 -> #DIV/0! | AC7: =AB7/AA6 -> #DIV/0! | AD7: =J7-AA7 -> #DIV/0! | AE7: =AA7+AD7 -> #DIV/0! | AF7: =(AE7-AE6)/AE6 -> #DIV/0! | AG7: =AF7-I7 -> #DIV/0! | AH7: =AF7-T8 -> #DIV/0! | AI7: =AF7-X7 -> #DIV/0! | AJ7: =AF7-Z7 -> #DIV/0! | AK7: =IF(AG7>0, "inflation",IF(AG7<0,"deflation","stable")) -> #DIV/0! | AL7: =IFERROR(IF(AK7=C7,1,0),"") | AM7: =AD7/AN7 -> #DIV/0! | AN7: =Y7 -> #DIV/0!
A8: 1965 | B8: =INDEX(p, MATCH($B$1, 'p2'!$B$5:$B$271, 0), MATCH(A8, 'p2'!$A$5:$BQ$5, 0)) -> 1.359912 | C8: =IF(B8>B7,"inflation",IF(B8<B7,"deflation","stable")) -> inflation | D8: =IF(I8>0,"expansive","contractive") -> expansive | E8: =IF(AND(C8="inflation",D8="expansive"),"inflationary expansion",IF(AND(C8="inflation",D8="contractive"),"stagflation",IF(AND(C8="deflation",D8="expansive"),"deflationary growth",IF(AND(C8="deflation",D8="contractive"),"recession",0)))) -> inflationary expansion | F8: =(B8-B7)/B7 -> 0.091648666 | G8: =J8/B8 -> 1.8736227e+10 | H8: =G8-G7 -> 1.1026513e+09 | I8: =H8/G7 -> 0.062531349 | J8: =INDEX(PQ, MATCH($B$1, PQ!$B$5:$B$271, 0), MATCH(A8, PQ!$A$5:$BQ$5, 0)) -> 2.547962e+10 | K8: =J8-J7 -> 3.5127436e+09 | L8: =K8/J7 -> 0.15991093 | M8: =L8-I8 -> 0.097379581 | N8: =IF(L8>I8, "inflation",IF(L8<I8, "deflation","stable")) -> inflation | O8: =IFERROR(IF(N8=C8,1,0),"") -> 1 | P8: =M8-F8 -> 0.0057309147 | Q8: =J8-J7 -> 3.5127436e+09 | R8: =Q8/J7 -> 0.15991093 | S8: =INDEX(m, MATCH($B$1, 'M stock'!$B$5:$B$271, 0), MATCH(A8, 'M stock'!$A$5:$BQ$5, 0)) -> 0 | T8: =(S8-S7)/S7 -> #DIV/0! | U8: =S8*Y8 -> #DIV/0! | V8: =(U8-U7)/U7 -> #DIV/0! | W8: =S8/B8 -> 0 | X8: =(W8-W7)/W7 -> #DIV/0! | Y8: =J8/S8 -> #DIV/0! | Z8: =(Y8-Y7)/Y7 -> #DIV/0! | AA8: =W8*Y8 -> #DIV/0! | AB8: =AA8-AA7 -> #DIV/0! | AC8: =AB8/AA7 -> #DIV/0! | AD8: =J8-AA8 -> #DIV/0! | AE8: =AA8+AD8 -> #DIV/0! | AF8: =(AE8-AE7)/AE7 -> #DIV/0! | AG8: =AF8-I8 -> #DIV/0! | AH8: =AF8-T9 -> #DIV/0! | AI8: =AF8-X8 -> #DIV/0! | AJ8: =AF8-Z8 -> #DIV/0! | AK8: =IF(AG8>0, "inflation",IF(AG8<0,"deflation","stable")) -> #DIV/0! | AL8: =IFERROR(IF(AK8=C8,1,0),"") | AM8: =AD8/AN8 -> #DIV/0! | AN8: =Y8 -> #DIV/0!
A9: 1966 | B9: =INDEX(p, MATCH($B$1, 'p2'!$B$5:$B$271, 0), MATCH(A9, 'p2'!$A$5:$BQ$5, 0)) -> 1.4710677 | C9: =IF(B9>B8,"inflation",IF(B9<B8,"deflation","stable")) -> inflation | D9: =IF(I9>0,"expansive","contractive") -> expansive | E9: =IF(AND(C9="inflation",D9="expansive"),"inflationary expansion",IF(AND(C9="inflation",D9="contractive"),"stagflation",IF(AND(C9="deflation",D9="expansive"),"deflationary growth",IF(AND(C9="deflation",D9="contractive"),"recession",0)))) -> inflationary expansion | F9: =(B9-B8)/B8 -> 0.081737434 | G9: =J9/B9 -> 2.0093865e+10 | H9: =G9-G8 -> 1.3576383e+09 | I9: =H9/G8 -> 0.072460603 | J9: =INDEX(PQ, MATCH($B$1, PQ!$B$5:$B$271, 0), MATCH(A9, PQ!$A$5:$BQ$5, 0)) -> 2.9559436e+10 | K9: =J9-J8 -> 4.0798166e+09 | L9: =K9/J8 -> 0.16012078 | M9: =L9-I9 -> 0.087660177 | N9: =IF(L9>I9, "inflation",IF(L9<I9, "deflation","stable")) -> inflation | O9: =IFERROR(IF(N9=C9,1,0),"") -> 1 | P9: =M9-F9 -> 0.0059227437 | Q9: =J9-J8 -> 4.0798166e+09 | R9: =Q9/J8 -> 0.16012078 | S9: =INDEX(m, MATCH($B$1, 'M stock'!$B$5:$B$271, 0), MATCH(A9, 'M stock'!$A$5:$BQ$5, 0)) -> 0 | T9: =(S9-S8)/S8 -> #DIV/0! | U9: =S9*Y9 -> #DIV/0! | V9: =(U9-U8)/U8 -> #DIV/0! | W9: =S9/B9 -> 0 | X9: =(W9-W8)/W8 -> #DIV/0! | Y9: =J9/S9 -> #DIV/0! | Z9: =(Y9-Y8)/Y8 -> #DIV/0! | AA9: =W9*Y9 -> #DIV/0! | AB9: =AA9-AA8 -> #DIV/0! | AC9: =AB9/AA8 -> #DIV/0! | AD9: =J9-AA9 -> #DIV/0! | AE9: =AA9+AD9 -> #DIV/0! | AF9: =(AE9-AE8)/AE8 -> #DIV/0! | AG9: =AF9-I9 -> #DIV/0! | AH9: =AF9-T10 -> #DIV/0! | AI9: =AF9-X9 -> #DIV/0! | AJ9: =AF9-Z9 -> #DIV/0! | AK9: =IF(AG9>0, "inflation",IF(AG9<0,"deflation","stable")) -> #DIV/0! | AL9: =IFERROR(IF(AK9=C9,1,0),"") | AM9: =AD9/AN9 -> #DIV/0! | AN9: =Y9 -> #DIV/0!
A10: 1967 | B10: =INDEX(p, MATCH($B$1, 'p2'!$B$5:$B$271, 0), MATCH(A10, 'p2'!$A$5:$BQ$5, 0)) -> 1.5966633 | C10: =IF(B10>B9,"inflation",IF(B10<B9,"deflation","stable")) -> inflation | D10: =IF(I10>0,"expansive","contractive") -> expansive | E10: =IF(AND(C10="inflation",D10="expansive"),"inflationary expansion",IF(AND(C10="inflation",D10="contractive"),"stagflation",IF(AND(C10="deflation",D10="expansive"),"deflationary growth",IF(AND(C10="deflation",D10="contractive"),"recession",0)))) -> inflationary expansion | F10: =(B10-B9)/B9 -> 0.085377191 | G10: =J10/B10 -> 2.0399357e+10 | H10: =G10-G9 -> 3.0549182e+08 | I10: =H10/G9 -> 0.015203238 | J10: =INDEX(PQ, MATCH($B$1, PQ!$B$5:$B$271, 0), MATCH(A10, PQ!$A$5:$BQ$5, 0)) -> 3.2570905e+10 | K10: =J10-J9 -> 3.0114692e+09 | L10: =K10/J9 -> 0.10187844 | M10: =L10-I10 -> 0.086675201 | N10: =IF(L10>I10, "inflation",IF(L10<I10, "deflation","stable")) -> inflation | O10: =IFERROR(IF(N10=C10,1,0),"") -> 1 | P10: =M10-F10 -> 0.0012980098 | Q10: =J10-J9 -> 3.0114692e+09 | R10: =Q10/J9 -> 0.10187844 | S10: =INDEX(m, MATCH($B$1, 'M stock'!$B$5:$B$271, 0), MATCH(A10, 'M stock'!$A$5:$BQ$5, 0)) -> 0 | T10: =(S10-S9)/S9 -> #DIV/0! | U10: =S10*Y10 -> #DIV/0! | V10: =(U10-U9)/U9 -> #DIV/0! | W10: =S10/B10 -> 0 | X10: =(W10-W9)/W9 -> #DIV/0! | Y10: =J10/S10 -> #DIV/0! | Z10: =(Y10-Y9)/Y9 -> #DIV/0! | AA10: =W10*Y10 -> #DIV/0! | AB10: =AA10-AA9 -> #DIV/0! | AC10: =AB10/AA9 -> #DIV/0! | AD10: =J10-AA10 -> #DIV/0! | AE10: =AA10+AD10 -> #DIV/0! | AF10: =(AE10-AE9)/AE9 -> #DIV/0! | AG10: =AF10-I10 -> #DIV/0! | AH10: =AF10-T11 -> #DIV/0! | AI10: =AF10-X10 -> #DIV/0! | AJ10: =AF10-Z10 -> #DIV/0! | AK10: =IF(AG10>0, "inflation",IF(AG10<0,"deflation","stable")) -> #DIV/0! | AL10: =IFERROR(IF(AK10=C10,1,0),"") | AM10: =AD10/AN10 -> #DIV/0! | AN10: =Y10 -> #DIV/0!
A11: 1968 | B11: =INDEX(p, MATCH($B$1, 'p2'!$B$5:$B$271, 0), MATCH(A11, 'p2'!$A$5:$BQ$5, 0)) -> 1.6910442 | C11: =IF(B11>B10,"inflation",IF(B11<B10,"deflation","stable")) -> inflation | D11: =IF(I11>0,"expansive","contractive") -> contractive | E11: =IF(AND(C11="inflation",D11="expansive"),"inflationary expansion",IF(AND(C11="inflation",D11="contractive"),"stagflation",IF(AND(C11="deflation",D11="expansive"),"deflationary growth",IF(AND(C11="deflation",D11="contractive"),"recession",0)))) -> stagflation | F11: =(B11-B10)/B10 -> 0.059111301 | G11: =J11/B11 -> 1.9156405e+10 | H11: =G11-G10 -> -1.2429525e+09 | I11: =H11/G10 -> -0.060930963 | J11: =INDEX(PQ, MATCH($B$1, PQ!$B$5:$B$271, 0), MATCH(A11, PQ!$A$5:$BQ$5, 0)) -> 3.2394326e+10 | K11: =J11-J10 -> -1.7657893e+08 | L11: =K11/J10 -> -0.0054213701 | M11: =L11-I11 -> 0.055509593 | N11: =IF(L11>I11, "inflation",IF(L11<I11, "deflation","stable")) -> inflation | O11: =IFERROR(IF(N11=C11,1,0),"") -> 1 | P11: =M11-F11 -> -0.0036017085 | Q11: =J11-J10 -> -1.7657893e+08 | R11: =Q11/J10 -> -0.0054213701 | S11: =INDEX(m, MATCH($B$1, 'M stock'!$B$5:$B$271, 0), MATCH(A11, 'M stock'!$A$5:$BQ$5, 0)) -> 0 | T11: =(S11-S10)/S10 -> #DIV/0! | U11: =S11*Y11 -> #DIV/0! | V11: =(U11-U10)/U10 -> #DIV/0! | W11: =S11/B11 -> 0 | X11: =(W11-W10)/W10 -> #DIV/0! | Y11: =J11/S11 -> #DIV/0! | Z11: =(Y11-Y10)/Y10 -> #DIV/0! | AA11: =W11*Y11 -> #DIV/0! | AB11: =AA11-AA10 -> #DIV/0! | AC11: =AB11/AA10 -> #DIV/0! | AD11: =J11-AA11 -> #DIV/0! | AE11: =AA11+AD11 -> #DIV/0! | AF11: =(AE11-AE10)/AE10 -> #DIV/0! | AG11: =AF11-I11 -> #DIV/0! | AH11: =AF11-T12 -> #DIV/0! | AI11: =AF11-X11 -> #DIV/0! | AJ11: =AF11-Z11 -> #DIV/0! | AK11: =IF(AG11>0, "inflation",IF(AG11<0,"deflation","stable")) -> #DIV/0! | AL11: =IFERROR(IF(AK11=C11,1,0),"") | AM11: =AD11/AN11 -> #DIV/0! | AN11: =Y11 -> #DIV/0!
A12: 1969 | B12: =INDEX(p, MATCH($B$1, 'p2'!$B$5:$B$271, 0), MATCH(A12, 'p2'!$A$5:$BQ$5, 0)) -> 1.7778497 | C12: =IF(B12>B11,"inflation",IF(B12<B11,"deflation","stable")) -> inflation | D12: =IF(I12>0,"expansive","contractive") -> expansive | E12: =IF(AND(C12="inflation",D12="expansive"),"inflationary expansion",IF(AND(C12="inflation",D12="contractive"),"stagflation",IF(AND(C12="deflation",D12="expansive"),"deflationary growth",IF(AND(C12="deflation",D12="contractive"),"recession",0)))) -> inflationary expansion | F12: =(B12-B11)/B11 -> 0.051332506 | G12: =J12/B12 -> 2.0862668e+10 | H12: =G12-G11 -> 1.7062639e+09 | I12: =H12/G11 -> 0.089070156 | J12: =INDEX(PQ, MATCH($B$1, PQ!$B$5:$B$271, 0), MATCH(A12, PQ!$A$5:$BQ$5, 0)) -> 3.7090689e+10 | K12: =J12-J11 -> 4.6963628e+09 | L12: =K12/J11 -> 0.14497486 | M12: =L12-I12 -> 0.055904701 | N12: =IF(L12>I12, "inflation",IF(L12<I12, "deflation","stable")) -> inflation | O12: =IFERROR(IF(N12=C12,1,0),"") -> 1 | P12: =M12-F12 -> 0.0045721943 | Q12: =J12-J11 -> 4.6963628e+09 | R12: =Q12/J11 -> 0.14497486 | S12: =INDEX(m, MATCH($B$1, 'M stock'!$B$5:$B$271, 0), MATCH(A12, 'M stock'!$A$5:$BQ$5, 0)) -> 0 | T12: =(S12-S11)/S11 -> #DIV/0! | U12: =S12*Y12 -> #DIV/0! | V12: =(U12-U11)/U11 -> #DIV/0! | W12: =S12/B12 -> 0 | X12: =(W12-W11)/W11 -> #DIV/0! | Y12: =J12/S12 -> #DIV/0! | Z12: =(Y12-Y11)/Y11 -> #DIV/0! | AA12: =W12*Y12 -> #DIV/0! | AB12: =AA12-AA11 -> #DIV/0! | AC12: =AB12/AA11 -> #DIV/0! | AD12: =J12-AA12 -> #DIV/0! | AE12: =AA12+AD12 -> #DIV/0! | AF12: =(AE12-AE11)/AE11 -> #DIV/0! | AG12: =AF12-I12 -> #DIV/0! | AH12: =AF12-T13 -> #DIV/0! | AI12: =AF12-X12 -> #DIV/0! | AJ12: =AF12-Z12 -> #DIV/0! | AK12: =IF(AG12>0, "inflation",IF(AG12<0,"deflation","stable")) -> #DIV/0! | AL12: =IFERROR(IF(AK12=C12,1,0),"") | AM12: =AD12/AN12 -> #DIV/0! | AN12: =Y12 -> #DIV/0!
A13: 1970 | B13: =INDEX(p, MATCH($B$1, 'p2'!$B$5:$B$271, 0), MATCH(A13, 'p2'!$A$5:$BQ$5, 0)) -> 1.8835 | C13: =IF(B13>B12,"inflation",IF(B13<B12,"deflation","stable")) -> inflation | D13: =IF(I13>0,"expansive","contractive") -> expansive | E13: =IF(AND(C13="inflation",D13="expansive"),"inflationary expansion",IF(AND(C13="inflation",D13="contractive"),"stagflation",IF(AND(C13="deflation",D13="expansive"),"deflationary growth",IF(AND(C13="deflation",D13="contractive"),"recession",0)))) -> inflationary expansion | F13: =(B13-B12)/B12 -> 0.059425863 | G13: =J13/B13 -> 2.1748721e+10 | H13: =G13-G12 -> 8.8605242e+08 | I13: =H13/G12 -> 0.042470714 | J13: =INDEX(PQ, MATCH($B$1, PQ!$B$5:$B$271, 0), MATCH(A13, PQ!$A$5:$BQ$5, 0)) -> 4.0963715e+10 | K13: =J13-J12 -> 3.8730259e+09 | L13: =K13/J12 -> 0.10442044 | M13: =L13-I13 -> 0.061949722 | N13: =IF(L13>I13, "inflation",IF(L13<I13, "deflation","stable")) -> inflation | O13: =IFERROR(IF(N13=C13,1,0),"") -> 1 | P13: =M13-F13 -> 0.0025238588 | Q13: =J13-J12 -> 3.8730259e+09 | R13: =Q13/J12 -> 0.10442044 | S13: =INDEX(m, MATCH($B$1, 'M stock'!$B$5:$B$271, 0), MATCH(A13, 'M stock'!$A$5:$BQ$5, 0)) -> 0 | T13: =(S13-S12)/S12 -> #DIV/0! | U13: =S13*Y13 -> #DIV/0! | V13: =(U13-U12)/U12 -> #DIV/0! | W13: =S13/B13 -> 0 | X13: =(W13-W12)/W12 -> #DIV/0! | Y13: =J13/S13 -> #DIV/0! | Z13: =(Y13-Y12)/Y12 -> #DIV/0! | AA13: =W13*Y13 -> #DIV/0! | AB13: =AA13-AA12 -> #DIV/0! | AC13: =AB13/AA12 -> #DIV/0! | AD13: =J13-AA13 -> #DIV/0! | AE13: =AA13+AD13 -> #DIV/0! | AF13: =(AE13-AE12)/AE12 -> #DIV/0! | AG13: =AF13-I13 -> #DIV/0! | AH13: =AF13-T14 -> #DIV/0! | AI13: =AF13-X13 -> #DIV/0! | AJ13: =AF13-Z13 -> #DIV/0! | AK13: =IF(AG13>0, "inflation",IF(AG13<0,"deflation","stable")) -> #DIV/0! | AL13: =IFERROR(IF(AK13=C13,1,0),"") | AM13: =AD13/AN13 -> #DIV/0! | AN13: =Y13 -> #DIV/0!
A14: 1971 | B14: =INDEX(p, MATCH($B$1, 'p2'!$B$5:$B$271, 0), MATCH(A14, 'p2'!$A$5:$BQ$5, 0)) -> 2.0312798 | C14: =IF(B14>B13,"inflation",IF(B14<B13,"deflation","stable")) -> inflation | D14: =IF(I14>0,"expansive","contractive") -> expansive | E14: =IF(AND(C14="inflation",D14="expansive"),"inflationary expansion",IF(AND(C14="inflation",D14="contractive"),"stagflation",IF(AND(C14="deflation",D14="expansive"),"deflationary growth",IF(AND(C14="deflation",D14="contractive"),"recession",0)))) -> inflationary expansion | F14: =(B14-B13)/B13 -> 0.078460194 | G14: =J14/B14 -> 2.2934369e+10 | H14: =G14-G13 -> 1.1856484e+09 | I14: =H14/G13 -> 0.054515774 | J14: =INDEX(PQ, MATCH($B$1, PQ!$B$5:$B$271, 0), MATCH(A14, PQ!$A$5:$BQ$5, 0)) -> 4.658612e+10 | K14: =J14-J13 -> 5.6224045e+09 | L14: =K14/J13 -> 0.13725329 | M14: =L14-I14 -> 0.082737512 | N14: =IF(L14>I14, "inflation",IF(L14<I14, "deflation","stable")) -> inflation | O14: =IFERROR(IF(N14=C14,1,0),"") -> 1 | P14: =M14-F14 -> 0.0042773182 | Q14: =J14-J13 -> 5.6224045e+09 | R14: =Q14/J13 -> 0.13725329 | S14: =INDEX(m, MATCH($B$1, 'M stock'!$B$5:$B$271, 0), MATCH(A14, 'M stock'!$A$5:$BQ$5, 0)) -> 0 | T14: =(S14-S13)/S13 -> #DIV/0! | U14: =S14*Y14 -> #DIV/0! | V14: =(U14-U13)/U13 -> #DIV/0! | W14: =S14/B14 -> 0 | X14: =(W14-W13)/W13 -> #DIV/0! | Y14: =J14/S14 -> #DIV/0! | Z14: =(Y14-Y13)/Y13 -> #DIV/0! | AA14: =W14*Y14 -> #DIV/0! | AB14: =AA14-AA13 -> #DIV/0! | AC14: =AB14/AA13 -> #DIV/0! | AD14: =J14-AA14 -> #DIV/0! | AE14: =AA14+AD14 -> #DIV/0! | AF14: =(AE14-AE13)/AE13 -> #DIV/0! | AG14: =AF14-I14 -> #DIV/0! | AH14: =AF14-T15 -> #DIV/0! | AI14: =AF14-X14 -> #DIV/0! | AJ14: =AF14-Z14 -> #DIV/0! | AK14: =IF(AG14>0, "inflation",IF(AG14<0,"deflation","stable")) -> #DIV/0! | AL14: =IFERROR(IF(AK14=C14,1,0),"") | AM14: =AD14/AN14 -> #DIV/0! | AN14: =Y14 -> #DIV/0!
