Workbook
Name m: 'M stock'!$A$5:$BQ$271
Name p: 'p2'!$A$5:$BQ$271
Name PQ: PQ!$A$5:$BQ$271

Sheet Subject
B1: =VLOOKUP(C1,PQ!A6:B271,2,FALSE) -> VEN | C1: Venezuela, RB | H1: =IFERROR(B3+B4,"wrong") -> 2.0201373
A2: Period | B2: P | C2: Observe | D2: Economy | E2: Diagnosis | F2: Δ P % | G2: Q | H2: Δ Q | I2: Δ Q % | J2: PQ | K2: Δ PQ | L2: Δ PQ % | M2: Δ PQ % - Δ Q % | N2: test | O2: match? | P2: (Δ PQ % - Δ Q %) -Δ P % = Δ P x Δ Q (interaction) | Q2: ΔPQ | R2: Δ%PQ | S2: M | T2: ΔM % | U2: MV | V2: ΔMV % | W2: M(d.) | X2: ΔM(d.) % | Y2: V | Z2: Δ V % | AA2: MV(d.) | AB2: ΔMV(d.) | AC2: Δ%MV(d.) | AD2: PQ-MV(d.) (FAC) | AE2: MV(d.) + FAC | AF2: Δ MV(d.)+FAC % | AG2: Δ MV(d.)+FAC % - Δ Q % | AH2: Δ MV(d.)+FAC % - Δ M % | AI2: Δ MV(d.)+FAC % - Δ M % | AJ2: Δ MV(d.)+FAC % - Δ V % | AK2: test | AL2: match? | AM2: M_FAC | AN2: V_FAC
A3: 1960 | B3: =INDEX(p, MATCH($B$1, 'p2'!$B$5:$B$271, 0), MATCH(A3, 'p2'!$A$5:$BQ$5, 0)) -> 1 | G3: =J3/B3 -> 7.6639383e+09 | H3: =G3-G2 -> #VALUE! | I3: =H3-H2 -> #VALUE! | J3: =INDEX(PQ, MATCH($B$1, PQ!$B$5:$B$271, 0), MATCH(A3, PQ!$A$5:$BQ$5, 0)) -> 7.6639383e+09 | K3: =J3-J2 -> #VALUE! | L3: =(K3-K2)/K2 -> #VALUE! | M3: =L3-I3 -> #VALUE! | S3: =INDEX(m, MATCH($B$1, 'M stock'!$B$5:$B$271, 0), MATCH(A3, 'M stock'!$A$5:$BQ$5, 0)) -> 1.5718373e+09 | U3: =S3*Y3 -> 7.6639383e+09 | W3: =S3/B3 -> 1.5718373e+09 | Y3: =J3/S3 -> 4.8757835 | AA3: =W3*Y3 -> 7.6639383e+09 | AD3: =J3-AA3 -> 0 | AE3: =AA3+AD3 -> 7.6639383e+09 | AG3: =AF3-I3 -> #VALUE! | AH3: =AF3-T4 -> -0.011700369 | AI3: =AF3-X3 -> 0 | AJ3: =AF3-Z3 -> 0
A4: 1961 | B4: =INDEX(p, MATCH($B$1, 'p2'!$B$5:$B$271, 0), MATCH(A4, 'p2'!$A$5:$BQ$5, 0)) -> 1.0201373 | C4: =IF(B4>B3,"inflation",IF(B4<B3,"deflation","stable")) -> inflation | D4: =IF(I4>0,"expansive","contractive") -> expansive | E4: =IF(AND(C4="inflation",D4="expansive"),"inflationary expansion",IF(AND(C4="inflation",D4="contractive"),"stagflation",IF(AND(C4="deflation",D4="expansive"),"deflationary growth",IF(AND(C4="deflation",D4="contractive"),"recession",0)))) -> inflationary expansion | F4: =(B4-B3)/B3 -> 0.020137306 | G4: =J4/B4 -> 7.9080208e+09 | H4: =G4-G3 -> 2.440825e+08 | I4: =H4/G3 -> 0.031848181 | J4: =INDEX(PQ, MATCH($B$1, PQ!$B$5:$B$271, 0), MATCH(A4, PQ!$A$5:$BQ$5, 0)) -> 8.067267e+09 | K4: =J4-J3 -> 4.0332873e+08 | L4: =K4/J3 -> 0.052626823 | M4: =L4-I4 -> 0.020778642 | N4: =IF(L4>I4, "inflation",IF(L4<I4, "deflation","stable")) -> inflation | O4: =IFERROR(IF(N4=C4,1,0),"") -> 1 | P4: =M4-F4 -> 0.00064133656 | Q4: =J4-J3 -> 4.0332873e+08 | R4: =Q4/J3 -> 0.052626823 | S4: =INDEX(m, MATCH($B$1, 'M stock'!$B$5:$B$271, 0), MATCH(A4, 'M stock'!$A$5:$BQ$5, 0)) -> 1.5902284e+09 | T4: =(S4-S3)/S3 -> 0.011700369 | U4: =S4*Y4 -> 8.067267e+09 | V4: =(U4-U3)/U3 -> 0.052626823 | W4: =S4/B4 -> 1.5588376e+09 | X4: =(W4-W3)/W3 -> -0.0082703932 | Y4: =J4/S4 -> 5.0730242 | Z4: =(Y4-Y3)/Y3 -> 0.040453138 | AA4: =W4*Y4 -> 7.9080208e+09 | AB4: =AA4-AA3 -> 2.440825e+08 | AC4: =AB4/AA3 -> 0.031848181 | AD4: =J4-AA4 -> 1.5924623e+08 | AE4: =AA4+AD4 -> 8.067267e+09 | AF4: =(AE4-AE3)/AE3 -> 0.052626823 | AG4: =AF4-I4 -> 0.020778642 | AH4: =AF4-T5 -> 0.03699529 | AI4: =AF4-X4 -> 0.060897217 | AJ4: =AF4-Z4 -> 0.012173686 | AK4: =IF(AG4>0, "inflation",IF(AG4<0,"deflation","stable")) -> inflation | AL4: =IFERROR(IF(AK4=C4,1,0),"") -> 1 | AM4: =AD4/AN4 -> 31390789 | AN4: =Y4 -> 5.0730242
A5: 1962 | B5: =INDEX(p, MATCH($B$1, 'p2'!$B$5:$B$271, 0), MATCH(A5, 'p2'!$A$5:$BQ$5, 0)) -> 1.0269218 | C5: =IF(B5>B4,"inflation",IF(B5<B4,"deflation","stable")) -> inflation | D5: =IF(I5>0,"expansive","contractive") -> expansive | E5: =IF(AND(C5="inflation",D5="expansive"),"inflationary expansion",IF(AND(C5="inflation",D5="contractive"),"stagflation",IF(AND(C5="deflation",D5="expansive"),"deflationary growth",IF(AND(C5="deflation",D5="contractive"),"recession",0)))) -> inflationary expansion | F5: =(B5-B4)/B4 -> 0.0066505414 | G5: =J5/B5 -> 8.583234e+09 | H5: =G5-G4 -> 6.7521322e+08 | I5: =H5/G4 -> 0.085383339 | J5: =INDEX(PQ, MATCH($B$1, PQ!$B$5:$B$271, 0), MATCH(A5, PQ!$A$5:$BQ$5, 0)) -> 8.8143099e+09 | K5: =J5-J4 -> 7.4704285e+08 | L5: =K5/J4 -> 0.092601726 | M5: =L5-I5 -> 0.0072183868 | N5: =IF(L5>I5, "inflation",IF(L5<I5, "deflation","stable")) -> inflation | O5: =IFERROR(IF(N5=C5,1,0),"") -> 1 | P5: =M5-F5 -> 0.00056784543 | Q5: =J5-J4 -> 7.4704285e+08 | R5: =Q5/J4 -> 0.092601726 | S5: =INDEX(m, MATCH($B$1, 'M stock'!$B$5:$B$271, 0), MATCH(A5, 'M stock'!$A$5:$BQ$5, 0)) -> 1.6150861e+09 | T5: =(S5-S4)/S4 -> 0.015631534 | U5: =S5*Y5 -> 8.8143099e+09 | V5: =(U5-U4)/U4 -> 0.092601726 | W5: =S5/B5 -> 1.572745e+09 | X5: =(W5-W4)/W4 -> 0.0089216586 | Y5: =J5/S5 -> 5.4574861 | Z5: =(Y5-Y4)/Y4 -> 0.075785548 | AA5: =W5*Y5 -> 8.583234e+09 | AB5: =AA5-AA4 -> 6.7521322e+08 | AC5: =AB5/AA4 -> 0.085383339 | AD5: =J5-AA5 -> 2.3107586e+08 | AE5: =AA5+AD5 -> 8.8143099e+09 | AF5: =(AE5-AE4)/AE4 -> 0.092601726 | AG5: =AF5-I5 -> 0.0072183868 | AH5: =AF5-T6 -> -0.069856684 | AI5: =AF5-X5 -> 0.083680068 | AJ5: =AF5-Z5 -> 0.016816178 | AK5: =IF(AG5>0, "inflation",IF(AG5<0,"deflation","stable")) -> inflation | AL5: =IFERROR(IF(AK5=C5,1,0),"") -> 1 | AM5: =AD5/AN5 -> 42341081 | AN5: =Y5 -> 5.4574861
A6: 1963 | B6: =INDEX(p, MATCH($B$1, 'p2'!$B$5:$B$271, 0), MATCH(A6, 'p2'!$A$5:$BQ$5, 0)) -> 1.0774446 | C6: =IF(B6>B5,"inflation",IF(B6<B5,"deflation","stable")) -> inflation | D6: =IF(I6>0,"expansive","contractive") -> expansive | E6: =IF(AND(C6="inflation",D6="expansive"),"inflationary expansion",IF(AND(C6="inflation",D6="contractive"),"stagflation",IF(AND(C6="deflation",D6="expansive"),"deflationary growth",IF(AND(C6="deflation",D6="contractive"),"recession",0)))) -> inflationary expansion | F6: =(B6-B5)/B5 -> 0.049198298 | G6: =J6/B6 -> 8.9180618e+09 | H6: =G6-G5 -> 3.3482777e+08 | I6: =H6/G5 -> 0.039009512 | J6: =INDEX(PQ, MATCH($B$1, PQ!$B$5:$B$271, 0), MATCH(A6, PQ!$A$5:$BQ$5, 0)) -> 9.6087173e+09 | K6: =J6-J5 -> 7.944074e+08 | L6: =K6/J5 -> 0.090127011 | M6: =L6-I6 -> 0.051117499 | N6: =IF(L6>I6, "inflation",IF(L6<I6, "deflation","stable")) -> inflation | O6: =IFERROR(IF(N6=C6,1,0),"") -> 1 | P6: =M6-F6 -> 0.0019192016 | Q6: =J6-J5 -> 7.944074e+08 | R6: =Q6/J5 -> 0.090127011 | S6: =INDEX(m, MATCH($B$1, 'M stock'!$B$5:$B$271, 0), MATCH(A6, 'M stock'!$A$5:$BQ$5, 0)) -> 1.8774704e+09 | T6: =(S6-S5)/S5 -> 0.16245841 | U6: =S6*Y6 -> 9.6087173e+09 | V6: =(U6-U5)/U5 -> 0.090127011 | W6: =S6/B6 -> 1.7425216e+09 | X6: =(W6-W5)/W5 -> 0.1079492 | Y6: =J6/S6 -> 5.1179062 | Z6: =(Y6-Y5)/Y5 -> -0.062222785 | AA6: =W6*Y6 -> 8.9180618e+09 | AB6: =AA6-AA5 -> 3.3482777e+08 | AC6: =AB6/AA5 -> 0.039009512 | AD6: =J6-AA6 -> 6.906555e+08 | AE6: =AA6+AD6 -> 9.6087173e+09 | AF6: =(AE6-AE5)/AE5 -> 0.090127011 | AG6: =AF6-I6 -> 0.051117499 | AH6: =AF6-T7 -> 0.19506109 | AI6: =AF6-X6 -> -0.017822185 | AJ6: =AF6-Z6 -> 0.1523498 | AK6: =IF(AG6>0, "inflation",IF(AG6<0,"deflation","stable")) -> inflation | AL6: =IFERROR(IF(AK6=C6,1,0),"") -> 1 | AM6: =AD6/AN6 -> 1.3494884e+08 | AN6: =Y6 -> 5.1179062
A7: 1964 | B7: =INDEX(p, MATCH($B$1, 'p2'!$B$5:$B$271, 0), MATCH(A7, 'p2'!$A$5:$BQ$5, 0)) -> 1.0734957 | C7: =IF(B7>B6,"inflation",IF(B7<B6,"deflation","stable")) -> deflation | D7: =IF(I7>0,"expansive","contractive") -> contractive | E7: =IF(AND(C7="inflation",D7="expansive"),"inflationary expansion",IF(AND(C7="inflation",D7="contractive"),"stagflation",IF(AND(C7="deflation",D7="expansive"),"deflationary growth",IF(AND(C7="deflation",D7="contractive"),"recession",0)))) -> recession | F7: =(B7-B6)/B6 -> -0.0036650286 | G7: =J7/B7 -> 7.6315291e+09 | H7: =G7-G6 -> -1.2865326e+09 | I7: =H7/G6 -> -0.14426146 | J7: =INDEX(PQ, MATCH($B$1, PQ!$B$5:$B$271, 0), MATCH(A7, PQ!$A$5:$BQ$5, 0)) -> 8.1924138e+09 | K7: =J7-J6 -> -1.4163035e+09 | L7: =K7/J6 -> -0.14739777 | M7: =L7-I7 -> -0.0031363062 | N7: =IF(L7>I7, "inflation",IF(L7<I7, "deflation","stable")) -> deflation | O7: =IFERROR(IF(N7=C7,1,0),"") -> 1 | P7: =M7-F7 -> 0.00052872239 | Q7: =J7-J6 -> -1.4163035e+09 | R7: =Q7/J6 -> -0.14739777 | S7: =INDEX(m, MATCH($B$1, 'M stock'!$B$5:$B$271, 0), MATCH(A7, 'M stock'!$A$5:$BQ$5, 0)) -> 1.6804598e+09 | T7: =(S7-S6)/S6 -> -0.10493408 | U7: =S7*Y7 -> 8.1924138e+09 | V7: =(U7-U6)/U6 -> -0.14739777 | W7: =S7/B7 -> 1.5654089e+09 | X7: =(W7-W6)/W6 -> -0.10164157 | Y7: =J7/S7 -> 4.8751026 | Z7: =(Y7-Y6)/Y6 -> -0.047441971 | AA7: =W7*Y7 -> 7.6315291e+09 | AB7: =AA7-AA6 -> -1.2865326e+09 | AC7: =AB7/AA6 -> -0.14426146 | AD7: =J7-AA7 -> 5.6088464e+08 | AE7: =AA7+AD7 -> 8.1924138e+09 | AF7: =(AE7-AE6)/AE6 -> -0.14739777 | AG7: =AF7-I7 -> -0.0031363062 | AH7: =AF7-T8 -> -0.1928524 | AI7: =AF7-X7 -> -0.0457562 | AJ7: =AF7-Z7 -> -0.099955799 | AK7: =IF(AG7>0, "inflation",IF(AG7<0,"deflation","stable")) -> deflation | AL7: =IFERROR(IF(AK7=C7,1,0),"") -> 1 | AM7: =AD7/AN7 -> 1.1505084e+08 | AN7: =Y7 -> 4.8751026
A8: 1965 | B8: =INDEX(p, MATCH($B$1, 'p2'!$B$5:$B$271, 0), MATCH(A8, 'p2'!$A$5:$BQ$5, 0)) -> 1.0967606 | C8: =IF(B8>B7,"inflation",IF(B8<B7,"deflation","stable")) -> inflation | D8: =IF(I8>0,"expansive","contractive") -> expansive | E8: =IF(AND(C8="inflation",D8="expansive"),"inflationary expansion",IF(AND(C8="inflation",D8="contractive"),"stagflation",IF(AND(C8="deflation",D8="expansive"),"deflationary growth",IF(AND(C8="deflation",D8="contractive"),"recession",0)))) -> inflationary expansion | F8: =(B8-B7)/B7 -> 0.021672088 | G8: =J8/B8 -> 7.6842455e+09 | H8: =G8-G7 -> 52716399 | I8: =H8/G7 -> 0.0069077111 | J8: =INDEX(PQ, MATCH($B$1, PQ!$B$5:$B$271, 0), MATCH(A8, PQ!$A$5:$BQ$5, 0)) -> 8.4277778e+09 | K8: =J8-J7 -> 2.3536398e+08 | L8: =K8/J7 -> 0.028729504 | M8: =L8-I8 -> 0.021821793 | N8: =IF(L8>I8, "inflation",IF(L8<I8, "deflation","stable")) -> inflation | O8: =IFERROR(IF(N8=C8,1,0),"") -> 1 | P8: =M8-F8 -> 0.00014970453 | Q8: =J8-J7 -> 2.3536398e+08 | R8: =Q8/J7 -> 0.028729504 | S8: =INDEX(m, MATCH($B$1, 'M stock'!$B$5:$B$271, 0), MATCH(A8, 'M stock'!$A$5:$BQ$5, 0)) -> 1.7568444e+09 | T8: =(S8-S7)/S7 -> 0.045454628 | U8: =S8*Y8 -> 8.4277778e+09 | V8: =(U8-U7)/U7 -> 0.028729504 | W8: =S8/B8 -> 1.6018486e+09 | X8: =(W8-W7)/W7 -> 0.023278056 | Y8: =J8/S8 -> 4.797111 | Z8: =(Y8-Y7)/Y7 -> -0.015997944 | AA8: =W8*Y8 -> 7.6842455e+09 | AB8: =AA8-AA7 -> 52716399 | AC8: =AB8/AA7 -> 0.0069077111 | AD8: =J8-AA8 -> 7.4353223e+08 | AE8: =AA8+AD8 -> 8.4277778e+09 | AF8: =(AE8-AE7)/AE7 -> 0.028729504 | AG8: =AF8-I8 -> 0.021821793 | AH8: =AF8-T9 -> 0.029058376 | AI8: =AF8-X8 -> 0.0054514481 | AJ8: =AF8-Z8 -> 0.044727448 | AK8: =IF(AG8>0, "inflation",IF(AG8<0,"deflation","stable")) -> inflation | AL8: =IFERROR(IF(AK8=C8,1,0),"") -> 1 | AM8: =AD8/AN8 -> 1.5499584e+08 | AN8: =Y8 -> 4.797111
A9: 1966 | B9: =INDEX(p, MATCH($B$1, 'p2'!$B$5:$B$271, 0), MATCH(A9, 'p2'!$A$5:$BQ$5, 0)) -> 1.1257691 | C9: =IF(B9>B8,"inflation",IF(B9<B8,"deflation","stable")) -> inflation | D9: =IF(I9>0,"expansive","contractive") -> expansive | E9: =IF(AND(C9="inflation",D9="expansive"),"inflationary expansion",IF(AND(C9="inflation",D9="contractive"),"stagflation",IF(AND(C9="deflation",D9="expansive"),"deflationary growth",IF(AND(C9="deflation",D9="contractive"),"recession",0)))) -> inflationary expansion | F9: =(B9-B8)/B8 -> 0.026449268 | G9: =J9/B9 -> 7.8002969e+09 | H9: =G9-G8 -> 1.1605133e+08 | I9: =H9/G8 -> 0.015102501 | J9: =INDEX(PQ, MATCH($B$1, PQ!$B$5:$B$271, 0), MATCH(A9, PQ!$A$5:$BQ$5, 0)) -> 8.7813333e+09 | K9: =J9-J8 -> 3.5355556e+08 | L9: =K9/J8 -> 0.04195122 | M9: =L9-I9 -> 0.026848718 | N9: =IF(L9>I9, "inflation",IF(L9<I9, "deflation","stable")) -> inflation | O9: =IFERROR(IF(N9=C9,1,0),"") -> 1 | P9: =M9-F9 -> 0.0003994501 | Q9: =J9-J8 -> 3.5355556e+08 | R9: =Q9/J8 -> 0.04195122 | S9: =INDEX(m, MATCH($B$1, 'M stock'!$B$5:$B$271, 0), MATCH(A9, 'M stock'!$A$5:$BQ$5, 0)) -> 1.7562667e+09 | T9: =(S9-S8)/S8 -> -0.00032887247 | U9: =S9*Y9 -> 8.7813333e+09 | V9: =(U9-U8)/U8 -> 0.04195122 | W9: =S9/B9 -> 1.5600594e+09 | X9: =(W9-W8)/W8 -> -0.026088129 | Y9: =J9/S9 -> 5 | Z9: =(Y9-Y8)/Y8 -> 0.042294001 | AA9: =W9*Y9 -> 7.8002969e+09 | AB9: =AA9-AA8 -> 1.1605133e+08 | AC9: =AB9/AA8 -> 0.015102501 | AD9: =J9-AA9 -> 9.8103646e+08 | AE9: =AA9+AD9 -> 8.7813333e+09 | AF9: =(AE9-AE8)/AE8 -> 0.04195122 | AG9: =AF9-I9 -> 0.026848718 | AH9: =AF9-T10 -> -0.093512896 | AI9: =AF9-X9 -> 0.068039348 | AJ9: =AF9-Z9 -> -0.00034278181 | AK9: =IF(AG9>0, "inflation",IF(AG9<0,"deflation","stable")) -> inflation | AL9: =IFERROR(IF(AK9=C9,1,0),"") -> 1 | AM9: =AD9/AN9 -> 1.9620729e+08 | AN9: =Y9 -> 5
A10: 1967 | B10: =INDEX(p, MATCH($B$1, 'p2'!$B$5:$B$271, 0), MATCH(A10, 'p2'!$A$5:$BQ$5, 0)) -> 1.1531729 | C10: =IF(B10>B9,"inflation",IF(B10<B9,"deflation","stable")) -> inflation | D10: =IF(I10>0,"expansive","contractive") -> expansive | E10: =IF(AND(C10="inflation",D10="expansive"),"inflationary expansion",IF(AND(C10="inflation",D10="contractive"),"stagflation",IF(AND(C10="deflation",D10="expansive"),"deflationary growth",IF(AND(C10="deflation",D10="contractive"),"recession",0)))) -> inflationary expansion | F10: =(B10-B9)/B9 -> 0.024342268 | G10: =J10/B10 -> 8.0213471e+09 | H10: =G10-G9 -> 2.210502e+08 | I10: =H10/G9 -> 0.02833869 | J10: =INDEX(PQ, MATCH($B$1, PQ!$B$5:$B$271, 0), MATCH(A10, PQ!$A$5:$BQ$5, 0)) -> 9250000000 | K10: =J10-J9 -> 4.6866667e+08 | L10: =K10/J9 -> 0.053370787 | M10: =L10-I10 -> 0.025032096 | N10: =IF(L10>I10, "inflation",IF(L10<I10, "deflation","stable")) -> inflation | O10: =IFERROR(IF(N10=C10,1,0),"") -> 1 | P10: =M10-F10 -> 0.000689828 | Q10: =J10-J9 -> 4.6866667e+08 | R10: =Q10/J9 -> 0.053370787 | S10: =INDEX(m, MATCH($B$1, 'M stock'!$B$5:$B$271, 0), MATCH(A10, 'M stock'!$A$5:$BQ$5, 0)) -> 1.9941778e+09 | T10: =(S10-S9)/S9 -> 0.13546412 | U10: =S10*Y10 -> 9250000000 | V10: =(U10-U9)/U9 -> 0.053370787 | W10: =S10/B10 -> 1.7292964e+09 | X10: =(W10-W9)/W9 -> 0.10848117 | Y10: =J10/S10 -> 4.6385032 | Z10: =(Y10-Y9)/Y9 -> -0.07229936 | AA10: =W10*Y10 -> 8.0213471e+09 | AB10: =AA10-AA9 -> 2.210502e+08 | AC10: =AB10/AA9 -> 0.02833869 | AD10: =J10-AA10 -> 1.2286529e+09 | AE10: =AA10+AD10 -> 9250000000 | AF10: =(AE10-AE9)/AE9 -> 0.053370787 | AG10: =AF10-I10 -> 0.025032096 | AH10: =AF10-T11 -> -0.041940007 | AI10: =AF10-X10 -> -0.055110383 | AJ10: =AF10-Z10 -> 0.12567015 | AK10: =IF(AG10>0, "inflation",IF(AG10<0,"deflation","stable")) -> inflation | AL10: =IFERROR(IF(AK10=C10,1,0),"") -> 1 | AM10: =AD10/AN10 -> 2.6488134e+08 | AN10: =Y10 -> 4.6385032
A11: 1968 | B11: =INDEX(p, MATCH($B$1, 'p2'!$B$5:$B$271, 0), MATCH(A11, 'p2'!$A$5:$BQ$5, 0)) -> 1.1654553 | C11: =IF(B11>B10,"inflation",IF(B11<B10,"deflation","stable")) -> inflation | D11: =IF(I11>0,"expansive","contractive") -> expansive | E11: =IF(AND(C11="inflation",D11="expansive"),"inflationary expansion",IF(AND(C11="inflation",D11="contractive"),"stagflation",IF(AND(C11="deflation",D11="expansive"),"deflationary growth",IF(AND(C11="deflation",D11="contractive"),"recession",0)))) -> inflationary expansion | F11: =(B11-B10)/B10 -> 0.01065099 | G11: =J11/B11 -> 8.609892e+09 | H11: =G11-G10 -> 5.885449e+08 | I11: =H11/G10 -> 0.073372327 | J11: =INDEX(PQ, MATCH($B$1, PQ!$B$5:$B$271, 0), MATCH(A11, PQ!$A$5:$BQ$5, 0)) -> 1.0034444e+10 | K11: =J11-J10 -> 7.8444444e+08 | L11: =K11/J10 -> 0.084804805 | M11: =L11-I11 -> 0.011432478 | N11: =IF(L11>I11, "inflation",IF(L11<I11, "deflation","stable")) -> inflation | O11: =IFERROR(IF(N11=C11,1,0),"") -> 1 | P11: =M11-F11 -> 0.00078148794 | Q11: =J11-J10 -> 7.8444444e+08 | R11: =Q11/J10 -> 0.084804805 | S11: =INDEX(m, MATCH($B$1, 'M stock'!$B$5:$B$271, 0), MATCH(A11, 'M stock'!$A$5:$BQ$5, 0)) -> 2.1842444e+09 | T11: =(S11-S10)/S10 -> 0.095310794 | U11: =S11*Y11 -> 1.0034444e+10 | V11: =(U11-U10)/U10 -> 0.084804805 | W11: =S11/B11 -> 1.8741554e+09 | X11: =(W11-W10)/W10 -> 0.083767596 | Y11: =J11/S11 -> 4.5940117 | Z11: =(Y11-Y10)/Y10 -> -0.0095917879 | AA11: =W11*Y11 -> 8.609892e+09 | AB11: =AA11-AA10 -> 5.885449e+08 | AC11: =AB11/AA10 -> 0.073372327 | AD11: =J11-AA11 -> 1.4245525e+09 | AE11: =AA11+AD11 -> 1.0034444e+10 | AF11: =(AE11-AE10)/AE10 -> 0.084804805 | AG11: =AF11-I11 -> 0.011432478 | AH11: =AF11-T12 -> -0.02387249 | AI11: =AF11-X11 -> 0.0010372093 | AJ11: =AF11-Z11 -> 0.094396593 | AK11: =IF(AG11>0, "inflation",IF(AG11<0,"deflation","stable")) -> inflation | AL11: =IFERROR(IF(AK11=C11,1,0),"") -> 1 | AM11: =AD11/AN11 -> 3.10089e+08 | AN11: =Y11 -> 4.5940117
A12: 1969 | B12: =INDEX(p, MATCH($B$1, 'p2'!$B$5:$B$271, 0), MATCH(A12, 'p2'!$A$5:$BQ$5, 0)) -> 1.1861942 | C12: =IF(B12>B11,"inflation",IF(B12<B11,"deflation","stable")) -> inflation | D12: =IF(I12>0,"expansive","contractive") -> expansive | E12: =IF(AND(C12="inflation",D12="expansive"),"inflationary expansion",IF(AND(C12="inflation",D12="contractive"),"stagflation",IF(AND(C12="deflation",D12="expansive"),"deflationary growth",IF(AND(C12="deflation",D12="contractive"),"recession",0)))) -> inflationary expansion | F12: =(B12-B11)/B11 -> 0.017794618 | G12: =J12/B12 -> 8.670681e+09 | H12: =G12-G11 -> 60789005 | I12: =H12/G11 -> 0.007060368 | J12: =INDEX(PQ, MATCH($B$1, PQ!$B$5:$B$271, 0), MATCH(A12, PQ!$A$5:$BQ$5, 0)) -> 1.0285111e+10 | K12: =J12-J11 -> 2.5066667e+08 | L12: =K12/J11 -> 0.024980622 | M12: =L12-I12 -> 0.017920254 | N12: =IF(L12>I12, "inflation",IF(L12<I12, "deflation","stable")) -> inflation | O12: =IFERROR(IF(N12=C12,1,0),"") -> 1 | P12: =M12-F12 -> 0.00012563655 | Q12: =J12-J11 -> 2.5066667e+08 | R12: =Q12/J11 -> 0.024980622 | S12: =INDEX(m, MATCH($B$1, 'M stock'!$B$5:$B$271, 0), MATCH(A12, 'M stock'!$A$5:$BQ$5, 0)) -> 2.4216222e+09 | T12: =(S12-S11)/S11 -> 0.10867729 | U12: =S12*Y12 -> 1.0285111e+10 | V12: =(U12-U11)/U11 -> 0.024980622 | W12: =S12/B12 -> 2.0415058e+09 | X12: =(W12-W11)/W11 -> 0.089293729 | Y12: =J12/S12 -> 4.2471988 | Z12: =(Y12-Y11)/Y11 -> -0.075492366 | AA12: =W12*Y12 -> 8.670681e+09 | AB12: =AA12-AA11 -> 60789005 | AC12: =AB12/AA11 -> 0.007060368 | AD12: =J12-AA12 -> 1.6144301e+09 | AE12: =AA12+AD12 -> 1.0285111e+10 | AF12: =(AE12-AE11)/AE11 -> 0.024980622 | AG12: =AF12-I12 -> 0.017920254 | AH12: =AF12-T13 -> -0.052515638 | AI12: =AF12-X12 -> -0.064313107 | AJ12: =AF12-Z12 -> 0.10047299 | AK12: =IF(AG12>0, "inflation",IF(AG12<0,"deflation","stable")) -> inflation | AL12: =IFERROR(IF(AK12=C12,1,0),"") -> 1 | AM12: =AD12/AN12 -> 3.8011645e+08 | AN12: =Y12 -> 4.2471988
A13: 1970 | B13: =INDEX(p, MATCH($B$1, 'p2'!$B$5:$B$271, 0), MATCH(A13, 'p2'!$A$5:$BQ$5, 0)) -> 1.2378916 | C13: =IF(B13>B12,"inflation",IF(B13<B12,"deflation","stable")) -> inflation | D13: =IF(I13>0,"expansive","contractive") -> expansive | E13: =IF(AND(C13="inflation",D13="expansive"),"inflationary expansion",IF(AND(C13="inflation",D13="contractive"),"stagflation",IF(AND(C13="deflation",D13="expansive"),"deflationary growth",IF(AND(C13="deflation",D13="contractive"),"recession",0)))) -> inflationary expansion | F13: =(B13-B12)/B12 -> 0.043582632 | G13: =J13/B13 -> 9.3393565e+09 | H13: =G13-G12 -> 6.6867549e+08 | I13: =H13/G12 -> 0.077119144 | J13: =INDEX(PQ, MATCH($B$1, PQ!$B$5:$B$271, 0), MATCH(A13, PQ!$A$5:$BQ$5, 0)) -> 1.1561111e+10 | K13: =J13-J12 -> 1276000000 | L13: =K13/J12 -> 0.12406283 | M13: =L13-I13 -> 0.046943687 | N13: =IF(L13>I13, "inflation",IF(L13<I13, "deflation","stable")) -> inflation | O13: =IFERROR(IF(N13=C13,1,0),"") -> 1 | P13: =M13-F13 -> 0.0033610552 | Q13: =J13-J12 -> 1276000000 | R13: =Q13/J12 -> 0.12406283 | S13: =INDEX(m, MATCH($B$1, 'M stock'!$B$5:$B$271, 0), MATCH(A13, 'M stock'!$A$5:$BQ$5, 0)) -> 2.6092889e+09 | T13: =(S13-S12)/S12 -> 0.077496261 | U13: =S13*Y13 -> 1.1561111e+10 | V13: =(U13-U12)/U12 -> 0.12406283 | W13: =S13/B13 -> 2.1078492e+09 | X13: =(W13-W12)/W12 -> 0.03249731 | Y13: =J13/S13 -> 4.4307517 | Z13: =(Y13-Y12)/Y12 -> 0.043217385 | AA13: =W13*Y13 -> 9.3393565e+09 | AB13: =AA13-AA12 -> 6.6867549e+08 | AC13: =AB13/AA12 -> 0.077119144 | AD13: =J13-AA13 -> 2.2217546e+09 | AE13: =AA13+AD13 -> 1.1561111e+10 | AF13: =(AE13-AE12)/AE12 -> 0.12406283 | AG13: =AF13-I13 -> 0.046943687 | AH13: =AF13-T14 -> -0.069749021 | AI13: =AF13-X13 -> 0.09156552 | AJ13: =AF13-Z13 -> 0.080845446 | AK13: =IF(AG13>0, "inflation",IF(AG13<0,"deflation","stable")) -> inflation | AL13: =IFERROR(IF(AK13=C13,1,0),"") -> 1 | AM13: =AD13/AN13 -> 5.0143967e+08 | AN13: =Y13 -> 4.4307517
A14: 1971 | B14: =INDEX(p, MATCH($B$1, 'p2'!$B$5:$B$271, 0), MATCH(A14, 'p2'!$A$5:$BQ$5, 0)) -> 1.339803 | C14: =IF(B14>B13,"inflation",IF(B14<B13,"deflation","stable")) -> inflation | D14: =IF(I14>0,"expansive","contractive") -> expansive | E14: =IF(AND(C14="inflation",D14="expansive"),"inflationary expansion",IF(AND(C14="inflation",D14="contractive"),"stagflation",IF(AND(C14="deflation",D14="expansive"),"deflationary growth",IF(AND(C14="deflation",D14="contractive"),"recession",0)))) -> inflationary expansion | F14: =(B14-B13)/B13 -> 0.082326576 | G14: =J14/B14 -> 9.6929108e+09 | H14: =G14-G13 -> 3.535543e+08 | I14: =H14/G13 -> 0.037856387 | J14: =INDEX(PQ, MATCH($B$1, PQ!$B$5:$B$271, 0), MATCH(A14, PQ!$A$5:$BQ$5, 0)) -> 1.2986591e+10 | K14: =J14-J13 -> 1.4254798e+09 | L14: =K14/J13 -> 0.12329955 | M14: =L14-I14 -> 0.085443163 | N14: =IF(L14>I14, "inflation",IF(L14<I14, "deflation","stable")) -> inflation | O14: =IFERROR(IF(N14=C14,1,0),"") -> 1 | P14: =M14-F14 -> 0.0031165867 | Q14: =J14-J13 -> 1.4254798e+09 | R14: =Q14/J13 -> 0.12329955 | S14: =INDEX(m, MATCH($B$1, 'M stock'!$B$5:$B$271, 0), MATCH(A14, 'M stock'!$A$5:$BQ$5, 0)) -> 3.115e+09 | T14: =(S14-S13)/S13 -> 0.19381185 | U14: =S14*Y14 -> 1.2986591e+10 | V14: =(U14-U13)/U13 -> 0.12329955 | W14: =S14/B14 -> 2.3249687e+09 | X14: =(W14-W13)/W13 -> 0.10300521 | Y14: =J14/S14 -> 4.1690501 | Z14: =(Y14-Y13)/Y13 -> -0.059064836 | AA14: =W14*Y14 -> 9.6929108e+09 | AB14: =AA14-AA13 -> 3.535543e+08 | AC14: =AB14/AA13 -> 0.037856387 | AD14: =J14-AA14 -> 3.2936801e+09 | AE14: =AA14+AD14 -> 1.2986591e+10 | AF14: =(AE14-AE13)/AE13 -> 0.12329955 | AG14: =AF14-I14 -> 0.085443163 | AH14: =AF14-T15 -> -0.073621506 | AI14: =AF14-X14 -> 0.02029434 | AJ14: =AF14-Z14 -> 0.18236439 | AK14: =IF(AG14>0, "inflation",IF(AG14<0,"deflation","stable")) -> inflation | AL14: =IFERROR(IF(AK14=C14,1,0),"") -> 1 | AM14: =AD14/AN14 -> 7.9003133e+08 | AN14: =Y14 -> 4.1690501
A15: 1972 | B15: =INDEX(p, MATCH($B$1, 'p2'!$B$5:$B$271, 0), MATCH(A15, 'p2'!$A$5:$BQ$5, 0)) -> 1.4237923 | C15: =IF(B15>B14,"inflation",IF(B15<B14,"deflation","stable")) -> inflation | D15: =IF(I15>0,"expansive","contractive") -> expansive | E15: =IF(AND(C15="inflation",D15="expansive"),"inflationary expansion",IF(AND(C15="inflation",D15="contractive"),"stagflation",IF(AND(C15="deflation",D15="expansive"),"deflationary growth",IF(AND(C15="deflation",D15="contractive"),"recession",0)))) -> inflationary expansion | F15: =(B15-B14)/B14 -> 0.062687768 | G15: =J15/B15 -> 9.8172519e+09 | H15: =G15-G14 -> 1.2434115e+08 | I15: =H15/G14 -> 0.01282805 | J15: =INDEX(PQ, MATCH($B$1, PQ!$B$5:$B$271, 0), MATCH(A15, PQ!$A$5:$BQ$5, 0)) -> 1.3977727e+10 | K15: =J15-J14 -> 9.9113636e+08 | L15: =K15/J14 -> 0.07631998 | M15: =L15-I15 -> 0.06349193 | N15: =IF(L15>I15, "inflation",IF(L15<I15, "deflation","stable")) -> inflation | O15: =IFERROR(IF(N15=C15,1,0),"") -> 1 | P15: =M15-F15 -> 0.00080416185 | Q15: =J15-J14 -> 9.9113636e+08 | R15: =Q15/J14 -> 0.07631998 | S15: =INDEX(m, MATCH($B$1, 'M stock'!$B$5:$B$271, 0), MATCH(A15, 'M stock'!$A$5:$BQ$5, 0)) -> 3.7284091e+09 | T15: =(S15-S14)/S14 -> 0.19692106 | U15: =S15*Y15 -> 1.3977727e+10 | V15: =(U15-U14)/U14 -> 0.07631998 | W15: =S15/B15 -> 2.6186468e+09 | X15: =(W15-W14)/W14 -> 0.12631489 | Y15: =J15/S15 -> 3.748979 | Z15: =(Y15-Y14)/Y14 -> -0.10075942 | AA15: =W15*Y15 -> 9.8172519e+09 | AB15: =AA15-AA14 -> 1.2434115e+08 | AC15: =AB15/AA14 -> 0.01282805 | AD15: =J15-AA15 -> 4.1604754e+09 | AE15: =AA15+AD15 -> 1.3977727e+10 | AF15: =(AE15-AE14)/AE14 -> 0.07631998 | AG15: =AF15-I15 -> 0.06349193 | AH15: =AF15-T16 -> -0.14828738 | AI15: =AF15-X15 -> -0.049994909 | AJ15: =AF15-Z15 -> 0.1770794 | AK15: =IF(AG15>0, "inflation",IF(AG15<0,"deflation","stable")) -> inflation | AL15: =IFERROR(IF(AK15=C15,1,0),"") -> 1 | AM15: =AD15/AN15 -> 1.1097623e+09 | AN15: =Y15 -> 3.748979
... A67: 2024 | B67: =INDEX(p, MATCH($B$1, 'p2'!$B$5:$B$271, 0), MATCH(A67, 'p2'!$A$5:$BQ$5, 0)) -> 0 | C67: =IF(B67>B66,"inflation",IF(B67<B66,"deflation","stable")) -> stable | D67: =IF(I67>0,"expansive","contractive") -> #DIV/0! | E67: =IF(AND(C67="inflation",D67="expansive"),"inflationary expansion",IF(AND(C67="inflation",D67="contractive"),"stagflation",IF(AND(C67="deflation",D67="expansive"),"deflationary growth",IF(AND(C67="deflation",D67="contractive"),"recession",0)))) -> #DIV/0! | F67: =(B67-B66)/B66 -> #DIV/0! | G67: =J67/B67 -> #DIV/0! | H67: =G67-G66 -> #DIV/0! | I67: =H67/G66 -> #DIV/0! | J67: =INDEX(PQ, MATCH($B$1, PQ!$B$5:$B$271, 0), MATCH(A67, PQ!$A$5:$BQ$5, 0)) -> 0 | K67: =J67-J66 -> 0 | L67: =K67/J66 -> #DIV/0! | M67: =L67-I67 -> #DIV/0! | N67: =IF(L67>I67, "inflation",IF(L67<I67, "deflation","stable")) -> #DIV/0! | O67: =IFERROR(IF(N67=C67,1,0),"") | P67: =M67-F67 -> #DIV/0! | Q67: =J67-J66 -> 0 | R67: =Q67/J66 -> #DIV/0! | S67: =INDEX(m, MATCH($B$1, 'M stock'!$B$5:$B$271, 0), MATCH(A67, 'M stock'!$A$5:$BQ$5, 0)) -> 0 | T67: =(S67-S66)/S66 -> #DIV/0! | U67: =S67*Y67 -> #DIV/0! | V67: =(U67-U66)/U66 -> #DIV/0! | W67: =S67/B67 -> #DIV/0! | X67: =(W67-W66)/W66 -> #DIV/0! | Y67: =J67/S67 -> #DIV/0! | Z67: =(Y67-Y66)/Y66 -> #DIV/0! | AA67: =W67*Y67 -> #DIV/0! | AB67: =AA67-AA66 -> #DIV/0! | AC67: =AB67/AA66 -> #DIV/0! | AD67: =J67-AA67 -> #DIV/0! | AE67: =AA67+AD67 -> #DIV/0! | AF67: =(AE67-AE66)/AE66 -> #DIV/0! | AG67: =AF67-I67 -> #DIV/0! | AH67: =AF67-T68 -> #DIV/0! | AI67: =AF67-X67 -> #DIV/0! | AJ67: =AF67-Z67 -> #DIV/0! | AK67: =IF(AG67>0, "inflation",IF(AG67<0,"deflation","stable")) -> #DIV/0! | AL67: =IFERROR(IF(AK67=C67,1,0),"") | AM67: =AD67/AN67 -> #DIV/0! | AN67: =Y67 -> #DIV/0!
N69: Economic Themal Dynamic Accuracy (Left Side PQ) | O69: =SUM(O4:O57)/COUNT(O4:O57) -> 1 | AK69: Economic Themal Dynamic Accuracy (Right Side MV+FAC) | AL69: =SUM(AL4:AL57)/COUNT(AL4:AL57) -> 1
N71: Matches | O71: =SUM(O3:O67) -> 54 | AK71: Matches | AL71: =SUM(AL3:AL67) -> 53
N72: Count | O72: =COUNT(O3:O67) -> 54 | AK72: Count | AL72: =COUNT(AL3:AL67) -> 53
A74: Source:
A75: World Bank
A76: https://data.worldbank.org/
A78: Broad Money (% of GDP)
A79: API_FM.LBL.BMNY.GD.ZS_DS2_en_csv_v2_123670
A80: Used to analyze monetary aggregates relative to GDP
A82: GDP Deflator (scaled to start meaningful P at 1)_
A83: API_NY.GDP.DEFL.ZS_DS2_en_csv_v2_124034
A84: Used to convert nominal GDP to real terms and track change in P over time
A86: GDP (current US$)
A87: API_NY.GDP.MKTP.CD_DS2_en_csv_v2_130122
A88: Core GDP series for nominal valuation
... A108: affirming the robustness of our own data sources and calculations.

Sheet USA History
A2: Period | B2: P | C2: Observe | D2: Economy | E2: Diagnosis | F2: Δ P % | G2: Q | H2: Δ Q | I2: Δ Q % | J2: PQ | K2: Δ PQ | L2: Δ PQ % | M2: Δ PQ % - Δ Q % | N2: test | O2: match? | P2: (Δ PQ % - Δ Q %) -Δ P % = Δ P x Δ Q (interaction) | Q2: ΔPQ | R2: Δ%PQ | S2: M | T2: ΔM % | U2: MV | V2: ΔMV % | W2: M(d.) | X2: ΔM(d.) % | Y2: V | Z2: Δ V % | AA2: MV(d.) | AB2: ΔMV(d.) | AC2: Δ%MV(d.) | AD2: PQ-MV(d.) (FAC) | AE2: MV(d.) + FAC | AF2: Δ MV(d.)+FAC % | AG2: Δ MV(d.)+FAC % - Δ Q % | AH2: Δ MV(d.)+FAC % - Δ M % | AI2: Δ MV(d.)+FAC % - Δ M % | AJ2: Δ MV(d.)+FAC % - Δ V % | AK2: test | AL2: match? | AM2: M_FAC | AN2: V_FAC
A3: 1781 | G3: =J3/B3 -> #DIV/0! | H3: =G3-G2 -> #DIV/0! | I3: =H3-H2 -> #DIV/0! | K3: =J3-J2 -> #VALUE! | L3: =(K3-K2)/K2 -> #VALUE! | M3: =L3-I3 -> #VALUE! | U3: =S3*Y3 -> #DIV/0! | W3: =S3/B3 -> #DIV/0! | Y3: =J3/S3 -> #DIV/0! | AA3: =W3*Y3 -> #DIV/0! | AD3: =J3-AA3 -> #DIV/0! | AE3: =AA3+AD3 -> #DIV/0! | AG3: =AF3-I3 -> #DIV/0! | AH3: =AF3-T4 -> #DIV/0! | AI3: =AF3-X3 -> 0 | AJ3: =AF3-Z3 -> 0
A4: 1782 | C4: =IF(B4>B3,"inflation",IF(B4<B3,"deflation","stable")) -> stable | D4: =IFERROR(IF(I4>0,"expansive","contractive"),"") | E4: =IF(AND(C4="inflation",D4="expansive"),"inflationary expansion",IF(AND(C4="inflation",D4="contractive"),"stagflation",IF(AND(C4="deflation",D4="expansive"),"deflationary growth",IF(AND(C4="deflation",D4="contractive"),"recession",0)))) -> 0 | F4: =(B4-B3)/B3 -> #DIV/0! | G4: =J4/B4 -> #DIV/0! | H4: =G4-G3 -> #DIV/0! | I4: =H4/G3 -> #DIV/0! | K4: =J4-J3 -> 0 | L4: =K4/J3 -> #DIV/0! | M4: =L4-I4 -> #DIV/0! | N4: =IF(L4>I4, "inflation",IF(L4<I4, "deflation","stable")) -> #DIV/0! | O4: =IFERROR(IF(N4=C4,1,0),"") | P4: =M4-F4 -> #DIV/0! | Q4: =J4-J3 -> 0 | R4: =Q4/J3 -> #DIV/0! | T4: =(S4-S3)/S3 -> #DIV/0! | U4: =S4*Y4 -> #DIV/0! | V4: =(U4-U3)/U3 -> #DIV/0! | W4: =S4/B4 -> #DIV/0! | X4: =(W4-W3)/W3 -> #DIV/0! | Y4: =J4/S4 -> #DIV/0! | Z4: =(Y4-Y3)/Y3 -> #DIV/0! | AA4: =W4*Y4 -> #DIV/0! | AB4: =AA4-AA3 -> #DIV/0! | AC4: =AB4/AA3 -> #DIV/0! | AD4: =J4-AA4 -> #DIV/0! | AE4: =AA4+AD4 -> #DIV/0! | AF4: =(AE4-AE3)/AE3 -> #DIV/0! | AG4: =AF4-I4 -> #DIV/0! | AH4: =AF4-T5 -> #DIV/0! | AI4: =AF4-X4 -> #DIV/0! | AJ4: =AF4-Z4 -> #DIV/0! | AK4: =IF(AG4>0, "inflation",IF(AG4<0,"deflation","stable")) -> #DIV/0! | AL4: =IFERROR(IF(AK4=C4,1,0),"") | AM4: =AD4/AN4 -> #DIV/0! | AN4: =Y4 -> #DIV/0!
A5: 1783 | C5: =IF(B5>B4,"inflation",IF(B5<B4,"deflation","stable")) -> stable | D5: =IF(I5>0,"expansive","contractive") -> #DIV/0! | E5: =IF(AND(C5="inflation",D5="expansive"),"inflationary expansion",IF(AND(C5="inflation",D5="contractive"),"stagflation",IF(AND(C5="deflation",D5="expansive"),"deflationary growth",IF(AND(C5="deflation",D5="contractive"),"recession",0)))) -> #DIV/0! | F5: =(B5-B4)/B4 -> #DIV/0! | G5: =J5/B5 -> #DIV/0! | H5: =G5-G4 -> #DIV/0! | I5: =H5/G4 -> #DIV/0! | K5: =J5-J4 -> 0 | L5: =K5/J4 -> #DIV/0! | M5: =L5-I5 -> #DIV/0! | N5: =IF(L5>I5, "inflation",IF(L5<I5, "deflation","stable")) -> #DIV/0! | O5: =IFERROR(IF(N5=C5,1,0),"") | P5: =M5-F5 -> #DIV/0! | Q5: =J5-J4 -> 0 | R5: =Q5/J4 -> #DIV/0! | T5: =(S5-S4)/S4 -> #DIV/0! | U5: =S5*Y5 -> #DIV/0! | V5: =(U5-U4)/U4 -> #DIV/0! | W5: =S5/B5 -> #DIV/0! | X5: =(W5-W4)/W4 -> #DIV/0! | Y5: =J5/S5 -> #DIV/0! | Z5: =(Y5-Y4)/Y4 -> #DIV/0! | AA5: =W5*Y5 -> #DIV/0! | AB5: =AA5-AA4 -> #DIV/0! | AC5: =AB5/AA4 -> #DIV/0! | AD5: =J5-AA5 -> #DIV/0! | AE5: =AA5+AD5 -> #DIV/0! | AF5: =(AE5-AE4)/AE4 -> #DIV/0! | AG5: =AF5-I5 -> #DIV/0! | AH5: =AF5-T6 -> #DIV/0! | AI5: =AF5-X5 -> #DIV/0! | AJ5: =AF5-Z5 -> #DIV/0! | AK5: =IF(AG5>0, "inflation",IF(AG5<0,"deflation","stable")) -> #DIV/0! | AL5: =IFERROR(IF(AK5=C5,1,0),"") | AM5: =AD5/AN5 -> #DIV/0! | AN5: =Y5 -> #DIV/0!
A6: 1784 | C6: =IF(B6>B5,"inflation",IF(B6<B5,"deflation","stable")) -> stable | D6: =IF(I6>0,"expansive","contractive") -> #DIV/0! | E6: =IF(AND(C6="inflation",D6="expansive"),"inflationary expansion",IF(AND(C6="inflation",D6="contractive"),"stagflation",IF(AND(C6="deflation",D6="expansive"),"deflationary growth",IF(AND(C6="deflation",D6="contractive"),"recession",0)))) -> #DIV/0! | F6: =(B6-B5)/B5 -> #DIV/0! | G6: =J6/B6 -> #DIV/0! | H6: =G6-G5 -> #DIV/0! | I6: =H6/G5 -> #DIV/0! | K6: =J6-J5 -> 0 | L6: =K6/J5 -> #DIV/0! | M6: =L6-I6 -> #DIV/0! | N6: =IF(L6>I6, "inflation",IF(L6<I6, "deflation","stable")) -> #DIV/0! | O6: =IFERROR(IF(N6=C6,1,0),"") | P6: =M6-F6 -> #DIV/0! | Q6: =J6-J5 -> 0 | R6: =Q6/J5 -> #DIV/0! | T6: =(S6-S5)/S5 -> #DIV/0! | U6: =S6*Y6 -> #DIV/0! | V6: =(U6-U5)/U5 -> #DIV/0! | W6: =S6/B6 -> #DIV/0! | X6: =(W6-W5)/W5 -> #DIV/0! | Y6: =J6/S6 -> #DIV/0! | Z6: =(Y6-Y5)/Y5 -> #DIV/0! | AA6: =W6*Y6 -> #DIV/0! | AB6: =AA6-AA5 -> #DIV/0! | AC6: =AB6/AA5 -> #DIV/0! | AD6: =J6-AA6 -> #DIV/0! | AE6: =AA6+AD6 -> #DIV/0! | AF6: =(AE6-AE5)/AE5 -> #DIV/0! | AG6: =AF6-I6 -> #DIV/0! | AH6: =AF6-T7 -> #DIV/0! | AI6: =AF6-X6 -> #DIV/0! | AJ6: =AF6-Z6 -> #DIV/0! | AK6: =IF(AG6>0, "inflation",IF(AG6<0,"deflation","stable")) -> #DIV/0! | AL6: =IFERROR(IF(AK6=C6,1,0),"") | AM6: =AD6/AN6 -> #DIV/0! | AN6: =Y6 -> #DIV/0!
A7: 1785 | C7: =IF(B7>B6,"inflation",IF(B7<B6,"deflation","stable")) -> stable | D7: =IF(I7>0,"expansive","contractive") -> #DIV/0! | E7: =IF(AND(C7="inflation",D7="expansive"),"inflationary expansion",IF(AND(C7="inflation",D7="contractive"),"stagflation",IF(AND(C7="deflation",D7="expansive"),"deflationary growth",IF(AND(C7="deflation",D7="contractive"),"recession",0)))) -> #DIV/0! | F7: =(B7-B6)/B6 -> #DIV/0! | G7: =J7/B7 -> #DIV/0! | H7: =G7-G6 -> #DIV/0! | I7: =H7/G6 -> #DIV/0! | K7: =J7-J6 -> 0 | L7: =K7/J6 -> #DIV/0! | M7: =L7-I7 -> #DIV/0! | N7: =IF(L7>I7, "inflation",IF(L7<I7, "deflation","stable")) -> #DIV/0! | O7: =IFERROR(IF(N7=C7,1,0),"") | P7: =M7-F7 -> #DIV/0! | Q7: =J7-J6 -> 0 | R7: =Q7/J6 -> #DIV/0! | T7: =(S7-S6)/S6 -> #DIV/0! | U7: =S7*Y7 -> #DIV/0! | V7: =(U7-U6)/U6 -> #DIV/0! | W7: =S7/B7 -> #DIV/0! | X7: =(W7-W6)/W6 -> #DIV/0! | Y7: =J7/S7 -> #DIV/0! | Z7: =(Y7-Y6)/Y6 -> #DIV/0! | AA7: =W7*Y7 -> #DIV/0! | AB7: =AA7-AA6 -> #DIV/0! | AC7: =AB7/AA6 -> #DIV/0! | AD7: =J7-AA7 -> #DIV/0! | AE7: =AA7+AD7 -> #DIV/0! | AF7: =(AE7-AE6)/AE6 -> #DIV/0! | AG7: =AF7-I7 -> #DIV/0! | AH7: =AF7-T8 -> #DIV/0! | AI7: =AF7-X7 -> #DIV/0! | AJ7: =AF7-Z7 -> #DIV/0! | AK7: =IF(AG7>0, "inflation",IF(AG7<0,"deflation","stable")) -> #DIV/0! | AL7: =IFERROR(IF(AK7=C7,1,0),"") | AM7: =AD7/AN7 -> #DIV/0! | AN7: =Y7 -> #DIV/0!
A8: 1786 | C8: =IF(B8>B7,"inflation",IF(B8<B7,"deflation","stable")) -> stable | D8: =IF(I8>0,"expansive","contractive") -> #DIV/0! | E8: =IF(AND(C8="inflation",D8="expansive"),"inflationary expansion",IF(AND(C8="inflation",D8="contractive"),"stagflation",IF(AND(C8="deflation",D8="expansive"),"deflationary growth",IF(AND(C8="deflation",D8="contractive"),"recession",0)))) -> #DIV/0! | F8: =(B8-B7)/B7 -> #DIV/0! | G8: =J8/B8 -> #DIV/0! | H8: =G8-G7 -> #DIV/0! | I8: =H8/G7 -> #DIV/0! | K8: =J8-J7 -> 0 | L8: =K8/J7 -> #DIV/0! | M8: =L8-I8 -> #DIV/0! | N8: =IF(L8>I8, "inflation",IF(L8<I8, "deflation","stable")) -> #DIV/0! | O8: =IFERROR(IF(N8=C8,1,0),"") | P8: =M8-F8 -> #DIV/0! | Q8: =J8-J7 -> 0 | R8: =Q8/J7 -> #DIV/0! | T8: =(S8-S7)/S7 -> #DIV/0! | U8: =S8*Y8 -> #DIV/0! | V8: =(U8-U7)/U7 -> #DIV/0! | W8: =S8/B8 -> #DIV/0! | X8: =(W8-W7)/W7 -> #DIV/0! | Y8: =J8/S8 -> #DIV/0! | Z8: =(Y8-Y7)/Y7 -> #DIV/0! | AA8: =W8*Y8 -> #DIV/0! | AB8: =AA8-AA7 -> #DIV/0! | AC8: =AB8/AA7 -> #DIV/0! | AD8: =J8-AA8 -> #DIV/0! | AE8: =AA8+AD8 -> #DIV/0! | AF8: =(AE8-AE7)/AE7 -> #DIV/0! | AG8: =AF8-I8 -> #DIV/0! | AH8: =AF8-T9 -> #DIV/0! | AI8: =AF8-X8 -> #DIV/0! | AJ8: =AF8-Z8 -> #DIV/0! | AK8: =IF(AG8>0, "inflation",IF(AG8<0,"deflation","stable")) -> #DIV/0! | AL8: =IFERROR(IF(AK8=C8,1,0),"") | AM8: =AD8/AN8 -> #DIV/0! | AN8: =Y8 -> #DIV/0!
A9: 1787 | C9: =IF(B9>B8,"inflation",IF(B9<B8,"deflation","stable")) -> stable | D9: =IF(I9>0,"expansive","contractive") -> #DIV/0! | E9: =IF(AND(C9="inflation",D9="expansive"),"inflationary expansion",IF(AND(C9="inflation",D9="contractive"),"stagflation",IF(AND(C9="deflation",D9="expansive"),"deflationary growth",IF(AND(C9="deflation",D9="contractive"),"recession",0)))) -> #DIV/0! | F9: =(B9-B8)/B8 -> #DIV/0! | G9: =J9/B9 -> #DIV/0! | H9: =G9-G8 -> #DIV/0! | I9: =H9/G8 -> #DIV/0! | K9: =J9-J8 -> 0 | L9: =K9/J8 -> #DIV/0! | M9: =L9-I9 -> #DIV/0! | N9: =IF(L9>I9, "inflation",IF(L9<I9, "deflation","stable")) -> #DIV/0! | O9: =IFERROR(IF(N9=C9,1,0),"") | P9: =M9-F9 -> #DIV/0! | Q9: =J9-J8 -> 0 | R9: =Q9/J8 -> #DIV/0! | T9: =(S9-S8)/S8 -> #DIV/0! | U9: =S9*Y9 -> #DIV/0! | V9: =(U9-U8)/U8 -> #DIV/0! | W9: =S9/B9 -> #DIV/0! | X9: =(W9-W8)/W8 -> #DIV/0! | Y9: =J9/S9 -> #DIV/0! | Z9: =(Y9-Y8)/Y8 -> #DIV/0! | AA9: =W9*Y9 -> #DIV/0! | AB9: =AA9-AA8 -> #DIV/0! | AC9: =AB9/AA8 -> #DIV/0! | AD9: =J9-AA9 -> #DIV/0! | AE9: =AA9+AD9 -> #DIV/0! | AF9: =(AE9-AE8)/AE8 -> #DIV/0! | AG9: =AF9-I9 -> #DIV/0! | AH9: =AF9-T10 -> #DIV/0! | AI9: =AF9-X9 -> #DIV/0! | AJ9: =AF9-Z9 -> #DIV/0! | AK9: =IF(AG9>0, "inflation",IF(AG9<0,"deflation","stable")) -> #DIV/0! | AL9: =IFERROR(IF(AK9=C9,1,0),"") | AM9: =AD9/AN9 -> #DIV/0! | AN9: =Y9 -> #DIV/0!
A10: 1788 | C10: =IF(B10>B9,"inflation",IF(B10<B9,"deflation","stable")) -> stable | D10: =IF(I10>0,"expansive","contractive") -> #DIV/0! | E10: =IF(AND(C10="inflation",D10="expansive"),"inflationary expansion",IF(AND(C10="inflation",D10="contractive"),"stagflation",IF(AND(C10="deflation",D10="expansive"),"deflationary growth",IF(AND(C10="deflation",D10="contractive"),"recession",0)))) -> #DIV/0! | F10: =(B10-B9)/B9 -> #DIV/0! | G10: =J10/B10 -> #DIV/0! | H10: =G10-G9 -> #DIV/0! | I10: =H10/G9 -> #DIV/0! | K10: =J10-J9 -> 0 | L10: =K10/J9 -> #DIV/0! | M10: =L10-I10 -> #DIV/0! | N10: =IF(L10>I10, "inflation",IF(L10<I10, "deflation","stable")) -> #DIV/0! | O10: =IFERROR(IF(N10=C10,1,0),"") | P10: =M10-F10 -> #DIV/0! | Q10: =J10-J9 -> 0 | R10: =Q10/J9 -> #DIV/0! | T10: =(S10-S9)/S9 -> #DIV/0! | U10: =S10*Y10 -> #DIV/0! | V10: =(U10-U9)/U9 -> #DIV/0! | W10: =S10/B10 -> #DIV/0! | X10: =(W10-W9)/W9 -> #DIV/0! | Y10: =J10/S10 -> #DIV/0! | Z10: =(Y10-Y9)/Y9 -> #DIV/0! | AA10: =W10*Y10 -> #DIV/0! | AB10: =AA10-AA9 -> #DIV/0! | AC10: =AB10/AA9 -> #DIV/0! | AD10: =J10-AA10 -> #DIV/0! | AE10: =AA10+AD10 -> #DIV/0! | AF10: =(AE10-AE9)/AE9 -> #DIV/0! | AG10: =AF10-I10 -> #DIV/0! | AH10: =AF10-T11 -> #DIV/0! | AI10: =AF10-X10 -> #DIV/0! | AJ10: =AF10-Z10 -> #DIV/0! | AK10: =IF(AG10>0, "inflation",IF(AG10<0,"deflation","stable")) -> #DIV/0! | AL10: =IFERROR(IF(AK10=C10,1,0),"") | AM10: =AD10/AN10 -> #DIV/0! | AN10: =Y10 -> #DIV/0!
A11: 1789 | C11: =IF(B11>B10,"inflation",IF(B11<B10,"deflation","stable")) -> stable | D11: =IF(I11>0,"expansive","contractive") -> #DIV/0! | E11: =IF(AND(C11="inflation",D11="expansive"),"inflationary expansion",IF(AND(C11="inflation",D11="contractive"),"stagflation",IF(AND(C11="deflation",D11="expansive"),"deflationary growth",IF(AND(C11="deflation",D11="contractive"),"recession",0)))) -> #DIV/0! | F11: =(B11-B10)/B10 -> #DIV/0! | G11: =J11/B11 -> #DIV/0! | H11: =G11-G10 -> #DIV/0! | I11: =H11/G10 -> #DIV/0! | K11: =J11-J10 -> 0 | L11: =K11/J10 -> #DIV/0! | M11: =L11-I11 -> #DIV/0! | N11: =IF(L11>I11, "inflation",IF(L11<I11, "deflation","stable")) -> #DIV/0! | O11: =IFERROR(IF(N11=C11,1,0),"") | P11: =M11-F11 -> #DIV/0! | Q11: =J11-J10 -> 0 | R11: =Q11/J10 -> #DIV/0! | T11: =(S11-S10)/S10 -> #DIV/0! | U11: =S11*Y11 -> #DIV/0! | V11: =(U11-U10)/U10 -> #DIV/0! | W11: =S11/B11 -> #DIV/0! | X11: =(W11-W10)/W10 -> #DIV/0! | Y11: =J11/S11 -> #DIV/0! | Z11: =(Y11-Y10)/Y10 -> #DIV/0! | AA11: =W11*Y11 -> #DIV/0! | AB11: =AA11-AA10 -> #DIV/0! | AC11: =AB11/AA10 -> #DIV/0! | AD11: =J11-AA11 -> #DIV/0! | AE11: =AA11+AD11 -> #DIV/0! | AF11: =(AE11-AE10)/AE10 -> #DIV/0! | AG11: =AF11-I11 -> #DIV/0! | AH11: =AF11-T12 -> #DIV/0! | AI11: =AF11-X11 -> #DIV/0! | AJ11: =AF11-Z11 -> #DIV/0! | AK11: =IF(AG11>0, "inflation",IF(AG11<0,"deflation","stable")) -> #DIV/0! | AL11: =IFERROR(IF(AK11=C11,1,0),"") | AM11: =AD11/AN11 -> #DIV/0! | AN11: =Y11 -> #DIV/0!
A12: 1790 | B12: 1 | C12: =IF(B12>B11,"inflation",IF(B12<B11,"deflation","stable")) -> inflation | D12: =IF(I12>0,"expansive","contractive") -> #DIV/0! | E12: =IF(AND(C12="inflation",D12="expansive"),"inflationary expansion",IF(AND(C12="inflation",D12="contractive"),"stagflation",IF(AND(C12="deflation",D12="expansive"),"deflationary growth",IF(AND(C12="deflation",D12="contractive"),"recession",0)))) -> #DIV/0! | F12: =(B12-B11)/B11 -> #DIV/0! | G12: =J12/B12 -> 0.19289785 | H12: =G12-G11 -> #DIV/0! | I12: =H12/G11 -> #DIV/0! | J12: 0.19289785 | K12: =J12-J11 -> 0.19289785 | L12: =K12/J11 -> #DIV/0! | M12: =L12-I12 -> #DIV/0! | N12: =IF(L12>I12, "inflation",IF(L12<I12, "deflation","stable")) -> #DIV/0! | O12: =IFERROR(IF(N12=C12,1,0),"") | P12: =M12-F12 -> #DIV/0! | Q12: =J12-J11 -> 0.19289785 | R12: =Q12/J11 -> #DIV/0! | T12: =(S12-S11)/S11 -> #DIV/0! | U12: =S12*Y12 -> #DIV/0! | V12: =(U12-U11)/U11 -> #DIV/0! | W12: =S12/B12 -> 0 | X12: =(W12-W11)/W11 -> #DIV/0! | Y12: =J12/S12 -> #DIV/0! | Z12: =(Y12-Y11)/Y11 -> #DIV/0! | AA12: =W12*Y12 -> #DIV/0! | AB12: =AA12-AA11 -> #DIV/0! | AC12: =AB12/AA11 -> #DIV/0! | AD12: =J12-AA12 -> #DIV/0! | AE12: =AA12+AD12 -> #DIV/0! | AF12: =(AE12-AE11)/AE11 -> #DIV/0! | AG12: =AF12-I12 -> #DIV/0! | AH12: =AF12-T13 -> #DIV/0! | AI12: =AF12-X12 -> #DIV/0! | AJ12: =AF12-Z12 -> #DIV/0! | AK12: =IF(AG12>0, "inflation",IF(AG12<0,"deflation","stable")) -> #DIV/0! | AL12: =IFERROR(IF(AK12=C12,1,0),"") | AM12: =AD12/AN12 -> #DIV/0! | AN12: =Y12 -> #DIV/0!
A13: 1791 | B13: 1.0272727 | C13: =IF(B13>B12,"inflation",IF(B13<B12,"deflation","stable")) -> inflation | D13: =IF(I13>0,"expansive","contractive") -> expansive | E13: =IF(AND(C13="inflation",D13="expansive"),"inflationary expansion",IF(AND(C13="inflation",D13="contractive"),"stagflation",IF(AND(C13="deflation",D13="expansive"),"deflationary growth",IF(AND(C13="deflation",D13="contractive"),"recession",0)))) -> inflationary expansion | F13: =(B13-B12)/B12 -> 0.027272727 | G13: =J13/B13 -> 0.20448798 | H13: =G13-G12 -> 0.011590128 | I13: =H13/G12 -> 0.060084275 | J13: 0.21006493 | K13: =J13-J12 -> 0.017167073 | L13: =K13/J12 -> 0.088995664 | M13: =L13-I13 -> 0.028911389 | N13: =IF(L13>I13, "inflation",IF(L13<I13, "deflation","stable")) -> inflation | O13: =IFERROR(IF(N13=C13,1,0),"") -> 1 | P13: =M13-F13 -> 0.001638662 | Q13: =J13-J12 -> 0.017167073 | R13: =Q13/J12 -> 0.088995664 | T13: =(S13-S12)/S12 -> #DIV/0! | U13: =S13*Y13 -> #DIV/0! | V13: =(U13-U12)/U12 -> #DIV/0! | W13: =S13/B13 -> 0 | X13: =(W13-W12)/W12 -> #DIV/0! | Y13: =J13/S13 -> #DIV/0! | Z13: =(Y13-Y12)/Y12 -> #DIV/0! | AA13: =W13*Y13 -> #DIV/0! | AB13: =AA13-AA12 -> #DIV/0! | AC13: =AB13/AA12 -> #DIV/0! | AD13: =J13-AA13 -> #DIV/0! | AE13: =AA13+AD13 -> #DIV/0! | AF13: =(AE13-AE12)/AE12 -> #DIV/0! | AG13: =AF13-I13 -> #DIV/0! | AH13: =AF13-T14 -> #DIV/0! | AI13: =AF13-X13 -> #DIV/0! | AJ13: =AF13-Z13 -> #DIV/0! | AK13: =IF(AG13>0, "inflation",IF(AG13<0,"deflation","stable")) -> #DIV/0! | AL13: =IFERROR(IF(AK13=C13,1,0),"") | AM13: =AD13/AN13 -> #DIV/0! | AN13: =Y13 -> #DIV/0!
A14: 1792 | B14: 1.0454545 | C14: =IF(B14>B13,"inflation",IF(B14<B13,"deflation","stable")) -> inflation | D14: =IF(I14>0,"expansive","contractive") -> expansive | E14: =IF(AND(C14="inflation",D14="expansive"),"inflationary expansion",IF(AND(C14="inflation",D14="contractive"),"stagflation",IF(AND(C14="deflation",D14="expansive"),"deflationary growth",IF(AND(C14="deflation",D14="contractive"),"recession",0)))) -> inflationary expansion | F14: =(B14-B13)/B13 -> 0.017699115 | G14: =J14/B14 -> 0.21955966 | H14: =G14-G13 -> 0.015071681 | I14: =H14/G13 -> 0.073704482 | J14: 0.22953965 | K14: =J14-J13 -> 0.01947472 | L14: =K14/J13 -> 0.092708101 | M14: =L14-I14 -> 0.019003619 | N14: =IF(L14>I14, "inflation",IF(L14<I14, "deflation","stable")) -> inflation | O14: =IFERROR(IF(N14=C14,1,0),"") -> 1 | P14: =M14-F14 -> 0.0013045041 | Q14: =J14-J13 -> 0.01947472 | R14: =Q14/J13 -> 0.092708101 | T14: =(S14-S13)/S13 -> #DIV/0! | U14: =S14*Y14 -> #DIV/0! | V14: =(U14-U13)/U13 -> #DIV/0! | W14: =S14/B14 -> 0 | X14: =(W14-W13)/W13 -> #DIV/0! | Y14: =J14/S14 -> #DIV/0! | Z14: =(Y14-Y13)/Y13 -> #DIV/0! | AA14: =W14*Y14 -> #DIV/0! | AB14: =AA14-AA13 -> #DIV/0! | AC14: =AB14/AA13 -> #DIV/0! | AD14: =J14-AA14 -> #DIV/0! | AE14: =AA14+AD14 -> #DIV/0! | AF14: =(AE14-AE13)/AE13 -> #DIV/0! | AG14: =AF14-I14 -> #DIV/0! | AH14: =AF14-T15 -> #DIV/0! | AI14: =AF14-X14 -> #DIV/0! | AJ14: =AF14-Z14 -> #DIV/0! | AK14: =IF(AG14>0, "inflation",IF(AG14<0,"deflation","stable")) -> #DIV/0! | AL14: =IFERROR(IF(AK14=C14,1,0),"") | AM14: =AD14/AN14 -> #DIV/0! | AN14: =Y14 -> #DIV/0!
A15: 1793 | B15: 1.0818182 | C15: =IF(B15>B14,"inflation",IF(B15<B14,"deflation","stable")) -> inflation | D15: =IF(I15>0,"expansive","contractive") -> expansive | E15: =IF(AND(C15="inflation",D15="expansive"),"inflationary expansion",IF(AND(C15="inflation",D15="contractive"),"stagflation",IF(AND(C15="deflation",D15="expansive"),"deflationary growth",IF(AND(C15="deflation",D15="contractive"),"recession",0)))) -> inflationary expansion | F15: =(B15-B14)/B14 -> 0.034782609 | G15: =J15/B15 -> 0.23700405 | H15: =G15-G14 -> 0.017444385 | I15: =H15/G14 -> 0.079451686 | J15: 0.25639529 | K15: =J15-J14 -> 0.026855641 | L15: =K15/J14 -> 0.11699783 | M15: =L15-I15 -> 0.037546146 | N15: =IF(L15>I15, "inflation",IF(L15<I15, "deflation","stable")) -> inflation | O15: =IFERROR(IF(N15=C15,1,0),"") -> 1 | P15: =M15-F15 -> 0.0027635369 | Q15: =J15-J14 -> 0.026855641 | R15: =Q15/J14 -> 0.11699783 | T15: =(S15-S14)/S14 -> #DIV/0! | U15: =S15*Y15 -> #DIV/0! | V15: =(U15-U14)/U14 -> #DIV/0! | W15: =S15/B15 -> 0 | X15: =(W15-W14)/W14 -> #DIV/0! | Y15: =J15/S15 -> #DIV/0! | Z15: =(Y15-Y14)/Y14 -> #DIV/0! | AA15: =W15*Y15 -> #DIV/0! | AB15: =AA15-AA14 -> #DIV/0! | AC15: =AB15/AA14 -> #DIV/0! | AD15: =J15-AA15 -> #DIV/0! | AE15: =AA15+AD15 -> #DIV/0! | AF15: =(AE15-AE14)/AE14 -> #DIV/0! | AG15: =AF15-I15 -> #DIV/0! | AH15: =AF15-T16 -> #DIV/0! | AI15: =AF15-X15 -> #DIV/0! | AJ15: =AF15-Z15 -> #DIV/0! | AK15: =IF(AG15>0, "inflation",IF(AG15<0,"deflation","stable")) -> #DIV/0! | AL15: =IFERROR(IF(AK15=C15,1,0),"") | AM15: =AD15/AN15 -> #DIV/0! | AN15: =Y15 -> #DIV/0!
A16: 1794 | B16: 1.2 | C16: =IF(B16>B15,"inflation",IF(B16<B15,"deflation","stable")) -> inflation | D16: =IF(I16>0,"expansive","contractive") -> expansive | E16: =IF(AND(C16="inflation",D16="expansive"),"inflationary expansion",IF(AND(C16="inflation",D16="contractive"),"stagflation",IF(AND(C16="deflation",D16="expansive"),"deflationary growth",IF(AND(C16="deflation",D16="contractive"),"recession",0)))) -> inflationary expansion | F16: =(B16-B15)/B15 -> 0.1092437 | G16: =J16/B16 -> 0.26773939 | H16: =G16-G15 -> 0.030735341 | I16: =H16/G15 -> 0.12968277 | J16: 0.32128727 | K16: =J16-J15 -> 0.064891979 | L16: =K16/J15 -> 0.25309349 | M16: =L16-I16 -> 0.12341072 | N16: =IF(L16>I16, "inflation",IF(L16<I16, "deflation","stable")) -> inflation | O16: =IFERROR(IF(N16=C16,1,0),"") -> 1 | P16: =M16-F16 -> 0.014167025 | Q16: =J16-J15 -> 0.064891979 | R16: =Q16/J15 -> 0.25309349 | T16: =(S16-S15)/S15 -> #DIV/0! | U16: =S16*Y16 -> #DIV/0! | V16: =(U16-U15)/U15 -> #DIV/0! | W16: =S16/B16 -> 0 | X16: =(W16-W15)/W15 -> #DIV/0! | Y16: =J16/S16 -> #DIV/0! | Z16: =(Y16-Y15)/Y15 -> #DIV/0! | AA16: =W16*Y16 -> #DIV/0! | AB16: =AA16-AA15 -> #DIV/0! | AC16: =AB16/AA15 -> #DIV/0! | AD16: =J16-AA16 -> #DIV/0! | AE16: =AA16+AD16 -> #DIV/0! | AF16: =(AE16-AE15)/AE15 -> #DIV/0! | AG16: =AF16-I16 -> #DIV/0! | AH16: =AF16-T17 -> #DIV/0! | AI16: =AF16-X16 -> #DIV/0! | AJ16: =AF16-Z16 -> #DIV/0! | AK16: =IF(AG16>0, "inflation",IF(AG16<0,"deflation","stable")) -> #DIV/0! | AL16: =IFERROR(IF(AK16=C16,1,0),"") | AM16: =AD16/AN16 -> #DIV/0! | AN16: =Y16 -> #DIV/0!
A17: 1795 | B17: 1.3727273 | C17: =IF(B17>B16,"inflation",IF(B17<B16,"deflation","stable")) -> inflation | D17: =IF(I17>0,"expansive","contractive") -> expansive | E17: =IF(AND(C17="inflation",D17="expansive"),"inflationary expansion",IF(AND(C17="inflation",D17="contractive"),"stagflation",IF(AND(C17="deflation",D17="expansive"),"deflationary growth",IF(AND(C17="deflation",D17="contractive"),"recession",0)))) -> inflationary expansion | F17: =(B17-B16)/B16 -> 0.14393939 | G17: =J17/B17 -> 0.28425703 | H17: =G17-G16 -> 0.016517646 | I17: =H17/G16 -> 0.061692998 | J17: 0.39020738 | K17: =J17-J16 -> 0.068920117 | L17: =K17/J16 -> 0.21451245 | M17: =L17-I17 -> 0.15281945 | N17: =IF(L17>I17, "inflation",IF(L17<I17, "deflation","stable")) -> inflation | O17: =IFERROR(IF(N17=C17,1,0),"") -> 1 | P17: =M17-F17 -> 0.0088800528 | Q17: =J17-J16 -> 0.068920117 | R17: =Q17/J16 -> 0.21451245 | T17: =(S17-S16)/S16 -> #DIV/0! | U17: =S17*Y17 -> #DIV/0! | V17: =(U17-U16)/U16 -> #DIV/0! | W17: =S17/B17 -> 0 | X17: =(W17-W16)/W16 -> #DIV/0! | Y17: =J17/S17 -> #DIV/0! | Z17: =(Y17-Y16)/Y16 -> #DIV/0! | AA17: =W17*Y17 -> #DIV/0! | AB17: =AA17-AA16 -> #DIV/0! | AC17: =AB17/AA16 -> #DIV/0! | AD17: =J17-AA17 -> #DIV/0! | AE17: =AA17+AD17 -> #DIV/0! | AF17: =(AE17-AE16)/AE16 -> #DIV/0! | AG17: =AF17-I17 -> #DIV/0! | AH17: =AF17-T18 -> #DIV/0! | AI17: =AF17-X17 -> #DIV/0! | AJ17: =AF17-Z17 -> #DIV/0! | AK17: =IF(AG17>0, "inflation",IF(AG17<0,"deflation","stable")) -> #DIV/0! | AL17: =IFERROR(IF(AK17=C17,1,0),"") | AM17: =AD17/AN17 -> #DIV/0! | AN17: =Y17 -> #DIV/0!
A18: 1796 | B18: 1.4454545 | C18: =IF(B18>B17,"inflation",IF(B18<B17,"deflation","stable")) -> inflation | D18: =IF(I18>0,"expansive","contractive") -> expansive | E18: =IF(AND(C18="inflation",D18="expansive"),"inflationary expansion",IF(AND(C18="inflation",D18="contractive"),"stagflation",IF(AND(C18="deflation",D18="expansive"),"deflationary growth",IF(AND(C18="deflation",D18="contractive"),"recession",0)))) -> inflationary expansion | F18: =(B18-B17)/B17 -> 0.052980132 | G18: =J18/B18 -> 0.29283567 | H18: =G18-G17 -> 0.0085786341 | I18: =H18/G17 -> 0.030179144 | J18: 0.42328065 | K18: =J18-J17 -> 0.033073265 | L18: =K18/J17 -> 0.084758172 | M18: =L18-I18 -> 0.054579028 | N18: =IF(L18>I18, "inflation",IF(L18<I18, "deflation","stable")) -> inflation | O18: =IFERROR(IF(N18=C18,1,0),"") -> 1 | P18: =M18-F18 -> 0.0015988951 | Q18: =J18-J17 -> 0.033073265 | R18: =Q18/J17 -> 0.084758172 | T18: =(S18-S17)/S17 -> #DIV/0! | U18: =S18*Y18 -> #DIV/0! | V18: =(U18-U17)/U17 -> #DIV/0! | W18: =S18/B18 -> 0 | X18: =(W18-W17)/W17 -> #DIV/0! | Y18: =J18/S18 -> #DIV/0! | Z18: =(Y18-Y17)/Y17 -> #DIV/0! | AA18: =W18*Y18 -> #DIV/0! | AB18: =AA18-AA17 -> #DIV/0! | AC18: =AB18/AA17 -> #DIV/0! | AD18: =J18-AA18 -> #DIV/0! | AE18: =AA18+AD18 -> #DIV/0! | AF18: =(AE18-AE17)/AE17 -> #DIV/0! | AG18: =AF18-I18 -> #DIV/0! | AH18: =AF18-T19 -> #DIV/0! | AI18: =AF18-X18 -> #DIV/0! | AJ18: =AF18-Z18 -> #DIV/0! | AK18: =IF(AG18>0, "inflation",IF(AG18<0,"deflation","stable")) -> #DIV/0! | AL18: =IFERROR(IF(AK18=C18,1,0),"") | AM18: =AD18/AN18 -> #DIV/0! | AN18: =Y18 -> #DIV/0!
A19: 1797 | B19: 1.3909091 | C19: =IF(B19>B18,"inflation",IF(B19<B18,"deflation","stable")) -> deflation | D19: =IF(I19>0,"expansive","contractive") -> expansive | E19: =IF(AND(C19="inflation",D19="expansive"),"inflationary expansion",IF(AND(C19="inflation",D19="contractive"),"stagflation",IF(AND(C19="deflation",D19="expansive"),"deflationary growth",IF(AND(C19="deflation",D19="contractive"),"recession",0)))) -> deflationary growth | F19: =(B19-B18)/B18 -> -0.037735849 | G19: =J19/B19 -> 0.29824088 | H19: =G19-G18 -> 0.0054052131 | I19: =H19/G18 -> 0.018458179 | J19: 0.41482595 | K19: =J19-J18 -> -0.0084546946 | L19: =K19/J18 -> -0.019974205 | M19: =L19-I19 -> -0.038432384 | N19: =IF(L19>I19, "inflation",IF(L19<I19, "deflation","stable")) -> deflation | O19: =IFERROR(IF(N19=C19,1,0),"") -> 1 | P19: =M19-F19 -> -0.00069653504 | Q19: =J19-J18 -> -0.0084546946 | R19: =Q19/J18 -> -0.019974205 | T19: =(S19-S18)/S18 -> #DIV/0! | U19: =S19*Y19 -> #DIV/0! | V19: =(U19-U18)/U18 -> #DIV/0! | W19: =S19/B19 -> 0 | X19: =(W19-W18)/W18 -> #DIV/0! | Y19: =J19/S19 -> #DIV/0! | Z19: =(Y19-Y18)/Y18 -> #DIV/0! | AA19: =W19*Y19 -> #DIV/0! | AB19: =AA19-AA18 -> #DIV/0! | AC19: =AB19/AA18 -> #DIV/0! | AD19: =J19-AA19 -> #DIV/0! | AE19: =AA19+AD19 -> #DIV/0! | AF19: =(AE19-AE18)/AE18 -> #DIV/0! | AG19: =AF19-I19 -> #DIV/0! | AH19: =AF19-T20 -> #DIV/0! | AI19: =AF19-X19 -> #DIV/0! | AJ19: =AF19-Z19 -> #DIV/0! | AK19: =IF(AG19>0, "inflation",IF(AG19<0,"deflation","stable")) -> #DIV/0! | AL19: =IFERROR(IF(AK19=C19,1,0),"") | AM19: =AD19/AN19 -> #DIV/0! | AN19: =Y19 -> #DIV/0!
A20: 1798 | B20: 1.3454545 | C20: =IF(B20>B19,"inflation",IF(B20<B19,"deflation","stable")) -> deflation | D20: =IF(I20>0,"expansive","contractive") -> expansive | E20: =IF(AND(C20="inflation",D20="expansive"),"inflationary expansion",IF(AND(C20="inflation",D20="contractive"),"stagflation",IF(AND(C20="deflation",D20="expansive"),"deflationary growth",IF(AND(C20="deflation",D20="contractive"),"recession",0)))) -> deflationary growth | F20: =(B20-B19)/B19 -> -0.032679739 | G20: =J20/B20 -> 0.31054937 | H20: =G20-G19 -> 0.012308485 | I20: =H20/G19 -> 0.041270282 | J20: 0.41783006 | K20: =J20-J19 -> 0.003004104 | L20: =K20/J19 -> 0.0072418419 | M20: =L20-I20 -> -0.034028441 | N20: =IF(L20>I20, "inflation",IF(L20<I20, "deflation","stable")) -> deflation | O20: =IFERROR(IF(N20=C20,1,0),"") -> 1 | P20: =M20-F20 -> -0.001348702 | Q20: =J20-J19 -> 0.003004104 | R20: =Q20/J19 -> 0.0072418419 | T20: =(S20-S19)/S19 -> #DIV/0! | U20: =S20*Y20 -> #DIV/0! | V20: =(U20-U19)/U19 -> #DIV/0! | W20: =S20/B20 -> 0 | X20: =(W20-W19)/W19 -> #DIV/0! | Y20: =J20/S20 -> #DIV/0! | Z20: =(Y20-Y19)/Y19 -> #DIV/0! | AA20: =W20*Y20 -> #DIV/0! | AB20: =AA20-AA19 -> #DIV/0! | AC20: =AB20/AA19 -> #DIV/0! | AD20: =J20-AA20 -> #DIV/0! | AE20: =AA20+AD20 -> #DIV/0! | AF20: =(AE20-AE19)/AE19 -> #DIV/0! | AG20: =AF20-I20 -> #DIV/0! | AH20: =AF20-T21 -> #DIV/0! | AI20: =AF20-X20 -> #DIV/0! | AJ20: =AF20-Z20 -> #DIV/0! | AK20: =IF(AG20>0, "inflation",IF(AG20<0,"deflation","stable")) -> #DIV/0! | AL20: =IFERROR(IF(AK20=C20,1,0),"") | AM20: =AD20/AN20 -> #DIV/0! | AN20: =Y20 -> #DIV/0!
A21: 1799 | B21: 1.3454545 | C21: =IF(B21>B20,"inflation",IF(B21<B20,"deflation","stable")) -> stable | D21: =IF(I21>0,"expansive","contractive") -> expansive | E21: =IF(AND(C21="inflation",D21="expansive"),"inflationary expansion",IF(AND(C21="inflation",D21="contractive"),"stagflation",IF(AND(C21="deflation",D21="expansive"),"deflationary growth",IF(AND(C21="deflation",D21="contractive"),"recession",0)))) -> 0 | F21: =(B21-B20)/B20 -> 0 | G21: =J21/B21 -> 0.33193739 | H21: =G21-G20 -> 0.021388026 | I21: =H21/G20 -> 0.068871581 | J21: 0.44660667 | K21: =J21-J20 -> 0.028776617 | L21: =K21/J20 -> 0.068871581 | M21: =L21-I21 -> 0 | N21: =IF(L21>I21, "inflation",IF(L21<I21, "deflation","stable")) -> inflation | O21: =IFERROR(IF(N21=C21,1,0),"") -> 0 | P21: =M21-F21 -> 0 | Q21: =J21-J20 -> 0.028776617 | R21: =Q21/J20 -> 0.068871581 | T21: =(S21-S20)/S20 -> #DIV/0! | U21: =S21*Y21 -> #DIV/0! | V21: =(U21-U20)/U20 -> #DIV/0! | W21: =S21/B21 -> 0 | X21: =(W21-W20)/W20 -> #DIV/0! | Y21: =J21/S21 -> #DIV/0! | Z21: =(Y21-Y20)/Y20 -> #DIV/0! | AA21: =W21*Y21 -> #DIV/0! | AB21: =AA21-AA20 -> #DIV/0! | AC21: =AB21/AA20 -> #DIV/0! | AD21: =J21-AA21 -> #DIV/0! | AE21: =AA21+AD21 -> #DIV/0! | AF21: =(AE21-AE20)/AE20 -> #DIV/0! | AG21: =AF21-I21 -> #DIV/0! | AH21: =AF21-T22 -> #DIV/0! | AI21: =AF21-X21 -> #DIV/0! | AJ21: =AF21-Z21 -> #DIV/0! | AK21: =IF(AG21>0, "inflation",IF(AG21<0,"deflation","stable")) -> #DIV/0! | AL21: =IFERROR(IF(AK21=C21,1,0),"") | AM21: =AD21/AN21 -> #DIV/0! | AN21: =Y21 -> #DIV/0!
A22: 1800 | B22: 1.3837977 | C22: =IF(B22>B21,"inflation",IF(B22<B21,"deflation","stable")) -> inflation | D22: =IF(I22>0,"expansive","contractive") -> expansive | E22: =IF(AND(C22="inflation",D22="expansive"),"inflationary expansion",IF(AND(C22="inflation",D22="contractive"),"stagflation",IF(AND(C22="deflation",D22="expansive"),"deflationary growth",IF(AND(C22="deflation",D22="contractive"),"recession",0)))) -> inflationary expansion | F22: =(B22-B21)/B21 -> 0.028498256 | G22: =J22/B22 -> 0.35084877 | H22: =G22-G21 -> 0.018911375 | I22: =H22/G21 -> 0.056972716 | J22: 0.4855037 | K22: =J22-J21 -> 0.038897027 | L22: =K22/J21 -> 0.087094595 | M22: =L22-I22 -> 0.030121879 | N22: =IF(L22>I22, "inflation",IF(L22<I22, "deflation","stable")) -> inflation | O22: =IFERROR(IF(N22=C22,1,0),"") -> 1 | P22: =M22-F22 -> 0.0016236231 | Q22: =J22-J21 -> 0.038897027 | R22: =Q22/J21 -> 0.087094595 | S22: 0.028 | T22: =(S22-S21)/S21 -> #DIV/0! | U22: =S22*Y22 -> 0.4855037 | V22: =(U22-U21)/U21 -> #DIV/0! | W22: =S22/B22 -> 0.020234172 | X22: =(W22-W21)/W21 -> #DIV/0! | Y22: =J22/S22 -> 17.339418 | Z22: =(Y22-Y21)/Y21 -> #DIV/0! | AA22: =W22*Y22 -> 0.35084877 | AB22: =AA22-AA21 -> #DIV/0! | AC22: =AB22/AA21 -> #DIV/0! | AD22: =J22-AA22 -> 0.13465493 | AE22: =AA22+AD22 -> 0.4855037 | AF22: =(AE22-AE21)/AE21 -> #DIV/0! | AG22: =AF22-I22 -> #DIV/0! | AH22: =AF22-T23 -> #DIV/0! | AI22: =AF22-X22 -> #DIV/0! | AJ22: =AF22-Z22 -> #DIV/0! | AK22: =IF(AG22>0, "inflation",IF(AG22<0,"deflation","stable")) -> #DIV/0! | AL22: =IFERROR(IF(AK22=C22,1,0),"") | AM22: =AD22/AN22 -> 0.0077658278 | AN22: =Y22 -> 17.339418
A23: 1801 | B23: 1.4133431 | C23: =IF(B23>B22,"inflation",IF(B23<B22,"deflation","stable")) -> inflation | D23: =IF(I23>0,"expansive","contractive") -> expansive | E23: =IF(AND(C23="inflation",D23="expansive"),"inflationary expansion",IF(AND(C23="inflation",D23="contractive"),"stagflation",IF(AND(C23="deflation",D23="expansive"),"deflationary growth",IF(AND(C23="deflation",D23="contractive"),"recession",0)))) -> inflationary expansion | F23: =(B23-B22)/B22 -> 0.021350993 | G23: =J23/B23 -> 0.36794688 | H23: =G23-G22 -> 0.017098107 | I23: =H23/G22 -> 0.048733554 | J23: 0.52003518 | K23: =J23-J22 -> 0.034531479 | L23: =K23/J22 -> 0.071125057 | M23: =L23-I23 -> 0.022391503 | N23: =IF(L23>I23, "inflation",IF(L23<I23, "deflation","stable")) -> inflation | O23: =IFERROR(IF(N23=C23,1,0),"") -> 1 | P23: =M23-F23 -> 0.0010405098 | Q23: =J23-J22 -> 0.034531479 | R23: =Q23/J22 -> 0.071125057 | S23: 0 | T23: =(S23-S22)/S22 -> -1 | U23: =S23*Y23 -> #DIV/0! | V23: =(U23-U22)/U22 -> #DIV/0! | W23: =S23/B23 -> 0 | X23: =(W23-W22)/W22 -> -1 | Y23: =J23/S23 -> #DIV/0! | Z23: =(Y23-Y22)/Y22 -> #DIV/0! | AA23: =W23*Y23 -> #DIV/0! | AB23: =AA23-AA22 -> #DIV/0! | AC23: =AB23/AA22 -> #DIV/0! | AD23: =J23-AA23 -> #DIV/0! | AE23: =AA23+AD23 -> #DIV/0! | AF23: =(AE23-AE22)/AE22 -> #DIV/0! | AG23: =AF23-I23 -> #DIV/0! | AH23: =AF23-T24 -> #DIV/0! | AI23: =AF23-X23 -> #DIV/0! | AJ23: =AF23-Z23 -> #DIV/0! | AK23: =IF(AG23>0, "inflation",IF(AG23<0,"deflation","stable")) -> #DIV/0! | AL23: =IFERROR(IF(AK23=C23,1,0),"") | AM23: =AD23/AN23 -> #DIV/0! | AN23: =Y23 -> #DIV/0!
A24: 1802 | B24: 1.2010997 | C24: =IF(B24>B23,"inflation",IF(B24<B23,"deflation","stable")) -> deflation | D24: =IF(I24>0,"expansive","contractive") -> expansive | E24: =IF(AND(C24="inflation",D24="expansive"),"inflationary expansion",IF(AND(C24="inflation",D24="contractive"),"stagflation",IF(AND(C24="deflation",D24="expansive"),"deflationary growth",IF(AND(C24="deflation",D24="contractive"),"recession",0)))) -> deflationary growth | F24: =(B24-B23)/B23 -> -0.15017118 | G24: =J24/B24 -> 0.37951843 | H24: =G24-G23 -> 0.011571554 | I24: =H24/G23 -> 0.031448979 | J24: 0.45583947 | K24: =J24-J23 -> -0.064195707 | L24: =K24/J23 -> -0.12344493 | M24: =L24-I24 -> -0.15489391 | N24: =IF(L24>I24, "inflation",IF(L24<I24, "deflation","stable")) -> deflation | O24: =IFERROR(IF(N24=C24,1,0),"") -> 1 | P24: =M24-F24 -> -0.0047227303 | Q24: =J24-J23 -> -0.064195707 | R24: =Q24/J23 -> -0.12344493 | S24: 0 | T24: =(S24-S23)/S23 -> #DIV/0! | U24: =S24*Y24 -> #DIV/0! | V24: =(U24-U23)/U23 -> #DIV/0! | W24: =S24/B24 -> 0 | X24: =(W24-W23)/W23 -> #DIV/0! | Y24: =J24/S24 -> #DIV/0! | Z24: =(Y24-Y23)/Y23 -> #DIV/0! | AA24: =W24*Y24 -> #DIV/0! | AB24: =AA24-AA23 -> #DIV/0! | AC24: =AB24/AA23 -> #DIV/0! | AD24: =J24-AA24 -> #DIV/0! | AE24: =AA24+AD24 -> #DIV/0! | AF24: =(AE24-AE23)/AE23 -> #DIV/0! | AG24: =AF24-I24 -> #DIV/0! | AH24: =AF24-T25 -> #DIV/0! | AI24: =AF24-X24 -> #DIV/0! | AJ24: =AF24-Z24 -> #DIV/0! | AK24: =IF(AG24>0, "inflation",IF(AG24<0,"deflation","stable")) -> #DIV/0! | AL24: =IFERROR(IF(AK24=C24,1,0),"") | AM24: =AD24/AN24 -> #DIV/0! | AN24: =Y24 -> #DIV/0!
A25: 1803 | B25: 1.2762463 | C25: =IF(B25>B24,"inflation",IF(B25<B24,"deflation","stable")) -> inflation | D25: =IF(I25>0,"expansive","contractive") -> expansive | E25: =IF(AND(C25="inflation",D25="expansive"),"inflationary expansion",IF(AND(C25="inflation",D25="contractive"),"stagflation",IF(AND(C25="deflation",D25="expansive"),"deflationary growth",IF(AND(C25="deflation",D25="contractive"),"recession",0)))) -> inflationary expansion | F25: =(B25-B24)/B24 -> 0.062564854 | G25: =J25/B25 -> 0.38595236 | H25: =G25-G24 -> 0.0064339303 | I25: =H25/G24 -> 0.01695288 | J25: 0.49257028 | K25: =J25-J24 -> 0.03673081 | L25: =K25/J24 -> 0.080578388 | M25: =L25-I25 -> 0.063625508 | N25: =IF(L25>I25, "inflation",IF(L25<I25, "deflation","stable")) -> inflation | O25: =IFERROR(IF(N25=C25,1,0),"") -> 1 | P25: =M25-F25 -> 0.0010606544 | Q25: =J25-J24 -> 0.03673081 | R25: =Q25/J24 -> 0.080578388 | S25: 0 | T25: =(S25-S24)/S24 -> #DIV/0! | U25: =S25*Y25 -> #DIV/0! | V25: =(U25-U24)/U24 -> #DIV/0! | W25: =S25/B25 -> 0 | X25: =(W25-W24)/W24 -> #DIV/0! | Y25: =J25/S25 -> #DIV/0! | Z25: =(Y25-Y24)/Y24 -> #DIV/0! | AA25: =W25*Y25 -> #DIV/0! | AB25: =AA25-AA24 -> #DIV/0! | AC25: =AB25/AA24 -> #DIV/0! | AD25: =J25-AA25 -> #DIV/0! | AE25: =AA25+AD25 -> #DIV/0! | AF25: =(AE25-AE24)/AE24 -> #DIV/0! | AG25: =AF25-I25 -> #DIV/0! | AH25: =AF25-T26 -> #DIV/0! | AI25: =AF25-X25 -> #DIV/0! | AJ25: =AF25-Z25 -> #DIV/0! | AK25: =IF(AG25>0, "inflation",IF(AG25<0,"deflation","stable")) -> #DIV/0! | AL25: =IFERROR(IF(AK25=C25,1,0),"") | AM25: =AD25/AN25 -> #DIV/0! | AN25: =Y25 -> #DIV/0!
A26: 1804 | B26: 1.3429619 | C26: =IF(B26>B25,"inflation",IF(B26<B25,"deflation","stable")) -> inflation | D26: =IF(I26>0,"expansive","contractive") -> expansive | E26: =IF(AND(C26="inflation",D26="expansive"),"inflationary expansion",IF(AND(C26="inflation",D26="contractive"),"stagflation",IF(AND(C26="deflation",D26="expansive"),"deflationary growth",IF(AND(C26="deflation",D26="contractive"),"recession",0)))) -> inflationary expansion | F26: =(B26-B25)/B25 -> 0.052274816 | G26: =J26/B26 -> 0.40093907 | H26: =G26-G25 -> 0.014986707 | I26: =H26/G25 -> 0.038830458 | J26: 0.53844588 | K26: =J26-J25 -> 0.045875597 | L26: =K26/J25 -> 0.093135129 | M26: =L26-I26 -> 0.054304671 | N26: =IF(L26>I26, "inflation",IF(L26<I26, "deflation","stable")) -> inflation | O26: =IFERROR(IF(N26=C26,1,0),"") -> 1 | P26: =M26-F26 -> 0.0020298551 | Q26: =J26-J25 -> 0.045875597 | R26: =Q26/J25 -> 0.093135129 | S26: 0 | T26: =(S26-S25)/S25 -> #DIV/0! | U26: =S26*Y26 -> #DIV/0! | V26: =(U26-U25)/U25 -> #DIV/0! | W26: =S26/B26 -> 0 | X26: =(W26-W25)/W25 -> #DIV/0! | Y26: =J26/S26 -> #DIV/0! | Z26: =(Y26-Y25)/Y25 -> #DIV/0! | AA26: =W26*Y26 -> #DIV/0! | AB26: =AA26-AA25 -> #DIV/0! | AC26: =AB26/AA25 -> #DIV/0! | AD26: =J26-AA26 -> #DIV/0! | AE26: =AA26+AD26 -> #DIV/0! | AF26: =(AE26-AE25)/AE25 -> #DIV/0! | AG26: =AF26-I26 -> #DIV/0! | AH26: =AF26-T27 -> #DIV/0! | AI26: =AF26-X26 -> #DIV/0! | AJ26: =AF26-Z26 -> #DIV/0! | AK26: =IF(AG26>0, "inflation",IF(AG26<0,"deflation","stable")) -> #DIV/0! | AL26: =IFERROR(IF(AK26=C26,1,0),"") | AM26: =AD26/AN26 -> #DIV/0! | AN26: =Y26 -> #DIV/0!
A27: 1805 | B27: 1.3438416 | C27: =IF(B27>B26,"inflation",IF(B27<B26,"deflation","stable")) -> inflation | D27: =IF(I27>0,"expansive","contractive") -> expansive | E27: =IF(AND(C27="inflation",D27="expansive"),"inflationary expansion",IF(AND(C27="inflation",D27="contractive"),"stagflation",IF(AND(C27="deflation",D27="expansive"),"deflationary growth",IF(AND(C27="deflation",D27="contractive"),"recession",0)))) -> inflationary expansion | F27: =(B27-B26)/B26 -> 0.00065509335 | G27: =J27/B27 -> 0.42218369 | H27: =G27-G26 -> 0.021244621 | I27: =H27/G26 -> 0.052987156 | J27: 0.56734802 | K27: =J27-J26 -> 0.028902139 | L27: =K27/J26 -> 0.053676961 | M27: =L27-I27 -> 0.00068980488 | N27: =IF(L27>I27, "inflation",IF(L27<I27, "deflation","stable")) -> inflation | O27: =IFERROR(IF(N27=C27,1,0),"") -> 1 | P27: =M27-F27 -> 3.4711534e-05 | Q27: =J27-J26 -> 0.028902139 | R27: =Q27/J26 -> 0.053676961 | S27: 0 | T27: =(S27-S26)/S26 -> #DIV/0! | U27: =S27*Y27 -> #DIV/0! | V27: =(U27-U26)/U26 -> #DIV/0! | W27: =S27/B27 -> 0 | X27: =(W27-W26)/W26 -> #DIV/0! | Y27: =J27/S27 -> #DIV/0! | Z27: =(Y27-Y26)/Y26 -> #DIV/0! | AA27: =W27*Y27 -> #DIV/0! | AB27: =AA27-AA26 -> #DIV/0! | AC27: =AB27/AA26 -> #DIV/0! | AD27: =J27-AA27 -> #DIV/0! | AE27: =AA27+AD27 -> #DIV/0! | AF27: =(AE27-AE26)/AE26 -> #DIV/0! | AG27: =AF27-I27 -> #DIV/0! | AH27: =AF27-T28 -> #DIV/0! | AI27: =AF27-X27 -> #DIV/0! | AJ27: =AF27-Z27 -> #DIV/0! | AK27: =IF(AG27>0, "inflation",IF(AG27<0,"deflation","stable")) -> #DIV/0! | AL27: =IFERROR(IF(AK27=C27,1,0),"") | AM27: =AD27/AN27 -> #DIV/0! | AN27: =Y27 -> #DIV/0!
A28: 1806 | B28: 1.4118035 | C28: =IF(B28>B27,"inflation",IF(B28<B27,"deflation","stable")) -> inflation | D28: =IF(I28>0,"expansive","contractive") -> expansive | E28: =IF(AND(C28="inflation",D28="expansive"),"inflationary expansion",IF(AND(C28="inflation",D28="contractive"),"stagflation",IF(AND(C28="deflation",D28="expansive"),"deflationary growth",IF(AND(C28="deflation",D28="contractive"),"recession",0)))) -> inflationary expansion | F28: =(B28-B27)/B27 -> 0.050572831 | G28: =J28/B28 -> 0.4421442 | H28: =G28-G27 -> 0.019960508 | I28: =H28/G27 -> 0.047279202 | J28: 0.62422073 | K28: =J28-J27 -> 0.056872711 | L28: =K28/J27 -> 0.10024308 | M28: =L28-I28 -> 0.052963875 | N28: =IF(L28>I28, "inflation",IF(L28<I28, "deflation","stable")) -> inflation | O28: =IFERROR(IF(N28=C28,1,0),"") -> 1 | P28: =M28-F28 -> 0.0023910431 | Q28: =J28-J27 -> 0.056872711 | R28: =Q28/J27 -> 0.10024308 | S28: 0 | T28: =(S28-S27)/S27 -> #DIV/0! | U28: =S28*Y28 -> #DIV/0! | V28: =(U28-U27)/U27 -> #DIV/0! | W28: =S28/B28 -> 0 | X28: =(W28-W27)/W27 -> #DIV/0! | Y28: =J28/S28 -> #DIV/0! | Z28: =(Y28-Y27)/Y27 -> #DIV/0! | AA28: =W28*Y28 -> #DIV/0! | AB28: =AA28-AA27 -> #DIV/0! | AC28: =AB28/AA27 -> #DIV/0! | AD28: =J28-AA28 -> #DIV/0! | AE28: =AA28+AD28 -> #DIV/0! | AF28: =(AE28-AE27)/AE27 -> #DIV/0! | AG28: =AF28-I28 -> #DIV/0! | AH28: =AF28-T29 -> #DIV/0! | AI28: =AF28-X28 -> #DIV/0! | AJ28: =AF28-Z28 -> #DIV/0! | AK28: =IF(AG28>0, "inflation",IF(AG28<0,"deflation","stable")) -> #DIV/0! | AL28: =IFERROR(IF(AK28=C28,1,0),"") | AM28: =AD28/AN28 -> #DIV/0! | AN28: =Y28 -> #DIV/0!
A29: 1807 | B29: 1.3451613 | C29: =IF(B29>B28,"inflation",IF(B29<B28,"deflation","stable")) -> deflation | D29: =IF(I29>0,"expansive","contractive") -> expansive | E29: =IF(AND(C29="inflation",D29="expansive"),"inflationary expansion",IF(AND(C29="inflation",D29="contractive"),"stagflation",IF(AND(C29="deflation",D29="expansive"),"deflationary growth",IF(AND(C29="deflation",D29="contractive"),"recession",0)))) -> deflationary growth | F29: =(B29-B28)/B28 -> -0.047203614 | G29: =J29/B29 -> 0.44255534 | H29: =G29-G28 -> 0.00041114192 | I29: =H29/G28 -> 0.00092988199 | J29: 0.59530831 | K29: =J29-J28 -> -0.028912422 | L29: =K29/J28 -> -0.046317626 | M29: =L29-I29 -> -0.047247508 | N29: =IF(L29>I29, "inflation",IF(L29<I29, "deflation","stable")) -> deflation | O29: =IFERROR(IF(N29=C29,1,0),"") -> 1 | P29: =M29-F29 -> -4.3893791e-05 | Q29: =J29-J28 -> -0.028912422 | R29: =Q29/J28 -> -0.046317626 | S29: 0 | T29: =(S29-S28)/S28 -> #DIV/0! | U29: =S29*Y29 -> #DIV/0! | V29: =(U29-U28)/U28 -> #DIV/0! | W29: =S29/B29 -> 0 | X29: =(W29-W28)/W28 -> #DIV/0! | Y29: =J29/S29 -> #DIV/0! | Z29: =(Y29-Y28)/Y28 -> #DIV/0! | AA29: =W29*Y29 -> #DIV/0! | AB29: =AA29-AA28 -> #DIV/0! | AC29: =AB29/AA28 -> #DIV/0! | AD29: =J29-AA29 -> #DIV/0! | AE29: =AA29+AD29 -> #DIV/0! | AF29: =(AE29-AE28)/AE28 -> #DIV/0! | AG29: =AF29-I29 -> #DIV/0! | AH29: =AF29-T30 -> #DIV/0! | AI29: =AF29-X29 -> #DIV/0! | AJ29: =AF29-Z29 -> #DIV/0! | AK29: =IF(AG29>0, "inflation",IF(AG29<0,"deflation","stable")) -> #DIV/0! | AL29: =IFERROR(IF(AK29=C29,1,0),"") | AM29: =AD29/AN29 -> #DIV/0! | AN29: =Y29 -> #DIV/0!
A30: 1808 | B30: 1.4723607 | C30: =IF(B30>B29,"inflation",IF(B30<B29,"deflation","stable")) -> inflation | D30: =IF(I30>0,"expansive","contractive") -> expansive | E30: =IF(AND(C30="inflation",D30="expansive"),"inflationary expansion",IF(AND(C30="inflation",D30="contractive"),"stagflation",IF(AND(C30="deflation",D30="expansive"),"deflationary growth",IF(AND(C30="deflation",D30="contractive"),"recession",0)))) -> inflationary expansion | F30: =(B30-B29)/B29 -> 0.094560715 | G30: =J30/B30 -> 0.44354292 | H30: =G30-G29 -> 0.00098758551 | I30: =H30/G29 -> 0.0022315526 | J30: 0.65305517 | K30: =J30-J29 -> 0.057746861 | L30: =K30/J29 -> 0.097003285 | M30: =L30-I30 -> 0.094771732 | N30: =IF(L30>I30, "inflation",IF(L30<I30, "deflation","stable")) -> inflation | O30: =IFERROR(IF(N30=C30,1,0),"") -> 1 | P30: =M30-F30 -> 0.00021101721 | Q30: =J30-J29 -> 0.057746861 | R30: =Q30/J29 -> 0.097003285 | S30: 0 | T30: =(S30-S29)/S29 -> #DIV/0! | U30: =S30*Y30 -> #DIV/0! | V30: =(U30-U29)/U29 -> #DIV/0! | W30: =S30/B30 -> 0 | X30: =(W30-W29)/W29 -> #DIV/0! | Y30: =J30/S30 -> #DIV/0! | Z30: =(Y30-Y29)/Y29 -> #DIV/0! | AA30: =W30*Y30 -> #DIV/0! | AB30: =AA30-AA29 -> #DIV/0! | AC30: =AB30/AA29 -> #DIV/0! | AD30: =J30-AA30 -> #DIV/0! | AE30: =AA30+AD30 -> #DIV/0! | AF30: =(AE30-AE29)/AE29 -> #DIV/0! | AG30: =AF30-I30 -> #DIV/0! | AH30: =AF30-T31 -> #DIV/0! | AI30: =AF30-X30 -> #DIV/0! | AJ30: =AF30-Z30 -> #DIV/0! | AK30: =IF(AG30>0, "inflation",IF(AG30<0,"deflation","stable")) -> #DIV/0! | AL30: =IFERROR(IF(AK30=C30,1,0),"") | AM30: =AD30/AN30 -> #DIV/0! | AN30: =Y30 -> #DIV/0!
A31: 1809 | B31: 1.4539589 | C31: =IF(B31>B30,"inflation",IF(B31<B30,"deflation","stable")) -> deflation | D31: =IF(I31>0,"expansive","contractive") -> expansive | E31: =IF(AND(C31="inflation",D31="expansive"),"inflationary expansion",IF(AND(C31="inflation",D31="contractive"),"stagflation",IF(AND(C31="deflation",D31="expansive"),"deflationary growth",IF(AND(C31="deflation",D31="contractive"),"recession",0)))) -> deflationary growth | F31: =(B31-B30)/B30 -> -0.012498133 | G31: =J31/B31 -> 0.4774725 | H31: =G31-G30 -> 0.033929578 | I31: =H31/G30 -> 0.076496718 | J31: 0.69422541 | K31: =J31-J30 -> 0.041170243 | L31: =K31/J30 -> 0.063042519 | M31: =L31-I31 -> -0.013454199 | N31: =IF(L31>I31, "inflation",IF(L31<I31, "deflation","stable")) -> deflation | O31: =IFERROR(IF(N31=C31,1,0),"") -> 1 | P31: =M31-F31 -> -0.00095606613 | Q31: =J31-J30 -> 0.041170243 | R31: =Q31/J30 -> 0.063042519 | S31: 0 | T31: =(S31-S30)/S30 -> #DIV/0! | U31: =S31*Y31 -> #DIV/0! | V31: =(U31-U30)/U30 -> #DIV/0! | W31: =S31/B31 -> 0 | X31: =(W31-W30)/W30 -> #DIV/0! | Y31: =J31/S31 -> #DIV/0! | Z31: =(Y31-Y30)/Y30 -> #DIV/0! | AA31: =W31*Y31 -> #DIV/0! | AB31: =AA31-AA30 -> #DIV/0! | AC31: =AB31/AA30 -> #DIV/0! | AD31: =J31-AA31 -> #DIV/0! | AE31: =AA31+AD31 -> #DIV/0! | AF31: =(AE31-AE30)/AE30 -> #DIV/0! | AG31: =AF31-I31 -> #DIV/0! | AH31: =AF31-T32 -> #DIV/0! | AI31: =AF31-X31 -> #DIV/0! | AJ31: =AF31-Z31 -> #DIV/0! | AK31: =IF(AG31>0, "inflation",IF(AG31<0,"deflation","stable")) -> #DIV/0! | AL31: =IFERROR(IF(AK31=C31,1,0),"") | AM31: =AD31/AN31 -> #DIV/0! | AN31: =Y31 -> #DIV/0!
A32: 1810 | B32: 1.4166703 | C32: =IF(B32>B31,"inflation",IF(B32<B31,"deflation","stable")) -> deflation | D32: =IF(I32>0,"expansive","contractive") -> expansive | E32: =IF(AND(C32="inflation",D32="expansive"),"inflationary expansion",IF(AND(C32="inflation",D32="contractive"),"stagflation",IF(AND(C32="deflation",D32="expansive"),"deflationary growth",IF(AND(C32="deflation",D32="contractive"),"recession",0)))) -> deflationary growth | F32: =(B32-B31)/B31 -> -0.025646278 | G32: =J32/B32 -> 0.50392749 | H32: =G32-G31 -> 0.026454989 | I32: =H32/G31 -> 0.055406309 | J32: 0.71389911 | K32: =J32-J31 -> 0.019673699 | L32: =K32/J31 -> 0.028339065 | M32: =L32-I32 -> -0.027067244 | N32: =IF(L32>I32, "inflation",IF(L32<I32, "deflation","stable")) -> deflation | O32: =IFERROR(IF(N32=C32,1,0),"") -> 1 | P32: =M32-F32 -> -0.0014209656 | Q32: =J32-J31 -> 0.019673699 | R32: =Q32/J31 -> 0.028339065 | S32: 0.058 | T32: =(S32-S31)/S31 -> #DIV/0! | U32: =S32*Y32 -> 0.71389911 | V32: =(U32-U31)/U31 -> #DIV/0! | W32: =S32/B32 -> 0.040941071 | X32: =(W32-W31)/W31 -> #DIV/0! | Y32: =J32/S32 -> 12.308605 | Z32: =(Y32-Y31)/Y31 -> #DIV/0! | AA32: =W32*Y32 -> 0.50392749 | AB32: =AA32-AA31 -> #DIV/0! | AC32: =AB32/AA31 -> #DIV/0! | AD32: =J32-AA32 -> 0.20997162 | AE32: =AA32+AD32 -> 0.71389911 | AF32: =(AE32-AE31)/AE31 -> #DIV/0! | AG32: =AF32-I32 -> #DIV/0! | AH32: =AF32-T33 -> #DIV/0! | AI32: =AF32-X32 -> #DIV/0! | AJ32: =AF32-Z32 -> #DIV/0! | AK32: =IF(AG32>0, "inflation",IF(AG32<0,"deflation","stable")) -> #DIV/0! | AL32: =IFERROR(IF(AK32=C32,1,0),"") | AM32: =AD32/AN32 -> 0.017058929 | AN32: =Y32 -> 12.308605
A33: 1811 | B33: 1.4725831 | C33: =IF(B33>B32,"inflation",IF(B33<B32,"deflation","stable")) -> inflation | D33: =IF(I33>0,"expansive","contractive") -> expansive | E33: =IF(AND(C33="inflation",D33="expansive"),"inflationary expansion",IF(AND(C33="inflation",D33="contractive"),"stagflation",IF(AND(C33="deflation",D33="expansive"),"deflationary growth",IF(AND(C33="deflation",D33="contractive"),"recession",0)))) -> inflationary expansion | F33: =(B33-B32)/B32 -> 0.039467777 | G33: =J33/B33 -> 0.52683857 | H33: =G33-G32 -> 0.022911085 | I33: =H33/G32 -> 0.045465044 | J33: 0.7758136 | K33: =J33-J32 -> 0.061914489 | L33: =K33/J32 -> 0.086727225 | M33: =L33-I33 -> 0.041262182 | N33: =IF(L33>I33, "inflation",IF(L33<I33, "deflation","stable")) -> inflation | O33: =IFERROR(IF(N33=C33,1,0),"") -> 1 | P33: =M33-F33 -> 0.0017944042 | Q33: =J33-J32 -> 0.061914489 | R33: =Q33/J32 -> 0.086727225 | S33: 0 | T33: =(S33-S32)/S32 -> -1 | U33: =S33*Y33 -> #DIV/0! | V33: =(U33-U32)/U32 -> #DIV/0! | W33: =S33/B33 -> 0 | X33: =(W33-W32)/W32 -> -1 | Y33: =J33/S33 -> #DIV/0! | Z33: =(Y33-Y32)/Y32 -> #DIV/0! | AA33: =W33*Y33 -> #DIV/0! | AB33: =AA33-AA32 -> #DIV/0! | AC33: =AB33/AA32 -> #DIV/0! | AD33: =J33-AA33 -> #DIV/0! | AE33: =AA33+AD33 -> #DIV/0! | AF33: =(AE33-AE32)/AE32 -> #DIV/0! | AG33: =AF33-I33 -> #DIV/0! | AH33: =AF33-T34 -> #DIV/0! | AI33: =AF33-X33 -> #DIV/0! | AJ33: =AF33-Z33 -> #DIV/0! | AK33: =IF(AG33>0, "inflation",IF(AG33<0,"deflation","stable")) -> #DIV/0! | AL33: =IFERROR(IF(AK33=C33,1,0),"") | AM33: =AD33/AN33 -> #DIV/0! | AN33: =Y33 -> #DIV/0!
... A244: 2022 | B244: 30.432385 | C244: =IF(B244>B243,"inflation",IF(B244<B243,"deflation","stable")) -> inflation | D244: =IF(I244>0,"expansive","contractive") -> expansive | E244: =IF(AND(C244="inflation",D244="expansive"),"inflationary expansion",IF(AND(C244="inflation",D244="contractive"),"stagflation",IF(AND(C244="deflation",D244="expansive"),"deflationary growth",IF(AND(C244="deflation",D244="contractive"),"recession",0)))) -> inflationary expansion | F244: =(B244-B243)/B243 -> 0.070549809 | G244: =J244/B244 -> 845.94447 | H244: =G244-G243 -> 15.954142 | I244: =H244/G243 -> 0.019222082 | J244: 25744.108 | K244: =J244-J243 -> 2150.077 | L244: =K244/J243 -> 0.091128006 | M244: =L244-I244 -> 0.071905924 | N244: =IF(L244>I244, "inflation",IF(L244<I244, "deflation","stable")) -> inflation | O244: =IFERROR(IF(N244=C244,1,0),"") -> 1 | P244: =M244-F244 -> 0.0013561142 | Q244: =J244-J243 -> 2150.077 | R244: =Q244/J243 -> 0.091128006 | S244: 21031.424 | T244: =(S244-S243)/S243 -> 0.12720601 | U244: =S244*Y244 -> 25744.108 | V244: =(U244-U243)/U243 -> 0.091128006 | W244: =S244/B244 -> 691.08693 | X244: =(W244-W243)/W243 -> 0.052922527 | Y244: =J244/S244 -> 1.2240782 | Z244: =(Y244-Y243)/Y243 -> -0.032006576 | AA244: =W244*Y244 -> 845.94447 | AB244: =AA244-AA243 -> 15.954142 | AC244: =AB244/AA243 -> 0.019222082 | AD244: =J244-AA244 -> 24898.164 | AE244: =AA244+AD244 -> 25744.108 | AF244: =(AE244-AE243)/AE243 -> 0.091128006 | AG244: =AF244-I244 -> 0.071905924 | AH244: =AF244-T245 -> 0.091128006 | AI244: =AF244-X244 -> 0.038205479 | AJ244: =AF244-Z244 -> 0.12313458 | AK244: =IF(AG244>0, "inflation",IF(AG244<0,"deflation","stable")) -> inflation | AL244: =IFERROR(IF(AK244=C244,1,0),"") -> 1 | AM244: =AD244/AN244 -> 20340.337 | AN244: =Y244 -> 1.2240782
N246: Matches | O246: =SUM(O3:O244) -> 231 | AK246: Matches | AL246: =SUM(AL3:AL244) -> 192
N247: Count | O247: =COUNT(O3:O244) -> 232 | AK247: Count | AL247: =COUNT(AL3:AL244) -> 192
N248: Economic Themal Dynamic Accuracy (Left Side PQ) | O248: =O246/O247 -> 0.99568966 | AK248: Economic Themal Dynamic Accuracy (Right Side MV+FAC) | AL248: =AL246/AL247 -> 1
A252: Source:
A254: Nominal GDP (PQ) and Price (P):
A255: 1790-2022:
A256: GDP deflator was scaled to 1970
A257: https://www.measuringworth.com/datasets/usgdp/newGDP.xlsx
A258: Construction of Annual GDP, 1790–1928” was composed by the team behind MeasuringWorth,
A259: a research initiative focused economists and historians, including:
A260: Louis Johnston and Samuel H. Williamson, who are credited with the compilation and publication of the GDP series.
A262: The document also references extensive work by scholars such as Gallman, Weiss, Kendrick, McCusker, and others,
A263: indicating collaboration or reliance on historical economic research from institutions like the
A264: National Bureau of Economic Research (NBER) and various universities
A267: Money Supply Calculation:
... A280: Federal Reserve Bank of St. Louis

Sheet Instructions
A1: Instructions:
A3: On Subject Page, change cell c1 to preferred country to analyze. You may need to download excel sheet to do that.
A5: We hid some worksheets (data source). Unhide it by right clicking tabs below, and click unhide
A7: USA Long History was included for your data review from our own reconstruction

Sheet history corr rsquared
A1: Period | B1: P | E1: ΔP | G1: Δ%P | H1: Q | I1: ΔQ | J1: Δ%Q | L1: PQ | M1: ΔPQ | N1: Δ%PQ | S1: M | T1: ΔM | U1: Δ%M | V1: M(deflated) | W1: ΔM (delated) | X1: Δ%M (deflated) | AA1: V | AB1: ΔV | AC1: Δ%V | AD1: MV | AE1: ΔMV | AF1: Δ%MV | AI1: PQ-MV Δ | AJ1: PQ-MV Δ^2 | AK1: PQ-MV Δ^3 | AL1: Δ%MV /Δ%PQ | AM1: Δ%PQ /Δ%Q
A2: 1781 | V2: =S2/B2 -> #DIV/0! | AA2: =L2/S2 -> #DIV/0! | AD2: =V2*AA2 -> #DIV/0! | AI2: =L2-AD2 -> #DIV/0!
A3: 1782 | E3: =B3-B2 -> 0 | G3: =E3/B2 -> #DIV/0! | I3: =H3-H2 -> 0 | J3: =I3/H2 -> #DIV/0! | M3: =L3-L2 -> 0 | N3: =M3/L2 -> #DIV/0! | T3: =S3-S2 -> 0 | U3: =T3/S2 -> #DIV/0! | V3: =S3/B3 -> #DIV/0! | W3: =V3-V2 -> #DIV/0! | X3: =W3/V2 -> #DIV/0! | AA3: =L3/S3 -> #DIV/0! | AB3: =AA3-AA2 -> #DIV/0! | AC3: =AB3/AA2 -> #DIV/0! | AD3: =V3*AA3 -> #DIV/0! | AE3: =AD3-AD2 -> #DIV/0! | AF3: =AE3/AD2 -> #DIV/0! | AI3: =L3-AD3 -> #DIV/0! | AJ3: =AI3-AI2 -> #DIV/0! | AL3: =AF3/N3 -> #DIV/0!
A4: 1783 | E4: =B4-B3 -> 0 | G4: =E4/B3 -> #DIV/0! | I4: =H4-H3 -> 0 | J4: =I4/H3 -> #DIV/0! | M4: =L4-L3 -> 0 | N4: =M4/L3 -> #DIV/0! | T4: =S4-S3 -> 0 | U4: =T4/S3 -> #DIV/0! | V4: =S4/B4 -> #DIV/0! | W4: =V4-V3 -> #DIV/0! | X4: =W4/V3 -> #DIV/0! | AA4: =L4/S4 -> #DIV/0! | AB4: =AA4-AA3 -> #DIV/0! | AC4: =AB4/AA3 -> #DIV/0! | AD4: =V4*AA4 -> #DIV/0! | AE4: =AD4-AD3 -> #DIV/0! | AF4: =AE4/AD3 -> #DIV/0! | AI4: =L4-AD4 -> #DIV/0! | AJ4: =AI4-AI3 -> #DIV/0! | AK4: =AJ4-AJ3 -> #DIV/0! | AL4: =AF4/N4 -> #DIV/0!
A5: 1784 | E5: =B5-B4 -> 0 | G5: =E5/B4 -> #DIV/0! | I5: =H5-H4 -> 0 | J5: =I5/H4 -> #DIV/0! | M5: =L5-L4 -> 0 | N5: =M5/L4 -> #DIV/0! | T5: =S5-S4 -> 0 | U5: =T5/S4 -> #DIV/0! | V5: =S5/B5 -> #DIV/0! | W5: =V5-V4 -> #DIV/0! | X5: =W5/V4 -> #DIV/0! | AA5: =L5/S5 -> #DIV/0! | AB5: =AA5-AA4 -> #DIV/0! | AC5: =AB5/AA4 -> #DIV/0! | AD5: =V5*AA5 -> #DIV/0! | AE5: =AD5-AD4 -> #DIV/0! | AF5: =AE5/AD4 -> #DIV/0! | AI5: =L5-AD5 -> #DIV/0! | AJ5: =AI5-AI4 -> #DIV/0! | AK5: =AJ5-AJ4 -> #DIV/0! | AL5: =AF5/N5 -> #DIV/0!
A6: 1785 | E6: =B6-B5 -> 0 | G6: =E6/B5 -> #DIV/0! | I6: =H6-H5 -> 0 | J6: =I6/H5 -> #DIV/0! | M6: =L6-L5 -> 0 | N6: =M6/L5 -> #DIV/0! | T6: =S6-S5 -> 0 | U6: =T6/S5 -> #DIV/0! | V6: =S6/B6 -> #DIV/0! | W6: =V6-V5 -> #DIV/0! | X6: =W6/V5 -> #DIV/0! | AA6: =L6/S6 -> #DIV/0! | AB6: =AA6-AA5 -> #DIV/0! | AC6: =AB6/AA5 -> #DIV/0! | AD6: =V6*AA6 -> #DIV/0! | AE6: =AD6-AD5 -> #DIV/0! | AF6: =AE6/AD5 -> #DIV/0! | AI6: =L6-AD6 -> #DIV/0! | AJ6: =AI6-AI5 -> #DIV/0! | AK6: =AJ6-AJ5 -> #DIV/0! | AL6: =AF6/N6 -> #DIV/0!
A7: 1786 | E7: =B7-B6 -> 0 | G7: =E7/B6 -> #DIV/0! | I7: =H7-H6 -> 0 | J7: =I7/H6 -> #DIV/0! | M7: =L7-L6 -> 0 | N7: =M7/L6 -> #DIV/0! | T7: =S7-S6 -> 0 | U7: =T7/S6 -> #DIV/0! | V7: =S7/B7 -> #DIV/0! | W7: =V7-V6 -> #DIV/0! | X7: =W7/V6 -> #DIV/0! | AA7: =L7/S7 -> #DIV/0! | AB7: =AA7-AA6 -> #DIV/0! | AC7: =AB7/AA6 -> #DIV/0! | AD7: =V7*AA7 -> #DIV/0! | AE7: =AD7-AD6 -> #DIV/0! | AF7: =AE7/AD6 -> #DIV/0! | AI7: =L7-AD7 -> #DIV/0! | AJ7: =AI7-AI6 -> #DIV/0! | AK7: =AJ7-AJ6 -> #DIV/0! | AL7: =AF7/N7 -> #DIV/0!
A8: 1787 | E8: =B8-B7 -> 0 | G8: =E8/B7 -> #DIV/0! | I8: =H8-H7 -> 0 | J8: =I8/H7 -> #DIV/0! | M8: =L8-L7 -> 0 | N8: =M8/L7 -> #DIV/0! | T8: =S8-S7 -> 0 | U8: =T8/S7 -> #DIV/0! | V8: =S8/B8 -> #DIV/0! | W8: =V8-V7 -> #DIV/0! | X8: =W8/V7 -> #DIV/0! | AA8: =L8/S8 -> #DIV/0! | AB8: =AA8-AA7 -> #DIV/0! | AC8: =AB8/AA7 -> #DIV/0! | AD8: =V8*AA8 -> #DIV/0! | AE8: =AD8-AD7 -> #DIV/0! | AF8: =AE8/AD7 -> #DIV/0! | AI8: =L8-AD8 -> #DIV/0! | AJ8: =AI8-AI7 -> #DIV/0! | AK8: =AJ8-AJ7 -> #DIV/0! | AL8: =AF8/N8 -> #DIV/0!
A9: 1788 | E9: =B9-B8 -> 0 | G9: =E9/B8 -> #DIV/0! | I9: =H9-H8 -> 0 | J9: =I9/H8 -> #DIV/0! | M9: =L9-L8 -> 0 | N9: =M9/L8 -> #DIV/0! | T9: =S9-S8 -> 0 | U9: =T9/S8 -> #DIV/0! | V9: =S9/B9 -> #DIV/0! | W9: =V9-V8 -> #DIV/0! | X9: =W9/V8 -> #DIV/0! | AA9: =L9/S9 -> #DIV/0! | AB9: =AA9-AA8 -> #DIV/0! | AC9: =AB9/AA8 -> #DIV/0! | AD9: =V9*AA9 -> #DIV/0! | AE9: =AD9-AD8 -> #DIV/0! | AF9: =AE9/AD8 -> #DIV/0! | AI9: =L9-AD9 -> #DIV/0! | AJ9: =AI9-AI8 -> #DIV/0! | AK9: =AJ9-AJ8 -> #DIV/0! | AL9: =AF9/N9 -> #DIV/0!
A10: 1789 | E10: =B10-B9 -> 0 | G10: =E10/B9 -> #DIV/0! | I10: =H10-H9 -> 0 | J10: =I10/H9 -> #DIV/0! | M10: =L10-L9 -> 0 | N10: =M10/L9 -> #DIV/0! | T10: =S10-S9 -> 0 | U10: =T10/S9 -> #DIV/0! | V10: =S10/B10 -> #DIV/0! | W10: =V10-V9 -> #DIV/0! | X10: =W10/V9 -> #DIV/0! | AA10: =L10/S10 -> #DIV/0! | AB10: =AA10-AA9 -> #DIV/0! | AC10: =AB10/AA9 -> #DIV/0! | AD10: =V10*AA10 -> #DIV/0! | AE10: =AD10-AD9 -> #DIV/0! | AF10: =AE10/AD9 -> #DIV/0! | AI10: =L10-AD10 -> #DIV/0! | AJ10: =AI10-AI9 -> #DIV/0! | AK10: =AJ10-AJ9 -> #DIV/0! | AL10: =AF10/N10 -> #DIV/0!
A11: 1790 | B11: 1 | E11: =B11-B10 -> 1 | G11: =E11/B10 -> #DIV/0! | H11: =L11/B11 -> 0.19289785 | I11: =H11-H10 -> 0.19289785 | J11: =I11/H10 -> #DIV/0! | L11: 0.19289785 | M11: =L11-L10 -> 0.19289785 | N11: =M11/L10 -> #DIV/0! | T11: =S11-S10 -> 0 | U11: =T11/S10 -> #DIV/0! | V11: =S11/B11 -> 0 | W11: =V11-V10 -> #DIV/0! | X11: =W11/V10 -> #DIV/0! | AA11: =L11/S11 -> #DIV/0! | AB11: =AA11-AA10 -> #DIV/0! | AC11: =AB11/AA10 -> #DIV/0! | AD11: =V11*AA11 -> #DIV/0! | AE11: =AD11-AD10 -> #DIV/0! | AF11: =AE11/AD10 -> #DIV/0! | AI11: =L11-AD11 -> #DIV/0! | AJ11: =AI11-AI10 -> #DIV/0! | AK11: =AJ11-AJ10 -> #DIV/0! | AL11: =AF11/N11 -> #DIV/0!
A12: 1791 | B12: 1.0272727 | C12: =IF(B12>B11,"inflation","deflation") -> inflation | D12: =IF(C12=Q12,1,0) -> 1 | E12: =B12-B11 -> 0.027272727 | F12: =E12/B11 -> 0.027272727 | G12: =E12/B11 -> 0.027272727 | H12: =L12/B12 -> 0.20448798 | I12: =H12-H11 -> 0.011590128 | J12: =I12/H11 -> 0.060084275 | L12: 0.21006493 | M12: =L12-L11 -> 0.017167073 | N12: =M12/L11 -> 0.088995664 | P12: =(N12/J12)-1 -> 0.48118063 | Q12: =IF(N12>J12, "inflation", "deflation") -> inflation | R12: =IF(C12=Q12,1,0) -> 1 | T12: =S12-S11 -> 0 | U12: =T12/S11 -> #DIV/0! | V12: =S12/B12 -> 0 | W12: =V12-V11 -> 0 | X12: =W12/V11 -> #DIV/0! | AA12: =L12/S12 -> #DIV/0! | AB12: =AA12-AA11 -> #DIV/0! | AC12: =AB12/AA11 -> #DIV/0! | AD12: =V12*AA12 -> #DIV/0! | AE12: =AD12-AD11 -> #DIV/0! | AF12: =AE12/AD11 -> #DIV/0! | AI12: =L12-AD12 -> #DIV/0! | AJ12: =AI12-AI11 -> #DIV/0! | AK12: =AJ12-AJ11 -> #DIV/0! | AL12: =AF12/N12 -> #DIV/0! | AM12: =N12/J12 -> 1.4811806 | AN12: =C12 -> inflation
A13: 1792 | B13: 1.0454545 | C13: =IF(B13>B12,"inflation","deflation") -> inflation | D13: =IF(C13=Q13,1,0) -> 1 | E13: =B13-B12 -> 0.018181818 | F13: =E13/B12 -> 0.017699115 | G13: =E13/B12 -> 0.017699115 | H13: =L13/B13 -> 0.21955966 | I13: =H13-H12 -> 0.015071681 | J13: =I13/H12 -> 0.073704482 | L13: 0.22953965 | M13: =L13-L12 -> 0.01947472 | N13: =M13/L12 -> 0.092708101 | P13: =N13/J13 -> 1.2578353 | Q13: =IF(N13>J13, "inflation", "deflation") -> inflation | R13: =IF(C13=Q13,1,0) -> 1 | T13: =S13-S12 -> 0 | U13: =T13/S12 -> #DIV/0! | V13: =S13/B13 -> 0 | W13: =V13-V12 -> 0 | X13: =W13/V12 -> #DIV/0! | AA13: =L13/S13 -> #DIV/0! | AB13: =AA13-AA12 -> #DIV/0! | AC13: =AB13/AA12 -> #DIV/0! | AD13: =V13*AA13 -> #DIV/0! | AE13: =AD13-AD12 -> #DIV/0! | AF13: =AE13/AD12 -> #DIV/0! | AI13: =L13-AD13 -> #DIV/0! | AJ13: =AI13-AI12 -> #DIV/0! | AK13: =AJ13-AJ12 -> #DIV/0! | AL13: =AF13/N13 -> #DIV/0! | AM13: =N13/J13 -> 1.2578353 | AN13: =C13 -> inflation
A14: 1793 | B14: 1.0818182 | C14: =IF(B14>B13,"inflation","deflation") -> inflation | D14: =IF(C14=Q14,1,0) -> 1 | E14: =B14-B13 -> 0.036363636 | F14: =E14/B13 -> 0.034782609 | G14: =E14/B13 -> 0.034782609 | H14: =L14/B14 -> 0.23700405 | I14: =H14-H13 -> 0.017444385 | J14: =I14/H13 -> 0.079451686 | L14: 0.25639529 | M14: =L14-L13 -> 0.026855641 | N14: =M14/L13 -> 0.11699783 | P14: =N14/J14 -> 1.4725657 | Q14: =IF(N14>J14, "inflation", "deflation") -> inflation | R14: =IF(C14=Q14,1,0) -> 1 | T14: =S14-S13 -> 0 | U14: =T14/S13 -> #DIV/0! | V14: =S14/B14 -> 0 | W14: =V14-V13 -> 0 | X14: =W14/V13 -> #DIV/0! | AA14: =L14/S14 -> #DIV/0! | AB14: =AA14-AA13 -> #DIV/0! | AC14: =AB14/AA13 -> #DIV/0! | AD14: =V14*AA14 -> #DIV/0! | AE14: =AD14-AD13 -> #DIV/0! | AF14: =AE14/AD13 -> #DIV/0! | AI14: =L14-AD14 -> #DIV/0! | AJ14: =AI14-AI13 -> #DIV/0! | AK14: =AJ14-AJ13 -> #DIV/0! | AL14: =AF14/N14 -> #DIV/0! | AM14: =N14/J14 -> 1.4725657 | AN14: =C14 -> inflation
A15: 1794 | B15: 1.2 | C15: =IF(B15>B14,"inflation","deflation") -> inflation | D15: =IF(C15=Q15,1,0) -> 1 | E15: =B15-B14 -> 0.11818182 | F15: =E15/B14 -> 0.1092437 | G15: =E15/B14 -> 0.1092437 | H15: =L15/B15 -> 0.26773939 | I15: =H15-H14 -> 0.030735341 | J15: =I15/H14 -> 0.12968277 | L15: 0.32128727 | M15: =L15-L14 -> 0.064891979 | N15: =M15/L14 -> 0.25309349 | P15: =N15/J15 -> 1.9516355 | Q15: =IF(N15>J15, "inflation", "deflation") -> inflation | R15: =IF(C15=Q15,1,0) -> 1 | T15: =S15-S14 -> 0 | U15: =T15/S14 -> #DIV/0! | V15: =S15/B15 -> 0 | W15: =V15-V14 -> 0 | X15: =W15/V14 -> #DIV/0! | AA15: =L15/S15 -> #DIV/0! | AB15: =AA15-AA14 -> #DIV/0! | AC15: =AB15/AA14 -> #DIV/0! | AD15: =V15*AA15 -> #DIV/0! | AE15: =AD15-AD14 -> #DIV/0! | AF15: =AE15/AD14 -> #DIV/0! | AI15: =L15-AD15 -> #DIV/0! | AJ15: =AI15-AI14 -> #DIV/0! | AK15: =AJ15-AJ14 -> #DIV/0! | AL15: =AF15/N15 -> #DIV/0! | AM15: =N15/J15 -> 1.9516355 | AN15: =C15 -> inflation
A16: 1795 | B16: 1.3727273 | C16: =IF(B16>B15,"inflation","deflation") -> inflation | D16: =IF(C16=Q16,1,0) -> 1 | E16: =B16-B15 -> 0.17272727 | F16: =E16/B15 -> 0.14393939 | G16: =E16/B15 -> 0.14393939 | H16: =L16/B16 -> 0.28425703 | I16: =H16-H15 -> 0.016517646 | J16: =I16/H15 -> 0.061692998 | L16: 0.39020738 | M16: =L16-L15 -> 0.068920117 | N16: =M16/L15 -> 0.21451245 | P16: =N16/J16 -> 3.4770955 | Q16: =IF(N16>J16, "inflation", "deflation") -> inflation | R16: =IF(C16=Q16,1,0) -> 1 | T16: =S16-S15 -> 0 | U16: =T16/S15 -> #DIV/0! | V16: =S16/B16 -> 0 | W16: =V16-V15 -> 0 | X16: =W16/V15 -> #DIV/0! | AA16: =L16/S16 -> #DIV/0! | AB16: =AA16-AA15 -> #DIV/0! | AC16: =AB16/AA15 -> #DIV/0! | AD16: =V16*AA16 -> #DIV/0! | AE16: =AD16-AD15 -> #DIV/0! | AF16: =AE16/AD15 -> #DIV/0! | AI16: =L16-AD16 -> #DIV/0! | AJ16: =AI16-AI15 -> #DIV/0! | AK16: =AJ16-AJ15 -> #DIV/0! | AL16: =AF16/N16 -> #DIV/0! | AM16: =N16/J16 -> 3.4770955 | AN16: =C16 -> inflation
A17: 1796 | B17: 1.4454545 | C17: =IF(B17>B16,"inflation","deflation") -> inflation | D17: =IF(C17=Q17,1,0) -> 1 | E17: =B17-B16 -> 0.072727273 | F17: =E17/B16 -> 0.052980132 | G17: =E17/B16 -> 0.052980132 | H17: =L17/B17 -> 0.29283567 | I17: =H17-H16 -> 0.0085786341 | J17: =I17/H16 -> 0.030179144 | L17: 0.42328065 | M17: =L17-L16 -> 0.033073265 | N17: =M17/L16 -> 0.084758172 | P17: =N17/J17 -> 2.8085015 | Q17: =IF(N17>J17, "inflation", "deflation") -> inflation | R17: =IF(C17=Q17,1,0) -> 1 | T17: =S17-S16 -> 0 | U17: =T17/S16 -> #DIV/0! | V17: =S17/B17 -> 0 | W17: =V17-V16 -> 0 | X17: =W17/V16 -> #DIV/0! | AA17: =L17/S17 -> #DIV/0! | AB17: =AA17-AA16 -> #DIV/0! | AC17: =AB17/AA16 -> #DIV/0! | AD17: =V17*AA17 -> #DIV/0! | AE17: =AD17-AD16 -> #DIV/0! | AF17: =AE17/AD16 -> #DIV/0! | AI17: =L17-AD17 -> #DIV/0! | AJ17: =AI17-AI16 -> #DIV/0! | AK17: =AJ17-AJ16 -> #DIV/0! | AL17: =AF17/N17 -> #DIV/0! | AM17: =N17/J17 -> 2.8085015 | AN17: =C17 -> inflation
A18: 1797 | B18: 1.3909091 | C18: =IF(B18>B17,"inflation","deflation") -> deflation | D18: =IF(C18=Q18,1,0) -> 1 | E18: =B18-B17 -> -0.054545455 | F18: =E18/B17 -> -0.037735849 | G18: =E18/B17 -> -0.037735849 | H18: =L18/B18 -> 0.29824088 | I18: =H18-H17 -> 0.0054052131 | J18: =I18/H17 -> 0.018458179 | L18: 0.41482595 | M18: =L18-L17 -> -0.0084546946 | N18: =M18/L17 -> -0.019974205 | P18: =N18/J18 -> -1.0821331 | Q18: =IF(N18>J18, "inflation", "deflation") -> deflation | R18: =IF(C18=Q18,1,0) -> 1 | T18: =S18-S17 -> 0 | U18: =T18/S17 -> #DIV/0! | V18: =S18/B18 -> 0 | W18: =V18-V17 -> 0 | X18: =W18/V17 -> #DIV/0! | AA18: =L18/S18 -> #DIV/0! | AB18: =AA18-AA17 -> #DIV/0! | AC18: =AB18/AA17 -> #DIV/0! | AD18: =V18*AA18 -> #DIV/0! | AE18: =AD18-AD17 -> #DIV/0! | AF18: =AE18/AD17 -> #DIV/0! | AI18: =L18-AD18 -> #DIV/0! | AJ18: =AI18-AI17 -> #DIV/0! | AK18: =AJ18-AJ17 -> #DIV/0! | AL18: =AF18/N18 -> #DIV/0! | AM18: =N18/J18 -> -1.0821331 | AN18: =C18 -> deflation
A19: 1798 | B19: 1.3454545 | C19: =IF(B19>B18,"inflation","deflation") -> deflation | D19: =IF(C19=Q19,1,0) -> 1 | E19: =B19-B18 -> -0.045454545 | F19: =E19/B18 -> -0.032679739 | G19: =E19/B18 -> -0.032679739 | H19: =L19/B19 -> 0.31054937 | I19: =H19-H18 -> 0.012308485 | J19: =I19/H18 -> 0.041270282 | L19: 0.41783006 | M19: =L19-L18 -> 0.003004104 | N19: =M19/L18 -> 0.0072418419 | P19: =N19/J19 -> 0.17547352 | Q19: =IF(N19>J19, "inflation", "deflation") -> deflation | R19: =IF(C19=Q19,1,0) -> 1 | T19: =S19-S18 -> 0 | U19: =T19/S18 -> #DIV/0! | V19: =S19/B19 -> 0 | W19: =V19-V18 -> 0 | X19: =W19/V18 -> #DIV/0! | AA19: =L19/S19 -> #DIV/0! | AB19: =AA19-AA18 -> #DIV/0! | AC19: =AB19/AA18 -> #DIV/0! | AD19: =V19*AA19 -> #DIV/0! | AE19: =AD19-AD18 -> #DIV/0! | AF19: =AE19/AD18 -> #DIV/0! | AI19: =L19-AD19 -> #DIV/0! | AJ19: =AI19-AI18 -> #DIV/0! | AK19: =AJ19-AJ18 -> #DIV/0! | AL19: =AF19/N19 -> #DIV/0! | AM19: =N19/J19 -> 0.17547352 | AN19: =C19 -> deflation
A20: 1799 | B20: 1.3454545 | C20: =IF(B20>B19,"inflation","deflation") -> deflation | D20: =IF(C20=Q20,1,0) -> 0 | E20: =B20-B19 -> 0 | F20: =E20/B19 -> 0 | G20: =E20/B19 -> 0 | H20: =L20/B20 -> 0.33193739 | I20: =H20-H19 -> 0.021388026 | J20: =I20/H19 -> 0.068871581 | L20: 0.44660667 | M20: =L20-L19 -> 0.028776617 | N20: =M20/L19 -> 0.068871581 | P20: =N20/J20 -> 1 | Q20: =IF(N20>J20, "inflation", "deflation") -> inflation | R20: =IF(C20=Q20,1,0) -> 0 | T20: =S20-S19 -> 0 | U20: =T20/S19 -> #DIV/0! | V20: =S20/B20 -> 0 | W20: =V20-V19 -> 0 | X20: =W20/V19 -> #DIV/0! | AA20: =L20/S20 -> #DIV/0! | AB20: =AA20-AA19 -> #DIV/0! | AC20: =AB20/AA19 -> #DIV/0! | AD20: =V20*AA20 -> #DIV/0! | AE20: =AD20-AD19 -> #DIV/0! | AF20: =AE20/AD19 -> #DIV/0! | AI20: =L20-AD20 -> #DIV/0! | AJ20: =AI20-AI19 -> #DIV/0! | AK20: =AJ20-AJ19 -> #DIV/0! | AL20: =AF20/N20 -> #DIV/0! | AM20: =N20/J20 -> 1 | AN20: =C20 -> deflation
A21: 1800 | B21: 1.3837977 | C21: =IF(B21>B20,"inflation","deflation") -> inflation | D21: =IF(C21=Q21,1,0) -> 1 | E21: =B21-B20 -> 0.038343109 | F21: =E21/B20 -> 0.028498256 | G21: =E21/B20 -> 0.028498256 | H21: =L21/B21 -> 0.35084877 | I21: =H21-H20 -> 0.018911375 | J21: =I21/H20 -> 0.056972716 | L21: 0.4855037 | M21: =L21-L20 -> 0.038897027 | N21: =M21/L20 -> 0.087094595 | P21: =N21/J21 -> 1.5287071 | Q21: =IF(N21>J21, "inflation", "deflation") -> inflation | R21: =IF(C21=Q21,1,0) -> 1 | S21: 0.028 | T21: =S21-S20 -> 0.028 | U21: =T21/S20 -> #DIV/0! | V21: =S21/B21 -> 0.020234172 | W21: =V21-V20 -> 0.020234172 | X21: =W21/V20 -> #DIV/0! | AA21: =L21/S21 -> 17.339418 | AB21: =AA21-AA20 -> #DIV/0! | AC21: =AB21/AA20 -> #DIV/0! | AD21: =V21*AA21 -> 0.35084877 | AE21: =AD21-AD20 -> #DIV/0! | AF21: =AE21/AD20 -> #DIV/0! | AI21: =L21-AD21 -> 0.13465493 | AJ21: =AI21-AI20 -> #DIV/0! | AK21: =AJ21-AJ20 -> #DIV/0! | AL21: =AF21/N21 -> #DIV/0! | AM21: =N21/J21 -> 1.5287071 | AN21: =C21 -> inflation
A22: 1801 | B22: 1.4133431 | C22: =IF(B22>B21,"inflation","deflation") -> inflation | D22: =IF(C22=Q22,1,0) -> 1 | E22: =B22-B21 -> 0.029545455 | F22: =E22/B21 -> 0.021350993 | G22: =E22/B21 -> 0.021350993 | H22: =L22/B22 -> 0.36794688 | I22: =H22-H21 -> 0.017098107 | J22: =I22/H21 -> 0.048733554 | L22: 0.52003518 | M22: =L22-L21 -> 0.034531479 | N22: =M22/L21 -> 0.071125057 | P22: =N22/J22 -> 1.4594679 | Q22: =IF(N22>J22, "inflation", "deflation") -> inflation | R22: =IF(C22=Q22,1,0) -> 1 | S22: 0 | T22: =S22-S21 -> -0.028 | U22: =T22/S21 -> -1 | V22: =S22/B22 -> 0 | W22: =V22-V21 -> -0.020234172 | X22: =W22/V21 -> -1 | AA22: =L22/S22 -> #DIV/0! | AB22: =AA22-AA21 -> #DIV/0! | AC22: =AB22/AA21 -> #DIV/0! | AD22: =V22*AA22 -> #DIV/0! | AE22: =AD22-AD21 -> #DIV/0! | AF22: =AE22/AD21 -> #DIV/0! | AI22: =L22-AD22 -> #DIV/0! | AJ22: =AI22-AI21 -> #DIV/0! | AK22: =AJ22-AJ21 -> #DIV/0! | AL22: =AF22/N22 -> #DIV/0! | AM22: =N22/J22 -> 1.4594679 | AN22: =C22 -> inflation
A23: 1802 | B23: 1.2010997 | C23: =IF(B23>B22,"inflation","deflation") -> deflation | D23: =IF(C23=Q23,1,0) -> 1 | E23: =B23-B22 -> -0.2122434 | F23: =E23/B22 -> -0.15017118 | G23: =E23/B22 -> -0.15017118 | H23: =L23/B23 -> 0.37951843 | I23: =H23-H22 -> 0.011571554 | J23: =I23/H22 -> 0.031448979 | L23: 0.45583947 | M23: =L23-L22 -> -0.064195707 | N23: =M23/L22 -> -0.12344493 | P23: =N23/J23 -> -3.9252444 | Q23: =IF(N23>J23, "inflation", "deflation") -> deflation | R23: =IF(C23=Q23,1,0) -> 1 | S23: 0 | T23: =S23-S22 -> 0 | U23: =T23/S22 -> #DIV/0! | V23: =S23/B23 -> 0 | W23: =V23-V22 -> 0 | X23: =W23/V22 -> #DIV/0! | AA23: =L23/S23 -> #DIV/0! | AB23: =AA23-AA22 -> #DIV/0! | AC23: =AB23/AA22 -> #DIV/0! | AD23: =V23*AA23 -> #DIV/0! | AE23: =AD23-AD22 -> #DIV/0! | AF23: =AE23/AD22 -> #DIV/0! | AI23: =L23-AD23 -> #DIV/0! | AJ23: =AI23-AI22 -> #DIV/0! | AK23: =AJ23-AJ22 -> #DIV/0! | AL23: =AF23/N23 -> #DIV/0! | AM23: =N23/J23 -> -3.9252444 | AN23: =C23 -> deflation
A24: 1803 | B24: 1.2762463 | C24: =IF(B24>B23,"inflation","deflation") -> inflation | D24: =IF(C24=Q24,1,0) -> 1 | E24: =B24-B23 -> 0.075146628 | F24: =E24/B23 -> 0.062564854 | G24: =E24/B23 -> 0.062564854 | H24: =L24/B24 -> 0.38595236 | I24: =H24-H23 -> 0.0064339303 | J24: =I24/H23 -> 0.01695288 | L24: 0.49257028 | M24: =L24-L23 -> 0.03673081 | N24: =M24/L23 -> 0.080578388 | P24: =N24/J24 -> 4.7530797 | Q24: =IF(N24>J24, "inflation", "deflation") -> inflation | R24: =IF(C24=Q24,1,0) -> 1 | S24: 0 | T24: =S24-S23 -> 0 | U24: =T24/S23 -> #DIV/0! | V24: =S24/B24 -> 0 | W24: =V24-V23 -> 0 | X24: =W24/V23 -> #DIV/0! | AA24: =L24/S24 -> #DIV/0! | AB24: =AA24-AA23 -> #DIV/0! | AC24: =AB24/AA23 -> #DIV/0! | AD24: =V24*AA24 -> #DIV/0! | AE24: =AD24-AD23 -> #DIV/0! | AF24: =AE24/AD23 -> #DIV/0! | AI24: =L24-AD24 -> #DIV/0! | AJ24: =AI24-AI23 -> #DIV/0! | AK24: =AJ24-AJ23 -> #DIV/0! | AL24: =AF24/N24 -> #DIV/0! | AM24: =N24/J24 -> 4.7530797 | AN24: =C24 -> inflation
A25: 1804 | B25: 1.3429619 | C25: =IF(B25>B24,"inflation","deflation") -> inflation | D25: =IF(C25=Q25,1,0) -> 1 | E25: =B25-B24 -> 0.066715543 | F25: =E25/B24 -> 0.052274816 | G25: =E25/B24 -> 0.052274816 | H25: =L25/B25 -> 0.40093907 | I25: =H25-H24 -> 0.014986707 | J25: =I25/H24 -> 0.038830458 | L25: 0.53844588 | M25: =L25-L24 -> 0.045875597 | N25: =M25/L24 -> 0.093135129 | P25: =N25/J25 -> 2.3985071 | Q25: =IF(N25>J25, "inflation", "deflation") -> inflation | R25: =IF(C25=Q25,1,0) -> 1 | S25: 0 | T25: =S25-S24 -> 0 | U25: =T25/S24 -> #DIV/0! | V25: =S25/B25 -> 0 | W25: =V25-V24 -> 0 | X25: =W25/V24 -> #DIV/0! | AA25: =L25/S25 -> #DIV/0! | AB25: =AA25-AA24 -> #DIV/0! | AC25: =AB25/AA24 -> #DIV/0! | AD25: =V25*AA25 -> #DIV/0! | AE25: =AD25-AD24 -> #DIV/0! | AF25: =AE25/AD24 -> #DIV/0! | AI25: =L25-AD25 -> #DIV/0! | AJ25: =AI25-AI24 -> #DIV/0! | AK25: =AJ25-AJ24 -> #DIV/0! | AL25: =AF25/N25 -> #DIV/0! | AM25: =N25/J25 -> 2.3985071 | AN25: =C25 -> inflation
A26: 1805 | B26: 1.3438416 | C26: =IF(B26>B25,"inflation","deflation") -> inflation | D26: =IF(C26=Q26,1,0) -> 1 | E26: =B26-B25 -> 0.0008797654 | F26: =E26/B25 -> 0.00065509335 | G26: =E26/B25 -> 0.00065509335 | H26: =L26/B26 -> 0.42218369 | I26: =H26-H25 -> 0.021244621 | J26: =I26/H25 -> 0.052987156 | L26: 0.56734802 | M26: =L26-L25 -> 0.028902139 | N26: =M26/L25 -> 0.053676961 | P26: =N26/J26 -> 1.0130183 | Q26: =IF(N26>J26, "inflation", "deflation") -> inflation | R26: =IF(C26=Q26,1,0) -> 1 | S26: 0 | T26: =S26-S25 -> 0 | U26: =T26/S25 -> #DIV/0! | V26: =S26/B26 -> 0 | W26: =V26-V25 -> 0 | X26: =W26/V25 -> #DIV/0! | AA26: =L26/S26 -> #DIV/0! | AB26: =AA26-AA25 -> #DIV/0! | AC26: =AB26/AA25 -> #DIV/0! | AD26: =V26*AA26 -> #DIV/0! | AE26: =AD26-AD25 -> #DIV/0! | AF26: =AE26/AD25 -> #DIV/0! | AI26: =L26-AD26 -> #DIV/0! | AJ26: =AI26-AI25 -> #DIV/0! | AK26: =AJ26-AJ25 -> #DIV/0! | AL26: =AF26/N26 -> #DIV/0! | AM26: =N26/J26 -> 1.0130183 | AN26: =C26 -> inflation
A27: 1806 | B27: 1.4118035 | C27: =IF(B27>B26,"inflation","deflation") -> inflation | D27: =IF(C27=Q27,1,0) -> 1 | E27: =B27-B26 -> 0.067961877 | F27: =E27/B26 -> 0.050572831 | G27: =E27/B26 -> 0.050572831 | H27: =L27/B27 -> 0.4421442 | I27: =H27-H26 -> 0.019960508 | J27: =I27/H26 -> 0.047279202 | L27: 0.62422073 | M27: =L27-L26 -> 0.056872711 | N27: =M27/L26 -> 0.10024308 | P27: =N27/J27 -> 2.1202362 | Q27: =IF(N27>J27, "inflation", "deflation") -> inflation | R27: =IF(C27=Q27,1,0) -> 1 | S27: 0 | T27: =S27-S26 -> 0 | U27: =T27/S26 -> #DIV/0! | V27: =S27/B27 -> 0 | W27: =V27-V26 -> 0 | X27: =W27/V26 -> #DIV/0! | AA27: =L27/S27 -> #DIV/0! | AB27: =AA27-AA26 -> #DIV/0! | AC27: =AB27/AA26 -> #DIV/0! | AD27: =V27*AA27 -> #DIV/0! | AE27: =AD27-AD26 -> #DIV/0! | AF27: =AE27/AD26 -> #DIV/0! | AI27: =L27-AD27 -> #DIV/0! | AJ27: =AI27-AI26 -> #DIV/0! | AK27: =AJ27-AJ26 -> #DIV/0! | AL27: =AF27/N27 -> #DIV/0! | AM27: =N27/J27 -> 2.1202362 | AN27: =C27 -> inflation
A28: 1807 | B28: 1.3451613 | C28: =IF(B28>B27,"inflation","deflation") -> deflation | D28: =IF(C28=Q28,1,0) -> 1 | E28: =B28-B27 -> -0.066642229 | F28: =E28/B27 -> -0.047203614 | G28: =E28/B27 -> -0.047203614 | H28: =L28/B28 -> 0.44255534 | I28: =H28-H27 -> 0.00041114192 | J28: =I28/H27 -> 0.00092988199 | L28: 0.59530831 | M28: =L28-L27 -> -0.028912422 | N28: =M28/L27 -> -0.046317626 | P28: =N28/J28 -> -49.81022 | Q28: =IF(N28>J28, "inflation", "deflation") -> deflation | R28: =IF(C28=Q28,1,0) -> 1 | S28: 0 | T28: =S28-S27 -> 0 | U28: =T28/S27 -> #DIV/0! | V28: =S28/B28 -> 0 | W28: =V28-V27 -> 0 | X28: =W28/V27 -> #DIV/0! | AA28: =L28/S28 -> #DIV/0! | AB28: =AA28-AA27 -> #DIV/0! | AC28: =AB28/AA27 -> #DIV/0! | AD28: =V28*AA28 -> #DIV/0! | AE28: =AD28-AD27 -> #DIV/0! | AF28: =AE28/AD27 -> #DIV/0! | AI28: =L28-AD28 -> #DIV/0! | AJ28: =AI28-AI27 -> #DIV/0! | AK28: =AJ28-AJ27 -> #DIV/0! | AL28: =AF28/N28 -> #DIV/0! | AM28: =N28/J28 -> -49.81022 | AN28: =C28 -> deflation
A29: 1808 | B29: 1.4723607 | C29: =IF(B29>B28,"inflation","deflation") -> inflation | D29: =IF(C29=Q29,1,0) -> 1 | E29: =B29-B28 -> 0.12719941 | F29: =E29/B28 -> 0.094560715 | G29: =E29/B28 -> 0.094560715 | H29: =L29/B29 -> 0.44354292 | I29: =H29-H28 -> 0.00098758551 | J29: =I29/H28 -> 0.0022315526 | L29: 0.65305517 | M29: =L29-L28 -> 0.057746861 | N29: =M29/L28 -> 0.097003285 | P29: =N29/J29 -> 43.468967 | Q29: =IF(N29>J29, "inflation", "deflation") -> inflation | R29: =IF(C29=Q29,1,0) -> 1 | S29: 0 | T29: =S29-S28 -> 0 | U29: =T29/S28 -> #DIV/0! | V29: =S29/B29 -> 0 | W29: =V29-V28 -> 0 | X29: =W29/V28 -> #DIV/0! | AA29: =L29/S29 -> #DIV/0! | AB29: =AA29-AA28 -> #DIV/0! | AC29: =AB29/AA28 -> #DIV/0! | AD29: =V29*AA29 -> #DIV/0! | AE29: =AD29-AD28 -> #DIV/0! | AF29: =AE29/AD28 -> #DIV/0! | AI29: =L29-AD29 -> #DIV/0! | AJ29: =AI29-AI28 -> #DIV/0! | AK29: =AJ29-AJ28 -> #DIV/0! | AL29: =AF29/N29 -> #DIV/0! | AM29: =N29/J29 -> 43.468967 | AN29: =C29 -> inflation
A30: 1809 | B30: 1.4539589 | C30: =IF(B30>B29,"inflation","deflation") -> deflation | D30: =IF(C30=Q30,1,0) -> 1 | E30: =B30-B29 -> -0.01840176 | F30: =E30/B29 -> -0.012498133 | G30: =E30/B29 -> -0.012498133 | H30: =L30/B30 -> 0.4774725 | I30: =H30-H29 -> 0.033929578 | J30: =I30/H29 -> 0.076496718 | L30: 0.69422541 | M30: =L30-L29 -> 0.041170243 | N30: =M30/L29 -> 0.063042519 | P30: =N30/J30 -> 0.82412057 | Q30: =IF(N30>J30, "inflation", "deflation") -> deflation | R30: =IF(C30=Q30,1,0) -> 1 | S30: 0 | T30: =S30-S29 -> 0 | U30: =T30/S29 -> #DIV/0! | V30: =S30/B30 -> 0 | W30: =V30-V29 -> 0 | X30: =W30/V29 -> #DIV/0! | AA30: =L30/S30 -> #DIV/0! | AB30: =AA30-AA29 -> #DIV/0! | AC30: =AB30/AA29 -> #DIV/0! | AD30: =V30*AA30 -> #DIV/0! | AE30: =AD30-AD29 -> #DIV/0! | AF30: =AE30/AD29 -> #DIV/0! | AI30: =L30-AD30 -> #DIV/0! | AJ30: =AI30-AI29 -> #DIV/0! | AK30: =AJ30-AJ29 -> #DIV/0! | AL30: =AF30/N30 -> #DIV/0! | AM30: =N30/J30 -> 0.82412057 | AN30: =C30 -> deflation
A31: 1810 | B31: 1.4166703 | C31: =IF(B31>B30,"inflation","deflation") -> deflation | D31: =IF(C31=Q31,1,0) -> 1 | E31: =B31-B30 -> -0.037288636 | F31: =E31/B30 -> -0.025646278 | G31: =E31/B30 -> -0.025646278 | H31: =L31/B31 -> 0.50392749 | I31: =H31-H30 -> 0.026454989 | J31: =I31/H30 -> 0.055406309 | L31: 0.71389911 | M31: =L31-L30 -> 0.019673699 | N31: =M31/L30 -> 0.028339065 | P31: =N31/J31 -> 0.51147723 | Q31: =IF(N31>J31, "inflation", "deflation") -> deflation | R31: =IF(C31=Q31,1,0) -> 1 | S31: 0.058 | T31: =S31-S30 -> 0.058 | U31: =T31/S30 -> #DIV/0! | V31: =S31/B31 -> 0.040941071 | W31: =V31-V30 -> 0.040941071 | X31: =W31/V30 -> #DIV/0! | AA31: =L31/S31 -> 12.308605 | AB31: =AA31-AA30 -> #DIV/0! | AC31: =AB31/AA30 -> #DIV/0! | AD31: =V31*AA31 -> 0.50392749 | AE31: =AD31-AD30 -> #DIV/0! | AF31: =AE31/AD30 -> #DIV/0! | AI31: =L31-AD31 -> 0.20997162 | AJ31: =AI31-AI30 -> #DIV/0! | AK31: =AJ31-AJ30 -> #DIV/0! | AL31: =AF31/N31 -> #DIV/0! | AM31: =N31/J31 -> 0.51147723 | AN31: =C31 -> deflation
A32: 1811 | B32: 1.4725831 | C32: =IF(B32>B31,"inflation","deflation") -> inflation | D32: =IF(C32=Q32,1,0) -> 1 | E32: =B32-B31 -> 0.055912828 | F32: =E32/B31 -> 0.039467777 | G32: =E32/B31 -> 0.039467777 | H32: =L32/B32 -> 0.52683857 | I32: =H32-H31 -> 0.022911085 | J32: =I32/H31 -> 0.045465044 | L32: 0.7758136 | M32: =L32-L31 -> 0.061914489 | N32: =M32/L31 -> 0.086727225 | P32: =N32/J32 -> 1.9075584 | Q32: =IF(N32>J32, "inflation", "deflation") -> inflation | R32: =IF(C32=Q32,1,0) -> 1 | S32: 0.055 | T32: =S32-S31 -> -0.003 | U32: =T32/S31 -> -0.051724138 | V32: =S32/B32 -> 0.037349334 | W32: =V32-V31 -> -0.0035917368 | X32: =W32/V31 -> -0.08772943 | Y32: =IF(X32>J32,"inflation","deflation") -> deflation | Z32: =IF(Y32=C32,1,0) -> 0 | AA32: =L32/S32 -> 14.105702 | AB32: =AA32-AA31 -> 1.7970965 | AC32: =AB32/AA31 -> 0.14600326 | AD32: =V32*AA32 -> 0.52683857 | AE32: =AD32-AD31 -> 0.022911085 | AF32: =AE32/AD31 -> 0.045465044 | AI32: =L32-AD32 -> 0.24897503 | AJ32: =AI32-AI31 -> 0.039003404 | AK32: =AJ32-AJ31 -> #DIV/0! | AL32: =AF32/N32 -> 0.52423035 | AM32: =N32/J32 -> 1.9075584 | AN32: =C32 -> inflation
A33: 1812 | B33: 1.4509114 | C33: =IF(B33>B32,"inflation","deflation") -> deflation | D33: =IF(C33=Q33,1,0) -> 1 | E33: =B33-B32 -> -0.021671746 | F33: =E33/B32 -> -0.014716823 | G33: =E33/B32 -> -0.014716823 | H33: =L33/B33 -> 0.54785554 | I33: =H33-H32 -> 0.021016963 | J33: =I33/H32 -> 0.039892604 | L33: 0.79488984 | M33: =L33-L32 -> 0.019076239 | N33: =M33/L32 -> 0.024588689 | P33: =N33/J33 -> 0.61637211 | Q33: =IF(N33>J33, "inflation", "deflation") -> deflation | R33: =IF(C33=Q33,1,0) -> 1 | S33: 0 | T33: =S33-S32 -> -0.055 | U33: =T33/S32 -> -1 | V33: =S33/B33 -> 0 | W33: =V33-V32 -> -0.037349334 | X33: =W33/V32 -> -1 | Y33: =IF(X33>J33,"inflation","deflation") -> deflation | Z33: =IF(Y33=C33,1,0) -> 1 | AA33: =L33/S33 -> #DIV/0! | AB33: =AA33-AA32 -> #DIV/0! | AC33: =AB33/AA32 -> #DIV/0! | AD33: =V33*AA33 -> #DIV/0! | AE33: =AD33-AD32 -> #DIV/0! | AF33: =AE33/AD32 -> #DIV/0! | AI33: =L33-AD33 -> #DIV/0! | AJ33: =AI33-AI32 -> #DIV/0! | AK33: =AJ33-AJ32 -> #DIV/0! | AL33: =AF33/N33 -> #DIV/0! | AM33: =N33/J33 -> 0.61637211 | AN33: =C33 -> deflation
A34: 1813 | B34: 1.6927192 | C34: =IF(B34>B33,"inflation","deflation") -> inflation | D34: =IF(C34=Q34,1,0) -> 1 | E34: =B34-B33 -> 0.24180783 | F34: =E34/B33 -> 0.16665927 | G34: =E34/B33 -> 0.16665927 | H34: =L34/B34 -> 0.57903386 | I34: =H34-H33 -> 0.031178322 | J34: =I34/H33 -> 0.056909751 | L34: 0.98014174 | M34: =L34-L33 -> 0.1852519 | N34: =M34/L33 -> 0.23305356 | P34: =N34/J34 -> 4.0951428 | Q34: =IF(N34>J34, "inflation", "deflation") -> inflation | R34: =IF(C34=Q34,1,0) -> 1 | S34: 0 | T34: =S34-S33 -> 0 | U34: =T34/S33 -> #DIV/0! | V34: =S34/B34 -> 0 | W34: =V34-V33 -> 0 | X34: =W34/V33 -> #DIV/0! | Y34: =IF(X34>J34,"inflation","deflation") -> #DIV/0! | Z34: =IF(Y34=C34,1,0) -> #DIV/0! | AA34: =L34/S34 -> #DIV/0! | AB34: =AA34-AA33 -> #DIV/0! | AC34: =AB34/AA33 -> #DIV/0! | AD34: =V34*AA34 -> #DIV/0! | AE34: =AD34-AD33 -> #DIV/0! | AF34: =AE34/AD33 -> #DIV/0! | AI34: =L34-AD34 -> #DIV/0! | AJ34: =AI34-AI33 -> #DIV/0! | AK34: =AJ34-AJ33 -> #DIV/0! | AL34: =AF34/N34 -> #DIV/0! | AM34: =N34/J34 -> 4.0951428 | AN34: =C34 -> inflation
A35: 1814 | B35: 1.8070664 | C35: =IF(B35>B34,"inflation","deflation") -> inflation | D35: =IF(C35=Q35,1,0) -> 1 | E35: =B35-B34 -> 0.11434717 | F35: =E35/B34 -> 0.067552356 | G35: =E35/B34 -> 0.067552356 | H35: =L35/B35 -> 0.60326053 | I35: =H35-H34 -> 0.024226671 | J35: =I35/H34 -> 0.041839817 | L35: 1.0901318 | M35: =L35-L34 -> 0.10999009 | N35: =M35/L34 -> 0.11221855 | P35: =N35/J35 -> 2.6820995 | Q35: =IF(N35>J35, "inflation", "deflation") -> inflation | R35: =IF(C35=Q35,1,0) -> 1 | S35: 0 | T35: =S35-S34 -> 0 | U35: =T35/S34 -> #DIV/0! | V35: =S35/B35 -> 0 | W35: =V35-V34 -> 0 | X35: =W35/V34 -> #DIV/0! | Y35: =IF(X35>J35,"inflation","deflation") -> #DIV/0! | Z35: =IF(Y35=C35,1,0) -> #DIV/0! | AA35: =L35/S35 -> #DIV/0! | AB35: =AA35-AA34 -> #DIV/0! | AC35: =AB35/AA34 -> #DIV/0! | AD35: =V35*AA35 -> #DIV/0! | AE35: =AD35-AD34 -> #DIV/0! | AF35: =AE35/AD34 -> #DIV/0! | AI35: =L35-AD35 -> #DIV/0! | AJ35: =AI35-AI34 -> #DIV/0! | AK35: =AJ35-AJ34 -> #DIV/0! | AL35: =AF35/N35 -> #DIV/0! | AM35: =N35/J35 -> 2.6820995 | AN35: =C35 -> inflation
A36: 1815 | B36: 1.5377839 | C36: =IF(B36>B35,"inflation","deflation") -> deflation | D36: =IF(C36=Q36,1,0) -> 1 | E36: =B36-B35 -> -0.26928248 | F36: =E36/B35 -> -0.14901637 | G36: =E36/B35 -> -0.14901637 | H36: =L36/B36 -> 0.60811125 | I36: =H36-H35 -> 0.0048507205 | J36: =I36/H35 -> 0.0080408386 | L36: 0.9351437 | M36: =L36-L35 -> -0.15498813 | N36: =M36/L35 -> -0.14217375 | P36: =N36/J36 -> -17.681458 | Q36: =IF(N36>J36, "inflation", "deflation") -> deflation | R36: =IF(C36=Q36,1,0) -> 1 | S36: 0.108 | T36: =S36-S35 -> 0.108 | U36: =T36/S35 -> #DIV/0! | V36: =S36/B36 -> 0.070230934 | W36: =V36-V35 -> 0.070230934 | X36: =W36/V35 -> #DIV/0! | Y36: =IF(X36>J36,"inflation","deflation") -> #DIV/0! | Z36: =IF(Y36=C36,1,0) -> #DIV/0! | AA36: =L36/S36 -> 8.6587379 | AB36: =AA36-AA35 -> #DIV/0! | AC36: =AB36/AA35 -> #DIV/0! | AD36: =V36*AA36 -> 0.60811125 | AE36: =AD36-AD35 -> #DIV/0! | AF36: =AE36/AD35 -> #DIV/0! | AI36: =L36-AD36 -> 0.32703245 | AJ36: =AI36-AI35 -> #DIV/0! | AK36: =AJ36-AJ35 -> #DIV/0! | AL36: =AF36/N36 -> #DIV/0! | AM36: =N36/J36 -> -17.681458 | AN36: =C36 -> deflation
A37: 1816 | B37: 1.3622068 | C37: =IF(B37>B36,"inflation","deflation") -> deflation | D37: =IF(C37=Q37,1,0) -> 1 | E37: =B37-B36 -> -0.17557712 | F37: =E37/B36 -> -0.11417542 | G37: =E37/B36 -> -0.11417542 | H37: =L37/B37 -> 0.60807585 | I37: =H37-H36 -> -3.5396738e-05 | J37: =I37/H36 -> -5.8207669e-05 | L37: 0.82832506 | M37: =L37-L36 -> -0.10681864 | N37: =M37/L36 -> -0.11422698 | P37: =N37/J37 -> 1962.4043 | Q37: =IF(N37>J37, "inflation", "deflation") -> deflation | R37: =IF(C37=Q37,1,0) -> 1 | S37: 0.155 | T37: =S37-S36 -> 0.047 | U37: =T37/S36 -> 0.43518519 | V37: =S37/B37 -> 0.11378595 | W37: =V37-V36 -> 0.043555021 | X37: =W37/V36 -> 0.62016861 | Y37: =IF(X37>J37,"inflation","deflation") -> inflation | Z37: =IF(Y37=C37,1,0) -> 0 | AA37: =L37/S37 -> 5.3440326 | AB37: =AA37-AA36 -> -3.3147053 | AC37: =AB37/AA36 -> -0.38281622 | AD37: =V37*AA37 -> 0.60807585 | AE37: =AD37-AD36 -> -3.5396738e-05 | AF37: =AE37/AD36 -> -5.8207669e-05 | AI37: =L37-AD37 -> 0.2202492 | AJ37: =AI37-AI36 -> -0.10678324 | AK37: =AJ37-AJ36 -> #DIV/0! | AL37: =AF37/N37 -> 0.000509579 | AM37: =N37/J37 -> 1962.4043 | AN37: =C37 -> deflation
A38: 1817 | B38: 1.2493512 | C38: =IF(B38>B37,"inflation","deflation") -> deflation | D38: =IF(C38=Q38,1,0) -> 1 | E38: =B38-B37 -> -0.1128556 | F38: =E38/B37 -> -0.082847624 | G38: =E38/B37 -> -0.082847624 | H38: =L38/B38 -> 0.62220214 | I38: =H38-H37 -> 0.014126282 | J38: =I38/H37 -> 0.023231118 | L38: 0.77734898 | M38: =L38-L37 -> -0.050976076 | N38: =M38/L37 -> -0.061541149 | P38: =N38/J38 -> -2.6490825 | Q38: =IF(N38>J38, "inflation", "deflation") -> deflation | R38: =IF(C38=Q38,1,0) -> 1 | S38: 0 | T38: =S38-S37 -> -0.155 | U38: =T38/S37 -> -1 | V38: =S38/B38 -> 0 | W38: =V38-V37 -> -0.11378595 | X38: =W38/V37 -> -1 | Y38: =IF(X38>J38,"inflation","deflation") -> deflation | Z38: =IF(Y38=C38,1,0) -> 1 | AA38: =L38/S38 -> #DIV/0! | AB38: =AA38-AA37 -> #DIV/0! | AC38: =AB38/AA37 -> #DIV/0! | AD38: =V38*AA38 -> #DIV/0! | AE38: =AD38-AD37 -> #DIV/0! | AF38: =AE38/AD37 -> #DIV/0! | AI38: =L38-AD38 -> #DIV/0! | AJ38: =AI38-AI37 -> #DIV/0! | AK38: =AJ38-AJ37 -> #DIV/0! | AL38: =AF38/N38 -> #DIV/0! | AM38: =N38/J38 -> -2.6490825 | AN38: =C38 -> deflation
A39: 1818 | B39: 1.1561437 | C39: =IF(B39>B38,"inflation","deflation") -> deflation | D39: =IF(C39=Q39,1,0) -> 1 | E39: =B39-B38 -> -0.093207502 | F39: =E39/B38 -> -0.074604725 | G39: =E39/B38 -> -0.074604725 | H39: =L39/B39 -> 0.6447981 | I39: =H39-H38 -> 0.022595961 | J39: =I39/H38 -> 0.03631611 | L39: 0.74547925 | M39: =L39-L38 -> -0.031869729 | N39: =M39/L38 -> -0.040997968 | P39: =N39/J39 -> -1.1289196 | Q39: =IF(N39>J39, "inflation", "deflation") -> deflation | R39: =IF(C39=Q39,1,0) -> 1 | S39: 0 | T39: =S39-S38 -> 0 | U39: =T39/S38 -> #DIV/0! | V39: =S39/B39 -> 0 | W39: =V39-V38 -> 0 | X39: =W39/V38 -> #DIV/0! | Y39: =IF(X39>J39,"inflation","deflation") -> #DIV/0! | Z39: =IF(Y39=C39,1,0) -> #DIV/0! | AA39: =L39/S39 -> #DIV/0! | AB39: =AA39-AA38 -> #DIV/0! | AC39: =AB39/AA38 -> #DIV/0! | AD39: =V39*AA39 -> #DIV/0! | AE39: =AD39-AD38 -> #DIV/0! | AF39: =AE39/AD38 -> #DIV/0! | AI39: =L39-AD39 -> #DIV/0! | AJ39: =AI39-AI38 -> #DIV/0! | AK39: =AJ39-AJ38 -> #DIV/0! | AL39: =AF39/N39 -> #DIV/0! | AM39: =N39/J39 -> -1.1289196 | AN39: =C39 -> deflation
A40: 1819 | B40: 1.1175953 | C40: =IF(B40>B39,"inflation","deflation") -> deflation | D40: =IF(C40=Q40,1,0) -> 1 | E40: =B40-B39 -> -0.038548387 | F40: =E40/B39 -> -0.033342211 | G40: =E40/B39 -> -0.033342211 | H40: =L40/B40 -> 0.65727906 | I40: =H40-H39 -> 0.01248096 | J40: =I40/H39 -> 0.019356385 | L40: 0.73457199 | M40: =L40-L39 -> -0.010907264 | N40: =M40/L39 -> -0.014631211 | P40: =N40/J40 -> -0.7558855 | Q40: =IF(N40>J40, "inflation", "deflation") -> deflation | R40: =IF(C40=Q40,1,0) -> 1 | S40: 0 | T40: =S40-S39 -> 0 | U40: =T40/S39 -> #DIV/0! | V40: =S40/B40 -> 0 | W40: =V40-V39 -> 0 | X40: =W40/V39 -> #DIV/0! | Y40: =IF(X40>J40,"inflation","deflation") -> #DIV/0! | Z40: =IF(Y40=C40,1,0) -> #DIV/0! | AA40: =L40/S40 -> #DIV/0! | AB40: =AA40-AA39 -> #DIV/0! | AC40: =AB40/AA39 -> #DIV/0! | AD40: =V40*AA40 -> #DIV/0! | AE40: =AD40-AD39 -> #DIV/0! | AF40: =AE40/AD39 -> #DIV/0! | AI40: =L40-AD40 -> #DIV/0! | AJ40: =AI40-AI39 -> #DIV/0! | AK40: =AJ40-AJ39 -> #DIV/0! | AL40: =AF40/N40 -> #DIV/0! | AM40: =N40/J40 -> -0.7558855 | AN40: =C40 -> deflation
A41: 1820 | B41: 1.0498861 | C41: =IF(B41>B40,"inflation","deflation") -> deflation | D41: =IF(C41=Q41,1,0) -> 1 | E41: =B41-B40 -> -0.067709252 | F41: =E41/B40 -> -0.060584768 | G41: =E41/B40 -> -0.060584768 | H41: =L41/B41 -> 0.68355076 | I41: =H41-H40 -> 0.026271705 | J41: =I41/H40 -> 0.039970397 | L41: 0.71765041 | M41: =L41-L40 -> -0.016921577 | N41: =M41/L40 -> -0.023035968 | P41: =N41/J41 -> -0.57632573 | Q41: =IF(N41>J41, "inflation", "deflation") -> deflation | R41: =IF(C41=Q41,1,0) -> 1 | S41: 0.2171 | T41: =S41-S40 -> 0.2171 | U41: =T41/S40 -> #DIV/0! | V41: =S41/B41 -> 0.20678434 | W41: =V41-V40 -> 0.20678434 | X41: =W41/V40 -> #DIV/0! | Y41: =IF(X41>J41,"inflation","deflation") -> #DIV/0! | Z41: =IF(Y41=C41,1,0) -> #DIV/0! | AA41: =L41/S41 -> 3.3056214 | AB41: =AA41-AA40 -> #DIV/0! | AC41: =AB41/AA40 -> #DIV/0! | AD41: =V41*AA41 -> 0.68355076 | AE41: =AD41-AD40 -> #DIV/0! | AF41: =AE41/AD40 -> #DIV/0! | AI41: =L41-AD41 -> 0.034099651 | AJ41: =AI41-AI40 -> #DIV/0! | AK41: =AJ41-AJ40 -> #DIV/0! | AL41: =AF41/N41 -> #DIV/0! | AM41: =N41/J41 -> -0.57632573 | AN41: =C41 -> deflation
A42: 1821 | B42: 1.0318941 | C42: =IF(B42>B41,"inflation","deflation") -> deflation | D42: =IF(C42=Q42,1,0) -> 1 | E42: =B42-B41 -> -0.017992 | F42: =E42/B41 -> -0.017137098 | G42: =E42/B41 -> -0.017137098 | H42: =L42/B42 -> 0.71918138 | I42: =H42-H41 -> 0.035630615 | J42: =I42/H41 -> 0.052125777 | L42: 0.74211899 | M42: =L42-L41 -> 0.024468574 | N42: =M42/L41 -> 0.034095395 | P42: =N42/J42 -> 0.65409854 | Q42: =IF(N42>J42, "inflation", "deflation") -> deflation | R42: =IF(C42=Q42,1,0) -> 1 | S42: 0 | T42: =S42-S41 -> -0.2171 | U42: =T42/S41 -> -1 | V42: =S42/B42 -> 0 | W42: =V42-V41 -> -0.20678434 | X42: =W42/V41 -> -1 | Y42: =IF(X42>J42,"inflation","deflation") -> deflation | Z42: =IF(Y42=C42,1,0) -> 1 | AA42: =L42/S42 -> #DIV/0! | AB42: =AA42-AA41 -> #DIV/0! | AC42: =AB42/AA41 -> #DIV/0! | AD42: =V42*AA42 -> #DIV/0! | AE42: =AD42-AD41 -> #DIV/0! | AF42: =AE42/AD41 -> #DIV/0! | AI42: =L42-AD42 -> #DIV/0! | AJ42: =AI42-AI41 -> #DIV/0! | AK42: =AJ42-AJ41 -> #DIV/0! | AL42: =AF42/N42 -> #DIV/0! | AM42: =N42/J42 -> 0.65409854 | AN42: =C42 -> deflation
A43: 1822 | B43: 1.0897766 | C43: =IF(B43>B42,"inflation","deflation") -> inflation | D43: =IF(C43=Q43,1,0) -> 1 | E43: =B43-B42 -> 0.057882563 | F43: =E43/B42 -> 0.056093513 | G43: =E43/B42 -> 0.056093513 | H43: =L43/B43 -> 0.74855456 | I43: =H43-H42 -> 0.029373183 | J43: =I43/H42 -> 0.040842525 | L43: 0.81575726 | M43: =L43-L42 -> 0.073638269 | N43: =M43/L42 -> 0.099227039 | P43: =N43/J43 -> 2.4295031 | Q43: =IF(N43>J43, "inflation", "deflation") -> inflation | R43: =IF(C43=Q43,1,0) -> 1 | S43: 0 | T43: =S43-S42 -> 0 | U43: =T43/S42 -> #DIV/0! | V43: =S43/B43 -> 0 | W43: =V43-V42 -> 0 | X43: =W43/V42 -> #DIV/0! | Y43: =IF(X43>J43,"inflation","deflation") -> #DIV/0! | Z43: =IF(Y43=C43,1,0) -> #DIV/0! | AA43: =L43/S43 -> #DIV/0! | AB43: =AA43-AA42 -> #DIV/0! | AC43: =AB43/AA42 -> #DIV/0! | AD43: =V43*AA43 -> #DIV/0! | AE43: =AD43-AD42 -> #DIV/0! | AF43: =AE43/AD42 -> #DIV/0! | AI43: =L43-AD43 -> #DIV/0! | AJ43: =AI43-AI42 -> #DIV/0! | AK43: =AJ43-AJ42 -> #DIV/0! | AL43: =AF43/N43 -> #DIV/0! | AM43: =N43/J43 -> 2.4295031 | AN43: =C43 -> inflation
... A50: 1829 | B50: 0.97653959 | C50: =IF(B50>B49,"inflation","deflation") -> deflation | D50: =IF(C50=Q50,1,0) -> 1 | E50: =B50-B49 -> -0.0013122346 | F50: =E50/B49 -> -0.0013419565 | G50: =E50/B49 -> -0.0013419565 | H50: =L50/B50 -> 0.96248728 | I50: =H50-H49 -> 0.035114289 | J50: =I50/H49 -> 0.037864257 | L50: 0.93990693 | M50: =L50-L49 -> 0.033073563 | N50: =M50/L49 -> 0.036471488 | P50: =N50/J50 -> 0.9632168 | Q50: =IF(N50>J50, "inflation", "deflation") -> deflation | R50: =IF(C50=Q50,1,0) -> 1 | S50: 0 | T50: =S50-S49 -> 0 | U50: =T50/S49 -> #DIV/0! | V50: =S50/B50 -> 0 | W50: =V50-V49 -> 0 | X50: =W50/V49 -> #DIV/0! | Y50: =IF(X50>J50,"inflation","deflation") -> #DIV/0! | Z50: =IF(Y50=C50,1,0) -> #DIV/0! | AA50: =L50/S50 -> #DIV/0! | AB50: =AA50-AA49 -> #DIV/0! | AC50: =AB50/AA49 -> #DIV/0! | AD50: =V50*AA50 -> #DIV/0! | AE50: =AD50-AD49 -> #DIV/0! | AF50: =AE50/AD49 -> #DIV/0! | AI50: =L50-AD50 -> #DIV/0! | AJ50: =AI50-AI49 -> #DIV/0! | AK50: =AJ50-AJ49 -> #DIV/0! | AL50: =AF50/N50 -> #DIV/0! | AM50: =N50/J50 -> 0.9632168 | AN50: =C50 -> deflation
A51: 1830 | B51: 0.98290394 | C51: =IF(B51>B50,"inflation","deflation") -> inflation | D51: =IF(C51=Q51,1,0) -> 1 | E51: =B51-B50 -> 0.0063643531 | F51: =E51/B50 -> 0.0065172505 | G51: =E51/B50 -> 0.0065172505 | H51: =L51/B51 -> 1.0503561 | I51: =H51-H50 -> 0.087868821 | J51: =I51/H50 -> 0.091293488 | L51: 1.0323992 | M51: =L51-L50 -> 0.092492219 | N51: =M51/L50 -> 0.098405721 | P51: =N51/J51 -> 1.0779052 | Q51: =IF(N51>J51, "inflation", "deflation") -> inflation | R51: =IF(C51=Q51,1,0) -> 1 | S51: 0.2825 | T51: =S51-S50 -> 0.2825 | U51: "" | V51: =S51/B51 -> 0.28741364 | W51: =V51-V50 -> 0.28741364 | X51: "" | Y51: =IF(X51>J51,"inflation","deflation") -> inflation | Z51: =IF(Y51=C51,1,0) -> 1 | AA51: =L51/S51 -> 3.6545103 | AB51: "" | AC51: "" | AD51: =V51*AA51 -> 1.0503561 | AE51: "" | AF51: "" | AI51: =L51-AD51 -> -0.017956948 | AJ51: "" | AK51: "" | AL51: "" | AM51: =N51/J51 -> 1.0779052 | AN51: =C51 -> inflation
A52: 1831 | B52: 0.93505126 | C52: =IF(B52>B51,"inflation","deflation") -> deflation | D52: =IF(C52=Q52,1,0) -> 1 | E52: =B52-B51 -> -0.047852686 | F52: =E52/B51 -> -0.048685007 | G52: =E52/B51 -> -0.048685007 | H52: =L52/B52 -> 1.1384661 | I52: =H52-H51 -> 0.08810996 | J52: =I52/H51 -> 0.083885798 | L52: 1.0645241 | M52: =L52-L51 -> 0.032124968 | N52: =M52/L51 -> 0.03111681 | P52: =N52/J52 -> 0.37094253 | Q52: =IF(N52>J52, "inflation", "deflation") -> deflation | R52: =IF(C52=Q52,1,0) -> 1 | S52: 0.109 | T52: =S52-S51 -> -0.1735 | U52: =T52/S51 -> -0.61415929 | V52: =S52/B52 -> 0.11657115 | W52: =V52-V51 -> -0.17084249 | X52: =W52/V51 -> -0.5944133 | Y52: =IF(X52>J52,"inflation","deflation") -> deflation | Z52: =IF(Y52=C52,1,0) -> 1 | AA52: =L52/S52 -> 9.7662763 | AB52: =AA52-AA51 -> 6.1117661 | AC52: =AB52/AA51 -> 1.6723899 | AD52: =V52*AA52 -> 1.1384661 | AE52: =AD52-AD51 -> 0.08810996 | AF52: =AE52/AD51 -> 0.083885798 | AG52: =IF(AF52>M51, "inflation", "deflation") -> deflation | AH52: =IF(AG52=C52,1,0) -> 1 | AI52: =L52-AD52 -> -0.07394194 | AJ52: =AI52-AI51 -> -0.055984991 | AK52: "" | AL52: =AF52/N52 -> 2.6958354 | AM52: =N52/J52 -> 0.37094253 | AN52: =C52 -> deflation
A53: 1832 | B53: 0.94005674 | C53: =IF(B53>B52,"inflation","deflation") -> inflation | D53: =IF(C53=Q53,1,0) -> 1 | E53: =B53-B52 -> 0.0050054831 | F53: =E53/B52 -> 0.0053531645 | G53: =E53/B52 -> 0.0053531645 | H53: =L53/B53 -> 1.2153364 | I53: =H53-H52 -> 0.076870297 | J53: =I53/H52 -> 0.067520939 | L53: 1.1424851 | M53: =L53-L52 -> 0.077961014 | N53: =M53/L52 -> 0.073235554 | P53: =N53/J53 -> 1.0846347 | Q53: =IF(N53>J53, "inflation", "deflation") -> inflation | R53: =IF(C53=Q53,1,0) -> 1 | S53: 0.122 | T53: =S53-S52 -> 0.013 | U53: =T53/S52 -> 0.11926606 | V53: =S53/B53 -> 0.1297794 | W53: =V53-V52 -> 0.013208251 | X53: =W53/V52 -> 0.11330634 | Y53: =IF(X53>J53,"inflation","deflation") -> inflation | Z53: =IF(Y53=C53,1,0) -> 1 | AA53: =L53/S53 -> 9.3646322 | AB53: =AA53-AA52 -> -0.40164409 | AC53: =AB53/AA52 -> -0.041125611 | AD53: =V53*AA53 -> 1.2153364 | AE53: =AD53-AD52 -> 0.076870297 | AF53: =AE53/AD52 -> 0.067520939 | AG53: =IF(AF53>M52, "inflation", "deflation") -> inflation | AH53: =IF(AG53=C53,1,0) -> 1 | AI53: =L53-AD53 -> -0.072851223 | AJ53: =AI53-AI52 -> 0.0010907165 | AK53: =AJ53-AJ52 -> 0.057075708 | AL53: =AF53/N53 -> 0.92196939 | AM53: =N53/J53 -> 1.0846347 | AN53: =C53 -> inflation
A54: 1833 | B54: 0.9355278 | C54: =IF(B54>B53,"inflation","deflation") -> deflation | D54: =IF(C54=Q54,1,0) -> 1 | E54: =B54-B53 -> -0.0045289423 | F54: =E54/B53 -> -0.0048177329 | G54: =E54/B53 -> -0.0048177329 | H54: =L54/B54 -> 1.2529646 | I54: =H54-H53 -> 0.037628273 | J54: =I54/H53 -> 0.030961201 | L54: 1.1721832 | M54: =L54-L53 -> 0.029698107 | N54: =M54/L53 -> 0.025994305 | P54: =N54/J54 -> 0.83957677 | Q54: =IF(N54>J54, "inflation", "deflation") -> deflation | R54: =IF(C54=Q54,1,0) -> 1 | S54: 0.122 | T54: =S54-S53 -> 0 | U54: =T54/S53 -> 0 | V54: =S54/B54 -> 0.13040767 | W54: =V54-V53 -> 0.00062826932 | X54: =W54/V53 -> 0.0048410558 | Y54: =IF(X54>J54,"inflation","deflation") -> deflation | Z54: =IF(Y54=C54,1,0) -> 1 | AA54: =L54/S54 -> 9.6080594 | AB54: =AA54-AA53 -> 0.24342711 | AC54: =AB54/AA53 -> 0.025994305 | AD54: =V54*AA54 -> 1.2529646 | AE54: =AD54-AD53 -> 0.037628273 | AF54: =AE54/AD53 -> 0.030961201 | AG54: =IF(AF54>M53, "inflation", "deflation") -> deflation | AH54: =IF(AG54=C54,1,0) -> 1 | AI54: =L54-AD54 -> -0.080781389 | AJ54: =AI54-AI53 -> -0.0079301659 | AK54: =AJ54-AJ53 -> -0.0090208823 | AL54: =AF54/N54 -> 1.1910763 | AM54: =N54/J54 -> 0.83957677 | AN54: =C54 -> deflation
A55: 1834 | B55: 0.96804946 | C55: =IF(B55>B54,"inflation","deflation") -> inflation | D55: =IF(C55=Q55,1,0) -> 1 | E55: =B55-B54 -> 0.032521664 | F55: =E55/B54 -> 0.034762905 | G55: =E55/B54 -> 0.034762905 | H55: =L55/B55 -> 1.2737514 | I55: =H55-H54 -> 0.020786757 | J55: =I55/H54 -> 0.016590059 | L55: 1.2330543 | M55: =L55-L54 -> 0.060871104 | N55: =M55/L54 -> 0.051929682 | P55: =N55/J55 -> 3.1301686 | Q55: =IF(N55>J55, "inflation", "deflation") -> inflation | R55: =IF(C55=Q55,1,0) -> 1 | S55: 0.237 | T55: =S55-S54 -> 0.115 | U55: =T55/S54 -> 0.94262295 | V55: =S55/B55 -> 0.2448222 | W55: =V55-V54 -> 0.11441453 | X55: =W55/V54 -> 0.87736045 | Y55: =IF(X55>J55,"inflation","deflation") -> inflation | Z55: =IF(Y55=C55,1,0) -> 1 | AA55: =L55/S55 -> 5.2027609 | AB55: =AA55-AA54 -> -4.4052984 | AC55: =AB55/AA54 -> -0.45850033 | AD55: =V55*AA55 -> 1.2737514 | AE55: =AD55-AD54 -> 0.020786757 | AF55: =AE55/AD54 -> 0.016590059 | AG55: =IF(AF55>M54, "inflation", "deflation") -> deflation | AH55: =IF(AG55=C55,1,0) -> 0 | AI55: =L55-AD55 -> -0.040697043 | AJ55: =AI55-AI54 -> 0.040084346 | AK55: =AJ55-AJ54 -> 0.048014512 | AL55: =AF55/N55 -> 0.31947161 | AM55: =N55/J55 -> 3.1301686 | AN55: =C55 -> inflation
A56: 1835 | B56: 1.0106491 | C56: =IF(B56>B55,"inflation","deflation") -> inflation | D56: =IF(C56=Q56,1,0) -> 1 | E56: =B56-B55 -> 0.042599637 | F56: =E56/B55 -> 0.044005641 | G56: =E56/B55 -> 0.044005641 | H56: =L56/B56 -> 1.3433051 | I56: =H56-H55 -> 0.069553735 | J56: =I56/H55 -> 0.054605424 | L56: 1.3576101 | M56: =L56-L55 -> 0.12455577 | N56: =M56/L55 -> 0.10101401 | P56: =N56/J56 -> 1.8498897 | Q56: =IF(N56>J56, "inflation", "deflation") -> inflation | R56: =IF(C56=Q56,1,0) -> 1 | S56: 0.277 | T56: =S56-S55 -> 0.04 | U56: =T56/S55 -> 0.16877637 | V56: =S56/B56 -> 0.27408128 | W56: =V56-V55 -> 0.02925908 | X56: =W56/V55 -> 0.11951155 | Y56: =IF(X56>J56,"inflation","deflation") -> inflation | Z56: =IF(Y56=C56,1,0) -> 1 | AA56: =L56/S56 -> 4.9011195 | AB56: =AA56-AA55 -> -0.30164142 | AC56: =AB56/AA55 -> -0.057977181 | AD56: =V56*AA56 -> 1.3433051 | AE56: =AD56-AD55 -> 0.069553735 | AF56: =AE56/AD55 -> 0.054605424 | AG56: =IF(AF56>M55, "inflation", "deflation") -> deflation | AH56: =IF(AG56=C56,1,0) -> 0 | AI56: =L56-AD56 -> 0.014304988 | AJ56: =AI56-AI55 -> 0.055002031 | AK56: =AJ56-AJ55 -> 0.014917685 | AL56: =AF56/N56 -> 0.54057277 | AM56: =N56/J56 -> 1.8498897 | AN56: =C56 -> inflation
A57: 1836 | B57: 1.083075 | C57: =IF(B57>B56,"inflation","deflation") -> inflation | D57: =IF(C57=Q57,1,0) -> 1 | E57: =B57-B56 -> 0.072425896 | F57: =E57/B56 -> 0.071662753 | G57: =E57/B56 -> 0.071662753 | H57: =L57/B57 -> 1.381925 | I57: =H57-H56 -> 0.038619859 | J57: =I57/H56 -> 0.028749878 | L57: 1.4967284 | M57: =L57-L56 -> 0.13911828 | N57: =M57/L56 -> 0.10247293 | P57: =N57/J57 -> 3.5642908 | Q57: =IF(N57>J57, "inflation", "deflation") -> inflation | R57: =IF(C57=Q57,1,0) -> 1 | S57: 0.371 | T57: =S57-S56 -> 0.094 | U57: =T57/S56 -> 0.33935018 | V57: =S57/B57 -> 0.34254322 | W57: =V57-V56 -> 0.068461942 | X57: =W57/V56 -> 0.249787 | Y57: =IF(X57>J57,"inflation","deflation") -> inflation | Z57: =IF(Y57=C57,1,0) -> 1 | AA57: =L57/S57 -> 4.0343083 | AB57: =AA57-AA56 -> -0.8668112 | AC57: =AB57/AA56 -> -0.17685984 | AD57: =V57*AA57 -> 1.381925 | AE57: =AD57-AD56 -> 0.038619859 | AF57: =AE57/AD56 -> 0.028749878 | AG57: =IF(AF57>M56, "inflation", "deflation") -> deflation | AH57: =IF(AG57=C57,1,0) -> 0 | AI57: =L57-AD57 -> 0.11480341 | AJ57: =AI57-AI56 -> 0.10049842 | AK57: =AJ57-AJ56 -> 0.045496391 | AL57: =AF57/N57 -> 0.28056072 | AM57: =N57/J57 -> 3.5642908 | AN57: =C57 -> inflation
A58: 1837 | B58: 1.1277129 | C58: =IF(B58>B57,"inflation","deflation") -> inflation | D58: =IF(C58=Q58,1,0) -> 1 | E58: =B58-B57 -> 0.044637942 | F58: =E58/B57 -> 0.041214082 | G58: =E58/B57 -> 0.041214082 | H58: =L58/B58 -> 1.3958559 | I58: =H58-H57 -> 0.013930955 | J58: =I58/H57 -> 0.010080833 | L58: 1.5741248 | M58: =L58-L57 -> 0.077396406 | N58: =M58/L57 -> 0.051710388 | P58: =N58/J58 -> 5.1295747 | Q58: =IF(N58>J58, "inflation", "deflation") -> inflation | R58: =IF(C58=Q58,1,0) -> 1 | S58: 0.412 | T58: =S58-S57 -> 0.041 | U58: =T58/S57 -> 0.11051213 | V58: =S58/B58 -> 0.3653412 | W58: =V58-V57 -> 0.022797979 | X58: =W58/V57 -> 0.066555042 | Y58: =IF(X58>J58,"inflation","deflation") -> inflation | Z58: =IF(Y58=C58,1,0) -> 1 | AA58: =L58/S58 -> 3.8206913 | AB58: =AA58-AA57 -> -0.21361708 | AC58: =AB58/AA57 -> -0.052950112 | AD58: =V58*AA58 -> 1.3958559 | AE58: =AD58-AD57 -> 0.013930955 | AF58: =AE58/AD57 -> 0.010080833 | AG58: =IF(AF58>M57, "inflation", "deflation") -> deflation | AH58: =IF(AG58=C58,1,0) -> 0 | AI58: =L58-AD58 -> 0.17826886 | AJ58: =AI58-AI57 -> 0.06346545 | AK58: =AJ58-AJ57 -> -0.037032972 | AL58: =AF58/N58 -> 0.19494793 | AM58: =N58/J58 -> 5.1295747 | AN58: =C58 -> inflation
A59: 1838 | B59: 1.1135137 | C59: =IF(B59>B58,"inflation","deflation") -> deflation | D59: =IF(C59=Q59,1,0) -> 1 | E59: =B59-B58 -> -0.014199255 | F59: =E59/B58 -> -0.012591196 | G59: =E59/B58 -> -0.012591196 | H59: =L59/B59 -> 1.4534511 | I59: =H59-H58 -> 0.057595166 | J59: =I59/H58 -> 0.04126154 | L59: 1.6184377 | M59: =L59-L58 -> 0.044312891 | N59: =M59/L58 -> 0.028150812 | P59: =N59/J59 -> 0.68225306 | Q59: =IF(N59>J59, "inflation", "deflation") -> deflation | R59: =IF(C59=Q59,1,0) -> 1 | S59: 0.35 | T59: =S59-S58 -> -0.062 | U59: =T59/S58 -> -0.15048544 | V59: =S59/B59 -> 0.31432034 | W59: =V59-V58 -> -0.051020861 | X59: =W59/V58 -> -0.13965263 | Y59: =IF(X59>J59,"inflation","deflation") -> deflation | Z59: =IF(Y59=C59,1,0) -> 1 | AA59: =L59/S59 -> 4.6241077 | AB59: =AA59-AA58 -> 0.80341643 | AC59: =AB59/AA58 -> 0.21028038 | AD59: =V59*AA59 -> 1.4534511 | AE59: =AD59-AD58 -> 0.057595166 | AF59: =AE59/AD58 -> 0.04126154 | AG59: =IF(AF59>M58, "inflation", "deflation") -> deflation | AH59: =IF(AG59=C59,1,0) -> 1 | AI59: =L59-AD59 -> 0.16498659 | AJ59: =AI59-AI58 -> -0.013282275 | AK59: =AJ59-AJ58 -> -0.076747725 | AL59: =AF59/N59 -> 1.4657318 | AM59: =N59/J59 -> 0.68225306 | AN59: =C59 -> deflation
A60: 1839 | B60: 1.128733 | C60: =IF(B60>B59,"inflation","deflation") -> inflation | D60: =IF(C60=Q60,1,0) -> 1 | E60: =B60-B59 -> 0.015219344 | F60: =E60/B59 -> 0.013667855 | G60: =E60/B59 -> 0.013667855 | H60: =L60/B60 -> 1.4930971 | I60: =H60-H59 -> 0.039645994 | J60: =I60/H59 -> 0.027277143 | L60: 1.685308 | M60: =L60-L59 -> 0.066870314 | N60: =M60/L59 -> 0.041317818 | P60: =N60/J60 -> 1.5147414 | Q60: =IF(N60>J60, "inflation", "deflation") -> inflation | R60: =IF(C60=Q60,1,0) -> 1 | S60: 0.365 | T60: =S60-S59 -> 0.015 | U60: =T60/S59 -> 0.042857143 | V60: =S60/B60 -> 0.32337142 | W60: =V60-V59 -> 0.0090510781 | X60: =W60/V59 -> 0.028795712 | Y60: =IF(X60>J60,"inflation","deflation") -> inflation | Z60: =IF(Y60=C60,1,0) -> 1 | AA60: =L60/S60 -> 4.6172822 | AB60: =AA60-AA59 -> -0.0068254826 | AC60: =AB60/AA59 -> -0.0014760648 | AD60: =V60*AA60 -> 1.4930971 | AE60: =AD60-AD59 -> 0.039645994 | AF60: =AE60/AD59 -> 0.027277143 | AG60: =IF(AF60>M59, "inflation", "deflation") -> deflation | AH60: =IF(AG60=C60,1,0) -> 0 | AI60: =L60-AD60 -> 0.19221091 | AJ60: =AI60-AI59 -> 0.02722432 | AK60: =AJ60-AJ59 -> 0.040506595 | AL60: =AF60/N60 -> 0.66017869 | AM60: =N60/J60 -> 1.5147414 | AN60: =C60 -> inflation
A61: 1840 | B61: 1.0663202 | C61: =IF(B61>B60,"inflation","deflation") -> deflation | D61: =IF(C61=Q61,1,0) -> 1 | E61: =B61-B60 -> -0.062412796 | F61: =E61/B60 -> -0.05529456 | G61: =E61/B60 -> -0.05529456 | H61: =L61/B61 -> 1.4909719 | I61: =H61-H60 -> -0.0021251561 | J61: =I61/H60 -> -0.0014233208 | L61: 1.5898535 | M61: =L61-L60 -> -0.095454462 | N61: =M61/L60 -> -0.056639179 | P61: =N61/J61 -> 39.793686 | Q61: =IF(N61>J61, "inflation", "deflation") -> deflation | R61: =IF(C61=Q61,1,0) -> 1 | S61: 0.31 | T61: =S61-S60 -> -0.055 | U61: =T61/S60 -> -0.15068493 | V61: =S61/B61 -> 0.29071942 | W61: =V61-V60 -> -0.032651998 | X61: =W61/V60 -> -0.10097367 | Y61: =IF(X61>J61,"inflation","deflation") -> deflation | Z61: =IF(Y61=C61,1,0) -> 1 | AA61: =L61/S61 -> 5.1285598 | AB61: =AA61-AA60 -> 0.51127761 | AC61: =AB61/AA60 -> 0.11073129 | AD61: =V61*AA61 -> 1.4909719 | AE61: =AD61-AD60 -> -0.0021251561 | AF61: =AE61/AD60 -> -0.0014233208 | AG61: =IF(AF61>M60, "inflation", "deflation") -> deflation | AH61: =IF(AG61=C61,1,0) -> 1 | AI61: =L61-AD61 -> 0.0988816 | AJ61: =AI61-AI60 -> -0.093329306 | AK61: =AJ61-AJ60 -> -0.12055363 | AL61: =AF61/N61 -> 0.025129615 | AM61: =N61/J61 -> 39.793686 | AN61: =C61 -> deflation
A62: 1841 | B62: 1.0949594 | C62: =IF(B62>B61,"inflation","deflation") -> inflation | D62: =IF(C62=Q62,1,0) -> 1 | E62: =B62-B61 -> 0.028639176 | F62: =E62/B61 -> 0.026857951 | G62: =E62/B61 -> 0.026857951 | H62: =L62/B62 -> 1.5327195 | I62: =H62-H61 -> 0.041747603 | J62: =I62/H61 -> 0.028000261 | L62: 1.6782657 | M62: =L62-L61 -> 0.088412138 | N62: =M62/L61 -> 0.055610241 | P62: =N62/J62 -> 1.9860615 | Q62: =IF(N62>J62, "inflation", "deflation") -> inflation | R62: =IF(C62=Q62,1,0) -> 1 | S62: 0.295 | T62: =S62-S61 -> -0.015 | U62: =T62/S61 -> -0.048387097 | V62: =S62/B62 -> 0.26941638 | W62: =V62-V61 -> -0.021303041 | X62: =W62/V61 -> -0.073276978 | Y62: =IF(X62>J62,"inflation","deflation") -> deflation | Z62: =IF(Y62=C62,1,0) -> 0 | AA62: =L62/S62 -> 5.6890362 | AB62: =AA62-AA61 -> 0.56047639 | AC62: =AB62/AA61 -> 0.10928534 | AD62: =V62*AA62 -> 1.5327195 | AE62: =AD62-AD61 -> 0.041747603 | AF62: =AE62/AD61 -> 0.028000261 | AG62: =IF(AF62>M61, "inflation", "deflation") -> inflation | AH62: =IF(AG62=C62,1,0) -> 1 | AI62: =L62-AD62 -> 0.14554614 | AJ62: =AI62-AI61 -> 0.046664535 | AK62: =AJ62-AJ61 -> 0.13999384 | AL62: =AF62/N62 -> 0.50350907 | AM62: =N62/J62 -> 1.9860615 | AN62: =C62 -> inflation
A63: 1842 | B63: 1.0391225 | C63: =IF(B63>B62,"inflation","deflation") -> deflation | D63: =IF(C63=Q63,1,0) -> 1 | E63: =B63-B62 -> -0.055836937 | F63: =E63/B62 -> -0.050994527 | G63: =E63/B62 -> -0.050994527 | H63: =L63/B63 -> 1.5844686 | I63: =H63-H62 -> 0.051749106 | J63: =I63/H62 -> 0.033762932 | L63: 1.646457 | M63: =L63-L62 -> -0.031808705 | N63: =M63/L62 -> -0.018953319 | P63: =N63/J63 -> -0.56136472 | Q63: =IF(N63>J63, "inflation", "deflation") -> deflation | R63: =IF(C63=Q63,1,0) -> 1 | S63: 0.252 | T63: =S63-S62 -> -0.043 | U63: =T63/S62 -> -0.14576271 | V63: =S63/B63 -> 0.24251232 | W63: =V63-V62 -> -0.026904061 | X63: =W63/V62 -> -0.099860525 | Y63: =IF(X63>J63,"inflation","deflation") -> deflation | Z63: =IF(Y63=C63,1,0) -> 1 | AA63: =L63/S63 -> 6.5335594 | AB63: =AA63-AA62 -> 0.84452322 | AC63: =AB63/AA62 -> 0.1484475 | AD63: =V63*AA63 -> 1.5844686 | AE63: =AD63-AD62 -> 0.051749106 | AF63: =AE63/AD62 -> 0.033762932 | AG63: =IF(AF63>M62, "inflation", "deflation") -> deflation | AH63: =IF(AG63=C63,1,0) -> 1 | AI63: =L63-AD63 -> 0.061988325 | AJ63: =AI63-AI62 -> -0.083557811 | AK63: =AJ63-AJ62 -> -0.13022235 | AL63: =AF63/N63 -> -1.7813731 | AM63: =N63/J63 -> -0.56136472 | AN63: =C63 -> deflation
A64: 1843 | B64: 0.95927726 | C64: =IF(B64>B63,"inflation","deflation") -> deflation | D64: =IF(C64=Q64,1,0) -> 1 | E64: =B64-B63 -> -0.079845208 | F64: =E64/B63 -> -0.076839074 | G64: =E64/B63 -> -0.076839074 | H64: =L64/B64 -> 1.6628552 | I64: =H64-H63 -> 0.078386507 | J64: =I64/H63 -> 0.049471794 | L64: 1.5951391 | M64: =L64-L63 -> -0.051317836 | N64: =M64/L63 -> -0.031168647 | P64: =N64/J64 -> -0.63002863 | Q64: =IF(N64>J64, "inflation", "deflation") -> deflation | R64: =IF(C64=Q64,1,0) -> 1 | S64: 0.227 | T64: =S64-S63 -> -0.025 | U64: =T64/S63 -> -0.099206349 | V64: =S64/B64 -> 0.23663649 | W64: =V64-V63 -> -0.0058758333 | X64: =W64/V63 -> -0.02422901 | Y64: =IF(X64>J64,"inflation","deflation") -> deflation | Z64: =IF(Y64=C64,1,0) -> 1 | AA64: =L64/S64 -> 7.0270447 | AB64: =AA64-AA63 -> 0.49348524 | AC64: =AB64/AA63 -> 0.075530842 | AD64: =V64*AA64 -> 1.6628552 | AE64: =AD64-AD63 -> 0.078386507 | AF64: =AE64/AD63 -> 0.049471794 | AG64: =IF(AF64>M63, "inflation", "deflation") -> inflation | AH64: =IF(AG64=C64,1,0) -> 0 | AI64: =L64-AD64 -> -0.067716018 | AJ64: =AI64-AI63 -> -0.12970434 | AK64: =AJ64-AJ63 -> -0.046146532 | AL64: =AF64/N64 -> -1.5872295 | AM64: =N64/J64 -> -0.63002863 | AN64: =C64 -> deflation
... A242: 2021 | B242: 28.426875 | C242: =IF(B242>B241,"inflation","deflation") -> inflation | D242: =IF(C242=Q242,1,0) -> 1 | E242: =B242-B241 -> 1.2413223 | F242: =E242/B241 -> 0.045661104 | G242: =E242/B241 -> 0.045661104 | H242: =L242/B242 -> 829.99033 | I242: =H242-H241 -> 45.641724 | J242: =I242/H241 -> 0.05819061 | L242: 23594.031 | M242: =L242-L241 -> 2271.081 | N242: =M242/L241 -> 0.10650876 | P242: =N242/J242 -> 1.8303428 | Q242: =IF(N242>J242, "inflation", "deflation") -> inflation | R242: =IF(C242=Q242,1,0) -> 1 | S242: 18658.012 | T242: =S242-S241 -> 3537.6709 | U242: =T242/S241 -> 0.23396765 | V242: =S242/B242 -> 656.35117 | W242: =V242-V241 -> 100.16083 | X242: =W242/V241 -> 0.18008373 | Y242: =IF(X242>J242,"inflation","deflation") -> inflation | Z242: =IF(Y242=C242,1,0) -> 1 | AA242: =L242/S242 -> 1.2645522 | AB242: =AA242-AA241 -> -0.14566394 | AC242: =AB242/AA241 -> -0.10329192 | AD242: =V242*AA242 -> 829.99033 | AE242: =AD242-AD241 -> 45.641724 | AF242: =AE242/AD241 -> 0.05819061 | AG242: =IF(AF242>M241, "inflation", "deflation") -> inflation | AH242: =IF(AG242=C242,1,0) -> 1 | AI242: =L242-AD242 -> 22764.041 | AJ242: =AI242-AI241 -> 2225.4393 | AK242: =AJ242-AJ241 -> 2405.9363 | AL242: =AF242/N242 -> 0.54634576 | AM242: =N242/J242 -> 1.8303428 | AN242: =C242 -> inflation
A243: 2022 | B243: 30.432385 | C243: =IF(B243>B242,"inflation","deflation") -> inflation | D243: =IF(C243=Q243,1,0) -> 1 | E243: =B243-B242 -> 2.0055106 | F243: =E243/B242 -> 0.070549809 | G243: =E243/B242 -> 0.070549809 | H243: =L243/B243 -> 845.94447 | I243: =H243-H242 -> 15.954142 | J243: =I243/H242 -> 0.019222082 | L243: 25744.108 | M243: =L243-L242 -> 2150.077 | N243: =M243/L242 -> 0.091128006 | P243: =N243/J243 -> 4.7407978 | Q243: =IF(N243>J243, "inflation", "deflation") -> inflation | R243: =IF(C243=Q243,1,0) -> 1 | S243: 21031.424 | T243: =S243-S242 -> 2373.4113 | U243: =T243/S242 -> 0.12720601 | W243: =V243-V242 -> -656.35117 | X243: =W243/V242 -> -1 | AB243: =AA243-AA242 -> -1.2645522 | AC243: =AB243/AA242 -> -1
B244: corr | E244: =CORREL($E$51:$E$243,E51:E243) -> 1 | G244: =CORREL($E$51:$E$243,G51:G243) -> 0.52035184 | H244: =CORREL($E$51:$E$243,H51:H243) -> 0.73450946 | I244: =CORREL($E$51:$E$243,I51:I243) -> 0.56728056 | J244: =CORREL($E$51:$E$243,J51:J243) -> -0.045446273 | L244: =CORREL($E$51:$E$243,L51:L243) -> 0.6817144 | M244: =CORREL($E$51:$E$243,M51:M243) -> 0.79900264 | N244: =CORREL($E$51:$E$243,N51:N243) -> 0.32336315 | S244: =CORREL($E$51:$E$243,S51:S243) -> 0.69099727 | T244: =CORREL($E$51:$E$243,T51:T243) -> 0.67781192 | U244: =CORREL($E$51:$E$243,U51:U243) -> 0.1505702 | V244: =CORREL($E$51:$E$243,V51:V243) -> 0.71827762 | W244: =CORREL($E$51:$E$243,W51:W243) -> -0.41374074 | X244: =CORREL($E$51:$E$243,X51:X243) -> -0.3636644 | AA244: =CORREL($E$51:$E$243,AA51:AA243) -> -0.28678426 | AB244: =CORREL($E$51:$E$243,AB51:AB243) -> -0.057622104 | AC244: =CORREL($E$51:$E$243,AC51:AC243) -> -0.21068702 | AD244: =CORREL($E$51:$E$243,AD51:AD243) -> 0.74086398 | AE244: =CORREL($E$51:$E$243,AE51:AE243) -> 0.5949133 | AF244: =CORREL($E$51:$E$243,AF51:AF243) -> -0.033228852 | AI244: =CORREL($E$51:$E$243,AI51:AI243) -> 0.63864483 | AJ244: =CORREL($E$51:$E$243,AJ51:AJ243) -> 0.73691973 | AK244: =CORREL($E$51:$E$243,AK51:AK243) -> 0.29322157 | AL244: =CORREL($E$51:$E$243,AL51:AL243) -> 0.0029490177
B245: r square | E245: =RSQ($E$51:$E$243,E51:E243) -> 1 | G245: =RSQ($E$51:$E$243,G51:G243) -> 0.27076603 | H245: =RSQ($E$51:$E$243,H51:H243) -> 0.53950415 | I245: =RSQ($E$51:$E$243,I51:I243) -> 0.32180723 | J245: =RSQ($E$51:$E$243,J51:J243) -> 0.0020653637 | L245: =RSQ($E$51:$E$243,L51:L243) -> 0.46473452 | M245: =RSQ($E$51:$E$243,M51:M243) -> 0.63840522 | N245: =RSQ($E$51:$E$243,N51:N243) -> 0.10456373 | S245: =RSQ($E$51:$E$243,S51:S243) -> 0.47747722 | T245: =RSQ($E$51:$E$243,T51:T243) -> 0.459429 | U245: =RSQ($E$51:$E$243,U51:U243) -> 0.022671386 | V245: =RSQ($E$51:$E$243,V51:V243) -> 0.51592275 | W245: =RSQ($E$51:$E$243,W51:W243) -> 0.1711814 | X245: =RSQ($E$51:$E$243,X51:X243) -> 0.1322518 | AA245: =RSQ($E$51:$E$243,AA51:AA243) -> 0.082245212 | AB245: =RSQ($E$51:$E$243,AB51:AB243) -> 0.0033203069 | AC245: =RSQ($E$51:$E$243,AC51:AC243) -> 0.04438902 | AD245: =RSQ($E$51:$E$243,AD51:AD243) -> 0.54887944 | AE245: =RSQ($E$51:$E$243,AE51:AE243) -> 0.35392183 | AF245: =RSQ($E$51:$E$243,AF51:AF243) -> 0.0011041566 | AI245: =RSQ($E$51:$E$243,AI51:AI243) -> 0.40786722 | AJ245: =RSQ($E$51:$E$243,AJ51:AJ243) -> 0.54305069 | AK245: =RSQ($E$51:$E$243,AK51:AK243) -> 0.085978891 | AL245: =RSQ($E$51:$E$243,AL51:AL243) -> 8.6967056e-06
B247: =CORREL($B$51:$B$243,B51:B243) -> 1 | E247: =CORREL($B$51:$B$243,E51:E243) -> 0.73360962 | G247: =CORREL($B$51:$B$243,G51:G243) -> 0.12029712 | H247: =CORREL($B$51:$B$243,H51:H243) -> 0.9929967 | I247: =CORREL($B$51:$B$243,I51:I243) -> 0.66497234 | J247: =CORREL($B$51:$B$243,J51:J243) -> -0.13492032 | L247: =CORREL($B$51:$B$243,L51:L243) -> 0.96491973 | M247: =CORREL($B$51:$B$243,M51:M243) -> 0.80597402 | N247: =CORREL($B$51:$B$243,N51:N243) -> -0.0053159639 | S247: =CORREL($B$51:$B$243,S51:S243) -> 0.91450977 | T247: =CORREL($B$51:$B$243,T51:T243) -> 0.68863403 | U247: =CORREL($B$51:$B$243,U51:U243) -> 0.012112444 | V247: =CORREL($B$51:$B$243,V51:V243) -> 0.96871598 | W247: =CORREL($B$51:$B$243,W51:W243) -> -0.10562692 | X247: =CORREL($B$51:$B$243,X51:X243) -> -0.17005637 | AA247: =CORREL($B$51:$B$243,AA51:AA243) -> -0.31269453 | AB247: =CORREL($B$51:$B$243,AB51:AB243) -> -0.038595275 | AC247: =CORREL($B$51:$B$243,AC51:AC243) -> -0.14661749 | AD247: =CORREL($B$51:$B$243,AD51:AD243) -> 0.99268741 | AE247: =CORREL($B$51:$B$243,AE51:AE243) -> 0.66057488 | AF247: =CORREL($B$51:$B$243,AF51:AF243) -> -0.12883002 | AI247: =CORREL($B$51:$B$243,AI51:AI243) -> 0.96240776 | AJ247: =CORREL($B$51:$B$243,AJ51:AJ243) -> 0.81616889 | AK247: =CORREL($B$51:$B$243,AK51:AK243) -> 0.13428624 | AL247: =CORREL($B$51:$B$243,AL51:AL243) -> -0.041503138
B248: =RSQ($B$51:$B$243,B51:B243) -> 1 | E248: =RSQ($B$51:$B$243,E51:E243) -> 0.53818308 | G248: =RSQ($B$51:$B$243,G51:G243) -> 0.014471397 | H248: =RSQ($B$51:$B$243,H51:H243) -> 0.98604245 | I248: =RSQ($B$51:$B$243,I51:I243) -> 0.44218821 | J248: =RSQ($B$51:$B$243,J51:J243) -> 0.018203492 | L248: =RSQ($B$51:$B$243,L51:L243) -> 0.93107008 | M248: =RSQ($B$51:$B$243,M51:M243) -> 0.64959412 | N248: =RSQ($B$51:$B$243,N51:N243) -> 2.8259472e-05 | S248: =RSQ($B$51:$B$243,S51:S243) -> 0.83632812 | T248: =RSQ($B$51:$B$243,T51:T243) -> 0.47421683 | U248: =RSQ($B$51:$B$243,U51:U243) -> 0.0001467113 | V248: =RSQ($B$51:$B$243,V51:V243) -> 0.93841065 | W248: =RSQ($B$51:$B$243,W51:W243) -> 0.011157047 | X248: =RSQ($B$51:$B$243,X51:X243) -> 0.028919167 | AA248: =RSQ($B$51:$B$243,AA51:AA243) -> 0.097777872 | AB248: =RSQ($B$51:$B$243,AB51:AB243) -> 0.0014895952 | AC248: =RSQ($B$51:$B$243,AC51:AC243) -> 0.02149669 | AD248: =RSQ($B$51:$B$243,AD51:AD243) -> 0.9854283 | AE248: =RSQ($B$51:$B$243,AE51:AE243) -> 0.43635917 | AF248: =RSQ($B$51:$B$243,AF51:AF243) -> 0.016597175 | AI248: =RSQ($B$51:$B$243,AI51:AI243) -> 0.9262287 | AJ248: =RSQ($B$51:$B$243,AJ51:AJ243) -> 0.66613165 | AK248: =RSQ($B$51:$B$243,AK51:AK243) -> 0.018032795 | AL248: =RSQ($B$51:$B$243,AL51:AL243) -> 0.0017225104
G250: =CORREL($G$51:$G$243,G51:G243) -> 1 | H250: =CORREL($G$51:$G$243,H51:H243) -> 0.13441797 | I250: =CORREL($G$51:$G$243,I51:I243) -> 0.13667555 | J250: =CORREL($G$51:$G$243,J51:J243) -> 0.14645053 | L250: =CORREL($G$51:$G$243,L51:L243) -> 0.071008787 | M250: =CORREL($G$51:$G$243,M51:M243) -> 0.13143871 | N250: =CORREL($G$51:$G$243,N51:N243) -> 0.77549859 | P250: =CORREL($G$51:$G$243,P51:P243) -> -0.094822313 | S250: =CORREL($G$51:$G$243,S51:S243) -> 0.071967767 | T250: =CORREL($G$51:$G$243,T51:T243) -> 0.086087665 | U250: =CORREL($G$51:$G$243,U51:U243) -> 0.37811689 | V250: =CORREL($G$51:$G$243,V51:V243) -> 0.11459901 | W250: =CORREL($G$51:$G$243,W51:W243) -> -0.07132468 | X250: =CORREL($G$51:$G$243,X51:X243) -> -0.094952804 | AA250: =CORREL($G$51:$G$243,AA51:AA243) -> -0.12096559 | AB250: =CORREL($G$51:$G$243,AB51:AB243) -> -0.023466098 | AC250: =CORREL($G$51:$G$243,AC51:AC243) -> 0.018348296 | AD250: =CORREL($G$51:$G$243,AD51:AD243) -> 0.12150824 | AE250: =CORREL($G$51:$G$243,AE51:AE243) -> 0.12905666 | AF250: =CORREL($G$51:$G$243,AF51:AF243) -> 0.1510443 | AI250: =CORREL($G$51:$G$243,AI51:AI243) -> 0.048065308 | AJ250: =CORREL($G$51:$G$243,AJ51:AJ243) -> 0.10791574 | AK250: =CORREL($G$51:$G$243,AK51:AK243) -> 0.046964752 | AL250: =CORREL($G$51:$G$243,AL51:AL243) -> 0.067713043
G251: =RSQ($G$51:$G$243,G51:G243) -> 1 | H251: =RSQ($G$51:$G$243,H51:H243) -> 0.018068191 | I251: =RSQ($G$51:$G$243,I51:I243) -> 0.018680205 | J251: =RSQ($G$51:$G$243,J51:J243) -> 0.021447758 | L251: =RSQ($G$51:$G$243,L51:L243) -> 0.0050422479 | M251: =RSQ($G$51:$G$243,M51:M243) -> 0.017276135 | N251: =RSQ($G$51:$G$243,N51:N243) -> 0.60139807 | P251: =RSQ($G$51:$G$243,P51:P243) -> 0.008991271 | S251: =RSQ($G$51:$G$243,S51:S243) -> 0.0051793595 | T251: =RSQ($G$51:$G$243,T51:T243) -> 0.0074110861 | U251: =RSQ($G$51:$G$243,U51:U243) -> 0.14297238 | V251: =RSQ($G$51:$G$243,V51:V243) -> 0.013132933 | W251: =RSQ($G$51:$G$243,W51:W243) -> 0.0050872099 | X251: =RSQ($G$51:$G$243,X51:X243) -> 0.009016035 | AA251: =RSQ($G$51:$G$243,AA51:AA243) -> 0.014632675 | AB251: =RSQ($G$51:$G$243,AB51:AB243) -> 0.00055065774 | AC251: =RSQ($G$51:$G$243,AC51:AC243) -> 0.00033665997 | AD251: =RSQ($G$51:$G$243,AD51:AD243) -> 0.014764253 | AE251: =RSQ($G$51:$G$243,AE51:AE243) -> 0.016655621 | AF251: =RSQ($G$51:$G$243,AF51:AF243) -> 0.02281438 | AI251: =RSQ($G$51:$G$243,AI51:AI243) -> 0.0023102738 | AJ251: =RSQ($G$51:$G$243,AJ51:AJ243) -> 0.011645807 | AK251: =RSQ($G$51:$G$243,AK51:AK243) -> 0.0022056879 | AL251: =RSQ($G$51:$G$243,AL51:AL243) -> 0.0045850561
E253: =_xlfn.CONCAT("corr ",E1," ",E244) -> corr ΔP 1 | G253: =_xlfn.CONCAT("corr ",G1," ",G244) -> corr Δ%P 0.520351835008045 | H253: =_xlfn.CONCAT("corr ",H1," ",H244) -> corr Q 0.7345094643114 | I253: =_xlfn.CONCAT("corr ",I1," ",I244) -> corr ΔQ 0.567280559072202 | J253: =_xlfn.CONCAT("corr ",J1," ",J244) -> corr Δ%Q -0.0454462729841921 | L253: =_xlfn.CONCAT("corr ",L1," ",L244) -> corr PQ 0.681714395532625 | M253: =_xlfn.CONCAT("corr ",M1," ",M244) -> corr ΔPQ 0.799002640495176 | N253: =_xlfn.CONCAT("corr ",N1," ",N244) -> corr Δ%PQ 0.323363149087258 | S253: =_xlfn.CONCAT("corr ",S1," ",S244) -> corr M 0.690997267431864 | T253: =_xlfn.CONCAT("corr ",T1," ",T244) -> corr ΔM 0.677811922287101 | U253: =_xlfn.CONCAT("corr ",U1," ",U244) -> corr Δ%M 0.150570203837533 | V253: =_xlfn.CONCAT("corr ",V1," ",V244) -> corr M(deflated) 0.718277624697209 | W253: =_xlfn.CONCAT("corr ",W1," ",W244) -> corr ΔM (delated) -0.413740737603627 | X253: =_xlfn.CONCAT("corr ",X1," ",X244) -> corr Δ%M (deflated) -0.363664400842505 | AA253: =_xlfn.CONCAT("corr ",AA1," ",AA244) -> corr V -0.286784260321955 | AB253: =_xlfn.CONCAT("corr ",AB1," ",AB244) -> corr ΔV -0.0576221044131579 | AC253: =_xlfn.CONCAT("corr ",AC1," ",AC244) -> corr Δ%V -0.210687019338379 | AD253: =_xlfn.CONCAT("corr ",AD1," ",AD244) -> corr MV 0.740863981945505 | AE253: =_xlfn.CONCAT("corr ",AE1," ",AE244) -> corr ΔMV 0.594913295133142 | AF253: =_xlfn.CONCAT("corr ",AF1," ",AF244) -> corr Δ%MV -0.0332288524581674 | AI253: =_xlfn.CONCAT("corr ",AI1," ",AI244) -> corr PQ-MV Δ 0.638644831464129 | AJ253: =_xlfn.CONCAT("corr ",AJ1," ",AJ244) -> corr PQ-MV Δ^2 0.736919731626797 | AK253: =_xlfn.CONCAT("corr ",AK1," ",AK244) -> corr PQ-MV Δ^3 0.293221572744971 | AL253: =_xlfn.CONCAT("corr ",AL1," ",AL244) -> corr Δ%MV /Δ%PQ 0.00294901774101736
E254: =_xlfn.CONCAT("rsqr ",E1," ",E245) -> rsqr ΔP 1 | G254: =_xlfn.CONCAT("rsqr ",G1," ",G245) -> rsqr Δ%P 0.270766032196239 | H254: =_xlfn.CONCAT("rsqr ",H1," ",H245) -> rsqr Q 0.53950415316302 | I254: =_xlfn.CONCAT("rsqr ",I1," ",I245) -> rsqr ΔQ 0.32180723270127 | J254: =_xlfn.CONCAT("rsqr ",J1," ",J245) -> rsqr Δ%Q 0.00206536372815371 | L254: =_xlfn.CONCAT("rsqr ",L1," ",L245) -> rsqr PQ 0.464734517076412 | M254: =_xlfn.CONCAT("rsqr ",M1," ",M245) -> rsqr ΔPQ 0.638405219518263 | N254: =_xlfn.CONCAT("rsqr ",N1," ",N245) -> rsqr Δ%PQ 0.104563726187628 | S254: =_xlfn.CONCAT("rsqr ",S1," ",S245) -> rsqr M 0.477477223598303 | T254: =_xlfn.CONCAT("rsqr ",T1," ",T245) -> rsqr ΔM 0.459429001994535 | U254: =_xlfn.CONCAT("rsqr ",U1," ",U245) -> rsqr Δ%M 0.0226713862836763 | V254: =_xlfn.CONCAT("rsqr ",V1," ",V245) -> rsqr M(deflated) 0.515922746140664 | W254: =_xlfn.CONCAT("rsqr ",W1," ",W245) -> rsqr ΔM (delated) 0.171181397952794 | X254: =_xlfn.CONCAT("rsqr ",X1," ",X245) -> rsqr Δ%M (deflated) 0.132251796440138 | AA254: =_xlfn.CONCAT("rsqr ",AA1," ",AA245) -> rsqr V 0.0822452119684109 | AB254: =_xlfn.CONCAT("rsqr ",AB1," ",AB245) -> rsqr ΔV 0.00332030691700087 | AC254: =_xlfn.CONCAT("rsqr ",AC1," ",AC245) -> rsqr Δ%V 0.0443890201176904 | AD254: =_xlfn.CONCAT("rsqr ",AD1," ",AD245) -> rsqr MV 0.54887943974415 | AE254: =_xlfn.CONCAT("rsqr ",AE1," ",AE245) -> rsqr ΔMV 0.353921828726173 | AF254: =_xlfn.CONCAT("rsqr ",AF1," ",AF245) -> rsqr Δ%MV 0.00110415663568666 | AI254: =_xlfn.CONCAT("rsqr ",AI1," ",AI245) -> rsqr PQ-MV Δ 0.407867220755845 | AJ254: =_xlfn.CONCAT("rsqr ",AJ1," ",AJ245) -> rsqr PQ-MV Δ^2 0.543050690860911 | AK254: =_xlfn.CONCAT("rsqr ",AK1," ",AK245) -> rsqr PQ-MV Δ^3 0.0859788907230343 | AL254: =_xlfn.CONCAT("rsqr ",AL1," ",AL245) -> rsqr Δ%MV /Δ%PQ 8.69670563683515E-06
B255: =_xlfn.CONCAT("corr ",B1," ",B247) -> corr P 1 | E255: =_xlfn.CONCAT("corr ",E1," ",E247) -> corr ΔP 0.733609622967883 | G255: =_xlfn.CONCAT("corr ",G1," ",G247) -> corr Δ%P 0.120297118751269 | H255: =_xlfn.CONCAT("corr ",H1," ",H247) -> corr Q 0.992996700985854 | I255: =_xlfn.CONCAT("corr ",I1," ",I247) -> corr ΔQ 0.664972337475932 | J255: =_xlfn.CONCAT("corr ",J1," ",J247) -> corr Δ%Q -0.13492031551906 | L255: =_xlfn.CONCAT("corr ",L1," ",L247) -> corr PQ 0.964919727854628 | M255: =_xlfn.CONCAT("corr ",M1," ",M247) -> corr ΔPQ 0.805974019774217 | N255: =_xlfn.CONCAT("corr ",N1," ",N247) -> corr Δ%PQ -0.00531596388587504 | S255: =_xlfn.CONCAT("corr ",S1," ",S247) -> corr M 0.914509770668337 | T255: =_xlfn.CONCAT("corr ",T1," ",T247) -> corr ΔM 0.688634033323631 | U255: =_xlfn.CONCAT("corr ",U1," ",U247) -> corr Δ%M 0.0121124441714978 | V255: =_xlfn.CONCAT("corr ",V1," ",V247) -> corr M(deflated) 0.968715979381992 | W255: =_xlfn.CONCAT("corr ",W1," ",W247) -> corr ΔM (delated) -0.105626922522456 | X255: =_xlfn.CONCAT("corr ",X1," ",X247) -> corr Δ%M (deflated) -0.170056365627957 | AA255: =_xlfn.CONCAT("corr ",AA1," ",AA247) -> corr V -0.312694534754681 | AB255: =_xlfn.CONCAT("corr ",AB1," ",AB247) -> corr ΔV -0.0385952749464439 | AC255: =_xlfn.CONCAT("corr ",AC1," ",AC247) -> corr Δ%V -0.146617494537794 | AD255: =_xlfn.CONCAT("corr ",AD1," ",AD247) -> corr MV 0.992687412978141 | AE255: =_xlfn.CONCAT("corr ",AE1," ",AE247) -> corr ΔMV 0.660574879292389 | AF255: =_xlfn.CONCAT("corr ",AF1," ",AF247) -> corr Δ%MV -0.128830024232057 | AI255: =_xlfn.CONCAT("corr ",AI1," ",AI247) -> corr PQ-MV Δ 0.962407764101504 | AJ255: =_xlfn.CONCAT("corr ",AJ1," ",AJ247) -> corr PQ-MV Δ^2 0.816168887697467 | AK255: =_xlfn.CONCAT("corr ",AK1," ",AK247) -> corr PQ-MV Δ^3 0.134286242247919 | AL255: =_xlfn.CONCAT("corr ",AL1," ",AL247) -> corr Δ%MV /Δ%PQ -0.0415031377074798
B256: =_xlfn.CONCAT("rsqr ",B1," ",B248) -> rsqr P 1 | E256: =_xlfn.CONCAT("rsqr ",E1," ",E248) -> rsqr ΔP 0.538183078911079 | G256: =_xlfn.CONCAT("rsqr ",G1," ",G248) -> rsqr Δ%P 0.0144713967798569 | H256: =_xlfn.CONCAT("rsqr ",H1," ",H248) -> rsqr Q 0.986042448168789 | I256: =_xlfn.CONCAT("rsqr ",I1," ",I248) -> rsqr ΔQ 0.442188209608205 | J256: =_xlfn.CONCAT("rsqr ",J1," ",J248) -> rsqr Δ%Q 0.0182034915397627 | L256: =_xlfn.CONCAT("rsqr ",L1," ",L248) -> rsqr PQ 0.93107008120305 | M256: =_xlfn.CONCAT("rsqr ",M1," ",M248) -> rsqr ΔPQ 0.64959412055101 | N256: =_xlfn.CONCAT("rsqr ",N1," ",N248) -> rsqr Δ%PQ 2.82594720359277E-05 | S256: =_xlfn.CONCAT("rsqr ",S1," ",S248) -> rsqr M 0.836328120647855 | T256: =_xlfn.CONCAT("rsqr ",T1," ",T248) -> rsqr ΔM 0.474216831851571 | U256: =_xlfn.CONCAT("rsqr ",U1," ",U248) -> rsqr Δ%M 0.000146711303807651 | V256: =_xlfn.CONCAT("rsqr ",V1," ",V248) -> rsqr M(deflated) 0.938410648710011 | W256: =_xlfn.CONCAT("rsqr ",W1," ",W248) -> rsqr ΔM (delated) 0.0111570467615649 | X256: =_xlfn.CONCAT("rsqr ",X1," ",X248) -> rsqr Δ%M (deflated) 0.0289191674905893 | AA256: =_xlfn.CONCAT("rsqr ",AA1," ",AA248) -> rsqr V 0.0977778720654462 | AB256: =_xlfn.CONCAT("rsqr ",AB1," ",AB248) -> rsqr ΔV 0.0014895952481916 | AC256: =_xlfn.CONCAT("rsqr ",AC1," ",AC248) -> rsqr Δ%V 0.02149668970454 | AD256: =_xlfn.CONCAT("rsqr ",AD1," ",AD248) -> rsqr MV 0.985428299885235 | AE256: =_xlfn.CONCAT("rsqr ",AE1," ",AE248) -> rsqr ΔMV 0.436359171152154 | AF256: =_xlfn.CONCAT("rsqr ",AF1," ",AF248) -> rsqr Δ%MV 0.0165971751436323 | AI256: =_xlfn.CONCAT("rsqr ",AI1," ",AI248) -> rsqr PQ-MV Δ 0.926228704402857 | AJ256: =_xlfn.CONCAT("rsqr ",AJ1," ",AJ248) -> rsqr PQ-MV Δ^2 0.66613165324532 | AK256: =_xlfn.CONCAT("rsqr ",AK1," ",AK248) -> rsqr PQ-MV Δ^3 0.0180327948570669 | AL256: =_xlfn.CONCAT("rsqr ",AL1," ",AL248) -> rsqr Δ%MV /Δ%PQ 0.00172251043956603

Sheet PQ
A1: Data Source | B1: World Development Indicators
A3: Last Updated Date | B3: 45937
A5: Country Name | B5: Country Code | C5: Indicator Name | D5: Indicator Code | E5: 1960 | F5: 1961 | G5: 1962 | H5: 1963 | I5: 1964 | J5: 1965 | K5: 1966 | L5: 1967 | M5: 1968 | N5: 1969 | O5: 1970 | P5: 1971 | Q5: 1972 | R5: 1973 | S5: 1974 | T5: 1975 | U5: 1976 | V5: 1977 | W5: 1978 | X5: 1979 | Y5: 1980 | Z5: 1981 | AA5: 1982 | AB5: 1983 | AC5: 1984 | AD5: 1985 | AE5: 1986 | AF5: 1987 | AG5: 1988 | AH5: 1989 | AI5: 1990 | AJ5: 1991 | AK5: 1992 | AL5: 1993 | AM5: 1994 | AN5: 1995 | AO5: 1996 | AP5: 1997 | AQ5: 1998 | AR5: 1999 | AS5: 2000 | AT5: 2001 | AU5: 2002 | AV5: 2003 | AW5: 2004 | AX5: 2005 | AY5: 2006 | AZ5: 2007 | BA5: 2008 | BB5: 2009 | BC5: 2010 | BD5: 2011 | BE5: 2012 | BF5: 2013 | BG5: 2014 | BH5: 2015 | BI5: 2016 | BJ5: 2017 | BK5: 2018 | BL5: 2019 | BM5: 2020 | BN5: 2021 | BO5: 2022 | BP5: 2023 | BQ5: 2024
A6: Aruba | B6: ABW | C6: GDP (current US$) | D6: NY.GDP.MKTP.CD | AE6: 4.0558659e+08 | AF6: 4.877095e+08 | AG6: 5.9664804e+08 | AH6: 6.9553073e+08 | AI6: 7.6480447e+08 | AJ6: 8.7206704e+08 | AK6: 9.5865922e+08 | AL6: 1.0832402e+09 | AM6: 1.2458101e+09 | AN6: 1.3206704e+09 | AO6: 1.3798883e+09 | AP6: 1.5318436e+09 | AQ6: 1.6653631e+09 | AR6: 1.722905e+09 | AS6: 1.8734525e+09 | AT6: 1.896457e+09 | AU6: 1.9618436e+09 | AV6: 2.0441117e+09 | AW6: 2.2548307e+09 | AX6: 2.3600173e+09 | AY6: 2.4697827e+09 | AZ6: 2.6776413e+09 | BA6: 2.8430246e+09 | BB6: 2.5537933e+09 | BC6: 2.4535972e+09 | BD6: 2.6378592e+09 | BE6: 2.6152084e+09 | BF6: 2.7278497e+09 | BG6: 2.7908497e+09 | BH6: 2.9629073e+09 | BI6: 2.9836352e+09 | BJ6: 3.0924291e+09 | BK6: 3.2761844e+09 | BL6: 3.3957989e+09 | BM6: 2.4818571e+09 | BN6: 2.9294466e+09 | BO6: 3.2793435e+09 | BP6: 3.6485731e+09
A7: Africa Eastern and Southern | B7: AFE | C7: GDP (current US$) | D7: NY.GDP.MKTP.CD | E7: 2.4209933e+10 | F7: 2.4963256e+10 | G7: 2.7078015e+10 | H7: 3.1774831e+10 | I7: 3.0284919e+10 | J7: 3.3812194e+10 | K7: 3.6933908e+10 | L7: 3.845106e+10 | M7: 4.1749511e+10 | N7: 4.7056942e+10 | O7: 4.7602358e+10 | P7: 5.2197888e+10 | Q7: 5.6735886e+10 | R7: 7.309634e+10 | S7: 8.9551627e+10 | T7: 9.5312337e+10 | U7: 9.6023172e+10 | V7: 1.0922761e+11 | W7: 1.2410577e+11 | X7: 1.4212544e+11 | Y7: 1.785042e+11 | Z7: 1.851578e+11 | AA7: 1.7839994e+11 | AB7: 1.8581721e+11 | AC7: 1.7009517e+11 | AD7: 1.4939385e+11 | AE7: 1.6063306e+11 | AF7: 1.9026904e+11 | AG7: 2.0746433e+11 | AH7: 2.207061e+11 | AI7: 2.565049e+11 | AJ7: 2.770434e+11 | AK7: 2.4129787e+11 | AL7: 2.4009476e+11 | AM7: 2.4357114e+11 | AN7: 2.7343317e+11 | AO7: 2.7353099e+11 | AP7: 2.8837768e+11 | AQ7: 2.6883347e+11 | AR7: 2.6542929e+11 | AS7: 2.8720165e+11 | AT7: 2.6099223e+11 | AU7: 2.6781504e+11 | AV7: 3.5571637e+11 | AW7: 4.4269619e+11 | AX7: 5.1666107e+11 | AY7: 5.8024075e+11 | AZ7: 6.655987e+11 | BA7: 7.1350211e+11 | BB7: 7.1548535e+11 | BC7: 8.4940961e+11 | BD7: 9.4543903e+11 | BE7: 9.5299847e+11 | BF7: 9.6244129e+11 | BG7: 9.7874376e+11 | BH7: 8.9830885e+11 | BI7: 8.2896117e+11 | BJ7: 9.7302513e+11 | BK7: 1.0122912e+12 | BL7: 1.0097465e+12 | BM7: 9.3340723e+11 | BN7: 1.0856049e+12 | BO7: 1.1916386e+12 | BP7: 1.1338183e+12 | BQ7: 1.2059738e+12
A8: Afghanistan | B8: AFG | C8: GDP (current US$) | D8: NY.GDP.MKTP.CD | AS8: 3.5214181e+09 | AT8: 2.8135718e+09 | AU8: 3.8257014e+09 | AV8: 4.5209468e+09 | AW8: 5.2248967e+09 | AX8: 6.2032565e+09 | AY8: 6.9717583e+09 | AZ8: 9.7478862e+09 | BA8: 1.0109297e+10 | BB8: 1.2416153e+10 | BC8: 1.5856669e+10 | BD8: 1.7805098e+10 | BE8: 1.990733e+10 | BF8: 2.0146417e+10 | BG8: 2.0497129e+10 | BH8: 1.9134222e+10 | BI8: 1.8116572e+10 | BJ8: 1.8753456e+10 | BK8: 1.8053223e+10 | BL8: 1.8799444e+10 | BM8: 1.9955929e+10 | BN8: 1.4259995e+10 | BO8: 1.4497244e+10 | BP8: 1.7152235e+10
A9: Africa Western and Central | B9: AFW | C9: GDP (current US$) | D9: NY.GDP.MKTP.CD | E9: 1.1905108e+10 | F9: 1.2708033e+10 | G9: 1.3630921e+10 | H9: 1.4469258e+10 | I9: 1.5803937e+10 | J9: 1.6921238e+10 | K9: 1.8034329e+10 | L9: 1.6493846e+10 | M9: 1.7022944e+10 | N9: 1.9301602e+10 | O9: 2.6697431e+10 | P9: 2.4497038e+10 | Q9: 2.9489667e+10 | R9: 3.6891335e+10 | S9: 4.9688194e+10 | T9: 5.7280848e+10 | U9: 6.838632e+10 | V9: 7.1790695e+10 | W9: 7.87791e+10 | X9: 9.6682239e+10 | Y9: 1.2050108e+11 | Z9: 2.1691103e+11 | AA9: 1.9591794e+11 | AB9: 1.5122276e+11 | AC9: 1.3121816e+11 | AD9: 1.3780292e+11 | AE9: 1.09237e+11 | AF9: 1.1229477e+11 | AG9: 1.1122715e+11 | AH9: 1.0393437e+11 | AI9: 1.2371132e+11 | AJ9: 1.2994188e+11 | AK9: 1.2459933e+11 | AL9: 1.297326e+11 | AM9: 1.3477683e+11 | AN9: 2.0717697e+11 | AO9: 2.6260087e+11 | AP9: 2.7574225e+11 | AQ9: 2.9615243e+11 | AR9: 1.3946835e+11 | AS9: 1.4214008e+11 | AT9: 1.5005848e+11 | AU9: 1.7939007e+11 | AV9: 2.0775499e+11 | AW9: 2.5856666e+11 | AX9: 3.1709648e+11 | AY9: 4.0272422e+11 | AZ9: 4.7153781e+11 | BA9: 5.7505945e+11 | BB9: 5.1547403e+11 | BC9: 6.0628011e+11 | BD9: 6.9118746e+11 | BE9: 7.4812685e+11 | BF9: 8.4420257e+11 | BG9: 9.0393368e+11 | BH9: 7.7802206e+11 | BI9: 7.0002817e+11 | BJ9: 6.9405134e+11 | BK9: 7.7784041e+11 | BL9: 8.332889e+11 | BM9: 7.9729518e+11 | BN9: 8.5811451e+11 | BO9: 8.9363994e+11 | BP9: 8.1472853e+11 | BQ9: 6.7002566e+11
A10: Angola | B10: AGO | C10: GDP (current US$) | D10: NY.GDP.MKTP.CD | Y10: 5.9305034e+09 | Z10: 5.550483e+09 | AA10: 5.550483e+09 | AB10: 5.7843416e+09 | AC10: 6.1314751e+09 | AD10: 7.5540654e+09 | AE10: 7.0725361e+09 | AF10: 8.0844124e+09 | AG10: 8.7698368e+09 | AH10: 1.0201781e+10 | AI10: 1.1229516e+10 | AJ10: 1.0603785e+10 | AK10: 8.307811e+09 | AL10: 5.7687204e+09 | AM10: 4.438321e+09 | AN10: 5.5387493e+09 | AO10: 7.5264215e+09 | AP10: 7.6483802e+09 | AQ10: 6.5062216e+09 | AR10: 6.1529233e+09 | AS10: 9.129595e+09 | AT10: 8.9360791e+09 | AU10: 1.5285592e+10 | AV10: 1.7812705e+10 | AW10: 2.3552058e+10 | AX10: 3.6970901e+10 | AY10: 5.2381025e+10 | AZ10: 6.5266415e+10 | BA10: 8.8538665e+10 | BB10: 7.0307196e+10 | BC10: 8.3799474e+10 | BD10: 1.1178975e+11 | BE10: 1.2805292e+11 | BF10: 1.3233911e+11 | BG10: 1.359668e+11 | BH10: 9.0496421e+10 | BI10: 5.2761617e+10 | BJ10: 7.3690155e+10 | BK10: 7.9450688e+10 | BL10: 7.0897963e+10 | BM10: 4.8501561e+10 | BN10: 6.650513e+10 | BO10: 1.0439975e+11 | BP10: 8.4875162e+10 | BQ10: 8.0396942e+10
A11: Albania | B11: ALB | C11: GDP (current US$) | D11: NY.GDP.MKTP.CD | Y11: 1.5781021e+09 | Z11: 1.8081772e+09 | AA11: 1.8611632e+09 | AB11: 1.8814126e+09 | AC11: 1.857338e+09 | AD11: 1.8970501e+09 | AE11: 2097326250 | AF11: 2080796250 | AG11: 2051236250 | AH11: 2253090000 | AI11: 2028553750 | AJ11: 1.099559e+09 | AK11: 6.5217499e+08 | AL11: 1.1853155e+09 | AM11: 1.8809509e+09 | AN11: 2.9050928e+09 | AO11: 3.2344862e+09 | AP11: 2.293666e+09 | AQ11: 2.600357e+09 | AR11: 3.2839415e+09 | AS11: 3.5845702e+09 | AT11: 4.059064e+09 | AU11: 4.5150031e+09 | AV11: 5.801712e+09 | AW11: 7.4066458e+09 | AX11: 8.2566582e+09 | AY11: 9.1505281e+09 | AZ11: 1.1116938e+10 | BA11: 1.3258506e+10 | BB11: 1.2335541e+10 | BC11: 1.2086546e+10 | BD11: 1.2973756e+10 | BE11: 1.22465e+10 | BF11: 1.2796986e+10 | BG11: 1.3296323e+10 | BH11: 1.1470172e+10 | BI11: 1.1988669e+10 | BJ11: 1.3258268e+10 | BK11: 1.5379508e+10 | BL11: 1.5585112e+10 | BM11: 1.5241456e+10 | BN11: 1.8032009e+10 | BO11: 1.9017244e+10 | BP11: 2.354718e+10 | BQ11: 2.7177736e+10
A12: Andorra | B12: AND | C12: GDP (current US$) | D12: NY.GDP.MKTP.CD | O12: 78617711 | P12: 89406608 | Q12: 1.134144e+08 | R12: 1.5084164e+08 | S12: 1.8655708e+08 | T12: 2.2011257e+08 | U12: 2.2728385e+08 | V12: 2.539979e+08 | W12: 3.0802026e+08 | X12: 4.1154875e+08 | Y12: 4.4637778e+08 | Z12: 3.8898327e+08 | AA12: 3.7591474e+08 | AB12: 3.2785004e+08 | AC12: 3.3007308e+08 | AD12: 3.4674271e+08 | AE12: 4.8199601e+08 | AF12: 6.1129992e+08 | AG12: 7.2142594e+08 | AH12: 7.9548958e+08 | AI12: 1.0289897e+09 | AJ12: 1.1068914e+09 | AK12: 1.209992e+09 | AL12: 1.0070903e+09 | AM12: 1.0175441e+09 | AN12: 1.1787453e+09 | AO12: 1.2240241e+09 | AP12: 1.1806456e+09 | AQ12: 1.211954e+09 | AR12: 1.2402951e+09 | AS12: 1.4326062e+09 | AT12: 1.5482658e+09 | AU12: 1.7642798e+09 | AV12: 2.3669418e+09 | AW12: 2.9002453e+09 | AX12: 3.1610841e+09 | AY12: 3.459338e+09 | AZ12: 3.9576254e+09 | BA12: 4.1023194e+09 | BB12: 3.6889763e+09 | BC12: 3.4499257e+09 | BD12: 3.6291336e+09 | BE12: 3.1886528e+09 | BF12: 3.193513e+09 | BG12: 3.2716856e+09 | BH12: 2.7898813e+09 | BI12: 2.8966105e+09 | BJ12: 3.0001621e+09 | BK12: 3.2184199e+09 | BL12: 3.1551493e+09 | BM12: 2.8910011e+09 | BN12: 3.3246475e+09 | BO12: 3.3806126e+09 | BP12: 3.7850673e+09 | BQ12: 4.0398444e+09
A13: Arab World | B13: ARB | C13: GDP (current US$) | D13: NY.GDP.MKTP.CD | F13: 1.9997084e+10 | G13: 2.0327671e+10 | H13: 2.2362958e+10 | I13: 2.4811627e+10 | J13: 2.676929e+10 | K13: 2.8349127e+10 | L13: 3.0598798e+10 | M13: 3.4970677e+10 | N13: 3.8561008e+10 | O13: 4.3091222e+10 | P13: 4.9926771e+10 | Q13: 5.9966658e+10 | R13: 7.9125368e+10 | S13: 1.5218873e+11 | T13: 1.6815858e+11 | U13: 2.0999335e+11 | V13: 2.4227039e+11 | W13: 2.6539824e+11 | X13: 3.581113e+11 | Y13: 4.8640583e+11 | Z13: 4.9491642e+11 | AA13: 4.6308047e+11 | AB13: 4.3747118e+11 | AC13: 4.4018215e+11 | AD13: 4.328682e+11 | AE13: 4.054732e+11 | AF13: 4.3125767e+11 | AG13: 4.2938283e+11 | AH13: 4.5736906e+11 | AI13: 6.4171224e+11 | AJ13: 4.6795289e+11 | AK13: 4.6779432e+11 | AL13: 4.7892702e+11 | AM13: 4.9988012e+11 | AN13: 5.2848049e+11 | AO13: 5.7090972e+11 | AP13: 6.1459697e+11 | AQ13: 5.9878959e+11 | AR13: 6.6541537e+11 | AS13: 7.6341164e+11 | AT13: 7.4472854e+11 | AU13: 7.4664926e+11 | AV13: 8.3007647e+11 | AW13: 9.8731601e+11 | AX13: 1.2100804e+12 | AY13: 1.439471e+12 | AZ13: 1.674641e+12 | BA13: 2.1180711e+12 | BB13: 1.8298496e+12 | BC13: 2.1553453e+12 | BD13: 2565019402570 | BE13: 2.8053842e+12 | BF13: 2.8742756e+12 | BG13: 2.926205e+12 | BH13: 2.5686311e+12 | BI13: 2.5241029e+12 | BJ13: 2.5984755e+12 | BK13: 2.9073296e+12 | BL13: 2.949355e+12 | BM13: 2.5964226e+12 | BN13: 3.0779065e+12 | BO13: 3.7385845e+12 | BP13: 3.6060023e+12 | BQ13: 3.7047683e+12
A14: United Arab Emirates | B14: ARE | C14: GDP (current US$) | D14: NY.GDP.MKTP.CD | O14: 6.859867e+08 | P14: 9.398936e+08 | Q14: 1.4150869e+09 | R14: 4.2312436e+09 | S14: 1.1651506e+10 | T14: 1.4720728e+10 | U14: 1.9213159e+10 | V14: 2.4871775e+10 | W14: 2.3775764e+10 | X14: 3.122566e+10 | Y14: 4.359916e+10 | Z14: 4.9333424e+10 | AA14: 4.6622719e+10 | AB14: 4.2803323e+10 | AC14: 4.1807954e+10 | AD14: 4.060365e+10 | AE14: 3.3943612e+10 | AF14: 3.6384909e+10 | AG14: 3.6275674e+10 | AH14: 4.1464996e+10 | AI14: 5.0701444e+10 | AJ14: 5.1552166e+10 | AK14: 5.4239172e+10 | AL14: 5.562517e+10 | AM14: 5.9305094e+10 | AN14: 6.5743667e+10 | AO14: 7.3571234e+10 | AP14: 7.8839008e+10 | AQ14: 7.5674336e+10 | AR14: 8.4445473e+10 | AS14: 1.0433737e+11 | AT14: 1.0331164e+11 | AU14: 1.098162e+11 | AV14: 1.2434636e+11 | AW14: 1.4782437e+11 | AX14: 1.8061747e+11 | AY14: 2.2211654e+11 | AZ14: 2.5791613e+11 | BA14: 3.1547462e+11 | BB14: 2.5354736e+11 | BC14: 3.0018905e+11 | BD14: 3.6083274e+11 | BE14: 3.8461013e+11 | BF14: 4.0021853e+11 | BG14: 4.1410537e+11 | BH14: 3.7027547e+11 | BI14: 3.6925533e+11 | BJ14: 3.905168e+11 | BK14: 4.2704943e+11 | BL14: 4.1798972e+11 | BM14: 3.4947302e+11 | BN14: 4.1517879e+11 | BO14: 5.0273194e+11 | BP14: 5.1413043e+11 | BQ14: 5.3707883e+11
A15: Argentina | B15: ARG | C15: GDP (current US$) | D15: NY.GDP.MKTP.CD | E15: 1.5865474e+10 | F15: 2.013222e+10 | G15: 1.8337691e+10 | H15: 1.8272124e+10 | I15: 2.5605249e+10 | J15: 2.8344706e+10 | K15: 2.8630475e+10 | L15: 2.4256668e+10 | M15: 2.6436857e+10 | N15: 3.1256285e+10 | O15: 3.158421e+10 | P15: 3.3293199e+10 | Q15: 3.4733001e+10 | R15: 5.2544e+10 | S15: 7.2436777e+10 | T15: 5.2438648e+10 | U15: 5.11695e+10 | V15: 5.6781e+10 | W15: 8.9049453e+10 | X15: 6.9252329e+10 | Y15: 7.6961924e+10 | Z15: 7.8676842e+10 | AA15: 8.4307487e+10 | AB15: 1.0397911e+11 | AC15: 1.1691505e+11 | AD15: 8.8150892e+10 | AE15: 1.0587237e+11 | AF15: 1.0881089e+11 | AG15: 1.2689024e+11 | AH15: 7.6629729e+10 | AI15: 1.4135265e+11 | AJ15: 1.8971998e+11 | AK15: 2.2877892e+11 | AL15: 2.3674172e+11 | AM15: 257440000000 | AN15: 258031750000 | AO15: 272149750000 | AP15: 292859000000 | AQ15: 298948250000 | AR15: 283523000000 | AS15: 284203750000 | AT15: 268696750000 | AU15: 9.7724004e+10 | AV15: 1.2758697e+11 | AW15: 1.6465793e+11 | AX15: 1.987371e+11 | AY15: 2.3255726e+11 | AZ15: 2.8753051e+11 | BA15: 3.6155804e+11 | BB15: 3.3297648e+11 | BC15: 4.2362742e+11 | BD15: 5.3015812e+11 | BE15: 5.4598238e+11 | BF15: 5.5202514e+11 | BG15: 5.2631967e+11 | BH15: 5.9474929e+11 | BI15: 5.5753232e+11 | BJ15: 6.4362839e+11 | BK15: 5.2481989e+11 | BL15: 4.4775468e+11 | BM15: 3.8574051e+11 | BN15: 4.8656409e+11 | BO15: 6.3279007e+11 | BP15: 6.4607528e+11 | BQ15: 6.3326669e+11
A16: Armenia | B16: ARM | C16: GDP (current US$) | D16: NY.GDP.MKTP.CD | AI16: 2.2568634e+09 | AJ16: 2.0698701e+09 | AK16: 1.2728355e+09 | AL16: 1.2013128e+09 | AM16: 1.3151586e+09 | AN16: 1.4683174e+09 | AO16: 1.5969689e+09 | AP16: 1.6394924e+09 | AQ16: 1.8937264e+09 | AR16: 1.8454822e+09 | AS16: 1.9115637e+09 | AT16: 2.1184679e+09 | AU16: 2.376335e+09 | AV16: 2.807061e+09 | AW16: 3.5766152e+09 | AX16: 4.9004695e+09 | AY16: 6.3844521e+09 | AZ16: 9.2063013e+09 | BA16: 1.1662041e+10 | BB16: 8.6479371e+09 | BC16: 9.2602858e+09 | BD16: 1.0142112e+10 | BE16: 1.0619321e+10 | BF16: 1.1121464e+10 | BG16: 1.1609513e+10 | BH16: 1.0553338e+10 | BI16: 1.0546136e+10 | BJ16: 1.1527459e+10 | BK16: 1.2457941e+10 | BL16: 1.3619291e+10 | BM16: 1.2641699e+10 | BN16: 1.3878909e+10 | BO16: 1.9513507e+10 | BP16: 2.408575e+10 | BQ16: 2.5786586e+10
A17: American Samoa | B17: ASM | C17: GDP (current US$) | D17: NY.GDP.MKTP.CD | AU17: 512000000 | AV17: 524000000 | AW17: 509000000 | AX17: 500000000 | AY17: 493000000 | AZ17: 518000000 | BA17: 560000000 | BB17: 675000000 | BC17: 573000000 | BD17: 570000000 | BE17: 640000000 | BF17: 638000000 | BG17: 643000000 | BH17: 673000000 | BI17: 671000000 | BJ17: 612000000 | BK17: 639000000 | BL17: 647000000 | BM17: 721000000 | BN17: 750000000 | BO17: 871000000
A18: Antigua and Barbuda | B18: ATG | C18: GDP (current US$) | D18: NY.GDP.MKTP.CD | V18: 77507407 | W18: 88040741 | X18: 1.095963e+08 | Y18: 1.3245185e+08 | Z18: 1.4938889e+08 | AA18: 1.6644444e+08 | AB18: 1.8486667e+08 | AC18: 2.1221481e+08 | AD18: 2.4637037e+08 | AE18: 2.9756296e+08 | AF18: 3.4686667e+08 | AG18: 4.113963e+08 | AH18: 4.5517407e+08 | AI18: 4.7871852e+08 | AJ18: 5.0433704e+08 | AK18: 5.2513333e+08 | AL18: 5.6566296e+08 | AM18: 6.2508148e+08 | AN18: 6.1605185e+08 | AO18: 6.7914074e+08 | AP18: 7.3442222e+08 | AQ18: 7.8978889e+08 | AR18: 8.3554444e+08 | AS18: 9.010037e+08 | AT18: 8.7777407e+08 | AU18: 8.9809259e+08 | AV18: 948100000 | AW18: 1.0263296e+09 | AX18: 1.1438963e+09 | AY18: 1.3036741e+09 | AZ18: 1.4873815e+09 | BA18: 1.5576407e+09 | BB18: 1.3865185e+09 | BC18: 1.2983481e+09 | BD18: 1.2873593e+09 | BE18: 1.3647296e+09 | BF18: 1.3254963e+09 | BG18: 1.3787074e+09 | BH18: 1.4374852e+09 | BI18: 1.4896037e+09 | BJ18: 1.5348556e+09 | BK18: 1.6615296e+09 | BL18: 1.7264481e+09 | BM18: 1.411637e+09 | BN18: 1.6021259e+09 | BO18: 1.8665667e+09 | BP18: 2.0057852e+09 | BQ18: 2.2248148e+09
A19: Australia | B19: AUS | C19: GDP (current US$) | D19: NY.GDP.MKTP.CD | E19: 1.8607683e+10 | F19: 1.9684003e+10 | G19: 1.9923683e+10 | H19: 2.1540963e+10 | I19: 2.3801124e+10 | J19: 2.5977284e+10 | K19: 2.7308964e+10 | L19: 3.0442725e+10 | M19: 3.2714085e+10 | N19: 3.6684486e+10 | O19: 4.1334727e+10 | P19: 4.5217767e+10 | Q19: 5.2042056e+10 | R19: 6.383344e+10 | S19: 8.8965365e+10 | T19: 9.7304383e+10 | U19: 1.0506062e+11 | V19: 1.1035214e+11 | W19: 1.1849276e+11 | X19: 1.349006e+11 | Y19: 1.4998774e+11 | Z19: 1.7689539e+11 | AA19: 1.9404171e+11 | AB19: 1.7726729e+11 | AC19: 1.9352534e+11 | AD19: 1.8064327e+11 | AE19: 1.8248111e+11 | AF19: 1.8949576e+11 | AG19: 2.3616131e+11 | AH19: 2.9987591e+11 | AI19: 3.1142667e+11 | AJ19: 3.2597532e+11 | AK19: 3.2552538e+11 | AL19: 3.1213392e+11 | AM19: 3.2280664e+11 | AN19: 3.6816602e+11 | AO19: 4.0134188e+11 | AP19: 4.3564261e+11 | AQ19: 3.9967442e+11 | AR19: 3.8965221e+11 | AS19: 4.1616782e+11 | AT19: 3.796293e+11 | AU19: 3.957887e+11 | AV19: 4.6773908e+11 | AW19: 6.1465998e+11 | AX19: 6.956929e+11 | AY19: 7.4841756e+11 | AZ19: 8.5500746e+11 | BA19: 1.0561124e+12 | BB19: 9.2876212e+11 | BC19: 1.1488382e+12 | BD19: 1.3986106e+12 | BE19: 1.5475323e+12 | BF19: 1.5771233e+12 | BG19: 1.4682654e+12 | BH19: 1.3512964e+12 | BI19: 1.206837e+12 | BJ19: 1.3255827e+12 | BK19: 1.427809e+12 | BL19: 1.3927238e+12 | BM19: 1.3284141e+12 | BN19: 1.5567358e+12 | BO19: 1.6908582e+12 | BP19: 1.7280573e+12 | BQ19: 1.7521933e+12
A20: Austria | B20: AUT | C20: GDP (current US$) | D20: NY.GDP.MKTP.CD | E20: 6.6240863e+09 | F20: 7.346566e+09 | G20: 7.7930425e+09 | H20: 8.4140506e+09 | I20: 9.2136487e+09 | J20: 1.0041659e+10 | K20: 1.0939526e+10 | L20: 1.163457e+10 | M20: 1.2499864e+10 | N20: 1.3647476e+10 | O20: 1.5312792e+10 | P20: 1.7788537e+10 | Q20: 2.1973208e+10 | R20: 2.939986e+10 | S20: 3.5051469e+10 | T20: 3.9902301e+10 | U20: 4.2791707e+10 | V20: 5.1343861e+10 | W20: 6.1809209e+10 | X20: 7.3647694e+10 | Y20: 8.1737498e+10 | Z20: 7.0755997e+10 | AA20: 7.0996112e+10 | AB20: 7.1838528e+10 | AC20: 6.7719056e+10 | AD20: 6.9114996e+10 | AE20: 9.8648254e+10 | AF20: 1.2368209e+11 | AG20: 1.3281712e+11 | AH20: 1.3258445e+11 | AI20: 1.6581137e+11 | AJ20: 1.7311345e+11 | AK20: 1.9431403e+11 | AL20: 1.8963403e+11 | AM20: 2.0273802e+11 | AN20: 2.4009417e+11 | AO20: 2.3595258e+11 | AP20: 2.1172481e+11 | AQ20: 2.1706809e+11 | AR20: 2.1642181e+11 | AS20: 1.961816e+11 | AT20: 1.9647721e+11 | AU20: 2.1283722e+11 | AV20: 2.6077983e+11 | AW20: 2.9921041e+11 | AX20: 3.1395232e+11 | AY20: 3.3390598e+11 | AZ20: 3.8676018e+11 | BA20: 4.292344e+11 | BB20: 3.9929012e+11 | BC20: 3.8982779e+11 | BD20: 4.2895474e+11 | BE20: 4.0675049e+11 | BF20: 4.265805e+11 | BG20: 4.3855602e+11 | BH20: 3.795461e+11 | BI20: 3.9368736e+11 | BJ20: 4.1492614e+11 | BK20: 4.5258229e+11 | BL20: 4.4298364e+11 | BM20: 4.343976e+11 | BN20: 4.8046704e+11 | BO20: 4.7177363e+11 | BP20: 5.116852e+11 | BQ20: 5.2164247e+11
A21: Azerbaijan | B21: AZE | C21: GDP (current US$) | D21: NY.GDP.MKTP.CD | AI21: 8.8848485e+09 | AJ21: 5344000000 | AK21: 4.4465867e+08 | AL21: 1.5703926e+09 | AM21: 1.1931411e+09 | AN21: 2.4173312e+09 | AO21: 3.1765074e+09 | AP21: 3.9623624e+09 | AQ21: 4.4463686e+09 | AR21: 4.5812486e+09 | AS21: 5.2726157e+09 | AT21: 5.7076162e+09 | AU21: 6.2360877e+09 | AV21: 7.2764131e+09 | AW21: 8.6804057e+09 | AX21: 1.3245422e+10 | AY21: 2.0981929e+10 | AZ21: 3.3049419e+10 | BA21: 4.8851294e+10 | BB21: 4.4292427e+10 | BC21: 5.2909295e+10 | BD21: 6.5952796e+10 | BE21: 6.9679945e+10 | BF21: 7.416056e+10 | BG21: 7.5239785e+10 | BH21: 5.3076235e+10 | BI21: 3.7866997e+10 | BJ21: 4.0866627e+10 | BK21: 4.711247e+10 | BL21: 4.8174235e+10 | BM21: 42693000000 | BN21: 5.4825412e+10 | BO21: 7.8807471e+10 | BP21: 7.2428471e+10 | BQ21: 7.4315882e+10
A22: Burundi | B22: BDI | C22: GDP (current US$) | D22: NY.GDP.MKTP.CD | E22: 195999990 | F22: 202999992 | G22: 213500006 | H22: 232749998 | I22: 260750008 | J22: 1.5899496e+08 | K22: 1.6544457e+08 | L22: 1.7829714e+08 | M22: 183200000 | N22: 1.9020571e+08 | O22: 2.4273257e+08 | P22: 2.5284229e+08 | Q22: 2.4680457e+08 | R22: 3.0433952e+08 | S22: 3.4526349e+08 | T22: 4.2098667e+08 | U22: 4.4841275e+08 | V22: 5.4753556e+08 | W22: 6.1022556e+08 | X22: 7.8249667e+08 | Y22: 9.1972667e+08 | Z22: 9.6904667e+08 | AA22: 1.0132222e+09 | AB22: 1.0829263e+09 | AC22: 9.8714393e+08 | AD22: 1.1499793e+09 | AE22: 1.2017255e+09 | AF22: 1.1314665e+09 | AG22: 1.0824032e+09 | AH22: 1.1139241e+09 | AI22: 1.1321013e+09 | AJ22: 1.1673985e+09 | AK22: 1.0830377e+09 | AL22: 9.3863261e+08 | AM22: 9.2503059e+08 | AN22: 1.0004284e+09 | AO22: 8.6903386e+08 | AP22: 9.7289627e+08 | AQ22: 8.9377074e+08 | AR22: 8.0807722e+08 | AS22: 8.7048607e+08 | AT22: 8.7679472e+08 | AU22: 8.2539452e+08 | AV22: 7.8465442e+08 | AW22: 9.1525732e+08 | AX22: 1.1171131e+09 | AY22: 1.2733751e+09 | AZ22: 1.3561994e+09 | BA22: 1.6118359e+09 | BB22: 1.7814551e+09 | BC22: 2.0321352e+09 | BD22: 2.2358208e+09 | BE22: 2.3333413e+09 | BF22: 2.4516066e+09 | BG22: 2.7057833e+09 | BH22: 3.1040035e+09 | BI22: 2.6444878e+09 | BJ22: 2.723587e+09 | BK22: 2.6671822e+09 | BL22: 2.5765189e+09 | BM22: 2.6496803e+09 | BN22: 2.7757987e+09 | BO22: 3.3387228e+09 | BP22: 2.6293916e+09 | BQ22: 2.1623788e+09
A23: Belgium | B23: BEL | C23: GDP (current US$) | D23: NY.GDP.MKTP.CD | E23: 1.1810619e+10 | F23: 1.2561702e+10 | G23: 1.3436827e+10 | H23: 1.4445805e+10 | I23: 1.6168044e+10 | J23: 1.7597783e+10 | K23: 1.8894891e+10 | L23: 2.0252509e+10 | M23: 2.1654857e+10 | N23: 2.4019653e+10 | O23: 2.6706196e+10 | P23: 2.9821662e+10 | Q23: 3.7209418e+10 | R23: 4.7743801e+10 | S23: 5.6033078e+10 | T23: 6.5678189e+10 | U23: 7.1113883e+10 | V23: 8.2839905e+10 | W23: 1.0124653e+11 | X23: 1.1631546e+11 | Y23: 1.2682931e+11 | Z23: 1.0473002e+11 | AA23: 9.2095926e+10 | AB23: 8.7184239e+10 | AC23: 8.334953e+10 | AD23: 8.6268264e+10 | AE23: 1.2001879e+11 | AF23: 1.493944e+11 | AG23: 1.622991e+11 | AH23: 1.6422106e+11 | AI23: 2.0533175e+11 | AJ23: 2.10511e+11 | AK23: 2.3478165e+11 | AL23: 2.247218e+11 | AM23: 2.4488413e+11 | AN23: 2.8802559e+11 | AO23: 2.7920143e+11 | AP23: 2.5270805e+11 | AQ23: 2.5852834e+11 | AR23: 2.5824573e+11 | AS23: 2.3679246e+11 | AT23: 2.3674614e+11 | AU23: 2.583836e+11 | AV23: 3.1808253e+11 | AW23: 3.6921471e+11 | AX23: 3.8571476e+11 | AY23: 4.0825984e+11 | AZ23: 4.7092216e+11 | BA23: 5.1732809e+11 | BB23: 4.8501453e+11 | BC23: 4.815565e+11 | BD23: 5.2719665e+11 | BE23: 4.9841436e+11 | BF23: 5.2409703e+11 | BG23: 5.3798742e+11 | BH23: 4.6104477e+11 | BI23: 4.7427157e+11 | BJ23: 5.0090877e+11 | BK23: 5.4263891e+11 | BL23: 5.3672634e+11 | BM23: 5.2969447e+11 | BN23: 5.9852242e+11 | BO23: 5.9361457e+11 | BP23: 6.4465528e+11 | BQ23: 6.6456418e+11
A24: Benin | B24: BEN | C24: GDP (current US$) | D24: NY.GDP.MKTP.CD | E24: 2.2619558e+08 | F24: 2.3566822e+08 | G24: 2.3643495e+08 | H24: 2.539277e+08 | I24: 2.6981901e+08 | J24: 2.8990868e+08 | K24: 3.0292524e+08 | L24: 3.0622195e+08 | M24: 3.2632311e+08 | N24: 3.3074824e+08 | O24: 3.3362771e+08 | P24: 3.3507303e+08 | Q24: 4.1033186e+08 | R24: 5.0437607e+08 | S24: 5.5465486e+08 | T24: 6.7687014e+08 | U24: 6.9840826e+08 | V24: 7.5004978e+08 | W24: 9.2884347e+08 | X24: 1.186231e+09 | Y24: 1.4052518e+09 | Z24: 1.2911202e+09 | AA24: 1.2677787e+09 | AB24: 1.0953482e+09 | AC24: 1.051134e+09 | AD24: 1.0457128e+09 | AE24: 1.336102e+09 | AF24: 1.5624122e+09 | AG24: 1.6202461e+09 | AH24: 1.5022944e+09 | AI24: 1.9599653e+09 | AJ24: 1.9864378e+09 | AK24: 1.6953153e+09 | AL24: 2.2745581e+09 | AM24: 1.5980759e+09 | AN24: 2.1696271e+09 | AO24: 2.3611164e+09 | AP24: 2.2683016e+09 | AQ24: 2.4550927e+09 | AR24: 3.677394e+09 | AS24: 3.5199914e+09 | AT24: 3.6662226e+09 | AU24: 4.1943427e+09 | AV24: 5.3492581e+09 | AW24: 6.1902704e+09 | AX24: 6.567655e+09 | AY24: 7.0341113e+09 | AZ24: 8.1690484e+09 | BA24: 9.7877345e+09 | BB24: 9.7386265e+09 | BC24: 9.535345e+09 | BD24: 1.0693321e+10 | BE24: 1.1141358e+10 | BF24: 1.2517845e+10 | BG24: 1.3284528e+10 | BH24: 1.1388161e+10 | BI24: 1.1821066e+10 | BJ24: 1.2701656e+10 | BK24: 1.4262408e+10 | BL24: 1.4391686e+10 | BM24: 1.5686742e+10 | BN24: 1.7687624e+10 | BO24: 1.7425405e+10 | BP24: 1.9673291e+10 | BQ24: 2.1482644e+10
A25: Burkina Faso | B25: BFA | C25: GDP (current US$) | D25: NY.GDP.MKTP.CD | E25: 3.3044282e+08 | F25: 3.5024723e+08 | G25: 3.795671e+08 | H25: 3.9404067e+08 | I25: 4.1032164e+08 | J25: 4.2291679e+08 | K25: 4.3388977e+08 | L25: 4.5075392e+08 | M25: 4.6044269e+08 | N25: 4.7829865e+08 | O25: 4.5840427e+08 | P25: 4.8241118e+08 | Q25: 5.7859552e+08 | R25: 6.7477357e+08 | S25: 7.5113343e+08 | T25: 9.399727e+08 | U25: 9.7654719e+08 | V25: 1.1312249e+09 | W25: 1.4755836e+09 | X25: 1.7484806e+09 | Y25: 1.9287199e+09 | Z25: 1.7758423e+09 | AA25: 1.7544501e+09 | AB25: 1.6002786e+09 | AC25: 1.4598801e+09 | AD25: 1.5524932e+09 | AE25: 2.0363034e+09 | AF25: 2.3698349e+09 | AG25: 2.6160405e+09 | AH25: 2.6155877e+09 | AI25: 3.1013008e+09 | AJ25: 3.1350456e+09 | AK25: 3.3566925e+09 | AL25: 3.1995365e+09 | AM25: 1.8952906e+09 | AN25: 2.379518e+09 | AO25: 2.5865506e+09 | AP25: 2.4476691e+09 | AQ25: 2.8049024e+09 | AR25: 3.3895667e+09 | AS25: 2.9683701e+09 | AT25: 3.1903711e+09 | AU25: 3.6223501e+09 | AV25: 4.7407681e+09 | AW25: 5.4516885e+09 | AX25: 6.1463532e+09 | AY25: 6.5474198e+09 | AZ25: 7.6257228e+09 | BA25: 9.4514355e+09 | BB25: 9.4506969e+09 | BC25: 1.010962e+10 | BD25: 1.2080296e+10 | BE25: 1.2561015e+10 | BF25: 1.34443e+10 | BG25: 1.3943016e+10 | BH25: 1.1832159e+10 | BI25: 1.2833363e+10 | BJ25: 1.4106956e+10 | BK25: 1.5890066e+10 | BL25: 1.6032814e+10 | BM25: 1.7725011e+10 | BN25: 1.9697516e+10 | BO25: 1.8820219e+10 | BP25: 2.0324618e+10 | BQ25: 2.3250215e+10
A26: Bangladesh | B26: BGD | C26: GDP (current US$) | D26: NY.GDP.MKTP.CD | E26: 4.2748941e+09 | F26: 4817580375 | G26: 5.0814135e+09 | H26: 5.3194586e+09 | I26: 5.3860548e+09 | J26: 5.9066368e+09 | K26: 6.4396879e+09 | L26: 7.2535757e+09 | M26: 7.4836858e+09 | N26: 8.4710064e+09 | O26: 8.9927222e+09 | P26: 8.7518432e+09 | Q26: 6.2882459e+09 | R26: 8.0867257e+09 | S26: 1.2512461e+10 | T26: 1.9448348e+10 | U26: 1.0117113e+10 | V26: 9.6511493e+09 | W26: 1.3281767e+10 | X26: 1.556548e+10 | Y26: 1.8138049e+10 | Z26: 2.0249694e+10 | AA26: 1.8525399e+10 | AB26: 1.7609049e+10 | AC26: 18920840000 | AD26: 2.2278423e+10 | AE26: 2.1774033e+10 | AF26: 2.4298032e+10 | AG26: 2.6579006e+10 | AH26: 2.8781715e+10 | AI26: 3.1598341e+10 | AJ26: 3.0957484e+10 | AK26: 3.1708875e+10 | AL26: 3.3166519e+10 | AM26: 3.3768661e+10 | AN26: 3.7939749e+10 | AO26: 4.6438484e+10 | AP26: 4.8244309e+10 | AQ26: 4.9984559e+10 | AR26: 5.127057e+10 | AS26: 5.3369787e+10 | AT26: 5.399129e+10 | AU26: 5.4724081e+10 | AV26: 6.0158929e+10 | AW26: 6.5108544e+10 | AX26: 6.9476001e+10 | AY26: 7.1795736e+10 | AZ26: 7.9611645e+10 | BA26: 9.1636997e+10 | BB26: 1.0247516e+11 | BC26: 1.1527554e+11 | BD26: 1.2860748e+11 | BE26: 1.3331075e+11 | BF26: 1.4999896e+11 | BG26: 1.7288661e+11 | BH26: 1.9514661e+11 | BI26: 2.6522452e+11 | BJ26: 2.9373245e+11 | BK26: 3.2136275e+11 | BL26: 3.5123165e+11 | BM26: 3.7397944e+11 | BN26: 4.1627165e+11 | BO26: 4.6013169e+11 | BP26: 4.3741533e+11 | BQ26: 4.5011942e+11
A27: Bulgaria | B27: BGR | C27: GDP (current US$) | D27: NY.GDP.MKTP.CD | Y27: 1.9839231e+10 | Z27: 19870000000 | AA27: 19342000000 | AB27: 1.6563667e+10 | AC27: 1.7594944e+10 | AD27: 1.7155421e+10 | AE27: 2.0249294e+10 | AF27: 28101000000 | AG27: 2.2555941e+10 | AH27: 2.1988444e+10 | AI27: 2.0632091e+10 | AJ27: 7.6287385e+09 | AK27: 8.6028876e+09 | AL27: 1.0832065e+10 | AM27: 9.70924e+09 | AN27: 1.8991484e+10 | AO27: 1.2294965e+10 | AP27: 1.1316127e+10 | AQ27: 1.5031055e+10 | AR27: 1.3637099e+10 | AS27: 1.324599e+10 | AT27: 1.4183446e+10 | AU27: 1.6403044e+10 | AV27: 2.1144958e+10 | AW27: 2.6157743e+10 | AX27: 2.9868658e+10 | AY27: 3.4380536e+10 | AZ27: 4.4431257e+10 | BA27: 5.4480684e+10 | BB27: 5.2023801e+10 | BC27: 5.0689051e+10 | BD27: 5.7681293e+10 | BE27: 5.4297052e+10 | BF27: 5.5819262e+10 | BG27: 5.7080897e+10 | BH27: 5.0765918e+10 | BI27: 5.3929397e+10 | BJ27: 5.9167647e+10 | BK27: 6.6251582e+10 | BL27: 6.8634005e+10 | BM27: 7.0550652e+10 | BN27: 8.4414123e+10 | BO27: 9.0509237e+10 | BP27: 1.0239684e+11 | BQ27: 1.1221195e+11
A28: Bahrain | B28: BHR | C28: GDP (current US$) | D28: NY.GDP.MKTP.CD | O28: 3.9157736e+08 | P28: 4.2218156e+08 | Q28: 5.3408118e+08 | R28: 7.6113255e+08 | S28: 1.0421769e+09 | T28: 1.0991076e+09 | U28: 1.5817095e+09 | V28: 1.9890603e+09 | W28: 2.272043e+09 | X28: 2.7101607e+09 | Y28: 3.4938345e+09 | Z28: 3.9431095e+09 | AA28: 4.1454211e+09 | AB28: 4.2470305e+09 | AC28: 4.4408746e+09 | AD28: 4.1523765e+09 | AE28: 3.4707468e+09 | AF28: 3.8569227e+09 | AG28: 4.2098342e+09 | AH28: 4.393094e+09 | AI28: 4.809511e+09 | AJ28: 5.2489112e+09 | AK28: 5.4022324e+09 | AL28: 5.9130011e+09 | AM28: 6.3306279e+09 | AN28: 6.6511809e+09 | AO28: 6.9381668e+09 | AP28: 7.2194077e+09 | AQ28: 7.031309e+09 | AR28: 7.5284691e+09 | AS28: 9.0628989e+09 | AT28: 8.9761968e+09 | AU28: 9.5935106e+09 | AV28: 1.1074814e+10 | AW28: 1.315016e+10 | AX28: 1.5968723e+10 | AY28: 1.8504761e+10 | AZ28: 21730000000 | BA28: 2.5710904e+10 | BB28: 2.2938218e+10 | BC28: 2.6805984e+10 | BD28: 2.9914681e+10 | BE28: 3.1963404e+10 | BF28: 3.3823324e+10 | BG28: 3.4772527e+10 | BH28: 3.2523298e+10 | BI28: 3.3884681e+10 | BJ28: 3.7204814e+10 | BK28: 3.9567979e+10 | BL28: 4.0446809e+10 | BM28: 3.5837633e+10 | BN28: 4.0840213e+10 | BO28: 4.6458191e+10 | BP28: 4.6192261e+10 | BQ28: 4.7736702e+10
A29: Bahamas, The | B29: BHS | C29: GDP (current US$) | D29: NY.GDP.MKTP.CD | E29: 1.6973603e+08 | F29: 1.9002203e+08 | G29: 2.1217003e+08 | H29: 2.3765004e+08 | I29: 2.6656004e+08 | J29: 3.0027205e+08 | K29: 346800000 | L29: 398000000 | M29: 453800000 | N29: 538700000 | O29: 539500000 | P29: 573400000 | Q29: 590900000 | R29: 670900000 | S29: 632400000 | T29: 596200000 | U29: 642100000 | V29: 713000000 | W29: 832400000 | X29: 1139800100 | Y29: 1335300000 | Z29: 1426500000 | AA29: 1578300000 | AB29: 1732800000 | AC29: 2041100000 | AD29: 2320699900 | AE29: 2472500000 | AF29: 2713999900 | AG29: 2817900000 | AH29: 3062000000 | AI29: 3166000000 | AJ29: 3111160000 | AK29: 3109000000 | AL29: 3092000000 | AM29: 3259000000 | AN29: 3429000000 | AO29: 3609000000 | AP29: 6332360000 | AQ29: 6833220000 | AR29: 7683870000 | AS29: 8076470000 | AT29: 8317830000 | AU29: 8881160000 | AV29: 8870090000 | AW29: 9055290000 | AX29: 9836200000 | AY29: 10167250000 | AZ29: 10618340000 | BA29: 10526000000 | BB29: 9981960000 | BC29: 10095760000 | BD29: 10070450000 | BE29: 10720400000 | BF29: 10475300000 | BG29: 11139100000 | BH29: 11837600000 | BI29: 11880900000 | BJ29: 12446900000 | BK29: 12819200000 | BL29: 13277000000 | BM29: 10363200000 | BN29: 12037000000 | BO29: 13896800000 | BP29: 15271300000 | BQ29: 15832800000
A30: Bosnia and Herzegovina | B30: BIH | C30: GDP (current US$) | D30: NY.GDP.MKTP.CD | AI30: 7.7534783e+09 | AJ30: 6.1229592e+09 | AK30: 4.7350447e+09 | AL30: 3.6306689e+09 | AM30: 1.2558025e+09 | AN30: 1.866573e+09 | AO30: 2.7860453e+09 | AP30: 3.6719097e+09 | AQ30: 4.1167743e+09 | AR30: 4.6862564e+09 | AS30: 5.5677728e+09 | AT30: 5.8006155e+09 | AU30: 6.7282209e+09 | AV30: 8.4988944e+09 | AW30: 1.0156542e+10 | AX30: 1.1222796e+10 | AY30: 1.2864842e+10 | AZ30: 1.5778734e+10 | BA30: 1.9112797e+10 | BB30: 1.7613949e+10 | BC30: 1.7176316e+10 | BD30: 1.8644234e+10 | BE30: 1.7226736e+10 | BF30: 1.8179109e+10 | BG30: 1.8558734e+10 | BH30: 1.6404349e+10 | BI30: 1.7116926e+10 | BJ30: 1.8326373e+10 | BK30: 2.0484054e+10 | BL30: 2.0482609e+10 | BM30: 2.0226037e+10 | BN30: 2.3672712e+10 | BO30: 2.4534664e+10 | BP30: 2.7592361e+10 | BQ30: 2.8343394e+10
A31: Belarus | B31: BLR | C31: GDP (current US$) | D31: NY.GDP.MKTP.CD | AI31: 1.7389558e+10 | AJ31: 1.8404908e+10 | AK31: 1.693979e+10 | AL31: 1.6275074e+10 | AM31: 1.4931435e+10 | AN31: 1.3972683e+10 | AO31: 1.4756846e+10 | AP31: 1.4130586e+10 | AQ31: 1.5221353e+10 | AR31: 1.2138243e+10 | AS31: 1.273678e+10 | AT31: 1.235482e+10 | AU31: 1.4594901e+10 | AV31: 1.7825445e+10 | AW31: 2.3141566e+10 | AX31: 3.0210092e+10 | AY31: 3.6961894e+10 | AZ31: 4.5275712e+10 | BA31: 6.0752106e+10 | BB31: 5.0873167e+10 | BC31: 5.7231905e+10 | BD31: 6.1762382e+10 | BE31: 6.568589e+10 | BF31: 7.5527559e+10 | BG31: 7.8813069e+10 | BH31: 5.645477e+10 | BI31: 4.7723545e+10 | BJ31: 5.4725406e+10 | BK31: 6.0031027e+10 | BL31: 6.4410171e+10 | BM31: 6.1371673e+10 | BN31: 6.9673747e+10 | BO31: 7.377518e+10 | BP31: 7.247876e+10 | BQ31: 7.5961865e+10
A32: Belize | B32: BLZ | C32: GDP (current US$) | D32: NY.GDP.MKTP.CD | E32: 28072478 | F32: 29965000 | G32: 31857592 | H32: 33750114 | I32: 36194586 | J32: 40110040 | K32: 44450044 | L32: 47431256 | M32: 44999910 | N32: 47399905 | O32: 53339893 | P32: 59074687 | Q32: 65998069 | R32: 78214768 | S32: 1.0316045e+08 | T32: 1.1819403e+08 | U32: 97094227 | V32: 117650000 | W32: 136300000 | X32: 151800000 | Y32: 257400000 | Z32: 260750000 | AA32: 248550000 | AB32: 262150000 | AC32: 290350000 | AD32: 287300000 | AE32: 311500000 | AF32: 371100000 | AG32: 421450000 | AH32: 491100000 | AI32: 547150000 | AJ32: 597100000 | AK32: 696250000 | AL32: 752850000 | AM32: 772300000 | AN32: 819050000 | AO32: 850850000 | AP32: 873400000 | AQ32: 929500000 | AR32: 1000250000 | AS32: 1138900000 | AT32: 1172800000 | AU32: 1244650000 | AV32: 1308900000 | AW32: 1400850000 | AX32: 1474950000 | AY32: 1591150000 | AZ32: 1707100000 | BA32: 1738900000 | BB32: 1688500000 | BC32: 1745700000 | BD32: 1827050000 | BE32: 1909400000 | BF32: 2032750000 | BG32: 2138250000 | BH32: 2193050000 | BI32: 2240200000 | BJ32: 2266300000 | BK32: 2293250000 | BL32: 2388300000 | BM32: 2042850000 | BN32: 2420550000 | BO32: 2846700000 | BP32: 3066850000 | BQ32: 3.5157833e+09
A33: Bermuda | B33: BMU | C33: GDP (current US$) | D33: NY.GDP.MKTP.CD | E33: 72400000 | F33: 76500000 | G33: 80700000 | H33: 82600000 | I33: 92200000 | J33: 98000000 | K33: 115000000 | L33: 134800000 | M33: 150000000 | N33: 164900000 | O33: 186300000 | P33: 211100000 | Q33: 235400000 | R33: 269500000 | S33: 312600000 | T33: 345000000 | U33: 386300000 | V33: 447000000 | W33: 475800000 | X33: 517200000 | Y33: 613299968 | Z33: 739100032 | AA33: 785500032 | AB33: 889400000 | AC33: 985699968 | AD33: 1039500032 | AE33: 1173500032 | AF33: 1296499968 | AG33: 1415100032 | AH33: 1501500032 | AI33: 1592400000 | AJ33: 1634900000 | AK33: 1679900000 | AL33: 1820359900 | AM33: 1867160100 | AN33: 2030750000 | AO33: 2695390000 | AP33: 2932827000 | AQ33: 3130748000 | AR33: 3324433000 | AS33: 3480219000 | AT33: 3680483000 | AU33: 3937228000 | AV33: 4186525000 | AW33: 4484703000 | AX33: 4868136000 | AY33: 6144000000 | AZ33: 6767000000 | BA33: 6980000000 | BB33: 6656000000 | BC33: 6634526000 | BD33: 6312691000 | BE33: 6378188000 | BF33: 6465756000 | BG33: 6413988000 | BH33: 6654541000 | BI33: 6899911000 | BJ33: 7142316000 | BK33: 7225977000 | BL33: 7423465000 | BM33: 6887364000 | BN33: 7290037000 | BO33: 7874381000 | BP33: 8579242000 | BQ33: 8980200000
A34: Bolivia | B34: BOL | C34: GDP (current US$) | D34: NY.GDP.MKTP.CD | E34: 373250000 | F34: 406000000 | G34: 4.4391667e+08 | H34: 478000000 | I34: 5.3858333e+08 | J34: 5.9833333e+08 | K34: 662500000 | L34: 748250000 | M34: 8.4933333e+08 | N34: 9.2033333e+08 | O34: 1.0068333e+09 | P34: 1.0846667e+09 | Q34: 1.2861538e+09 | R34: 1263600000 | S34: 2101300000 | T34: 2405900000 | U34: 2733350000 | V34: 3229050000 | W34: 3760100000 | X34: 4510500000 | Y34: 4450360000 | Z34: 5778480000 | AA34: 5600390625 | AB34: 5.4140086e+09 | AC34: 6.1693045e+09 | AD34: 5.3772767e+09 | AE34: 3.9593835e+09 | AF34: 4.3479563e+09 | AG34: 4.5976117e+09 | AH34: 4.7159734e+09 | AI34: 4.8675826e+09 | AJ34: 5.3432625e+09 | AK34: 5.6438687e+09 | AL34: 5.7346995e+09 | AM34: 5.9812229e+09 | AN34: 6.7151617e+09 | AO34: 7.3969491e+09 | AP34: 7.9257368e+09 | AQ34: 8.4974947e+09 | AR34: 8.2850644e+09 | AS34: 8.3978555e+09 | AT34: 8.1415169e+09 | AU34: 7.9054851e+09 | AV34: 8.0823996e+09 | AW34: 8.7734518e+09 | AX34: 9.5491229e+09 | AY34: 1.1451845e+10 | AZ34: 1.3120108e+10 | BA34: 1.6674276e+10 | BB34: 1.7339992e+10 | BC34: 1.9649724e+10 | BD34: 2.3963165e+10 | BE34: 2.7084497e+10 | BF34: 3.0659339e+10 | BG34: 3.2996188e+10 | BH34: 3.3000198e+10 | BI34: 3.3941126e+10 | BJ34: 3.7508642e+10 | BK34: 4.0287648e+10 | BL34: 4.0895323e+10 | BM34: 3.6629844e+10 | BN34: 4.0406112e+10 | BO34: 4.4008283e+10 | BP34: 4.5135398e+10 | BQ34: 4.9668297e+10
A35: Brazil | B35: BRA | C35: GDP (current US$) | D35: NY.GDP.MKTP.CD | E35: 1.7030466e+10 | F35: 1.727594e+10 | G35: 1.9231748e+10 | H35: 2.3287713e+10 | I35: 2.0963734e+10 | J35: 2.2465523e+10 | K35: 2.8283324e+10 | L35: 3.1086389e+10 | M35: 3.3930457e+10 | N35: 3.7171641e+10 | O35: 4.2327665e+10 | P35: 4.8869831e+10 | Q35: 5.8434858e+10 | R35: 8.3592276e+10 | S35: 1.0979452e+11 | T35: 1.2920356e+11 | U35: 1.5316895e+11 | V35: 1.763441e+11 | W35: 2.0027865e+11 | X35: 2.213382e+11 | Y35: 2.3739349e+11 | Z35: 2.5801517e+11 | AA35: 2.7131411e+11 | AB35: 1.8965651e+11 | AC35: 1.8833997e+11 | AD35: 2.1087984e+11 | AE35: 2.5648085e+11 | AF35: 2.8305684e+11 | AG35: 3.0788193e+11 | AH35: 4.1299082e+11 | AI35: 3.8495982e+11 | AJ35: 3.4253409e+11 | AK35: 3.2819191e+11 | AL35: 3.6829203e+11 | AM35: 5.2536947e+11 | AN35: 7.6933305e+11 | AO35: 8.5042643e+11 | AP35: 8.8320618e+11 | AQ35: 8.6371076e+11 | AR35: 5.9964202e+11 | AS35: 6.5544823e+11 | AT35: 5.5998363e+11 | AU35: 5.0979527e+11 | AV35: 5.5823375e+11 | AW35: 6.6928942e+11 | AX35: 8.9163384e+11 | AY35: 1.1076265e+12 | AZ35: 1.3971145e+12 | BA35: 1.6958551e+12 | BB35: 1.6669964e+12 | BC35: 2.2088377e+12 | BD35: 2.6161562e+12 | BE35: 2.4652278e+12 | BF35: 2.4728195e+12 | BG35: 2.4560437e+12 | BH35: 1.8022122e+12 | BI35: 1.7956935e+12 | BJ35: 2.063515e+12 | BK35: 1.9169339e+12 | BL35: 1.8732882e+12 | BM35: 1.4761072e+12 | BN35: 1.6706474e+12 | BO35: 1.9519239e+12 | BP35: 2.1911318e+12 | BQ35: 2.1794121e+12
A36: Barbados | B36: BRB | C36: GDP (current US$) | D36: NY.GDP.MKTP.CD | E36: 80021847 | F36: 85363759 | G36: 88782583 | H36: 99893761 | I36: 99252731 | J36: 1.05022e+08 | K36: 1.1319512e+08 | L36: 1.2555401e+08 | M36: 1.2573367e+08 | N36: 141393142 | O36: 166210203 | P36: 1.868265e+08 | Q36: 2.1372522e+08 | R36: 2.6076783e+08 | S36: 3.1180463e+08 | T36: 4.0217861e+08 | U36: 4.3591127e+08 | V36: 4.9509767e+08 | W36: 5.5288371e+08 | X36: 6.7036245e+08 | Y36: 1.0122806e+09 | Z36: 1.1142047e+09 | AA36: 1.1639238e+09 | AB36: 1.2360165e+09 | AC36: 1.3468901e+09 | AD36: 1.4095361e+09 | AE36: 1.5477552e+09 | AF36: 1.7043703e+09 | AG36: 1.8127579e+09 | AH36: 2.0061652e+09 | AI36: 2.0121315e+09 | AJ36: 2.0205837e+09 | AK36: 1957000000 | AL36: 2.0633421e+09 | AM36: 2.1513449e+09 | AN36: 2.2169741e+09 | AO36: 2.3636454e+09 | AP36: 2.4983841e+09 | AQ36: 2.8170835e+09 | AR36: 2.9518222e+09 | AS36: 3059500000 | AT36: 3054500000 | AU36: 3106500000 | AV36: 3209500000 | AW36: 3444500000 | AX36: 3819500000 | AY36: 4217323400 | AZ36: 4675767950 | BA36: 4790410400 | BB36: 4466809600 | BC36: 5191188500 | BD36: 5342183800 | BE36: 5271257500 | BF36: 5361158350 | BG36: 5365976700 | BH36: 5288057750 | BI36: 5330761500 | BJ36: 5517340450 | BK36: 5629916200 | BL36: 5788288000 | BM36: 5168344450 | BN36: 5275242050 | BO36: 6257303500 | BP36: 6720733200 | BQ36: 7165000000
A37: Brunei Darussalam | B37: BRN | C37: GDP (current US$) | D37: NY.GDP.MKTP.CD | J37: 1.140395e+08 | K37: 1.3275753e+08 | L37: 1.3902954e+08 | M37: 1.6081824e+08 | N37: 1.6121024e+08 | O37: 1.7907893e+08 | P37: 1.9752577e+08 | Q37: 2.7082278e+08 | R37: 4.3309553e+08 | S37: 2.3195762e+09 | T37: 2.4964203e+09 | U37: 3.0547656e+09 | V37: 3.6812425e+09 | W37: 4.1004237e+09 | X37: 6.0443676e+09 | Y37: 1.0795432e+10 | Z37: 9.3672187e+09 | AA37: 8.9321982e+09 | AB37: 7.9275908e+09 | AC37: 7.6327881e+09 | AD37: 6.9676239e+09 | AE37: 4.19028e+09 | AF37: 4.9180101e+09 | AG37: 4.5351303e+09 | AH37: 4.9836229e+09 | AI37: 6.0398811e+09 | AJ37: 6.2844973e+09 | AK37: 6.3279664e+09 | AL37: 6.2033399e+09 | AM37: 6.4677825e+09 | AN37: 7.7001441e+09 | AO37: 7.6633773e+09 | AP37: 7.7930344e+09 | AQ37: 5.550846e+09 | AR37: 6.3090704e+09 | AS37: 6.5709991e+09 | AT37: 6.0961557e+09 | AU37: 6.3330829e+09 | AV37: 7.1677253e+09 | AW37: 8.6191788e+09 | AX37: 1.0547203e+10 | AY37: 1.2644616e+10 | AZ37: 1.3432029e+10 | BA37: 1.5926456e+10 | BB37: 1.1912905e+10 | BC37: 1.3707121e+10 | BD37: 1.8524791e+10 | BE37: 1.9048443e+10 | BF37: 1.8094148e+10 | BG37: 1.7097797e+10 | BH37: 1.2930297e+10 | BI37: 1.1400266e+10 | BJ37: 1.2128168e+10 | BK37: 1.3566908e+10 | BL37: 1.3469235e+10 | BM37: 1.20058e+10 | BN37: 1.4006497e+10 | BO37: 1.6681536e+10 | BP37: 1.5095085e+10 | BQ37: 1.5463134e+10
A38: Bhutan | B38: BTN | C38: GDP (current US$) | D38: NY.GDP.MKTP.CD | O38: 61812113 | P38: 66289450 | Q38: 70139867 | R38: 78900289 | S38: 92901784 | T38: 86820762 | U38: 88461263 | V38: 97884434 | W38: 94086228 | X38: 1.05378e+08 | Y38: 1.286692e+08 | Z38: 1.3917418e+08 | AA38: 1.4143932e+08 | AB38: 1.5670429e+08 | AC38: 1.6042349e+08 | AD38: 1.6328882e+08 | AE38: 1.9121812e+08 | AF38: 2.4274277e+08 | AG38: 2.7229807e+08 | AH38: 2.6479863e+08 | AI38: 2.8776501e+08 | AJ38: 2.4029429e+08 | AK38: 2.4023353e+08 | AL38: 2.2597369e+08 | AM38: 2.5895471e+08 | AN38: 2.9049098e+08 | AO38: 3.0340835e+08 | AP38: 3.5222908e+08 | AQ38: 3.6345838e+08 | AR38: 3.993112e+08 | AS38: 4.6073342e+08 | AT38: 4.9611023e+08 | AU38: 5.5934526e+08 | AV38: 6.5193543e+08 | AW38: 7.3534849e+08 | AX38: 8.60391e+08 | AY38: 9.4287988e+08 | AZ38: 1.255768e+09 | BA38: 1.3175178e+09 | BB38: 1.3313438e+09 | BC38: 1.7088807e+09 | BD38: 1.9777287e+09 | BE38: 1.9733872e+09 | BF38: 1.943697e+09 | BG38: 2.0890796e+09 | BH38: 2.1878158e+09 | BI38: 2.3575048e+09 | BJ38: 2.591358e+09 | BK38: 2.5833357e+09 | BL38: 2.7356836e+09 | BM38: 2.4576043e+09 | BN38: 2.768803e+09 | BO38: 2.8982277e+09 | BP38: 3.0192539e+09
A39: Botswana | B39: BWA | C39: GDP (current US$) | D39: NY.GDP.MKTP.CD | E39: 30411414 | F39: 32902613 | G39: 35644957 | H39: 38091843 | I39: 41616348 | J39: 45788696 | K39: 51465655 | L39: 58642354 | M39: 66248441 | N39: 77361547 | O39: 96243234 | P39: 1.2744861e+08 | Q39: 1.6446091e+08 | R39: 2.4412416e+08 | S39: 3.0604421e+08 | T39: 3.5516857e+08 | U39: 3.7202509e+08 | V39: 4.5162478e+08 | W39: 5.9040737e+08 | X39: 8.1987026e+08 | Y39: 1.0608897e+09 | Z39: 1.0738128e+09 | AA39: 1.0149457e+09 | AB39: 1.1722304e+09 | AC39: 1.2408222e+09 | AD39: 1.1147833e+09 | AE39: 1.3926022e+09 | AF39: 1.9652269e+09 | AG39: 2.6445542e+09 | AH39: 3.0838221e+09 | AI39: 3.7906363e+09 | AJ39: 3.9428767e+09 | AK39: 4.1464646e+09 | AL39: 4.1601292e+09 | AM39: 4.2592596e+09 | AN39: 4.7305991e+09 | AO39: 4.8477572e+09 | AP39: 5.0202656e+09 | AQ39: 4.7904815e+09 | AR39: 5.4842633e+09 | AS39: 5.7883296e+09 | AT39: 5.4896083e+09 | AU39: 5.438864e+09 | AV39: 7.5115822e+09 | AW39: 8.9574677e+09 | AX39: 9.9189071e+09 | AY39: 9.9191585e+09 | AZ39: 1.0567271e+10 | BA39: 1.0730829e+10 | BB39: 1.0118459e+10 | BC39: 1.2637273e+10 | BD39: 1.5110644e+10 | BE39: 1.3907465e+10 | BF39: 1.4271739e+10 | BG39: 1.5470089e+10 | BH39: 1.3530749e+10 | BI39: 1.5082637e+10 | BJ39: 1.6105156e+10 | BK39: 1.7031943e+10 | BL39: 1.6725908e+10 | BM39: 1.4960252e+10 | BN39: 1.8750182e+10 | BO39: 2.0321151e+10 | BP39: 1.9411267e+10 | BQ39: 1.9400775e+10
A40: Central African Republic | B40: CAF | C40: GDP (current US$) | D40: NY.GDP.MKTP.CD | E40: 1.121556e+08 | F40: 1.2313458e+08 | G40: 1.2448277e+08 | H40: 1.2937912e+08 | I40: 1.4202508e+08 | J40: 1.505748e+08 | K40: 1.5793002e+08 | L40: 1.6382051e+08 | M40: 1.9176744e+08 | N40: 1.8803921e+08 | O40: 1.8910653e+08 | P40: 2.014508e+08 | Q40: 2.3031788e+08 | R40: 2.7118308e+08 | S40: 2.8139871e+08 | T40: 3.7866002e+08 | U40: 4.5115246e+08 | V40: 5.0729815e+08 | W40: 6.1057863e+08 | X40: 7.0076475e+08 | Y40: 7.970482e+08 | Z40: 6.9480362e+08 | AA40: 7.4831239e+08 | AB40: 6.5867933e+08 | AC40: 6.3782067e+08 | AD40: 8.6484984e+08 | AE40: 1.122265e+09 | AF40: 1.200992e+09 | AG40: 1.2648993e+09 | AH40: 1.2339303e+09 | AI40: 1.4407115e+09 | AJ40: 1.377375e+09 | AK40: 1.4119176e+09 | AL40: 1.2787813e+09 | AM40: 8.5117436e+08 | AN40: 1.1153897e+09 | AO40: 1.0077911e+09 | AP40: 9.3774151e+08 | AQ40: 9.6733839e+08 | AR40: 9.9947751e+08 | AS40: 9.1677728e+08 | AT40: 9.326486e+08 | AU40: 9.9606814e+08 | AV40: 1.1423155e+09 | AW40: 1.2723605e+09 | AX40: 1.3378944e+09 | AY40: 1.4618598e+09 | AZ40: 1.6998113e+09 | BA40: 1.9934079e+09 | BB40: 2.0673817e+09 | BC40: 2.1425915e+09 | BD40: 2.4379827e+09 | BE40: 2.5101265e+09 | BF40: 1.6915441e+09 | BG40: 1.8948134e+09 | BH40: 1.6958257e+09 | BI40: 1.8250181e+09 | BJ40: 2.07235e+09 | BK40: 2.2209791e+09 | BL40: 2.2213014e+09 | BM40: 2.3267209e+09 | BN40: 2.5164984e+09 | BO40: 2.3826186e+09 | BP40: 2.5554921e+09 | BQ40: 2.7515445e+09
A41: Canada | B41: CAN | C41: GDP (current US$) | D41: NY.GDP.MKTP.CD | E41: 4.0563769e+10 | F41: 4.1038193e+10 | G41: 4.2336212e+10 | H41: 4.5140338e+10 | I41: 4.9503664e+10 | J41: 5.464941e+10 | K41: 6.1252415e+10 | L41: 6.5856924e+10 | M41: 7.2048833e+10 | N41: 7.9405011e+10 | O41: 8.8192258e+10 | P41: 9.9606455e+10 | Q41: 1.1346385e+11 | R41: 1.3176434e+11 | S41: 1.6094919e+11 | T41: 1.7441976e+11 | U41: 2.0727161e+11 | V41: 2.1232518e+11 | W41: 2.1936954e+11 | X41: 2.4389112e+11 | Y41: 2.7477657e+11 | Z41: 3.0724664e+11 | AA41: 3.1464781e+11 | AB41: 3.4186628e+11 | AC41: 3.567184e+11 | AD41: 3.6618601e+11 | AE41: 3.7900684e+11 | AF41: 4.3313424e+11 | AG41: 5.0938003e+11 | AH41: 5.6721199e+11 | AI41: 5.9607559e+11 | AJ41: 6.1252771e+11 | AK41: 5.9438736e+11 | AL41: 5.7905356e+11 | AM41: 5.7994435e+11 | AN41: 6.0596109e+11 | AO41: 6.3060799e+11 | AP41: 6.54987e+11 | AQ41: 634000000000 | AR41: 6.784122e+11 | AS41: 7.4477342e+11 | AT41: 7.3898179e+11 | AU41: 7.6064933e+11 | AV41: 8.9554065e+11 | AW41: 1.0266902e+12 | AX41: 1.1731086e+12 | AY41: 1.3192648e+12 | AZ41: 1.4688204e+12 | BA41: 1.5529897e+12 | BB41: 1.3746251e+12 | BC41: 1.6173434e+12 | BD41: 1.7933266e+12 | BE41: 1.8283665e+12 | BF41: 1.8465974e+12 | BG41: 1.8057499e+12 | BH41: 1.5565088e+12 | BI41: 1.5279947e+12 | BJ41: 1.6492656e+12 | BK41: 1.7253292e+12 | BL41: 1.7437252e+12 | BM41: 1.6556847e+12 | BN41: 2.0223787e+12 | BO41: 2.1904111e+12 | BP41: 2.1733397e+12 | BQ41: 2.2412532e+12
A42: Central Europe and the Baltics | B42: CEB | C42: GDP (current US$) | D42: NY.GDP.MKTP.CD | AI42: 2.721152e+11 | AJ42: 2.4671063e+11 | AK42: 2.5509685e+11 | AL42: 2.7037465e+11 | AM42: 3.0867598e+11 | AN42: 3.947624e+11 | AO42: 4.175181e+11 | AP42: 4.1114308e+11 | AQ42: 4.4984347e+11 | AR42: 4.3602764e+11 | AS42: 4.2941271e+11 | AT42: 4.6950142e+11 | AU42: 5.2852476e+11 | AV42: 6.3429113e+11 | AW42: 7.6349047e+11 | AX42: 8.8571582e+11 | AY42: 1.0013214e+12 | AZ42: 1.2642654e+12 | BA42: 1.5302707e+12 | BB42: 1.2892652e+12 | BC42: 1.3194503e+12 | BD42: 1.45817e+12 | BE42: 1.3619029e+12 | BF42: 1.4202287e+12 | BG42: 1.4674565e+12 | BH42: 1.2971476e+12 | BI42: 1.3215656e+12 | BJ42: 1.4675052e+12 | BK42: 1.6582152e+12 | BL42: 1.6860421e+12 | BM42: 1.6797703e+12 | BN42: 1.9279401e+12 | BO42: 1.9562743e+12 | BP42: 2.2739454e+12 | BQ42: 2.4555592e+12
A43: Switzerland | B43: CHE | C43: GDP (current US$) | D43: NY.GDP.MKTP.CD | E43: 1.0412233e+10 | F43: 1.1713349e+10 | G43: 1.298965e+10 | H43: 1.4283872e+10 | I43: 1.5833134e+10 | J43: 1.6780226e+10 | K43: 1.8019402e+10 | L43: 1.9397045e+10 | M43: 2.0712103e+10 | N43: 2.2442043e+10 | O43: 2.4998067e+10 | P43: 3.0040172e+10 | Q43: 3.6844319e+10 | R43: 4.9550006e+10 | S43: 5.7103011e+10 | T43: 6.5466082e+10 | U43: 6.8476525e+10 | V43: 7.3135771e+10 | W43: 1.0228047e+11 | X43: 1.1497009e+11 | Y43: 1.2255784e+11 | Z43: 1.1224481e+11 | AA43: 1.1504337e+11 | AB43: 1.1463436e+11 | AC43: 1.0945531e+11 | AD43: 1.1098031e+11 | AE43: 1.5908992e+11 | AF43: 1.9923637e+11 | AG43: 2.1554063e+11 | AH43: 2.0810585e+11 | AI43: 2.6576357e+11 | AJ43: 2.6890169e+11 | AK43: 2.7992143e+11 | AL43: 2.7223753e+11 | AM43: 3.0137506e+11 | AN43: 3.5283581e+11 | AO43: 3.4010396e+11 | AP43: 2.947882e+11 | AQ43: 3.0345901e+11 | AR43: 2.9787364e+11 | AS43: 2.7921603e+11 | AT43: 2.8658267e+11 | AU43: 3.0930142e+11 | AV43: 3.6207509e+11 | AW43: 4.0391289e+11 | AX43: 4.1828487e+11 | AY43: 4.4163467e+11 | AZ43: 4.9074072e+11 | BA43: 5.6726777e+11 | BB43: 5.5421292e+11 | BC43: 5.9885103e+11 | BD43: 7.1588813e+11 | BE43: 6.8642022e+11 | BF43: 7.0623494e+11 | BG43: 7.2653781e+11 | BH43: 6.9411819e+11 | BI43: 6.8789546e+11 | BJ43: 6.9520083e+11 | BK43: 7.2556872e+11 | BL43: 7.2136911e+11 | BM43: 7.4199941e+11 | BN43: 8.1530933e+11 | BO43: 8.2850893e+11 | BP43: 8.9442482e+11 | BQ43: 9.365642e+11
A44: Channel Islands | B44: CHI | C44: GDP (current US$) | D44: NY.GDP.MKTP.CD | AQ44: 5.9456774e+09 | AR44: 6.2627407e+09 | AS44: 6.4397034e+09 | AT44: 6.2329063e+09 | AU44: 6.6636691e+09 | AV44: 7.3322449e+09 | AW44: 8.5536434e+09 | AX44: 8.8272727e+09 | AY44: 9.676173e+09 | AZ44: 1.1514606e+10 | BB44: 9.1007557e+09 | BC44: 8.9020705e+09 | BD44: 9.6493139e+09 | BE44: 9.4553401e+09 | BF44: 9.5941609e+09 | BG44: 1.0528493e+10 | BH44: 1.0109969e+10 | BI44: 9.1692782e+09 | BJ44: 9.1700799e+09 | BK44: 1.0026153e+10 | BL44: 1.0032441e+10 | BM44: 9.4398108e+09 | BN44: 1.1157003e+10 | BO44: 1.13083e+10 | BP44: 1.2507927e+10
A45: Chile | B45: CHL | C45: GDP (current US$) | D45: NY.GDP.MKTP.CD | E45: 4.2111037e+09 | F45: 4.9485646e+09 | G45: 5.7659711e+09 | H45: 5.7025201e+09 | I45: 6.0657087e+09 | J45: 6.1839889e+09 | K45: 7.2568821e+09 | L45: 7.1450681e+09 | M45: 7.2868205e+09 | N45: 8.456519e+09 | O45: 9.2610065e+09 | P45: 1.0999808e+10 | Q45: 1.2057502e+10 | R45: 1.7237336e+10 | S45: 1.6584311e+10 | T45: 7.8121618e+09 | U45: 1.0523479e+10 | V45: 1.4272711e+10 | W45: 1.6373094e+10 | X45: 2.2249575e+10 | Y45: 2.9586677e+10 | Z45: 3.5180322e+10 | AA45: 1.9710229e+10 | AB45: 2.0629679e+10 | AC45: 1.9974595e+10 | AD45: 1.7933557e+10 | AE45: 1.9197818e+10 | AF45: 2.2605489e+10 | AG45: 2.6174859e+10 | AH45: 3.0101768e+10 | AI45: 3.342858e+10 | AJ45: 3.8232331e+10 | AK45: 4.6538896e+10 | AL45: 4.9934943e+10 | AM45: 5.7438274e+10 | AN45: 7.3820426e+10 | AO45: 7.8584099e+10 | AP45: 8.5741415e+10 | AQ45: 8.1990011e+10 | AR45: 7.5578686e+10 | AS45: 7.8339751e+10 | AT45: 7.157474e+10 | AU45: 7.0264046e+10 | AV45: 7.649258e+10 | AW45: 9.9075986e+10 | AX45: 1.2229415e+11 | AY45: 1.5384352e+11 | AZ45: 1.7249108e+11 | BA45: 1.7989459e+11 | BB45: 1.717779e+11 | BC45: 2.1705121e+11 | BD45: 2.5138257e+11 | BE45: 2.6702478e+11 | BF45: 2.7739502e+11 | BG45: 2.5956098e+11 | BH45: 2.4245036e+11 | BI45: 2.4934486e+11 | BJ45: 2.7615426e+11 | BK45: 2.9585756e+11 | BL45: 2.7828506e+11 | BM45: 2.5404216e+11 | BN45: 3.1532555e+11 | BO45: 3.0122658e+11 | BP45: 3.3551805e+11 | BQ45: 3.3026714e+11
